Workbook

Sheet Guide
A1: LeaseDisparity — Contracted vs Market Rent: Disparity Valuation
A2: Demo workbook built around a lease rental disparity brief: compare
A3: contracted rent with current market rent for up to 12 leases, and value
A4: the disparity over each remaining term at a single yield rate.
A6: How to use: replace the values in Leases columns A-G with your own
A7: leases (up to 12 rows; extend the ranges if you add rows). Every
A8: derived figure — disparity, present value, dashboard KPIs, the monthly
A9: run-off schedule and the Checks sheet — is a live formula. Change the
A10: yield on the Assumptions sheet and the whole valuation reprices.
A12: Valuation: monthly annuity in arrears. Monthly disparity = market
A13: rent minus contracted rent. PV = disparity x (1-(1+r)^-n)/r, where
A14: r is the monthly yield and n is the remaining term in months.
... A19: data. Rents are USD per month; yield 8.5% per year (see Assumptions).

Sheet Dashboard
A1: LeaseDisparity — Portfolio Dashboard (as of 2026-10-30)
A2: All values are live formulas over Leases / Assumptions.
A3: Leases in portfolio | B3: =COUNTA(Leases!$A$2:$A$13)
A4: Total contracted rent ($/month) | B4: =SUM(Leases!$E$2:$E$13)
A5: Total market rent ($/month) | B5: =SUM(Leases!$F$2:$F$13)
A6: Monthly disparity — market minus contract ($) | B6: =SUM(Leases!$H$2:$H$13)
A7: Annual disparity ($) | B7: =SUM(Leases!$I$2:$I$13)
A8: Undiscounted disparity over remaining terms ($) | B8: =SUM(Leases!$J$2:$J$13)
A9: Present value of disparity ($) | B9: =SUM(Leases!$K$2:$K$13)
A10: Under-rented leases | B10: =COUNTIF(Leases!$L$2:$L$13,"Under-rented")
A11: Over-rented leases | B11: =COUNTIF(Leases!$L$2:$L$13,"Over-rented")
A12: At-market leases | B12: =COUNTIF(Leases!$L$2:$L$13,"At market")
A13: Average remaining term (months) | B13: =AVERAGE(Leases!$G$2:$G$13)
A14: Annual yield | B14: =Assumptions!$B$2
A15: Charts below are wired to Leases / Schedule — they move with the data.

Sheet Assumptions
A1: Assumptions
A2: Annual yield | B2: 0.085
A3: Monthly yield | B3: =$B$2/12
A4: As-of date | B4: 2026-10-30
A5: Valuation basis | B5: Monthly annuity, payments in arrears
A6: At-market tolerance ($/month) | B6: 25
A7: Max leases in this workbook | B7: 12

Sheet Leases
A1: LeaseID | B1: Property | C1: Tenant | D1: Area | E1: Contract Rent ($/mo) | F1: Market Rent ($/mo) | G1: Remaining Term (months) | H1: Monthly Disparity ($) | I1: Annual Disparity ($) | J1: Undiscounted Disparity ($) | K1: PV of Disparity ($) | L1: Status
A2: L01 | B2: Harbor View Retail | C2: Marina Books LLC | D2: Long Beach | E2: 4200 | F2: 5800 | G2: 48 | H2: =$F2-$E2 | I2: =$H2*12 | J2: =$H2*$G2 | K2: =$H2*(1-(1+Assumptions!$B$3)^-$G2)/Assumptions!$B$3 | L2: =IF(ABS($H2)<=Assumptions!$B$6,"At market",IF($H2>0,"Under-rented","Over-rented"))
A3: L02 | B3: Arts District Loft Office | C3: Studio North Inc | D3: Los Angeles | E3: 6800 | F3: 7400 | G3: 36 | H3: =$F3-$E3 | I3: =$H3*12 | J3: =$H3*$G3 | K3: =$H3*(1-(1+Assumptions!$B$3)^-$G3)/Assumptions!$B$3 | L3: =IF(ABS($H3)<=Assumptions!$B$6,"At market",IF($H3>0,"Under-rented","Over-rented"))
A4: L03 | B4: Valley Warehouse Bay 4 | C4: Sunset Logistics Co | D4: Van Nuys | E4: 9500 | F4: 8200 | G4: 24 | H4: =$F4-$E4 | I4: =$H4*12 | J4: =$H4*$G4 | K4: =$H4*(1-(1+Assumptions!$B$3)^-$G4)/Assumptions!$B$3 | L4: =IF(ABS($H4)<=Assumptions!$B$6,"At market",IF($H4>0,"Under-rented","Over-rented"))
A5: L04 | B5: Pasadena Cafe Corner | C5: Rose City Roasters | D5: Pasadena | E5: 3100 | F5: 3900 | G5: 18 | H5: =$F5-$E5 | I5: =$H5*12 | J5: =$H5*$G5 | K5: =$H5*(1-(1+Assumptions!$B$3)^-$G5)/Assumptions!$B$3 | L5: =IF(ABS($H5)<=Assumptions!$B$6,"At market",IF($H5>0,"Under-rented","Over-rented"))
A6: L05 | B6: Downtown Flex Suite 210 | C6: Beacon Consulting | D6: Los Angeles | E6: 5400 | F6: 5400 | G6: 30 | H6: =$F6-$E6 | I6: =$H6*12 | J6: =$H6*$G6 | K6: =$H6*(1-(1+Assumptions!$B$3)^-$G6)/Assumptions!$B$3 | L6: =IF(ABS($H6)<=Assumptions!$B$6,"At market",IF($H6>0,"Under-rented","Over-rented"))
A7: L06 | B7: Burbank Sound Stage Office | C7: Echo Post LLC | D7: Burbank | E7: 11200 | F7: 12900 | G7: 60 | H7: =$F7-$E7 | I7: =$H7*12 | J7: =$H7*$G7 | K7: =$H7*(1-(1+Assumptions!$B$3)^-$G7)/Assumptions!$B$3 | L7: =IF(ABS($H7)<=Assumptions!$B$6,"At market",IF($H7>0,"Under-rented","Over-rented"))
A8: L07 | B8: Santa Monica Clinic Suite | C8: Pacific Wellness Group | D8: Santa Monica | E8: 7600 | F8: 7100 | G8: 12 | H8: =$F8-$E8 | I8: =$H8*12 | J8: =$H8*$G8 | K8: =$H8*(1-(1+Assumptions!$B$3)^-$G8)/Assumptions!$B$3 | L8: =IF(ABS($H8)<=Assumptions!$B$6,"At market",IF($H8>0,"Under-rented","Over-rented"))
A9: L08 | B9: Glendale Showroom | C9: Foothill Auto Gallery | D9: Glendale | E9: 8900 | F9: 9800 | G9: 42 | H9: =$F9-$E9 | I9: =$H9*12 | J9: =$H9*$G9 | K9: =$H9*(1-(1+Assumptions!$B$3)^-$G9)/Assumptions!$B$3 | L9: =IF(ABS($H9)<=Assumptions!$B$6,"At market",IF($H9>0,"Under-rented","Over-rented"))
A10: L09 | B10: Torrance Light Industrial | C10: Harbor Parts Supply | D10: Torrance | E10: 6300 | F10: 5900 | G10: 9 | H10: =$F10-$E10 | I10: =$H10*12 | J10: =$H10*$G10 | K10: =$H10*(1-(1+Assumptions!$B$3)^-$G10)/Assumptions!$B$3 | L10: =IF(ABS($H10)<=Assumptions!$B$6,"At market",IF($H10>0,"Under-rented","Over-rented"))
A11: L10 | B11: Hollywood Production Office | C11: Silverline Media | D11: Hollywood | E11: 4800 | F11: 6100 | G11: 27 | H11: =$F11-$E11 | I11: =$H11*12 | J11: =$H11*$G11 | K11: =$H11*(1-(1+Assumptions!$B$3)^-$G11)/Assumptions!$B$3 | L11: =IF(ABS($H11)<=Assumptions!$B$6,"At market",IF($H11>0,"Under-rented","Over-rented"))
A12: L11 | B12: Culver City Creative Studio | C12: Framehouse Films | D12: Culver City | E12: 5700 | F12: 6300 | G12: 15 | H12: =$F12-$E12 | I12: =$H12*12 | J12: =$H12*$G12 | K12: =$H12*(1-(1+Assumptions!$B$3)^-$G12)/Assumptions!$B$3 | L12: =IF(ABS($H12)<=Assumptions!$B$6,"At market",IF($H12>0,"Under-rented","Over-rented"))
A13: L12 | B13: Inglewood Retail Pad | C13: Forum Foods Inc | D13: Inglewood | E13: 2600 | F13: 3400 | G13: 54 | H13: =$F13-$E13 | I13: =$H13*12 | J13: =$H13*$G13 | K13: =$H13*(1-(1+Assumptions!$B$3)^-$G13)/Assumptions!$B$3 | L13: =IF(ABS($H13)<=Assumptions!$B$6,"At market",IF($H13>0,"Under-rented","Over-rented"))
A14: TOTAL | E14: =SUM($E$2:$E$13) | F14: =SUM($F$2:$F$13) | H14: =SUM($H$2:$H$13) | I14: =SUM($I$2:$I$13) | J14: =SUM($J$2:$J$13) | K14: =SUM($K$2:$K$13)

Sheet Schedule
A1: Month | B1: Monthly Disparity ($) | C1: Discount Factor | D1: Discounted Disparity ($) | E1: Cumulative PV ($)
A2: 1 | B2: =SUMPRODUCT((Leases!$G$2:$G$13>=$A2)*Leases!$H$2:$H$13) | C2: =(1+Assumptions!$B$3)^-$A2 | D2: =$B2*$C2 | E2: =SUM($D$2:$D2)
A3: 2 | B3: =SUMPRODUCT((Leases!$G$2:$G$13>=$A3)*Leases!$H$2:$H$13) | C3: =(1+Assumptions!$B$3)^-$A3 | D3: =$B3*$C3 | E3: =SUM($D$2:$D3)
A4: 3 | B4: =SUMPRODUCT((Leases!$G$2:$G$13>=$A4)*Leases!$H$2:$H$13) | C4: =(1+Assumptions!$B$3)^-$A4 | D4: =$B4*$C4 | E4: =SUM($D$2:$D4)
A5: 4 | B5: =SUMPRODUCT((Leases!$G$2:$G$13>=$A5)*Leases!$H$2:$H$13) | C5: =(1+Assumptions!$B$3)^-$A5 | D5: =$B5*$C5 | E5: =SUM($D$2:$D5)
A6: 5 | B6: =SUMPRODUCT((Leases!$G$2:$G$13>=$A6)*Leases!$H$2:$H$13) | C6: =(1+Assumptions!$B$3)^-$A6 | D6: =$B6*$C6 | E6: =SUM($D$2:$D6)
A7: 6 | B7: =SUMPRODUCT((Leases!$G$2:$G$13>=$A7)*Leases!$H$2:$H$13) | C7: =(1+Assumptions!$B$3)^-$A7 | D7: =$B7*$C7 | E7: =SUM($D$2:$D7)
A8: 7 | B8: =SUMPRODUCT((Leases!$G$2:$G$13>=$A8)*Leases!$H$2:$H$13) | C8: =(1+Assumptions!$B$3)^-$A8 | D8: =$B8*$C8 | E8: =SUM($D$2:$D8)
A9: 8 | B9: =SUMPRODUCT((Leases!$G$2:$G$13>=$A9)*Leases!$H$2:$H$13) | C9: =(1+Assumptions!$B$3)^-$A9 | D9: =$B9*$C9 | E9: =SUM($D$2:$D9)
A10: 9 | B10: =SUMPRODUCT((Leases!$G$2:$G$13>=$A10)*Leases!$H$2:$H$13) | C10: =(1+Assumptions!$B$3)^-$A10 | D10: =$B10*$C10 | E10: =SUM($D$2:$D10)
A11: 10 | B11: =SUMPRODUCT((Leases!$G$2:$G$13>=$A11)*Leases!$H$2:$H$13) | C11: =(1+Assumptions!$B$3)^-$A11 | D11: =$B11*$C11 | E11: =SUM($D$2:$D11)
A12: 11 | B12: =SUMPRODUCT((Leases!$G$2:$G$13>=$A12)*Leases!$H$2:$H$13) | C12: =(1+Assumptions!$B$3)^-$A12 | D12: =$B12*$C12 | E12: =SUM($D$2:$D12)
A13: 12 | B13: =SUMPRODUCT((Leases!$G$2:$G$13>=$A13)*Leases!$H$2:$H$13) | C13: =(1+Assumptions!$B$3)^-$A13 | D13: =$B13*$C13 | E13: =SUM($D$2:$D13)
... A61: 60 | B61: =SUMPRODUCT((Leases!$G$2:$G$13>=$A61)*Leases!$H$2:$H$13) | C61: =(1+Assumptions!$B$3)^-$A61 | D61: =$B61*$C61 | E61: =SUM($D$2:$D61)

Sheet Checks
A1: Check | B1: Expected | C1: Got | D1: Diff | E1: Status
A2: Lease count | B2: 12 | C2: =COUNTA(Leases!$A$2:$A$13) | D2: =$C2-$B2 | E2: =IF(ABS($D2)<=0,"PASS","FAIL")
A3: Dashboard contract total ties to Leases | B3: =SUM(Leases!$E$2:$E$13) | C3: =Dashboard!$B$4 | D3: =$C3-$B3 | E3: =IF(ABS($D3)<=0.01,"PASS","FAIL")
A4: Dashboard market total ties to Leases | B4: =SUM(Leases!$F$2:$F$13) | C4: =Dashboard!$B$5 | D4: =$C4-$B4 | E4: =IF(ABS($D4)<=0.01,"PASS","FAIL")
A5: Dashboard monthly disparity ties to Leases | B5: =SUM(Leases!$H$2:$H$13) | C5: =Dashboard!$B$6 | D5: =$C5-$B5 | E5: =IF(ABS($D5)<=0.01,"PASS","FAIL")
A6: Dashboard PV ties to Leases | B6: =SUM(Leases!$K$2:$K$13) | C6: =Dashboard!$B$9 | D6: =$C6-$B6 | E6: =IF(ABS($D6)<=0.01,"PASS","FAIL")
A7: Schedule month 1 ties to dashboard monthly disparity | B7: =Schedule!$B$2 | C7: =Dashboard!$B$6 | D7: =$C7-$B7 | E7: =IF(ABS($D7)<=0.01,"PASS","FAIL")
A8: Schedule cumulative PV ties to dashboard PV | B8: =Schedule!$E$61 | C8: =Dashboard!$B$9 | D8: =$C8-$B8 | E8: =IF(ABS($D8)<=1,"PASS","FAIL")
A9: Leases with negative remaining term | B9: 0 | C9: =COUNTIF(Leases!$G$2:$G$13,"<0") | D9: =$C9-$B9 | E9: =IF(ABS($D9)<=0,"PASS","FAIL")
A10: Leases with blank market rent | B10: 0 | C10: =COUNTBLANK(Leases!$F$2:$F$13) | D10: =$C10-$B10 | E10: =IF(ABS($D10)<=0,"PASS","FAIL")
