Workbook

Sheet Dashboard
A1: AquaBill — Billing, Sales & Inventory Dashboard
A2: AquaPure Distributors, Patna • Apr–Sep 2026 • All figures are live formulas
A4: Total revenue (incl GST) | B4: =SUM(Invoices!$F$2:$F$501)
A5: Invoices issued | B5: =COUNTA(Invoices!$A$2:$A$501)
A6: Units sold | B6: =SUM(InvoiceLines!$E$2:$E$4001)
A7: Avg invoice value | B7: =IFERROR(AVERAGEIF(Invoices!$A$2:$A$501,"<>",Invoices!$F$2:$F$501),0)
A8: GST collected (18%) | B8: =SUM(Invoices!$E$2:$E$501)
A9: Outstanding receivables | B9: =SUM(Invoices!$H$2:$H$501)
A10: SKUs at / below reorder level | B10: =SUMPRODUCT((Inventory!$H$2:$H$21="REORDER")*1)+SUMPRODUCT((Inventory!$H$2:$H$21="OUT OF STOCK")*1)
A11: Stock value on hand | B11: =SUM(Inventory!$I$2:$I$21)

Sheet InvoiceLines
A1: Inv No | B1: Date | C1: Line | D1: SKU | E1: Qty | F1: Rate (ex-GST) | G1: Line Total
A2: INV-2026-0001 | B2: 46113 | C2: 1 | D2: Hot & Cold Water Dispenser | E2: 2 | F2: 8500 | G2: =IF($A2="",0,ROUND($E2*$F2,2))
A3: INV-2026-0001 | B3: 46113 | C3: 2 | D3: Hot & Cold Water Dispenser | E3: 1 | F3: 8500 | G3: =IF($A3="",0,ROUND($E3*$F3,2))
A4: INV-2026-0002 | B4: 46114 | C4: 1 | D4: 500ml Bottle Case (24 pc) | E4: 18 | F4: 220 | G4: =IF($A4="",0,ROUND($E4*$F4,2))
A5: INV-2026-0003 | B5: 46115 | C5: 1 | D5: 1L Bottle Case (12 pc) | E5: 18 | F5: 240 | G5: =IF($A5="",0,ROUND($E5*$F5,2))
A6: INV-2026-0003 | B6: 46115 | C6: 2 | D6: 500ml Bottle Case (24 pc) | E6: 15 | F6: 220 | G6: =IF($A6="",0,ROUND($E6*$F6,2))
A7: INV-2026-0004 | B7: 46116 | C7: 1 | D7: 500ml Bottle Case (24 pc) | E7: 14 | F7: 220 | G7: =IF($A7="",0,ROUND($E7*$F7,2))
A8: INV-2026-0005 | B8: 46116 | C8: 1 | D8: 1L Bottle Case (12 pc) | E8: 24 | F8: 240 | G8: =IF($A8="",0,ROUND($E8*$F8,2))
A9: INV-2026-0005 | B9: 46116 | C9: 2 | D9: 500ml Bottle Case (24 pc) | E9: 33 | F9: 220 | G9: =IF($A9="",0,ROUND($E9*$F9,2))
A10: INV-2026-0006 | B10: 46118 | C10: 1 | D10: 500ml Bottle Case (24 pc) | E10: 22 | F10: 220 | G10: =IF($A10="",0,ROUND($E10*$F10,2))
A11: INV-2026-0007 | B11: 46118 | C11: 1 | D11: 5L Water Jar | E11: 16 | F11: 45 | G11: =IF($A11="",0,ROUND($E11*$F11,2))
A12: INV-2026-0007 | B12: 46118 | C12: 2 | D12: 500ml Bottle Case (24 pc) | E12: 5 | F12: 220 | G12: =IF($A12="",0,ROUND($E12*$F12,2))
A13: INV-2026-0008 | B13: 46118 | C13: 1 | D13: 20L Water Jar | E13: 79 | F13: 60 | G13: =IF($A13="",0,ROUND($E13*$F13,2))
... A365: INV-2026-0202 | B365: 46295 | C365: 2 | D365: 20L Water Jar | E365: 61 | F365: 60 | G365: =IF($A365="",0,ROUND($E365*$F365,2))
G366: =IF($A366="",0,ROUND($E366*$F366,2))
G367: =IF($A367="",0,ROUND($E367*$F367,2))
G368: =IF($A368="",0,ROUND($E368*$F368,2))
G369: =IF($A369="",0,ROUND($E369*$F369,2))
G370: =IF($A370="",0,ROUND($E370*$F370,2))
G371: =IF($A371="",0,ROUND($E371*$F371,2))
G372: =IF($A372="",0,ROUND($E372*$F372,2))
G373: =IF($A373="",0,ROUND($E373*$F373,2))
G374: =IF($A374="",0,ROUND($E374*$F374,2))
G375: =IF($A375="",0,ROUND($E375*$F375,2))
G376: =IF($A376="",0,ROUND($E376*$F376,2))
G377: =IF($A377="",0,ROUND($E377*$F377,2))
... G4001: =IF($A4001="",0,ROUND($E4001*$F4001,2))

Sheet Invoices
A1: Inv No | B1: Date | C1: Customer | D1: Subtotal | E1: GST 18% | F1: Grand Total | G1: Paid | H1: Balance | I1: Status
A2: INV-2026-0001 | B2: 46113 | C2: Ganga Boys Hostel | D2: =IF($A2="",0,ROUND(SUMIFS(InvoiceLines!$G$2:$G$4001,InvoiceLines!$A$2:$A$4001,$A2),2)) | E2: =IF($A2="",0,ROUND($D2*18%,2)) | F2: =IF($A2="",0,$D2+$E2) | G2: 30090 | H2: =IF($A2="",0,$F2-$G2) | I2: =IF($A2="","",IF($H2=0,"Paid",IF($G2=0,"Unpaid","Partial")))
A3: INV-2026-0002 | B3: 46114 | C3: Wedding Palace Events | D3: =IF($A3="",0,ROUND(SUMIFS(InvoiceLines!$G$2:$G$4001,InvoiceLines!$A$2:$A$4001,$A3),2)) | E3: =IF($A3="",0,ROUND($D3*18%,2)) | F3: =IF($A3="",0,$D3+$E3) | G3: 2056.03 | H3: =IF($A3="",0,$F3-$G3) | I3: =IF($A3="","",IF($H3=0,"Paid",IF($G3=0,"Unpaid","Partial")))
A4: INV-2026-0003 | B4: 46115 | C4: TechPark Canteen | D4: =IF($A4="",0,ROUND(SUMIFS(InvoiceLines!$G$2:$G$4001,InvoiceLines!$A$2:$A$4001,$A4),2)) | E4: =IF($A4="",0,ROUND($D4*18%,2)) | F4: =IF($A4="",0,$D4+$E4) | G4: 8991.6 | H4: =IF($A4="",0,$F4-$G4) | I4: =IF($A4="","",IF($H4=0,"Paid",IF($G4=0,"Unpaid","Partial")))
A5: INV-2026-0004 | B5: 46116 | C5: Sharma Tea Stall | D5: =IF($A5="",0,ROUND(SUMIFS(InvoiceLines!$G$2:$G$4001,InvoiceLines!$A$2:$A$4001,$A5),2)) | E5: =IF($A5="",0,ROUND($D5*18%,2)) | F5: =IF($A5="",0,$D5+$E5) | G5: 3634.4 | H5: =IF($A5="",0,$F5-$G5) | I5: =IF($A5="","",IF($H5=0,"Paid",IF($G5=0,"Unpaid","Partial")))
A6: INV-2026-0005 | B6: 46116 | C6: Wedding Palace Events | D6: =IF($A6="",0,ROUND(SUMIFS(InvoiceLines!$G$2:$G$4001,InvoiceLines!$A$2:$A$4001,$A6),2)) | E6: =IF($A6="",0,ROUND($D6*18%,2)) | F6: =IF($A6="",0,$D6+$E6) | G6: 10754.52 | H6: =IF($A6="",0,$F6-$G6) | I6: =IF($A6="","",IF($H6=0,"Paid",IF($G6=0,"Unpaid","Partial")))
A7: INV-2026-0006 | B7: 46118 | C7: MediCare Clinic | D7: =IF($A7="",0,ROUND(SUMIFS(InvoiceLines!$G$2:$G$4001,InvoiceLines!$A$2:$A$4001,$A7),2)) | E7: =IF($A7="",0,ROUND($D7*18%,2)) | F7: =IF($A7="",0,$D7+$E7) | G7: 5711.2 | H7: =IF($A7="",0,$F7-$G7) | I7: =IF($A7="","",IF($H7=0,"Paid",IF($G7=0,"Unpaid","Partial")))
A8: INV-2026-0007 | B8: 46118 | C8: City Gym | D8: =IF($A8="",0,ROUND(SUMIFS(InvoiceLines!$G$2:$G$4001,InvoiceLines!$A$2:$A$4001,$A8),2)) | E8: =IF($A8="",0,ROUND($D8*18%,2)) | F8: =IF($A8="",0,$D8+$E8) | G8: 2147.6 | H8: =IF($A8="",0,$F8-$G8) | I8: =IF($A8="","",IF($H8=0,"Paid",IF($G8=0,"Unpaid","Partial")))
A9: INV-2026-0008 | B9: 46118 | C9: Bright School Canteen | D9: =IF($A9="",0,ROUND(SUMIFS(InvoiceLines!$G$2:$G$4001,InvoiceLines!$A$2:$A$4001,$A9),2)) | E9: =IF($A9="",0,ROUND($D9*18%,2)) | F9: =IF($A9="",0,$D9+$E9) | G9: 15788.4 | H9: =IF($A9="",0,$F9-$G9) | I9: =IF($A9="","",IF($H9=0,"Paid",IF($G9=0,"Unpaid","Partial")))
A10: INV-2026-0009 | B10: 46119 | C10: Sharma Tea Stall | D10: =IF($A10="",0,ROUND(SUMIFS(InvoiceLines!$G$2:$G$4001,InvoiceLines!$A$2:$A$4001,$A10),2)) | E10: =IF($A10="",0,ROUND($D10*18%,2)) | F10: =IF($A10="",0,$D10+$E10) | G10: 0 | H10: =IF($A10="",0,$F10-$G10) | I10: =IF($A10="","",IF($H10=0,"Paid",IF($G10=0,"Unpaid","Partial")))
A11: INV-2026-0010 | B11: 46119 | C11: Cafe Brewlane | D11: =IF($A11="",0,ROUND(SUMIFS(InvoiceLines!$G$2:$G$4001,InvoiceLines!$A$2:$A$4001,$A11),2)) | E11: =IF($A11="",0,ROUND($D11*18%,2)) | F11: =IF($A11="",0,$D11+$E11) | G11: 8892.48 | H11: =IF($A11="",0,$F11-$G11) | I11: =IF($A11="","",IF($H11=0,"Paid",IF($G11=0,"Unpaid","Partial")))
A12: INV-2026-0011 | B12: 46120 | C12: City Gym | D12: =IF($A12="",0,ROUND(SUMIFS(InvoiceLines!$G$2:$G$4001,InvoiceLines!$A$2:$A$4001,$A12),2)) | E12: =IF($A12="",0,ROUND($D12*18%,2)) | F12: =IF($A12="",0,$D12+$E12) | G12: 10266 | H12: =IF($A12="",0,$F12-$G12) | I12: =IF($A12="","",IF($H12=0,"Paid",IF($G12=0,"Unpaid","Partial")))
A13: INV-2026-0012 | B13: 46121 | C13: Hotel Rajwada | D13: =IF($A13="",0,ROUND(SUMIFS(InvoiceLines!$G$2:$G$4001,InvoiceLines!$A$2:$A$4001,$A13),2)) | E13: =IF($A13="",0,ROUND($D13*18%,2)) | F13: =IF($A13="",0,$D13+$E13) | G13: 5251 | H13: =IF($A13="",0,$F13-$G13) | I13: =IF($A13="","",IF($H13=0,"Paid",IF($G13=0,"Unpaid","Partial")))
... A203: INV-2026-0202 | B203: 46295 | C203: OfficeHub Cowork | D203: =IF($A203="",0,ROUND(SUMIFS(InvoiceLines!$G$2:$G$4001,InvoiceLines!$A$2:$A$4001,$A203),2)) | E203: =IF($A203="",0,ROUND($D203*18%,2)) | F203: =IF($A203="",0,$D203+$E203) | G203: 7239.3 | H203: =IF($A203="",0,$F203-$G203) | I203: =IF($A203="","",IF($H203=0,"Paid",IF($G203=0,"Unpaid","Partial")))
D204: =IF($A204="",0,ROUND(SUMIFS(InvoiceLines!$G$2:$G$4001,InvoiceLines!$A$2:$A$4001,$A204),2)) | E204: =IF($A204="",0,ROUND($D204*18%,2)) | F204: =IF($A204="",0,$D204+$E204) | H204: =IF($A204="",0,$F204-$G204) | I204: =IF($A204="","",IF($H204=0,"Paid",IF($G204=0,"Unpaid","Partial")))
D205: =IF($A205="",0,ROUND(SUMIFS(InvoiceLines!$G$2:$G$4001,InvoiceLines!$A$2:$A$4001,$A205),2)) | E205: =IF($A205="",0,ROUND($D205*18%,2)) | F205: =IF($A205="",0,$D205+$E205) | H205: =IF($A205="",0,$F205-$G205) | I205: =IF($A205="","",IF($H205=0,"Paid",IF($G205=0,"Unpaid","Partial")))
D206: =IF($A206="",0,ROUND(SUMIFS(InvoiceLines!$G$2:$G$4001,InvoiceLines!$A$2:$A$4001,$A206),2)) | E206: =IF($A206="",0,ROUND($D206*18%,2)) | F206: =IF($A206="",0,$D206+$E206) | H206: =IF($A206="",0,$F206-$G206) | I206: =IF($A206="","",IF($H206=0,"Paid",IF($G206=0,"Unpaid","Partial")))
D207: =IF($A207="",0,ROUND(SUMIFS(InvoiceLines!$G$2:$G$4001,InvoiceLines!$A$2:$A$4001,$A207),2)) | E207: =IF($A207="",0,ROUND($D207*18%,2)) | F207: =IF($A207="",0,$D207+$E207) | H207: =IF($A207="",0,$F207-$G207) | I207: =IF($A207="","",IF($H207=0,"Paid",IF($G207=0,"Unpaid","Partial")))
D208: =IF($A208="",0,ROUND(SUMIFS(InvoiceLines!$G$2:$G$4001,InvoiceLines!$A$2:$A$4001,$A208),2)) | E208: =IF($A208="",0,ROUND($D208*18%,2)) | F208: =IF($A208="",0,$D208+$E208) | H208: =IF($A208="",0,$F208-$G208) | I208: =IF($A208="","",IF($H208=0,"Paid",IF($G208=0,"Unpaid","Partial")))
D209: =IF($A209="",0,ROUND(SUMIFS(InvoiceLines!$G$2:$G$4001,InvoiceLines!$A$2:$A$4001,$A209),2)) | E209: =IF($A209="",0,ROUND($D209*18%,2)) | F209: =IF($A209="",0,$D209+$E209) | H209: =IF($A209="",0,$F209-$G209) | I209: =IF($A209="","",IF($H209=0,"Paid",IF($G209=0,"Unpaid","Partial")))
D210: =IF($A210="",0,ROUND(SUMIFS(InvoiceLines!$G$2:$G$4001,InvoiceLines!$A$2:$A$4001,$A210),2)) | E210: =IF($A210="",0,ROUND($D210*18%,2)) | F210: =IF($A210="",0,$D210+$E210) | H210: =IF($A210="",0,$F210-$G210) | I210: =IF($A210="","",IF($H210=0,"Paid",IF($G210=0,"Unpaid","Partial")))
D211: =IF($A211="",0,ROUND(SUMIFS(InvoiceLines!$G$2:$G$4001,InvoiceLines!$A$2:$A$4001,$A211),2)) | E211: =IF($A211="",0,ROUND($D211*18%,2)) | F211: =IF($A211="",0,$D211+$E211) | H211: =IF($A211="",0,$F211-$G211) | I211: =IF($A211="","",IF($H211=0,"Paid",IF($G211=0,"Unpaid","Partial")))
D212: =IF($A212="",0,ROUND(SUMIFS(InvoiceLines!$G$2:$G$4001,InvoiceLines!$A$2:$A$4001,$A212),2)) | E212: =IF($A212="",0,ROUND($D212*18%,2)) | F212: =IF($A212="",0,$D212+$E212) | H212: =IF($A212="",0,$F212-$G212) | I212: =IF($A212="","",IF($H212=0,"Paid",IF($G212=0,"Unpaid","Partial")))
D213: =IF($A213="",0,ROUND(SUMIFS(InvoiceLines!$G$2:$G$4001,InvoiceLines!$A$2:$A$4001,$A213),2)) | E213: =IF($A213="",0,ROUND($D213*18%,2)) | F213: =IF($A213="",0,$D213+$E213) | H213: =IF($A213="",0,$F213-$G213) | I213: =IF($A213="","",IF($H213=0,"Paid",IF($G213=0,"Unpaid","Partial")))
D214: =IF($A214="",0,ROUND(SUMIFS(InvoiceLines!$G$2:$G$4001,InvoiceLines!$A$2:$A$4001,$A214),2)) | E214: =IF($A214="",0,ROUND($D214*18%,2)) | F214: =IF($A214="",0,$D214+$E214) | H214: =IF($A214="",0,$F214-$G214) | I214: =IF($A214="","",IF($H214=0,"Paid",IF($G214=0,"Unpaid","Partial")))
D215: =IF($A215="",0,ROUND(SUMIFS(InvoiceLines!$G$2:$G$4001,InvoiceLines!$A$2:$A$4001,$A215),2)) | E215: =IF($A215="",0,ROUND($D215*18%,2)) | F215: =IF($A215="",0,$D215+$E215) | H215: =IF($A215="",0,$F215-$G215) | I215: =IF($A215="","",IF($H215=0,"Paid",IF($G215=0,"Unpaid","Partial")))
... D501: =IF($A501="",0,ROUND(SUMIFS(InvoiceLines!$G$2:$G$4001,InvoiceLines!$A$2:$A$4001,$A501),2)) | E501: =IF($A501="",0,ROUND($D501*18%,2)) | F501: =IF($A501="",0,$D501+$E501) | H501: =IF($A501="",0,$F501-$G501) | I501: =IF($A501="","",IF($H501=0,"Paid",IF($G501=0,"Unpaid","Partial")))

Sheet Inventory
A1: SKU | B1: Rate (ex-GST) | C1: Opening Stock | D1: Purchased In | E1: Sold Out | F1: Closing Stock | G1: Reorder Level | H1: Status | I1: Stock Value
A2: 20L Water Jar | B2: 60 | C2: 800 | D2: =IF($A2="",0,ROUND(SUMIFS(Purchases!$D$2:$D$201,Purchases!$B$2:$B$201,$A2),2)) | E2: =IF($A2="",0,ROUND(SUMIFS(InvoiceLines!$E$2:$E$4001,InvoiceLines!$D$2:$D$4001,$A2),2)) | F2: =IF($A2="",0,$C2+$D2-$E2) | G2: 200 | H2: =IF($A2="","",IF($F2<=0,"OUT OF STOCK",IF($F2<=$G2,"REORDER","OK"))) | I2: =IF($A2="",0,ROUND($F2*$B2,2))
A3: 1L Bottle Case (12 pc) | B3: 240 | C3: 500 | D3: =IF($A3="",0,ROUND(SUMIFS(Purchases!$D$2:$D$201,Purchases!$B$2:$B$201,$A3),2)) | E3: =IF($A3="",0,ROUND(SUMIFS(InvoiceLines!$E$2:$E$4001,InvoiceLines!$D$2:$D$4001,$A3),2)) | F3: =IF($A3="",0,$C3+$D3-$E3) | G3: 150 | H3: =IF($A3="","",IF($F3<=0,"OUT OF STOCK",IF($F3<=$G3,"REORDER","OK"))) | I3: =IF($A3="",0,ROUND($F3*$B3,2))
A4: 500ml Bottle Case (24 pc) | B4: 220 | C4: 600 | D4: =IF($A4="",0,ROUND(SUMIFS(Purchases!$D$2:$D$201,Purchases!$B$2:$B$201,$A4),2)) | E4: =IF($A4="",0,ROUND(SUMIFS(InvoiceLines!$E$2:$E$4001,InvoiceLines!$D$2:$D$4001,$A4),2)) | F4: =IF($A4="",0,$C4+$D4-$E4) | G4: 150 | H4: =IF($A4="","",IF($F4<=0,"OUT OF STOCK",IF($F4<=$G4,"REORDER","OK"))) | I4: =IF($A4="",0,ROUND($F4*$B4,2))
A5: 5L Water Jar | B5: 45 | C5: 400 | D5: =IF($A5="",0,ROUND(SUMIFS(Purchases!$D$2:$D$201,Purchases!$B$2:$B$201,$A5),2)) | E5: =IF($A5="",0,ROUND(SUMIFS(InvoiceLines!$E$2:$E$4001,InvoiceLines!$D$2:$D$4001,$A5),2)) | F5: =IF($A5="",0,$C5+$D5-$E5) | G5: 100 | H5: =IF($A5="","",IF($F5<=0,"OUT OF STOCK",IF($F5<=$G5,"REORDER","OK"))) | I5: =IF($A5="",0,ROUND($F5*$B5,2))
A6: Paper Cups Pack (100 pc) | B6: 90 | C6: 1000 | D6: =IF($A6="",0,ROUND(SUMIFS(Purchases!$D$2:$D$201,Purchases!$B$2:$B$201,$A6),2)) | E6: =IF($A6="",0,ROUND(SUMIFS(InvoiceLines!$E$2:$E$4001,InvoiceLines!$D$2:$D$4001,$A6),2)) | F6: =IF($A6="",0,$C6+$D6-$E6) | G6: 300 | H6: =IF($A6="","",IF($F6<=0,"OUT OF STOCK",IF($F6<=$G6,"REORDER","OK"))) | I6: =IF($A6="",0,ROUND($F6*$B6,2))
A7: Hot & Cold Water Dispenser | B7: 8500 | C7: 25 | D7: =IF($A7="",0,ROUND(SUMIFS(Purchases!$D$2:$D$201,Purchases!$B$2:$B$201,$A7),2)) | E7: =IF($A7="",0,ROUND(SUMIFS(InvoiceLines!$E$2:$E$4001,InvoiceLines!$D$2:$D$4001,$A7),2)) | F7: =IF($A7="",0,$C7+$D7-$E7) | G7: 5 | H7: =IF($A7="","",IF($F7<=0,"OUT OF STOCK",IF($F7<=$G7,"REORDER","OK"))) | I7: =IF($A7="",0,ROUND($F7*$B7,2))
D8: =IF($A8="",0,ROUND(SUMIFS(Purchases!$D$2:$D$201,Purchases!$B$2:$B$201,$A8),2)) | E8: =IF($A8="",0,ROUND(SUMIFS(InvoiceLines!$E$2:$E$4001,InvoiceLines!$D$2:$D$4001,$A8),2)) | F8: =IF($A8="",0,$C8+$D8-$E8) | H8: =IF($A8="","",IF($F8<=0,"OUT OF STOCK",IF($F8<=$G8,"REORDER","OK"))) | I8: =IF($A8="",0,ROUND($F8*$B8,2))
D9: =IF($A9="",0,ROUND(SUMIFS(Purchases!$D$2:$D$201,Purchases!$B$2:$B$201,$A9),2)) | E9: =IF($A9="",0,ROUND(SUMIFS(InvoiceLines!$E$2:$E$4001,InvoiceLines!$D$2:$D$4001,$A9),2)) | F9: =IF($A9="",0,$C9+$D9-$E9) | H9: =IF($A9="","",IF($F9<=0,"OUT OF STOCK",IF($F9<=$G9,"REORDER","OK"))) | I9: =IF($A9="",0,ROUND($F9*$B9,2))
D10: =IF($A10="",0,ROUND(SUMIFS(Purchases!$D$2:$D$201,Purchases!$B$2:$B$201,$A10),2)) | E10: =IF($A10="",0,ROUND(SUMIFS(InvoiceLines!$E$2:$E$4001,InvoiceLines!$D$2:$D$4001,$A10),2)) | F10: =IF($A10="",0,$C10+$D10-$E10) | H10: =IF($A10="","",IF($F10<=0,"OUT OF STOCK",IF($F10<=$G10,"REORDER","OK"))) | I10: =IF($A10="",0,ROUND($F10*$B10,2))
D11: =IF($A11="",0,ROUND(SUMIFS(Purchases!$D$2:$D$201,Purchases!$B$2:$B$201,$A11),2)) | E11: =IF($A11="",0,ROUND(SUMIFS(InvoiceLines!$E$2:$E$4001,InvoiceLines!$D$2:$D$4001,$A11),2)) | F11: =IF($A11="",0,$C11+$D11-$E11) | H11: =IF($A11="","",IF($F11<=0,"OUT OF STOCK",IF($F11<=$G11,"REORDER","OK"))) | I11: =IF($A11="",0,ROUND($F11*$B11,2))
D12: =IF($A12="",0,ROUND(SUMIFS(Purchases!$D$2:$D$201,Purchases!$B$2:$B$201,$A12),2)) | E12: =IF($A12="",0,ROUND(SUMIFS(InvoiceLines!$E$2:$E$4001,InvoiceLines!$D$2:$D$4001,$A12),2)) | F12: =IF($A12="",0,$C12+$D12-$E12) | H12: =IF($A12="","",IF($F12<=0,"OUT OF STOCK",IF($F12<=$G12,"REORDER","OK"))) | I12: =IF($A12="",0,ROUND($F12*$B12,2))
D13: =IF($A13="",0,ROUND(SUMIFS(Purchases!$D$2:$D$201,Purchases!$B$2:$B$201,$A13),2)) | E13: =IF($A13="",0,ROUND(SUMIFS(InvoiceLines!$E$2:$E$4001,InvoiceLines!$D$2:$D$4001,$A13),2)) | F13: =IF($A13="",0,$C13+$D13-$E13) | H13: =IF($A13="","",IF($F13<=0,"OUT OF STOCK",IF($F13<=$G13,"REORDER","OK"))) | I13: =IF($A13="",0,ROUND($F13*$B13,2))
D14: =IF($A14="",0,ROUND(SUMIFS(Purchases!$D$2:$D$201,Purchases!$B$2:$B$201,$A14),2)) | E14: =IF($A14="",0,ROUND(SUMIFS(InvoiceLines!$E$2:$E$4001,InvoiceLines!$D$2:$D$4001,$A14),2)) | F14: =IF($A14="",0,$C14+$D14-$E14) | H14: =IF($A14="","",IF($F14<=0,"OUT OF STOCK",IF($F14<=$G14,"REORDER","OK"))) | I14: =IF($A14="",0,ROUND($F14*$B14,2))
D15: =IF($A15="",0,ROUND(SUMIFS(Purchases!$D$2:$D$201,Purchases!$B$2:$B$201,$A15),2)) | E15: =IF($A15="",0,ROUND(SUMIFS(InvoiceLines!$E$2:$E$4001,InvoiceLines!$D$2:$D$4001,$A15),2)) | F15: =IF($A15="",0,$C15+$D15-$E15) | H15: =IF($A15="","",IF($F15<=0,"OUT OF STOCK",IF($F15<=$G15,"REORDER","OK"))) | I15: =IF($A15="",0,ROUND($F15*$B15,2))
D16: =IF($A16="",0,ROUND(SUMIFS(Purchases!$D$2:$D$201,Purchases!$B$2:$B$201,$A16),2)) | E16: =IF($A16="",0,ROUND(SUMIFS(InvoiceLines!$E$2:$E$4001,InvoiceLines!$D$2:$D$4001,$A16),2)) | F16: =IF($A16="",0,$C16+$D16-$E16) | H16: =IF($A16="","",IF($F16<=0,"OUT OF STOCK",IF($F16<=$G16,"REORDER","OK"))) | I16: =IF($A16="",0,ROUND($F16*$B16,2))
D17: =IF($A17="",0,ROUND(SUMIFS(Purchases!$D$2:$D$201,Purchases!$B$2:$B$201,$A17),2)) | E17: =IF($A17="",0,ROUND(SUMIFS(InvoiceLines!$E$2:$E$4001,InvoiceLines!$D$2:$D$4001,$A17),2)) | F17: =IF($A17="",0,$C17+$D17-$E17) | H17: =IF($A17="","",IF($F17<=0,"OUT OF STOCK",IF($F17<=$G17,"REORDER","OK"))) | I17: =IF($A17="",0,ROUND($F17*$B17,2))
D18: =IF($A18="",0,ROUND(SUMIFS(Purchases!$D$2:$D$201,Purchases!$B$2:$B$201,$A18),2)) | E18: =IF($A18="",0,ROUND(SUMIFS(InvoiceLines!$E$2:$E$4001,InvoiceLines!$D$2:$D$4001,$A18),2)) | F18: =IF($A18="",0,$C18+$D18-$E18) | H18: =IF($A18="","",IF($F18<=0,"OUT OF STOCK",IF($F18<=$G18,"REORDER","OK"))) | I18: =IF($A18="",0,ROUND($F18*$B18,2))
D19: =IF($A19="",0,ROUND(SUMIFS(Purchases!$D$2:$D$201,Purchases!$B$2:$B$201,$A19),2)) | E19: =IF($A19="",0,ROUND(SUMIFS(InvoiceLines!$E$2:$E$4001,InvoiceLines!$D$2:$D$4001,$A19),2)) | F19: =IF($A19="",0,$C19+$D19-$E19) | H19: =IF($A19="","",IF($F19<=0,"OUT OF STOCK",IF($F19<=$G19,"REORDER","OK"))) | I19: =IF($A19="",0,ROUND($F19*$B19,2))
... D21: =IF($A21="",0,ROUND(SUMIFS(Purchases!$D$2:$D$201,Purchases!$B$2:$B$201,$A21),2)) | E21: =IF($A21="",0,ROUND(SUMIFS(InvoiceLines!$E$2:$E$4001,InvoiceLines!$D$2:$D$4001,$A21),2)) | F21: =IF($A21="",0,$C21+$D21-$E21) | H21: =IF($A21="","",IF($F21<=0,"OUT OF STOCK",IF($F21<=$G21,"REORDER","OK"))) | I21: =IF($A21="",0,ROUND($F21*$B21,2))

Sheet Purchases
A1: Date | B1: SKU | C1: Lot No | D1: Qty | E1: Rate
A2: 46112 | B2: 500ml Bottle Case (24 pc) | C2: LOT-027 | D2: 857 | E2: 220
A3: 46112 | B3: 1L Bottle Case (12 pc) | C3: LOT-028 | D3: 917 | E3: 240
A4: 46112 | B4: 20L Water Jar | C4: LOT-029 | D4: 4356 | E4: 60
A5: 46125 | B5: 5L Water Jar | C5: LOT-001 | D5: 212 | E5: 45
A6: 46131 | B6: Paper Cups Pack (100 pc) | C6: LOT-002 | D6: 87 | E6: 90
A7: 46131 | B7: 5L Water Jar | C7: LOT-003 | D7: 220 | E7: 45
A8: 46131 | B8: Hot & Cold Water Dispenser | C8: LOT-004 | D8: 6 | E8: 8500
A9: 46143 | B9: 20L Water Jar | C9: LOT-005 | D9: 40 | E9: 60
A10: 46143 | B10: 1L Bottle Case (12 pc) | C10: LOT-006 | D10: 15 | E10: 240
A11: 46143 | B11: Paper Cups Pack (100 pc) | C11: LOT-007 | D11: 88 | E11: 90
A12: 46161 | B12: 1L Bottle Case (12 pc) | C12: LOT-008 | D12: 115 | E12: 240
A13: 46161 | B13: 5L Water Jar | C13: LOT-009 | D13: 160 | E13: 45
... A30: 46287 | B30: Paper Cups Pack (100 pc) | C30: LOT-026 | D30: 78 | E30: 90

Sheet GST_Summary
A1: Month | B1: Taxable Value | C1: CGST 9% | D1: SGST 9% | E1: Total GST
A2: 46113 | B2: =ROUND(SUMIFS(Invoices!$D$2:$D$501,Invoices!$B$2:$B$501,">="&DATE(2026,4,1),Invoices!$B$2:$B$501,"<"&DATE(2026,5,1)),2) | C2: =ROUND($B2*9%,2) | D2: =ROUND($B2*9%,2) | E2: =$C2+$D2
A3: 46143 | B3: =ROUND(SUMIFS(Invoices!$D$2:$D$501,Invoices!$B$2:$B$501,">="&DATE(2026,5,1),Invoices!$B$2:$B$501,"<"&DATE(2026,6,1)),2) | C3: =ROUND($B3*9%,2) | D3: =ROUND($B3*9%,2) | E3: =$C3+$D3
A4: 46174 | B4: =ROUND(SUMIFS(Invoices!$D$2:$D$501,Invoices!$B$2:$B$501,">="&DATE(2026,6,1),Invoices!$B$2:$B$501,"<"&DATE(2026,7,1)),2) | C4: =ROUND($B4*9%,2) | D4: =ROUND($B4*9%,2) | E4: =$C4+$D4
A5: 46204 | B5: =ROUND(SUMIFS(Invoices!$D$2:$D$501,Invoices!$B$2:$B$501,">="&DATE(2026,7,1),Invoices!$B$2:$B$501,"<"&DATE(2026,8,1)),2) | C5: =ROUND($B5*9%,2) | D5: =ROUND($B5*9%,2) | E5: =$C5+$D5
A6: 46235 | B6: =ROUND(SUMIFS(Invoices!$D$2:$D$501,Invoices!$B$2:$B$501,">="&DATE(2026,8,1),Invoices!$B$2:$B$501,"<"&DATE(2026,9,1)),2) | C6: =ROUND($B6*9%,2) | D6: =ROUND($B6*9%,2) | E6: =$C6+$D6
A7: 46266 | B7: =ROUND(SUMIFS(Invoices!$D$2:$D$501,Invoices!$B$2:$B$501,">="&DATE(2026,9,1),Invoices!$B$2:$B$501,"<"&DATE(2026,10,1)),2) | C7: =ROUND($B7*9%,2) | D7: =ROUND($B7*9%,2) | E7: =$C7+$D7
A8: TOTAL | B8: =SUM(B2:B7) | C8: =SUM(C2:C7) | D8: =SUM(D2:D7) | E8: =SUM(E2:E7)

Sheet Daily
A1: Date | B1: Units Sold | C1: Revenue (ex-GST)
A2: 46113 | B2: =IF($A2="",0,SUMIFS(InvoiceLines!$E$2:$E$4001,InvoiceLines!$B$2:$B$4001,$A2)) | C2: =IF($A2="",0,ROUND(SUMIFS(InvoiceLines!$G$2:$G$4001,InvoiceLines!$B$2:$B$4001,$A2),2))
A3: 46114 | B3: =IF($A3="",0,SUMIFS(InvoiceLines!$E$2:$E$4001,InvoiceLines!$B$2:$B$4001,$A3)) | C3: =IF($A3="",0,ROUND(SUMIFS(InvoiceLines!$G$2:$G$4001,InvoiceLines!$B$2:$B$4001,$A3),2))
A4: 46115 | B4: =IF($A4="",0,SUMIFS(InvoiceLines!$E$2:$E$4001,InvoiceLines!$B$2:$B$4001,$A4)) | C4: =IF($A4="",0,ROUND(SUMIFS(InvoiceLines!$G$2:$G$4001,InvoiceLines!$B$2:$B$4001,$A4),2))
A5: 46116 | B5: =IF($A5="",0,SUMIFS(InvoiceLines!$E$2:$E$4001,InvoiceLines!$B$2:$B$4001,$A5)) | C5: =IF($A5="",0,ROUND(SUMIFS(InvoiceLines!$G$2:$G$4001,InvoiceLines!$B$2:$B$4001,$A5),2))
A6: 46117 | B6: =IF($A6="",0,SUMIFS(InvoiceLines!$E$2:$E$4001,InvoiceLines!$B$2:$B$4001,$A6)) | C6: =IF($A6="",0,ROUND(SUMIFS(InvoiceLines!$G$2:$G$4001,InvoiceLines!$B$2:$B$4001,$A6),2))
A7: 46118 | B7: =IF($A7="",0,SUMIFS(InvoiceLines!$E$2:$E$4001,InvoiceLines!$B$2:$B$4001,$A7)) | C7: =IF($A7="",0,ROUND(SUMIFS(InvoiceLines!$G$2:$G$4001,InvoiceLines!$B$2:$B$4001,$A7),2))
A8: 46119 | B8: =IF($A8="",0,SUMIFS(InvoiceLines!$E$2:$E$4001,InvoiceLines!$B$2:$B$4001,$A8)) | C8: =IF($A8="",0,ROUND(SUMIFS(InvoiceLines!$G$2:$G$4001,InvoiceLines!$B$2:$B$4001,$A8),2))
A9: 46120 | B9: =IF($A9="",0,SUMIFS(InvoiceLines!$E$2:$E$4001,InvoiceLines!$B$2:$B$4001,$A9)) | C9: =IF($A9="",0,ROUND(SUMIFS(InvoiceLines!$G$2:$G$4001,InvoiceLines!$B$2:$B$4001,$A9),2))
A10: 46121 | B10: =IF($A10="",0,SUMIFS(InvoiceLines!$E$2:$E$4001,InvoiceLines!$B$2:$B$4001,$A10)) | C10: =IF($A10="",0,ROUND(SUMIFS(InvoiceLines!$G$2:$G$4001,InvoiceLines!$B$2:$B$4001,$A10),2))
A11: 46122 | B11: =IF($A11="",0,SUMIFS(InvoiceLines!$E$2:$E$4001,InvoiceLines!$B$2:$B$4001,$A11)) | C11: =IF($A11="",0,ROUND(SUMIFS(InvoiceLines!$G$2:$G$4001,InvoiceLines!$B$2:$B$4001,$A11),2))
A12: 46123 | B12: =IF($A12="",0,SUMIFS(InvoiceLines!$E$2:$E$4001,InvoiceLines!$B$2:$B$4001,$A12)) | C12: =IF($A12="",0,ROUND(SUMIFS(InvoiceLines!$G$2:$G$4001,InvoiceLines!$B$2:$B$4001,$A12),2))
A13: 46124 | B13: =IF($A13="",0,SUMIFS(InvoiceLines!$E$2:$E$4001,InvoiceLines!$B$2:$B$4001,$A13)) | C13: =IF($A13="",0,ROUND(SUMIFS(InvoiceLines!$G$2:$G$4001,InvoiceLines!$B$2:$B$4001,$A13),2))
... A184: 46295 | B184: =IF($A184="",0,SUMIFS(InvoiceLines!$E$2:$E$4001,InvoiceLines!$B$2:$B$4001,$A184)) | C184: =IF($A184="",0,ROUND(SUMIFS(InvoiceLines!$G$2:$G$4001,InvoiceLines!$B$2:$B$4001,$A184),2))
A185: =IF(A184="","",A184+1) | B185: =IF($A185="",0,SUMIFS(InvoiceLines!$E$2:$E$4001,InvoiceLines!$B$2:$B$4001,$A185)) | C185: =IF($A185="",0,ROUND(SUMIFS(InvoiceLines!$G$2:$G$4001,InvoiceLines!$B$2:$B$4001,$A185),2))
A186: =IF(A185="","",A185+1) | B186: =IF($A186="",0,SUMIFS(InvoiceLines!$E$2:$E$4001,InvoiceLines!$B$2:$B$4001,$A186)) | C186: =IF($A186="",0,ROUND(SUMIFS(InvoiceLines!$G$2:$G$4001,InvoiceLines!$B$2:$B$4001,$A186),2))
A187: =IF(A186="","",A186+1) | B187: =IF($A187="",0,SUMIFS(InvoiceLines!$E$2:$E$4001,InvoiceLines!$B$2:$B$4001,$A187)) | C187: =IF($A187="",0,ROUND(SUMIFS(InvoiceLines!$G$2:$G$4001,InvoiceLines!$B$2:$B$4001,$A187),2))
A188: =IF(A187="","",A187+1) | B188: =IF($A188="",0,SUMIFS(InvoiceLines!$E$2:$E$4001,InvoiceLines!$B$2:$B$4001,$A188)) | C188: =IF($A188="",0,ROUND(SUMIFS(InvoiceLines!$G$2:$G$4001,InvoiceLines!$B$2:$B$4001,$A188),2))
A189: =IF(A188="","",A188+1) | B189: =IF($A189="",0,SUMIFS(InvoiceLines!$E$2:$E$4001,InvoiceLines!$B$2:$B$4001,$A189)) | C189: =IF($A189="",0,ROUND(SUMIFS(InvoiceLines!$G$2:$G$4001,InvoiceLines!$B$2:$B$4001,$A189),2))
A190: =IF(A189="","",A189+1) | B190: =IF($A190="",0,SUMIFS(InvoiceLines!$E$2:$E$4001,InvoiceLines!$B$2:$B$4001,$A190)) | C190: =IF($A190="",0,ROUND(SUMIFS(InvoiceLines!$G$2:$G$4001,InvoiceLines!$B$2:$B$4001,$A190),2))
A191: =IF(A190="","",A190+1) | B191: =IF($A191="",0,SUMIFS(InvoiceLines!$E$2:$E$4001,InvoiceLines!$B$2:$B$4001,$A191)) | C191: =IF($A191="",0,ROUND(SUMIFS(InvoiceLines!$G$2:$G$4001,InvoiceLines!$B$2:$B$4001,$A191),2))
A192: =IF(A191="","",A191+1) | B192: =IF($A192="",0,SUMIFS(InvoiceLines!$E$2:$E$4001,InvoiceLines!$B$2:$B$4001,$A192)) | C192: =IF($A192="",0,ROUND(SUMIFS(InvoiceLines!$G$2:$G$4001,InvoiceLines!$B$2:$B$4001,$A192),2))
A193: =IF(A192="","",A192+1) | B193: =IF($A193="",0,SUMIFS(InvoiceLines!$E$2:$E$4001,InvoiceLines!$B$2:$B$4001,$A193)) | C193: =IF($A193="",0,ROUND(SUMIFS(InvoiceLines!$G$2:$G$4001,InvoiceLines!$B$2:$B$4001,$A193),2))
A194: =IF(A193="","",A193+1) | B194: =IF($A194="",0,SUMIFS(InvoiceLines!$E$2:$E$4001,InvoiceLines!$B$2:$B$4001,$A194)) | C194: =IF($A194="",0,ROUND(SUMIFS(InvoiceLines!$G$2:$G$4001,InvoiceLines!$B$2:$B$4001,$A194),2))
A195: =IF(A194="","",A194+1) | B195: =IF($A195="",0,SUMIFS(InvoiceLines!$E$2:$E$4001,InvoiceLines!$B$2:$B$4001,$A195)) | C195: =IF($A195="",0,ROUND(SUMIFS(InvoiceLines!$G$2:$G$4001,InvoiceLines!$B$2:$B$4001,$A195),2))
A196: =IF(A195="","",A195+1) | B196: =IF($A196="",0,SUMIFS(InvoiceLines!$E$2:$E$4001,InvoiceLines!$B$2:$B$4001,$A196)) | C196: =IF($A196="",0,ROUND(SUMIFS(InvoiceLines!$G$2:$G$4001,InvoiceLines!$B$2:$B$4001,$A196),2))
... A401: =IF(A400="","",A400+1) | B401: =IF($A401="",0,SUMIFS(InvoiceLines!$E$2:$E$4001,InvoiceLines!$B$2:$B$4001,$A401)) | C401: =IF($A401="",0,ROUND(SUMIFS(InvoiceLines!$G$2:$G$4001,InvoiceLines!$B$2:$B$4001,$A401),2))

Sheet Checks
A1: Check | B1: Result | C1: What it proves
A2: Invoice grand totals = subtotal + GST | B2: =SUM(Invoices!$F$2:$F$501)=SUM(Invoices!$D$2:$D$501)+SUM(Invoices!$E$2:$E$501) | C2: Register math ties out
A3: Every line total = ROUND(qty × rate, 2) | B3: =SUMPRODUCT((InvoiceLines!$G$2:$G$4001<>ROUND(InvoiceLines!$E$2:$E$4001*InvoiceLines!$F$2:$F$4001,2))*(InvoiceLines!$A$2:$A$4001<>""))=0 | C3: No line-item pricing errors
A4: GST ≈ 18% of taxable (within rounding) | B4: =ABS(SUM(Invoices!$E$2:$E$501)-SUM(Invoices!$D$2:$D$501)*0.18)<0.5 | C4: Tax math sane
A5: No negative closing stock | B5: =SUMPRODUCT((Inventory!$F$2:$F$21<0)*1)=0 | C5: Stock counts consistent
A6: Invoice numbers unique | B6: =SUMPRODUCT((COUNTIF(Invoices!$A$2:$A$501,Invoices!$A$2:$A$501)>1)*(Invoices!$A$2:$A$501<>""))=0 | C6: No duplicate invoices
A7: Balance = grand − paid on every invoice | B7: =SUMPRODUCT(ABS(Invoices!$H$2:$H$501-(Invoices!$F$2:$F$501-Invoices!$G$2:$G$501)))<0.01 | C7: Receivables reconcile
A8: GST summary ties to invoice register | B8: =ABS(SUM(GST_Summary!$B$2:$B$7)-SUM(Invoices!$D$2:$D$501))<0.01 | C8: Monthly tax report reconciles
A9: Daily revenue ties to invoice lines | B9: =ABS(SUM(Daily!$C$2:$C$401)-SUM(InvoiceLines!$G$2:$G$4001))<0.01 | C9: Daily trend reconciles

Sheet Guide
A1: AquaBill — operator guide (AquaPure Distributors, Patna)
A3: What this is | B3: One workbook that runs billing, sales tracking and inventory for a packaged drinking-water distributor. Every figure is a live formula over the raw tables — paste new rows and the dashboard, GST summary and stock levels update.
A4: Add an invoice | B4: 1) Append one row per line item on InvoiceLines (Inv No, Date, Line, SKU, Qty, Rate). 2) Append one row on Invoices (Inv No, Date, Customer, Paid). Subtotal, GST, Grand, Balance and Status compute themselves.
A5: Record stock-in | B5: Append rows on Purchases (Date, SKU, Lot No, Qty, Rate). Inventory 'Purchased In' and 'Closing Stock' update automatically.
A6: Record a payment | B6: Update the Paid column on the invoice's row in Invoices. Balance and Status (Paid / Partial / Unpaid) recalc; Outstanding receivables on the dashboard follows.
A7: Change the GST rate | B7: Find/replace '18%' in the Invoices sheet formulas (and 9% in GST_Summary). The Checks sheet will confirm the new rate ties out.
A8: Trust but verify | B8: Open the Checks sheet after every paste — all 8 checks must read TRUE. They reconcile the register, tax, stock and daily trend against each other.
A9: Note | B9: All customers, transactions and figures are fictional demo data generated deterministically (generate.py --seed 20261013) for evaluation.
