Workbook
Name AsOf: Dashboard!$B$3
Name BookOpen: Dashboard!$B$4
Name PeriodStart: Dashboard!$E$1
Name PeriodEnd: Dashboard!$E$2

Sheet Raw_AP
A1: Bill ID | B1: Vendor | C1: Date | D1: Due Date | E1: Amount | F1: Paid Date | G1: Pay Mode | H1: Cleared | I1: Category | J1: Days Overdue | K1: Aging Bucket | L1: Outstanding
A2: BILL-0001 | B2: Das Brothers | C2: 46124 | D2: 46154 | E2: 134023 | G2: bank | H2: 1 | I2: Utilities | J2: =IF(F2="",AsOf-D2,F2-D2) | K2: =IF(F2<>"","Paid",IF(J2<=0,"Current",IF(J2<=30,"1-30",IF(J2<=60,"31-60",IF(J2<=90,"61-90","90+"))))) | L2: =IF(F2="",E2,0)
A3: BILL-0002 | B3: Verma Agro | C3: 46114 | D3: 46144 | E3: 178568 | F3: 46157 | G3: bank | H3: 1 | I3: Services | J3: =IF(F3="",AsOf-D3,F3-D3) | K3: =IF(F3<>"","Paid",IF(J3<=0,"Current",IF(J3<=30,"1-30",IF(J3<=60,"31-60",IF(J3<=90,"61-90","90+"))))) | L3: =IF(F3="",E3,0)
A4: BILL-0003 | B4: Verma Agro | C4: 46128 | D4: 46158 | E4: 230083 | F4: 46148 | G4: bank | H4: 1 | I4: Purchases | J4: =IF(F4="",AsOf-D4,F4-D4) | K4: =IF(F4<>"","Paid",IF(J4<=0,"Current",IF(J4<=30,"1-30",IF(J4<=60,"31-60",IF(J4<=90,"61-90","90+"))))) | L4: =IF(F4="",E4,0)
A5: BILL-0004 | B5: Singh & Co | C5: 46119 | D5: 46149 | E5: 105277 | G5: bank | H5: 1 | I5: Services | J5: =IF(F5="",AsOf-D5,F5-D5) | K5: =IF(F5<>"","Paid",IF(J5<=0,"Current",IF(J5<=30,"1-30",IF(J5<=60,"31-60",IF(J5<=90,"61-90","90+"))))) | L5: =IF(F5="",E5,0)
A6: BILL-0005 | B6: Mehta Enterprises | C6: 46126 | D6: 46156 | E6: 179327 | G6: bank | H6: 1 | I6: Rent | J6: =IF(F6="",AsOf-D6,F6-D6) | K6: =IF(F6<>"","Paid",IF(J6<=0,"Current",IF(J6<=30,"1-30",IF(J6<=60,"31-60",IF(J6<=90,"61-90","90+"))))) | L6: =IF(F6="",E6,0)
A7: BILL-0006 | B7: Das Brothers | C7: 46129 | D7: 46159 | E7: 44722 | G7: cheque | H7: 0 | I7: Purchases | J7: =IF(F7="",AsOf-D7,F7-D7) | K7: =IF(F7<>"","Paid",IF(J7<=0,"Current",IF(J7<=30,"1-30",IF(J7<=60,"31-60",IF(J7<=90,"61-90","90+"))))) | L7: =IF(F7="",E7,0)
A8: BILL-0007 | B8: Patel Wholesale | C8: 46123 | D8: 46153 | E8: 98450 | F8: 46142 | G8: bank | H8: 1 | I8: Utilities | J8: =IF(F8="",AsOf-D8,F8-D8) | K8: =IF(F8<>"","Paid",IF(J8<=0,"Current",IF(J8<=30,"1-30",IF(J8<=60,"31-60",IF(J8<=90,"61-90","90+"))))) | L8: =IF(F8="",E8,0)
A9: BILL-0008 | B9: Mehta Enterprises | C9: 46146 | D9: 46176 | E9: 144302 | F9: 46162 | G9: bank | H9: 1 | I9: Purchases | J9: =IF(F9="",AsOf-D9,F9-D9) | K9: =IF(F9<>"","Paid",IF(J9<=0,"Current",IF(J9<=30,"1-30",IF(J9<=60,"31-60",IF(J9<=90,"61-90","90+"))))) | L9: =IF(F9="",E9,0)
A10: BILL-0009 | B10: Khan Distributors | C10: 46170 | D10: 46200 | E10: 236901 | F10: 46188 | G10: bank | H10: 1 | I10: Utilities | J10: =IF(F10="",AsOf-D10,F10-D10) | K10: =IF(F10<>"","Paid",IF(J10<=0,"Current",IF(J10<=30,"1-30",IF(J10<=60,"31-60",IF(J10<=90,"61-90","90+"))))) | L10: =IF(F10="",E10,0)
A11: BILL-0010 | B11: Mehta Enterprises | C11: 46166 | D11: 46196 | E11: 104360 | G11: bank | H11: 1 | I11: Utilities | J11: =IF(F11="",AsOf-D11,F11-D11) | K11: =IF(F11<>"","Paid",IF(J11<=0,"Current",IF(J11<=30,"1-30",IF(J11<=60,"31-60",IF(J11<=90,"61-90","90+"))))) | L11: =IF(F11="",E11,0)
A12: BILL-0011 | B12: Das Brothers | C12: 46158 | D12: 46188 | E12: 37107 | F12: 46174 | G12: bank | H12: 1 | I12: Services | J12: =IF(F12="",AsOf-D12,F12-D12) | K12: =IF(F12<>"","Paid",IF(J12<=0,"Current",IF(J12<=30,"1-30",IF(J12<=60,"31-60",IF(J12<=90,"61-90","90+"))))) | L12: =IF(F12="",E12,0)
A13: BILL-0012 | B13: Sharma Traders | C13: 46146 | D13: 46176 | E13: 230590 | F13: 46163 | G13: bank | H13: 1 | I13: Marketing | J13: =IF(F13="",AsOf-D13,F13-D13) | K13: =IF(F13<>"","Paid",IF(J13<=0,"Current",IF(J13<=30,"1-30",IF(J13<=60,"31-60",IF(J13<=90,"61-90","90+"))))) | L13: =IF(F13="",E13,0)
A14: BILL-0013 | B14: Das Brothers | C14: 46155 | D14: 46185 | E14: 216515 | F14: 46181 | G14: bank | H14: 1 | I14: Purchases | J14: =IF(F14="",AsOf-D14,F14-D14) | K14: =IF(F14<>"","Paid",IF(J14<=0,"Current",IF(J14<=30,"1-30",IF(J14<=60,"31-60",IF(J14<=90,"61-90","90+"))))) | L14: =IF(F14="",E14,0)
A15: BILL-0014 | B15: Sharma Traders | C15: 46174 | D15: 46204 | E15: 244491 | F15: 46211 | G15: cheque | H15: 1 | I15: Rent | J15: =IF(F15="",AsOf-D15,F15-D15) | K15: =IF(F15<>"","Paid",IF(J15<=0,"Current",IF(J15<=30,"1-30",IF(J15<=60,"31-60",IF(J15<=90,"61-90","90+"))))) | L15: =IF(F15="",E15,0)
A16: BILL-0015 | B16: Das Brothers | C16: 46191 | D16: 46221 | E16: 156734 | F16: 46224 | G16: cheque | H16: 1 | I16: Purchases | J16: =IF(F16="",AsOf-D16,F16-D16) | K16: =IF(F16<>"","Paid",IF(J16<=0,"Current",IF(J16<=30,"1-30",IF(J16<=60,"31-60",IF(J16<=90,"61-90","90+"))))) | L16: =IF(F16="",E16,0)
A17: BILL-0016 | B17: Mehta Enterprises | C17: 46198 | D17: 46228 | E17: 136569 | F17: 46231 | G17: bank | H17: 1 | I17: Rent | J17: =IF(F17="",AsOf-D17,F17-D17) | K17: =IF(F17<>"","Paid",IF(J17<=0,"Current",IF(J17<=30,"1-30",IF(J17<=60,"31-60",IF(J17<=90,"61-90","90+"))))) | L17: =IF(F17="",E17,0)
A18: BILL-0017 | B18: Singh & Co | C18: 46192 | D18: 46222 | E18: 82079 | F18: 46216 | G18: bank | H18: 1 | I18: Rent | J18: =IF(F18="",AsOf-D18,F18-D18) | K18: =IF(F18<>"","Paid",IF(J18<=0,"Current",IF(J18<=30,"1-30",IF(J18<=60,"31-60",IF(J18<=90,"61-90","90+"))))) | L18: =IF(F18="",E18,0)
A19: BILL-0018 | B19: Singh & Co | C19: 46174 | D19: 46204 | E19: 237028 | F19: 46180 | G19: cheque | H19: 1 | I19: Purchases | J19: =IF(F19="",AsOf-D19,F19-D19) | K19: =IF(F19<>"","Paid",IF(J19<=0,"Current",IF(J19<=30,"1-30",IF(J19<=60,"31-60",IF(J19<=90,"61-90","90+"))))) | L19: =IF(F19="",E19,0)
A20: BILL-0019 | B20: Das Brothers | C20: 46184 | D20: 46214 | E20: 209504 | F20: 46225 | G20: bank | H20: 1 | I20: Purchases | J20: =IF(F20="",AsOf-D20,F20-D20) | K20: =IF(F20<>"","Paid",IF(J20<=0,"Current",IF(J20<=30,"1-30",IF(J20<=60,"31-60",IF(J20<=90,"61-90","90+"))))) | L20: =IF(F20="",E20,0)
A21: BILL-0020 | B21: Mehta Enterprises | C21: 46187 | D21: 46217 | E21: 221258 | F21: 46231 | G21: cheque | H21: 0 | I21: Purchases | J21: =IF(F21="",AsOf-D21,F21-D21) | K21: =IF(F21<>"","Paid",IF(J21<=0,"Current",IF(J21<=30,"1-30",IF(J21<=60,"31-60",IF(J21<=90,"61-90","90+"))))) | L21: =IF(F21="",E21,0)
A22: BILL-0021 | B22: Gupta Supplies | C22: 46225 | D22: 46255 | E22: 123224 | F22: 46264 | G22: bank | H22: 1 | I22: Purchases | J22: =IF(F22="",AsOf-D22,F22-D22) | K22: =IF(F22<>"","Paid",IF(J22<=0,"Current",IF(J22<=30,"1-30",IF(J22<=60,"31-60",IF(J22<=90,"61-90","90+"))))) | L22: =IF(F22="",E22,0)
A23: BILL-0022 | B23: Das Brothers | C23: 46219 | D23: 46249 | E23: 243729 | F23: 46255 | G23: bank | H23: 1 | I23: Marketing | J23: =IF(F23="",AsOf-D23,F23-D23) | K23: =IF(F23<>"","Paid",IF(J23<=0,"Current",IF(J23<=30,"1-30",IF(J23<=60,"31-60",IF(J23<=90,"61-90","90+"))))) | L23: =IF(F23="",E23,0)
A24: BILL-0023 | B24: Patel Wholesale | C24: 46214 | D24: 46244 | E24: 92031 | F24: 46253 | G24: cheque | H24: 0 | I24: Purchases | J24: =IF(F24="",AsOf-D24,F24-D24) | K24: =IF(F24<>"","Paid",IF(J24<=0,"Current",IF(J24<=30,"1-30",IF(J24<=60,"31-60",IF(J24<=90,"61-90","90+"))))) | L24: =IF(F24="",E24,0)
A25: BILL-0024 | B25: Verma Agro | C25: 46227 | D25: 46257 | E25: 141570 | G25: bank | H25: 1 | I25: Services | J25: =IF(F25="",AsOf-D25,F25-D25) | K25: =IF(F25<>"","Paid",IF(J25<=0,"Current",IF(J25<=30,"1-30",IF(J25<=60,"31-60",IF(J25<=90,"61-90","90+"))))) | L25: =IF(F25="",E25,0)
A26: BILL-0025 | B26: Singh & Co | C26: 46227 | D26: 46257 | E26: 79595 | F26: 46243 | G26: bank | H26: 1 | I26: Purchases | J26: =IF(F26="",AsOf-D26,F26-D26) | K26: =IF(F26<>"","Paid",IF(J26<=0,"Current",IF(J26<=30,"1-30",IF(J26<=60,"31-60",IF(J26<=90,"61-90","90+"))))) | L26: =IF(F26="",E26,0)
A27: BILL-0026 | B27: Mehta Enterprises | C27: 46209 | D27: 46239 | E27: 152411 | F27: 46248 | G27: bank | H27: 1 | I27: Purchases | J27: =IF(F27="",AsOf-D27,F27-D27) | K27: =IF(F27<>"","Paid",IF(J27<=0,"Current",IF(J27<=30,"1-30",IF(J27<=60,"31-60",IF(J27<=90,"61-90","90+"))))) | L27: =IF(F27="",E27,0)
A28: BILL-0027 | B28: Mehta Enterprises | C28: 46237 | D28: 46267 | E28: 238827 | G28: bank | H28: 1 | I28: Utilities | J28: =IF(F28="",AsOf-D28,F28-D28) | K28: =IF(F28<>"","Paid",IF(J28<=0,"Current",IF(J28<=30,"1-30",IF(J28<=60,"31-60",IF(J28<=90,"61-90","90+"))))) | L28: =IF(F28="",E28,0)
A29: BILL-0028 | B29: Mehta Enterprises | C29: 46262 | D29: 46292 | E29: 131235 | F29: 46285 | G29: bank | H29: 1 | I29: Rent | J29: =IF(F29="",AsOf-D29,F29-D29) | K29: =IF(F29<>"","Paid",IF(J29<=0,"Current",IF(J29<=30,"1-30",IF(J29<=60,"31-60",IF(J29<=90,"61-90","90+"))))) | L29: =IF(F29="",E29,0)
A30: BILL-0029 | B30: Khan Distributors | C30: 46249 | D30: 46279 | E30: 165923 | F30: 46288 | G30: bank | H30: 1 | I30: Services | J30: =IF(F30="",AsOf-D30,F30-D30) | K30: =IF(F30<>"","Paid",IF(J30<=0,"Current",IF(J30<=30,"1-30",IF(J30<=60,"31-60",IF(J30<=90,"61-90","90+"))))) | L30: =IF(F30="",E30,0)
A31: BILL-0030 | B31: Singh & Co | C31: 46262 | D31: 46292 | E31: 40649 | F31: 46293 | G31: bank | H31: 1 | I31: Services | J31: =IF(F31="",AsOf-D31,F31-D31) | K31: =IF(F31<>"","Paid",IF(J31<=0,"Current",IF(J31<=30,"1-30",IF(J31<=60,"31-60",IF(J31<=90,"61-90","90+"))))) | L31: =IF(F31="",E31,0)
A32: BILL-0031 | B32: Khan Distributors | C32: 46262 | D32: 46292 | E32: 119327 | F32: 46283 | G32: cheque | H32: 0 | I32: Services | J32: =IF(F32="",AsOf-D32,F32-D32) | K32: =IF(F32<>"","Paid",IF(J32<=0,"Current",IF(J32<=30,"1-30",IF(J32<=60,"31-60",IF(J32<=90,"61-90","90+"))))) | L32: =IF(F32="",E32,0)
A33: BILL-0032 | B33: Sharma Traders | C33: 46236 | D33: 46266 | E33: 64946 | G33: cheque | H33: 0 | I33: Services | J33: =IF(F33="",AsOf-D33,F33-D33) | K33: =IF(F33<>"","Paid",IF(J33<=0,"Current",IF(J33<=30,"1-30",IF(J33<=60,"31-60",IF(J33<=90,"61-90","90+"))))) | L33: =IF(F33="",E33,0)
A34: BILL-0033 | B34: Sharma Traders | C34: 46283 | D34: 46313 | E34: 80941 | F34: 46295 | G34: bank | H34: 1 | I34: Marketing | J34: =IF(F34="",AsOf-D34,F34-D34) | K34: =IF(F34<>"","Paid",IF(J34<=0,"Current",IF(J34<=30,"1-30",IF(J34<=60,"31-60",IF(J34<=90,"61-90","90+"))))) | L34: =IF(F34="",E34,0)
A35: BILL-0034 | B35: Verma Agro | C35: 46279 | D35: 46309 | E35: 99122 | F35: 46285 | G35: bank | H35: 1 | I35: Rent | J35: =IF(F35="",AsOf-D35,F35-D35) | K35: =IF(F35<>"","Paid",IF(J35<=0,"Current",IF(J35<=30,"1-30",IF(J35<=60,"31-60",IF(J35<=90,"61-90","90+"))))) | L35: =IF(F35="",E35,0)
A36: BILL-0035 | B36: Das Brothers | C36: 46276 | D36: 46306 | E36: 137111 | F36: 46295 | G36: bank | H36: 1 | I36: Purchases | J36: =IF(F36="",AsOf-D36,F36-D36) | K36: =IF(F36<>"","Paid",IF(J36<=0,"Current",IF(J36<=30,"1-30",IF(J36<=60,"31-60",IF(J36<=90,"61-90","90+"))))) | L36: =IF(F36="",E36,0)
A37: BILL-0036 | B37: Sharma Traders | C37: 46281 | D37: 46311 | E37: 23239 | G37: bank | H37: 1 | I37: Services | J37: =IF(F37="",AsOf-D37,F37-D37) | K37: =IF(F37<>"","Paid",IF(J37<=0,"Current",IF(J37<=30,"1-30",IF(J37<=60,"31-60",IF(J37<=90,"61-90","90+"))))) | L37: =IF(F37="",E37,0)
A38: BILL-0037 | B38: Mehta Enterprises | C38: 46292 | D38: 46322 | E38: 149022 | F38: 46292 | G38: bank | H38: 1 | I38: Rent | J38: =IF(F38="",AsOf-D38,F38-D38) | K38: =IF(F38<>"","Paid",IF(J38<=0,"Current",IF(J38<=30,"1-30",IF(J38<=60,"31-60",IF(J38<=90,"61-90","90+"))))) | L38: =IF(F38="",E38,0)
A39: BILL-0038 | B39: Singh & Co | C39: 46292 | D39: 46322 | E39: 26970 | F39: 46295 | G39: bank | H39: 1 | I39: Purchases | J39: =IF(F39="",AsOf-D39,F39-D39) | K39: =IF(F39<>"","Paid",IF(J39<=0,"Current",IF(J39<=30,"1-30",IF(J39<=60,"31-60",IF(J39<=90,"61-90","90+"))))) | L39: =IF(F39="",E39,0)
A40: BILL-0039 | B40: Mehta Enterprises | C40: 46270 | D40: 46300 | E40: 134415 | F40: 46291 | G40: bank | H40: 1 | I40: Marketing | J40: =IF(F40="",AsOf-D40,F40-D40) | K40: =IF(F40<>"","Paid",IF(J40<=0,"Current",IF(J40<=30,"1-30",IF(J40<=60,"31-60",IF(J40<=90,"61-90","90+"))))) | L40: =IF(F40="",E40,0)

Sheet Raw_AR
A1: Invoice ID | B1: Customer | C1: Date | D1: Due Date | E1: Amount | F1: Paid Date | G1: In Transit | H1: Days Overdue | I1: Aging Bucket | J1: Outstanding
A2: INV-0001 | B2: Fresh Bazar | C2: 46130 | D2: 46151 | E2: 51551 | F2: 46159 | G2: 0 | H2: =IF(F2="",AsOf-D2,F2-D2) | I2: =IF(F2<>"","Paid",IF(H2<=0,"Current",IF(H2<=30,"1-30",IF(H2<=60,"31-60",IF(H2<=90,"61-90","90+"))))) | J2: =IF(F2="",E2,0)
A3: INV-0002 | B3: Metro Retail | C3: 46137 | D3: 46158 | E3: 95943 | F3: 46150 | G3: 0 | H3: =IF(F3="",AsOf-D3,F3-D3) | I3: =IF(F3<>"","Paid",IF(H3<=0,"Current",IF(H3<=30,"1-30",IF(H3<=60,"31-60",IF(H3<=90,"61-90","90+"))))) | J3: =IF(F3="",E3,0)
A4: INV-0003 | B4: Daily Needs | C4: 46137 | D4: 46158 | E4: 129469 | G4: 0 | H4: =IF(F4="",AsOf-D4,F4-D4) | I4: =IF(F4<>"","Paid",IF(H4<=0,"Current",IF(H4<=30,"1-30",IF(H4<=60,"31-60",IF(H4<=90,"61-90","90+"))))) | J4: =IF(F4="",E4,0)
A5: INV-0004 | B5: Kiran Stores | C5: 46140 | D5: 46161 | E5: 385077 | F5: 46149 | G5: 0 | H5: =IF(F5="",AsOf-D5,F5-D5) | I5: =IF(F5<>"","Paid",IF(H5<=0,"Current",IF(H5<=30,"1-30",IF(H5<=60,"31-60",IF(H5<=90,"61-90","90+"))))) | J5: =IF(F5="",E5,0)
A6: INV-0005 | B6: Star Market | C6: 46115 | D6: 46136 | E6: 236189 | F6: 46142 | G6: 0 | H6: =IF(F6="",AsOf-D6,F6-D6) | I6: =IF(F6<>"","Paid",IF(H6<=0,"Current",IF(H6<=30,"1-30",IF(H6<=60,"31-60",IF(H6<=90,"61-90","90+"))))) | J6: =IF(F6="",E6,0)
A7: INV-0006 | B7: Daily Needs | C7: 46125 | D7: 46146 | E7: 399920 | F7: 46160 | G7: 0 | H7: =IF(F7="",AsOf-D7,F7-D7) | I7: =IF(F7<>"","Paid",IF(H7<=0,"Current",IF(H7<=30,"1-30",IF(H7<=60,"31-60",IF(H7<=90,"61-90","90+"))))) | J7: =IF(F7="",E7,0)
A8: INV-0007 | B8: Daily Needs | C8: 46139 | D8: 46160 | E8: 189632 | F8: 46167 | G8: 0 | H8: =IF(F8="",AsOf-D8,F8-D8) | I8: =IF(F8<>"","Paid",IF(H8<=0,"Current",IF(H8<=30,"1-30",IF(H8<=60,"31-60",IF(H8<=90,"61-90","90+"))))) | J8: =IF(F8="",E8,0)
A9: INV-0008 | B9: Metro Retail | C9: 46157 | D9: 46178 | E9: 83030 | F9: 46165 | G9: 0 | H9: =IF(F9="",AsOf-D9,F9-D9) | I9: =IF(F9<>"","Paid",IF(H9<=0,"Current",IF(H9<=30,"1-30",IF(H9<=60,"31-60",IF(H9<=90,"61-90","90+"))))) | J9: =IF(F9="",E9,0)
A10: INV-0009 | B10: Apna Bazar | C10: 46153 | D10: 46174 | E10: 171542 | F10: 46184 | G10: 0 | H10: =IF(F10="",AsOf-D10,F10-D10) | I10: =IF(F10<>"","Paid",IF(H10<=0,"Current",IF(H10<=30,"1-30",IF(H10<=60,"31-60",IF(H10<=90,"61-90","90+"))))) | J10: =IF(F10="",E10,0)
A11: INV-0010 | B11: Apna Bazar | C11: 46162 | D11: 46183 | E11: 88037 | G11: 0 | H11: =IF(F11="",AsOf-D11,F11-D11) | I11: =IF(F11<>"","Paid",IF(H11<=0,"Current",IF(H11<=30,"1-30",IF(H11<=60,"31-60",IF(H11<=90,"61-90","90+"))))) | J11: =IF(F11="",E11,0)
A12: INV-0011 | B12: Metro Retail | C12: 46162 | D12: 46183 | E12: 113098 | F12: 46182 | G12: 0 | H12: =IF(F12="",AsOf-D12,F12-D12) | I12: =IF(F12<>"","Paid",IF(H12<=0,"Current",IF(H12<=30,"1-30",IF(H12<=60,"31-60",IF(H12<=90,"61-90","90+"))))) | J12: =IF(F12="",E12,0)
A13: INV-0012 | B13: Value Plus | C13: 46155 | D13: 46176 | E13: 60287 | F13: 46171 | G13: 0 | H13: =IF(F13="",AsOf-D13,F13-D13) | I13: =IF(F13<>"","Paid",IF(H13<=0,"Current",IF(H13<=30,"1-30",IF(H13<=60,"31-60",IF(H13<=90,"61-90","90+"))))) | J13: =IF(F13="",E13,0)
A14: INV-0013 | B14: Local Hub | C14: 46178 | D14: 46199 | E14: 263391 | F14: 46211 | G14: 0 | H14: =IF(F14="",AsOf-D14,F14-D14) | I14: =IF(F14<>"","Paid",IF(H14<=0,"Current",IF(H14<=30,"1-30",IF(H14<=60,"31-60",IF(H14<=90,"61-90","90+"))))) | J14: =IF(F14="",E14,0)
A15: INV-0014 | B15: Metro Retail | C15: 46186 | D15: 46207 | E15: 139901 | G15: 0 | H15: =IF(F15="",AsOf-D15,F15-D15) | I15: =IF(F15<>"","Paid",IF(H15<=0,"Current",IF(H15<=30,"1-30",IF(H15<=60,"31-60",IF(H15<=90,"61-90","90+"))))) | J15: =IF(F15="",E15,0)
A16: INV-0015 | B16: City Mart | C16: 46190 | D16: 46211 | E16: 231128 | F16: 46200 | G16: 0 | H16: =IF(F16="",AsOf-D16,F16-D16) | I16: =IF(F16<>"","Paid",IF(H16<=0,"Current",IF(H16<=30,"1-30",IF(H16<=60,"31-60",IF(H16<=90,"61-90","90+"))))) | J16: =IF(F16="",E16,0)
A17: INV-0016 | B17: Green Grocer | C17: 46193 | D17: 46214 | E17: 213165 | F17: 46205 | G17: 0 | H17: =IF(F17="",AsOf-D17,F17-D17) | I17: =IF(F17<>"","Paid",IF(H17<=0,"Current",IF(H17<=30,"1-30",IF(H17<=60,"31-60",IF(H17<=90,"61-90","90+"))))) | J17: =IF(F17="",E17,0)
A18: INV-0017 | B18: Local Hub | C18: 46191 | D18: 46212 | E18: 122385 | F18: 46224 | G18: 0 | H18: =IF(F18="",AsOf-D18,F18-D18) | I18: =IF(F18<>"","Paid",IF(H18<=0,"Current",IF(H18<=30,"1-30",IF(H18<=60,"31-60",IF(H18<=90,"61-90","90+"))))) | J18: =IF(F18="",E18,0)
A19: INV-0018 | B19: Star Market | C19: 46181 | D19: 46202 | E19: 280358 | F19: 46214 | G19: 0 | H19: =IF(F19="",AsOf-D19,F19-D19) | I19: =IF(F19<>"","Paid",IF(H19<=0,"Current",IF(H19<=30,"1-30",IF(H19<=60,"31-60",IF(H19<=90,"61-90","90+"))))) | J19: =IF(F19="",E19,0)
A20: INV-0019 | B20: City Mart | C20: 46189 | D20: 46210 | E20: 139208 | G20: 0 | H20: =IF(F20="",AsOf-D20,F20-D20) | I20: =IF(F20<>"","Paid",IF(H20<=0,"Current",IF(H20<=30,"1-30",IF(H20<=60,"31-60",IF(H20<=90,"61-90","90+"))))) | J20: =IF(F20="",E20,0)
A21: INV-0020 | B21: Daily Needs | C21: 46212 | D21: 46233 | E21: 368240 | F21: 46236 | G21: 0 | H21: =IF(F21="",AsOf-D21,F21-D21) | I21: =IF(F21<>"","Paid",IF(H21<=0,"Current",IF(H21<=30,"1-30",IF(H21<=60,"31-60",IF(H21<=90,"61-90","90+"))))) | J21: =IF(F21="",E21,0)
A22: INV-0021 | B22: City Mart | C22: 46221 | D22: 46242 | E22: 301579 | F22: 46255 | G22: 0 | H22: =IF(F22="",AsOf-D22,F22-D22) | I22: =IF(F22<>"","Paid",IF(H22<=0,"Current",IF(H22<=30,"1-30",IF(H22<=60,"31-60",IF(H22<=90,"61-90","90+"))))) | J22: =IF(F22="",E22,0)
A23: INV-0022 | B23: Metro Retail | C23: 46207 | D23: 46228 | E23: 237961 | F23: 46210 | G23: 0 | H23: =IF(F23="",AsOf-D23,F23-D23) | I23: =IF(F23<>"","Paid",IF(H23<=0,"Current",IF(H23<=30,"1-30",IF(H23<=60,"31-60",IF(H23<=90,"61-90","90+"))))) | J23: =IF(F23="",E23,0)
A24: INV-0023 | B24: Value Plus | C24: 46228 | D24: 46249 | E24: 149428 | F24: 46242 | G24: 0 | H24: =IF(F24="",AsOf-D24,F24-D24) | I24: =IF(F24<>"","Paid",IF(H24<=0,"Current",IF(H24<=30,"1-30",IF(H24<=60,"31-60",IF(H24<=90,"61-90","90+"))))) | J24: =IF(F24="",E24,0)
A25: INV-0024 | B25: Kiran Stores | C25: 46204 | D25: 46225 | E25: 87052 | F25: 46209 | G25: 0 | H25: =IF(F25="",AsOf-D25,F25-D25) | I25: =IF(F25<>"","Paid",IF(H25<=0,"Current",IF(H25<=30,"1-30",IF(H25<=60,"31-60",IF(H25<=90,"61-90","90+"))))) | J25: =IF(F25="",E25,0)
A26: INV-0025 | B26: Star Market | C26: 46255 | D26: 46276 | E26: 356914 | F26: 46287 | G26: 0 | H26: =IF(F26="",AsOf-D26,F26-D26) | I26: =IF(F26<>"","Paid",IF(H26<=0,"Current",IF(H26<=30,"1-30",IF(H26<=60,"31-60",IF(H26<=90,"61-90","90+"))))) | J26: =IF(F26="",E26,0)
A27: INV-0026 | B27: Fresh Bazar | C27: 46253 | D27: 46274 | E27: 103365 | F27: 46274 | G27: 0 | H27: =IF(F27="",AsOf-D27,F27-D27) | I27: =IF(F27<>"","Paid",IF(H27<=0,"Current",IF(H27<=30,"1-30",IF(H27<=60,"31-60",IF(H27<=90,"61-90","90+"))))) | J27: =IF(F27="",E27,0)
A28: INV-0027 | B28: Apna Bazar | C28: 46252 | D28: 46273 | E28: 290257 | F28: 46265 | G28: 0 | H28: =IF(F28="",AsOf-D28,F28-D28) | I28: =IF(F28<>"","Paid",IF(H28<=0,"Current",IF(H28<=30,"1-30",IF(H28<=60,"31-60",IF(H28<=90,"61-90","90+"))))) | J28: =IF(F28="",E28,0)
A29: INV-0028 | B29: City Mart | C29: 46241 | D29: 46262 | E29: 157342 | F29: 46266 | G29: 0 | H29: =IF(F29="",AsOf-D29,F29-D29) | I29: =IF(F29<>"","Paid",IF(H29<=0,"Current",IF(H29<=30,"1-30",IF(H29<=60,"31-60",IF(H29<=90,"61-90","90+"))))) | J29: =IF(F29="",E29,0)
A30: INV-0029 | B30: Green Grocer | C30: 46244 | D30: 46265 | E30: 184200 | F30: 46252 | G30: 0 | H30: =IF(F30="",AsOf-D30,F30-D30) | I30: =IF(F30<>"","Paid",IF(H30<=0,"Current",IF(H30<=30,"1-30",IF(H30<=60,"31-60",IF(H30<=90,"61-90","90+"))))) | J30: =IF(F30="",E30,0)
A31: INV-0030 | B31: Apna Bazar | C31: 46259 | D31: 46280 | E31: 76967 | G31: 0 | H31: =IF(F31="",AsOf-D31,F31-D31) | I31: =IF(F31<>"","Paid",IF(H31<=0,"Current",IF(H31<=30,"1-30",IF(H31<=60,"31-60",IF(H31<=90,"61-90","90+"))))) | J31: =IF(F31="",E31,0)
A32: INV-0031 | B32: Daily Needs | C32: 46256 | D32: 46277 | E32: 64303 | F32: 46291 | G32: 0 | H32: =IF(F32="",AsOf-D32,F32-D32) | I32: =IF(F32<>"","Paid",IF(H32<=0,"Current",IF(H32<=30,"1-30",IF(H32<=60,"31-60",IF(H32<=90,"61-90","90+"))))) | J32: =IF(F32="",E32,0)
A33: INV-0032 | B33: Local Hub | C33: 46276 | D33: 46297 | E33: 242795 | F33: 46294 | G33: 1 | H33: =IF(F33="",AsOf-D33,F33-D33) | I33: =IF(F33<>"","Paid",IF(H33<=0,"Current",IF(H33<=30,"1-30",IF(H33<=60,"31-60",IF(H33<=90,"61-90","90+"))))) | J33: =IF(F33="",E33,0)
A34: INV-0033 | B34: Star Market | C34: 46286 | D34: 46307 | E34: 214272 | F34: 46293 | G34: 1 | H34: =IF(F34="",AsOf-D34,F34-D34) | I34: =IF(F34<>"","Paid",IF(H34<=0,"Current",IF(H34<=30,"1-30",IF(H34<=60,"31-60",IF(H34<=90,"61-90","90+"))))) | J34: =IF(F34="",E34,0)
A35: INV-0034 | B35: Local Hub | C35: 46267 | D35: 46288 | E35: 231991 | F35: 46280 | G35: 0 | H35: =IF(F35="",AsOf-D35,F35-D35) | I35: =IF(F35<>"","Paid",IF(H35<=0,"Current",IF(H35<=30,"1-30",IF(H35<=60,"31-60",IF(H35<=90,"61-90","90+"))))) | J35: =IF(F35="",E35,0)
A36: INV-0035 | B36: Value Plus | C36: 46290 | D36: 46311 | E36: 57837 | F36: 46295 | G36: 1 | H36: =IF(F36="",AsOf-D36,F36-D36) | I36: =IF(F36<>"","Paid",IF(H36<=0,"Current",IF(H36<=30,"1-30",IF(H36<=60,"31-60",IF(H36<=90,"61-90","90+"))))) | J36: =IF(F36="",E36,0)
A37: INV-0036 | B37: Metro Retail | C37: 46272 | D37: 46293 | E37: 260619 | F37: 46279 | G37: 0 | H37: =IF(F37="",AsOf-D37,F37-D37) | I37: =IF(F37<>"","Paid",IF(H37<=0,"Current",IF(H37<=30,"1-30",IF(H37<=60,"31-60",IF(H37<=90,"61-90","90+"))))) | J37: =IF(F37="",E37,0)

Sheet Payroll
A1: Emp ID | B1: Name | C1: Department | D1: Pay Date | E1: Gross | F1: Deductions | G1: Net
A2: E001 | B2: Ravi | C2: Sales | D2: 46142 | E2: 45000 | F2: 4500 | G2: =E2-F2
A3: E002 | B3: Sunita | C3: Sales | D3: 46142 | E3: 38000 | F3: 3800 | G3: =E3-F3
A4: E003 | B4: Amit | C4: Office | D4: 46142 | E4: 30000 | F4: 3000 | G4: =E4-F4
A5: E004 | B5: Pooja | C5: Office | D5: 46142 | E5: 28000 | F5: 2800 | G5: =E5-F5
A6: E005 | B6: Vikash | C6: Production | D6: 46142 | E6: 22000 | F6: 2200 | G6: =E6-F6
A7: E006 | B7: Rekha | C7: Production | D7: 46142 | E7: 20000 | F7: 2000 | G7: =E7-F7
A8: E007 | B8: Manoj | C8: Production | D8: 46142 | E8: 24000 | F8: 2400 | G8: =E8-F8
A9: E008 | B9: Kavita | C9: Office | D9: 46142 | E9: 26000 | F9: 2600 | G9: =E9-F9
A10: E001 | B10: Ravi | C10: Sales | D10: 46173 | E10: 45000 | F10: 4500 | G10: =E10-F10
A11: E002 | B11: Sunita | C11: Sales | D11: 46173 | E11: 38000 | F11: 3800 | G11: =E11-F11
A12: E003 | B12: Amit | C12: Office | D12: 46173 | E12: 30000 | F12: 3000 | G12: =E12-F12
A13: E004 | B13: Pooja | C13: Office | D13: 46173 | E13: 28000 | F13: 2800 | G13: =E13-F13
... A49: E008 | B49: Kavita | C49: Office | D49: 46295 | E49: 26000 | F49: 2600 | G49: =E49-F49

Sheet Bank
A1: Date | B1: Description | C1: Ref | D1: Withdrawal | E1: Deposit | F1: Net
A2: 46113 | B2: Opening balance | C2: OPEN-001 | D2: 0 | E2: 500000 | F2: =E2-D2
A3: 46142 | B3: NEFT - Patel Wholesale | C3: NEFT-0007 | D3: 98450 | E3: 0 | F3: =E3-D3
A4: 46142 | B4: Salary - Ravi | C4: SAL-E001-202604 | D4: 40500 | E4: 0 | F4: =E4-D4
A5: 46142 | B5: Salary - Sunita | C5: SAL-E002-202604 | D5: 34200 | E5: 0 | F5: =E5-D5
A6: 46142 | B6: Salary - Amit | C6: SAL-E003-202604 | D6: 27000 | E6: 0 | F6: =E6-D6
A7: 46142 | B7: Salary - Pooja | C7: SAL-E004-202604 | D7: 25200 | E7: 0 | F7: =E7-D7
A8: 46142 | B8: Salary - Vikash | C8: SAL-E005-202604 | D8: 19800 | E8: 0 | F8: =E8-D8
A9: 46142 | B9: Salary - Rekha | C9: SAL-E006-202604 | D9: 18000 | E9: 0 | F9: =E9-D9
A10: 46142 | B10: Salary - Manoj | C10: SAL-E007-202604 | D10: 21600 | E10: 0 | F10: =E10-D10
A11: 46142 | B11: Salary - Kavita | C11: SAL-E008-202604 | D11: 23400 | E11: 0 | F11: =E11-D11
A12: 46142 | B12: UPI - Star Market | C12: UPI-0005 | D12: 0 | E12: 236189 | F12: =E12-D12
A13: 46148 | B13: NEFT - Verma Agro | C13: NEFT-0003 | D13: 230083 | E13: 0 | F13: =E13-D13
... A108: 46295 | B108: Salary - Kavita | C108: SAL-E008-202609 | D108: 23400 | E108: 0 | F108: =E108-D108

Sheet Bank_Rec
A1: Bank Reconciliation (INR) - all figures are live formulas
A3: Bank balance per statement | B3: =SUM(Bank!F:F)
A4: Add: deposits in transit | B4: =SUMIFS(Raw_AR!E:E,Raw_AR!G:G,1)
A5: Less: outstanding cheques | B5: =SUMIFS(Raw_AP!E:E,Raw_AP!G:G,"cheque",Raw_AP!F:F,"<>"&"",Raw_AP!H:H,0)
A6: ADJUSTED BANK BALANCE | B6: =B3+B4-B5
A8: Book balance per books | B8: =BookOpen+SUMIFS(Raw_AR!E:E,Raw_AR!F:F,"<>"&"",Raw_AR!C:C,">="&PeriodStart,Raw_AR!C:C,"<"&PeriodEnd)-SUMIFS(Raw_AP!E:E,Raw_AP!F:F,"<>"&"",Raw_AP!C:C,">="&PeriodStart,Raw_AP!C:C,"<"&PeriodEnd)-SUMIFS(Payroll!G:G,Payroll!D:D,">="&PeriodStart,Payroll!D:D,"<"&PeriodEnd)
A9: Add: interest credited (not in books) | B9: =SUMIFS(Bank!E:E,Bank!C:C,"INT-*")
A10: Less: bank charges (not in books) | B10: =SUMIFS(Bank!D:D,Bank!C:C,"CHG-*")
A11: ADJUSTED BOOK BALANCE | B11: =B8+B9-B10
A13: Difference (adjusted bank - adjusted book) | B13: =B6-B11
A14: Status | B14: =IF(ABS(B13)<0.01,"OK - reconciled","OUT OF BALANCE - investigate")

Sheet AP_Aging
A1: AP Aging (INR) - live SUMIFS
A2: Bucket | B2: Outstanding | C2: Count
A3: Current | B3: =SUMIFS(Raw_AP!L:L,Raw_AP!K:K,A3) | C3: =COUNTIFS(Raw_AP!K:K,A3,Raw_AP!L:L,">0")
A4: 1-30 | B4: =SUMIFS(Raw_AP!L:L,Raw_AP!K:K,A4) | C4: =COUNTIFS(Raw_AP!K:K,A4,Raw_AP!L:L,">0")
A5: 31-60 | B5: =SUMIFS(Raw_AP!L:L,Raw_AP!K:K,A5) | C5: =COUNTIFS(Raw_AP!K:K,A5,Raw_AP!L:L,">0")
A6: 61-90 | B6: =SUMIFS(Raw_AP!L:L,Raw_AP!K:K,A6) | C6: =COUNTIFS(Raw_AP!K:K,A6,Raw_AP!L:L,">0")
A7: 90+ | B7: =SUMIFS(Raw_AP!L:L,Raw_AP!K:K,A7) | C7: =COUNTIFS(Raw_AP!K:K,A7,Raw_AP!L:L,">0")
A8: TOTAL | B8: =SUM(B3:B7) | C8: =SUM(C3:C7)
A9: Integrity check | B9: =IF(ABS(B8-SUM(Raw_AP!L:L))<0.01,"OK - ties to raw data","DIFF")

Sheet AR_Aging
A1: AR Aging (INR) - live SUMIFS
A2: Bucket | B2: Outstanding | C2: Count
A3: Current | B3: =SUMIFS(Raw_AR!J:J,Raw_AR!I:I,A3) | C3: =COUNTIFS(Raw_AR!I:I,A3,Raw_AR!J:J,">0")
A4: 1-30 | B4: =SUMIFS(Raw_AR!J:J,Raw_AR!I:I,A4) | C4: =COUNTIFS(Raw_AR!I:I,A4,Raw_AR!J:J,">0")
A5: 31-60 | B5: =SUMIFS(Raw_AR!J:J,Raw_AR!I:I,A5) | C5: =COUNTIFS(Raw_AR!I:I,A5,Raw_AR!J:J,">0")
A6: 61-90 | B6: =SUMIFS(Raw_AR!J:J,Raw_AR!I:I,A6) | C6: =COUNTIFS(Raw_AR!I:I,A6,Raw_AR!J:J,">0")
A7: 90+ | B7: =SUMIFS(Raw_AR!J:J,Raw_AR!I:I,A7) | C7: =COUNTIFS(Raw_AR!I:I,A7,Raw_AR!J:J,">0")
A8: TOTAL | B8: =SUM(B3:B7) | C8: =SUM(C3:C7)
A9: Integrity check | B9: =IF(ABS(B8-SUM(Raw_AR!J:J))<0.01,"OK - ties to raw data","DIFF")

Sheet P&L
A1: Profit & Loss (INR), Apr-Sep 2026
B2: 46113 | C2: 46143 | D2: 46174 | E2: 46204 | F2: 46235 | G2: 46266
A3: Line | B3: Apr-26 | C3: May-26 | D3: Jun-26 | E3: Jul-26 | F3: Aug-26 | G3: Sep-26 | H3: Total
A4: Revenue (invoiced) | B4: =SUMIFS(Raw_AR!E:E,Raw_AR!C:C,">="&B$2,Raw_AR!C:C,"<"&EDATE(B$2,1)) | C4: =SUMIFS(Raw_AR!E:E,Raw_AR!C:C,">="&C$2,Raw_AR!C:C,"<"&EDATE(C$2,1)) | D4: =SUMIFS(Raw_AR!E:E,Raw_AR!C:C,">="&D$2,Raw_AR!C:C,"<"&EDATE(D$2,1)) | E4: =SUMIFS(Raw_AR!E:E,Raw_AR!C:C,">="&E$2,Raw_AR!C:C,"<"&EDATE(E$2,1)) | F4: =SUMIFS(Raw_AR!E:E,Raw_AR!C:C,">="&F$2,Raw_AR!C:C,"<"&EDATE(F$2,1)) | G4: =SUMIFS(Raw_AR!E:E,Raw_AR!C:C,">="&G$2,Raw_AR!C:C,"<"&EDATE(G$2,1)) | H4: =SUM(B4:G4)
A5: Purchases | B5: =SUMIFS(Raw_AP!E:E,Raw_AP!I:I,"Purchases",Raw_AP!C:C,">="&B$2,Raw_AP!C:C,"<"&EDATE(B$2,1)) | C5: =SUMIFS(Raw_AP!E:E,Raw_AP!I:I,"Purchases",Raw_AP!C:C,">="&C$2,Raw_AP!C:C,"<"&EDATE(C$2,1)) | D5: =SUMIFS(Raw_AP!E:E,Raw_AP!I:I,"Purchases",Raw_AP!C:C,">="&D$2,Raw_AP!C:C,"<"&EDATE(D$2,1)) | E5: =SUMIFS(Raw_AP!E:E,Raw_AP!I:I,"Purchases",Raw_AP!C:C,">="&E$2,Raw_AP!C:C,"<"&EDATE(E$2,1)) | F5: =SUMIFS(Raw_AP!E:E,Raw_AP!I:I,"Purchases",Raw_AP!C:C,">="&F$2,Raw_AP!C:C,"<"&EDATE(F$2,1)) | G5: =SUMIFS(Raw_AP!E:E,Raw_AP!I:I,"Purchases",Raw_AP!C:C,">="&G$2,Raw_AP!C:C,"<"&EDATE(G$2,1)) | H5: =SUM(B5:G5)
A6: Gross Profit | B6: =B4-B5 | C6: =C4-C5 | D6: =D4-D5 | E6: =E4-E5 | F6: =F4-F5 | G6: =G4-G5 | H6: =H4-H5
A7: Payroll | B7: =SUMIFS(Payroll!G:G,Payroll!D:D,">="&B$2,Payroll!D:D,"<"&EDATE(B$2,1)) | C7: =SUMIFS(Payroll!G:G,Payroll!D:D,">="&C$2,Payroll!D:D,"<"&EDATE(C$2,1)) | D7: =SUMIFS(Payroll!G:G,Payroll!D:D,">="&D$2,Payroll!D:D,"<"&EDATE(D$2,1)) | E7: =SUMIFS(Payroll!G:G,Payroll!D:D,">="&E$2,Payroll!D:D,"<"&EDATE(E$2,1)) | F7: =SUMIFS(Payroll!G:G,Payroll!D:D,">="&F$2,Payroll!D:D,"<"&EDATE(F$2,1)) | G7: =SUMIFS(Payroll!G:G,Payroll!D:D,">="&G$2,Payroll!D:D,"<"&EDATE(G$2,1)) | H7: =SUM(B7:G7)
A8: Other operating expenses | B8: =SUMIFS(Raw_AP!E:E,Raw_AP!I:I,"<>"&"Purchases",Raw_AP!C:C,">="&B$2,Raw_AP!C:C,"<"&EDATE(B$2,1)) | C8: =SUMIFS(Raw_AP!E:E,Raw_AP!I:I,"<>"&"Purchases",Raw_AP!C:C,">="&C$2,Raw_AP!C:C,"<"&EDATE(C$2,1)) | D8: =SUMIFS(Raw_AP!E:E,Raw_AP!I:I,"<>"&"Purchases",Raw_AP!C:C,">="&D$2,Raw_AP!C:C,"<"&EDATE(D$2,1)) | E8: =SUMIFS(Raw_AP!E:E,Raw_AP!I:I,"<>"&"Purchases",Raw_AP!C:C,">="&E$2,Raw_AP!C:C,"<"&EDATE(E$2,1)) | F8: =SUMIFS(Raw_AP!E:E,Raw_AP!I:I,"<>"&"Purchases",Raw_AP!C:C,">="&F$2,Raw_AP!C:C,"<"&EDATE(F$2,1)) | G8: =SUMIFS(Raw_AP!E:E,Raw_AP!I:I,"<>"&"Purchases",Raw_AP!C:C,">="&G$2,Raw_AP!C:C,"<"&EDATE(G$2,1)) | H8: =SUM(B8:G8)
A9: Total operating expenses | B9: =B7+B8 | C9: =C7+C8 | D9: =D7+D8 | E9: =E7+E8 | F9: =F7+F8 | G9: =G7+G8 | H9: =H7+H8
A10: NET INCOME | B10: =B6-B9 | C10: =C6-C9 | D10: =D6-D9 | E10: =E6-E9 | F10: =F6-F9 | G10: =G6-G9 | H10: =H6-H9
A11: Total expenses (charts) | B11: =B5+B9 | C11: =C5+C9 | D11: =D5+D9 | E11: =E5+E9 | F11: =F5+F9 | G11: =G5+G9 | H11: =H5+H9

Sheet Dashboard
A1: AccountingPulse - Rajesh Kumar & Sons (INR) | E1: 46113
A2: Apr-Sep 2026 | All figures are live formulas - refresh = append rows + rerun generate.py | E2: 46296
A3: As-of date | B3: 46295
A4: Opening book cash | B4: 500000
A6: Key figures | G6: Department | H6: Payroll total
A7: AP Outstanding | B7: ='AP_Aging'!B8 | G7: Office | H7: =SUMIFS(Payroll!G:G,Payroll!C:C,G7)
A8: AR Outstanding | B8: ='AR_Aging'!B8 | G8: Production | H8: =SUMIFS(Payroll!G:G,Payroll!C:C,G8)
A9: Adjusted bank balance | B9: ='Bank_Rec'!B6 | G9: Sales | H9: =SUMIFS(Payroll!G:G,Payroll!C:C,G9)
A10: Bank-book difference | B10: ='Bank_Rec'!B13
A11: Reconciliation status | B11: ='Bank_Rec'!B14
A12: Monthly payroll run-rate | B12: =SUM(Payroll!G:G)/6
A13: Net income (6 mo) | B13: ='P&L'!H10
A14: AR overdue 90+ | B14: ='AR_Aging'!B7
