Workbook

Sheet Guide
A1: ReconPulse — Bank Reconciliation Workbench
A3: What this is | B3: A formula-driven bank reconciliation for Mehta Trading Co., Ludhiana (fictional demo data, 1–21 Oct 2026): every bank-statement line is auto-matched to the book ledger by amount + side, with a ±3-day clearing window.
A4: Inputs (yellow) | B4: Summary!B2 opening balance, Summary!B3 as-of date. Paste a fresh statement into Raw_Bank and the ledger into Raw_Book; extend the formula ranges on Recon/Unmatched/Daily/Summary/Checks.
A5: How matching works | B5: Recon!F builds a key amount|side (R=receipt, P=payment); Recon!G finds the key in the ledger; Recon!K marks MATCHED only when the booked date is within 3 days of the bank date.
A6: Unmatched items | B6: Bank-only items (charges, interest, unidentified deposits) and book-only items (unpresented cheques, deposits in transit) are extracted with a suggested action and days outstanding.
A7: Reconciliation | B7: Summary walks both sides to one adjusted balance; Checks!B1:B8 must all read TRUE and the recon difference must be zero.
A8: Demo state | B8: 128 bank lines, 127 book lines; 4 bank-only and 3 book-only items deliberately unmatched.

Sheet Raw_Bank
A1: Date | B1: Description | C1: Ref | D1: Debit | E1: Credit | F1: Balance
A2: 46296 | B2: Insurance premium | C2: UTR643943 | D2: 31500 | E2: 0 | F2: =Summary!$B$2+E2-D2
A3: 46297 | B3: Audit fee advance | C3: UTR825369 | D3: 5500 | E3: 0 | F3: =F2+E3-D3
A4: 46297 | B4: NEFT - Sharma Retail Store (inv 1074) | C4: UTR200560 | D4: 0 | E4: 57500 | F4: =F3+E4-D4
A5: 46297 | B5: RTGS - Kumar & Sons (inv 1143) | C5: UTR891119 | D5: 0 | E5: 8500 | F5: =F4+E5-D5
A6: 46297 | B6: RTGS - Mishra Mart (inv 1072) | C6: UTR716990 | D6: 0 | E6: 33500 | F6: =F5+E6-D6
A7: 46297 | B7: RTGS - Verma Traders (inv 1099) | C7: UTR785402 | D7: 0 | E7: 50500 | F7: =F6+E7-D7
A8: 46297 | B8: UPI - retail counter sales 1-Oct | C8: UTR831042 | D8: 0 | E8: 6744 | F8: =F7+E8-D8
A9: 46297 | B9: UPI - retail counter sales 16-Oct | C9: UTR915146 | D9: 0 | E9: 4594 | F9: =F8+E9-D9
A10: 46297 | B10: UPI - retail counter sales 16-Oct | C10: UTR125519 | D10: 0 | E10: 1103 | F10: =F9+E10-D10
A11: 46297 | B11: UPI - retail counter sales 3-Oct | C11: UTR320938 | D11: 0 | E11: 6011 | F11: =F10+E11-D11
A12: 46297 | B12: UPI - retail counter sales 3-Oct | C12: UTR518151 | D12: 0 | E12: 8292 | F12: =F11+E12-D12
A13: 46297 | B13: UPI - retail counter sales 6-Oct | C13: UTR482125 | D13: 0 | E13: 3000 | F13: =F12+E13-D13
A14: 46298 | B14: Electricity bill | C14: UTR315161 | D14: 10000 | E14: 0 | F14: =F13+E14-D14
... A129: 46316 | B129: UPI - retail counter sales 3-Oct | C129: UTR217340 | D129: 0 | E129: 4786 | F129: =F128+E129-D129

Sheet Raw_Book
A1: Date | B1: Narration | C1: Voucher | D1: Debit | E1: Credit | F1: Balance | G1: Key | H1: Matched? | I1: UPos
A2: 46296 | B2: Audit fee advance | C2: PV9334 | D2: 0 | E2: 5500 | F2: =Summary!$B$2+D2-E2 | G2: =TEXT(MAX(D2,E2),"0.00")&"|"&IF(D2>0,"R","P") | H2: =COUNTIFS(Recon!$F$2:$F$129,G2,Recon!$K$2:$K$129,"MATCHED")>0 | I2: =IF(H2=FALSE,ROW()-1,"")
A3: 46296 | B3: Insurance premium | C3: PV1346 | D3: 0 | E3: 31500 | F3: =F2+D3-E3 | G3: =TEXT(MAX(D3,E3),"0.00")&"|"&IF(D3>0,"R","P") | H3: =COUNTIFS(Recon!$F$2:$F$129,G3,Recon!$K$2:$K$129,"MATCHED")>0 | I3: =IF(H3=FALSE,ROW()-1,"")
A4: 46296 | B4: NEFT - Chawla Distributors (PO 541) | C4: PV3758 | D4: 0 | E4: 114250 | F4: =F3+D4-E4 | G4: =TEXT(MAX(D4,E4),"0.00")&"|"&IF(D4>0,"R","P") | H4: =COUNTIFS(Recon!$F$2:$F$129,G4,Recon!$K$2:$K$129,"MATCHED")>0 | I4: =IF(H4=FALSE,ROW()-1,"")
A5: 46296 | B5: UPI - retail counter sales 16-Oct | C5: RV5716 | D5: 1103 | E5: 0 | F5: =F4+D5-E5 | G5: =TEXT(MAX(D5,E5),"0.00")&"|"&IF(D5>0,"R","P") | H5: =COUNTIFS(Recon!$F$2:$F$129,G5,Recon!$K$2:$K$129,"MATCHED")>0 | I5: =IF(H5=FALSE,ROW()-1,"")
A6: 46297 | B6: Electricity bill | C6: PV3353 | D6: 0 | E6: 10000 | F6: =F5+D6-E6 | G6: =TEXT(MAX(D6,E6),"0.00")&"|"&IF(D6>0,"R","P") | H6: =COUNTIFS(Recon!$F$2:$F$129,G6,Recon!$K$2:$K$129,"MATCHED")>0 | I6: =IF(H6=FALSE,ROW()-1,"")
A7: 46297 | B7: NEFT - Chawla Distributors (PO 550) | C7: PV8438 | D7: 0 | E7: 162000 | F7: =F6+D7-E7 | G7: =TEXT(MAX(D7,E7),"0.00")&"|"&IF(D7>0,"R","P") | H7: =COUNTIFS(Recon!$F$2:$F$129,G7,Recon!$K$2:$K$129,"MATCHED")>0 | I7: =IF(H7=FALSE,ROW()-1,"")
A8: 46297 | B8: NEFT - Dhillon FMCG (PO 616) | C8: PV5385 | D8: 0 | E8: 66250 | F8: =F7+D8-E8 | G8: =TEXT(MAX(D8,E8),"0.00")&"|"&IF(D8>0,"R","P") | H8: =COUNTIFS(Recon!$F$2:$F$129,G8,Recon!$K$2:$K$129,"MATCHED")>0 | I8: =IF(H8=FALSE,ROW()-1,"")
A9: 46297 | B9: NEFT - Mishra Mart (inv 1107) | C9: RV2786 | D9: 31050 | E9: 0 | F9: =F8+D9-E9 | G9: =TEXT(MAX(D9,E9),"0.00")&"|"&IF(D9>0,"R","P") | H9: =COUNTIFS(Recon!$F$2:$F$129,G9,Recon!$K$2:$K$129,"MATCHED")>0 | I9: =IF(H9=FALSE,ROW()-1,"")
A10: 46297 | B10: NEFT - Sharma Retail Store (inv 1074) | C10: RV7076 | D10: 57500 | E10: 0 | F10: =F9+D10-E10 | G10: =TEXT(MAX(D10,E10),"0.00")&"|"&IF(D10>0,"R","P") | H10: =COUNTIFS(Recon!$F$2:$F$129,G10,Recon!$K$2:$K$129,"MATCHED")>0 | I10: =IF(H10=FALSE,ROW()-1,"")
A11: 46297 | B11: RTGS - Kumar & Sons (inv 1143) | C11: RV1467 | D11: 8500 | E11: 0 | F11: =F10+D11-E11 | G11: =TEXT(MAX(D11,E11),"0.00")&"|"&IF(D11>0,"R","P") | H11: =COUNTIFS(Recon!$F$2:$F$129,G11,Recon!$K$2:$K$129,"MATCHED")>0 | I11: =IF(H11=FALSE,ROW()-1,"")
A12: 46297 | B12: RTGS - Mishra Mart (inv 1072) | C12: RV3003 | D12: 33500 | E12: 0 | F12: =F11+D12-E12 | G12: =TEXT(MAX(D12,E12),"0.00")&"|"&IF(D12>0,"R","P") | H12: =COUNTIFS(Recon!$F$2:$F$129,G12,Recon!$K$2:$K$129,"MATCHED")>0 | I12: =IF(H12=FALSE,ROW()-1,"")
A13: 46297 | B13: RTGS - Patel Daily Needs (inv 1157) | C13: RV1676 | D13: 88000 | E13: 0 | F13: =F12+D13-E13 | G13: =TEXT(MAX(D13,E13),"0.00")&"|"&IF(D13>0,"R","P") | H13: =COUNTIFS(Recon!$F$2:$F$129,G13,Recon!$K$2:$K$129,"MATCHED")>0 | I13: =IF(H13=FALSE,ROW()-1,"")
A14: 46297 | B14: RTGS - Verma Traders (inv 1099) | C14: RV2581 | D14: 50500 | E14: 0 | F14: =F13+D14-E14 | G14: =TEXT(MAX(D14,E14),"0.00")&"|"&IF(D14>0,"R","P") | H14: =COUNTIFS(Recon!$F$2:$F$129,G14,Recon!$K$2:$K$129,"MATCHED")>0 | I14: =IF(H14=FALSE,ROW()-1,"")
... A128: 46316 | B128: UPI - retail counter sales 21-Oct | C128: RV3249 | D128: 2464 | E128: 0 | F128: =F127+D128-E128 | G128: =TEXT(MAX(D128,E128),"0.00")&"|"&IF(D128>0,"R","P") | H128: =COUNTIFS(Recon!$F$2:$F$129,G128,Recon!$K$2:$K$129,"MATCHED")>0 | I128: =IF(H128=FALSE,ROW()-1,"")

Sheet Recon
A1: Bank date | B1: Description | C1: Ref | D1: Bank debit | E1: Bank credit | F1: Key | G1: Match row | H1: Book date | I1: Book narration | J1: Date diff | K1: Status | L1: Amount | M1: Diff | N1: UPos
A2: =Raw_Bank!A2 | B2: =Raw_Bank!B2 | C2: =Raw_Bank!C2 | D2: =Raw_Bank!D2 | E2: =Raw_Bank!E2 | F2: =TEXT(MAX(D2,E2),"0.00")&"|"&IF(E2>0,"R","P") | G2: =MATCH(F2,Raw_Book!$G$2:$G$128,0) | H2: =IF(ISNA(G2),"",INDEX(Raw_Book!$A$2:$A$128,G2)) | I2: =IF(ISNA(G2),"",INDEX(Raw_Book!$B$2:$B$128,G2)) | J2: =IF(ISNA(G2),"",ABS(A2-H2)) | K2: =IF(OR(ISNA(G2),J2>3),"UNMATCHED","MATCHED") | L2: =MAX(D2,E2) | M2: =IF(K2="MATCHED",0,L2) | N2: =IF(K2="UNMATCHED",ROW()-1,"")
A3: =Raw_Bank!A3 | B3: =Raw_Bank!B3 | C3: =Raw_Bank!C3 | D3: =Raw_Bank!D3 | E3: =Raw_Bank!E3 | F3: =TEXT(MAX(D3,E3),"0.00")&"|"&IF(E3>0,"R","P") | G3: =MATCH(F3,Raw_Book!$G$2:$G$128,0) | H3: =IF(ISNA(G3),"",INDEX(Raw_Book!$A$2:$A$128,G3)) | I3: =IF(ISNA(G3),"",INDEX(Raw_Book!$B$2:$B$128,G3)) | J3: =IF(ISNA(G3),"",ABS(A3-H3)) | K3: =IF(OR(ISNA(G3),J3>3),"UNMATCHED","MATCHED") | L3: =MAX(D3,E3) | M3: =IF(K3="MATCHED",0,L3) | N3: =IF(K3="UNMATCHED",ROW()-1,"")
A4: =Raw_Bank!A4 | B4: =Raw_Bank!B4 | C4: =Raw_Bank!C4 | D4: =Raw_Bank!D4 | E4: =Raw_Bank!E4 | F4: =TEXT(MAX(D4,E4),"0.00")&"|"&IF(E4>0,"R","P") | G4: =MATCH(F4,Raw_Book!$G$2:$G$128,0) | H4: =IF(ISNA(G4),"",INDEX(Raw_Book!$A$2:$A$128,G4)) | I4: =IF(ISNA(G4),"",INDEX(Raw_Book!$B$2:$B$128,G4)) | J4: =IF(ISNA(G4),"",ABS(A4-H4)) | K4: =IF(OR(ISNA(G4),J4>3),"UNMATCHED","MATCHED") | L4: =MAX(D4,E4) | M4: =IF(K4="MATCHED",0,L4) | N4: =IF(K4="UNMATCHED",ROW()-1,"")
A5: =Raw_Bank!A5 | B5: =Raw_Bank!B5 | C5: =Raw_Bank!C5 | D5: =Raw_Bank!D5 | E5: =Raw_Bank!E5 | F5: =TEXT(MAX(D5,E5),"0.00")&"|"&IF(E5>0,"R","P") | G5: =MATCH(F5,Raw_Book!$G$2:$G$128,0) | H5: =IF(ISNA(G5),"",INDEX(Raw_Book!$A$2:$A$128,G5)) | I5: =IF(ISNA(G5),"",INDEX(Raw_Book!$B$2:$B$128,G5)) | J5: =IF(ISNA(G5),"",ABS(A5-H5)) | K5: =IF(OR(ISNA(G5),J5>3),"UNMATCHED","MATCHED") | L5: =MAX(D5,E5) | M5: =IF(K5="MATCHED",0,L5) | N5: =IF(K5="UNMATCHED",ROW()-1,"")
A6: =Raw_Bank!A6 | B6: =Raw_Bank!B6 | C6: =Raw_Bank!C6 | D6: =Raw_Bank!D6 | E6: =Raw_Bank!E6 | F6: =TEXT(MAX(D6,E6),"0.00")&"|"&IF(E6>0,"R","P") | G6: =MATCH(F6,Raw_Book!$G$2:$G$128,0) | H6: =IF(ISNA(G6),"",INDEX(Raw_Book!$A$2:$A$128,G6)) | I6: =IF(ISNA(G6),"",INDEX(Raw_Book!$B$2:$B$128,G6)) | J6: =IF(ISNA(G6),"",ABS(A6-H6)) | K6: =IF(OR(ISNA(G6),J6>3),"UNMATCHED","MATCHED") | L6: =MAX(D6,E6) | M6: =IF(K6="MATCHED",0,L6) | N6: =IF(K6="UNMATCHED",ROW()-1,"")
A7: =Raw_Bank!A7 | B7: =Raw_Bank!B7 | C7: =Raw_Bank!C7 | D7: =Raw_Bank!D7 | E7: =Raw_Bank!E7 | F7: =TEXT(MAX(D7,E7),"0.00")&"|"&IF(E7>0,"R","P") | G7: =MATCH(F7,Raw_Book!$G$2:$G$128,0) | H7: =IF(ISNA(G7),"",INDEX(Raw_Book!$A$2:$A$128,G7)) | I7: =IF(ISNA(G7),"",INDEX(Raw_Book!$B$2:$B$128,G7)) | J7: =IF(ISNA(G7),"",ABS(A7-H7)) | K7: =IF(OR(ISNA(G7),J7>3),"UNMATCHED","MATCHED") | L7: =MAX(D7,E7) | M7: =IF(K7="MATCHED",0,L7) | N7: =IF(K7="UNMATCHED",ROW()-1,"")
A8: =Raw_Bank!A8 | B8: =Raw_Bank!B8 | C8: =Raw_Bank!C8 | D8: =Raw_Bank!D8 | E8: =Raw_Bank!E8 | F8: =TEXT(MAX(D8,E8),"0.00")&"|"&IF(E8>0,"R","P") | G8: =MATCH(F8,Raw_Book!$G$2:$G$128,0) | H8: =IF(ISNA(G8),"",INDEX(Raw_Book!$A$2:$A$128,G8)) | I8: =IF(ISNA(G8),"",INDEX(Raw_Book!$B$2:$B$128,G8)) | J8: =IF(ISNA(G8),"",ABS(A8-H8)) | K8: =IF(OR(ISNA(G8),J8>3),"UNMATCHED","MATCHED") | L8: =MAX(D8,E8) | M8: =IF(K8="MATCHED",0,L8) | N8: =IF(K8="UNMATCHED",ROW()-1,"")
A9: =Raw_Bank!A9 | B9: =Raw_Bank!B9 | C9: =Raw_Bank!C9 | D9: =Raw_Bank!D9 | E9: =Raw_Bank!E9 | F9: =TEXT(MAX(D9,E9),"0.00")&"|"&IF(E9>0,"R","P") | G9: =MATCH(F9,Raw_Book!$G$2:$G$128,0) | H9: =IF(ISNA(G9),"",INDEX(Raw_Book!$A$2:$A$128,G9)) | I9: =IF(ISNA(G9),"",INDEX(Raw_Book!$B$2:$B$128,G9)) | J9: =IF(ISNA(G9),"",ABS(A9-H9)) | K9: =IF(OR(ISNA(G9),J9>3),"UNMATCHED","MATCHED") | L9: =MAX(D9,E9) | M9: =IF(K9="MATCHED",0,L9) | N9: =IF(K9="UNMATCHED",ROW()-1,"")
A10: =Raw_Bank!A10 | B10: =Raw_Bank!B10 | C10: =Raw_Bank!C10 | D10: =Raw_Bank!D10 | E10: =Raw_Bank!E10 | F10: =TEXT(MAX(D10,E10),"0.00")&"|"&IF(E10>0,"R","P") | G10: =MATCH(F10,Raw_Book!$G$2:$G$128,0) | H10: =IF(ISNA(G10),"",INDEX(Raw_Book!$A$2:$A$128,G10)) | I10: =IF(ISNA(G10),"",INDEX(Raw_Book!$B$2:$B$128,G10)) | J10: =IF(ISNA(G10),"",ABS(A10-H10)) | K10: =IF(OR(ISNA(G10),J10>3),"UNMATCHED","MATCHED") | L10: =MAX(D10,E10) | M10: =IF(K10="MATCHED",0,L10) | N10: =IF(K10="UNMATCHED",ROW()-1,"")
A11: =Raw_Bank!A11 | B11: =Raw_Bank!B11 | C11: =Raw_Bank!C11 | D11: =Raw_Bank!D11 | E11: =Raw_Bank!E11 | F11: =TEXT(MAX(D11,E11),"0.00")&"|"&IF(E11>0,"R","P") | G11: =MATCH(F11,Raw_Book!$G$2:$G$128,0) | H11: =IF(ISNA(G11),"",INDEX(Raw_Book!$A$2:$A$128,G11)) | I11: =IF(ISNA(G11),"",INDEX(Raw_Book!$B$2:$B$128,G11)) | J11: =IF(ISNA(G11),"",ABS(A11-H11)) | K11: =IF(OR(ISNA(G11),J11>3),"UNMATCHED","MATCHED") | L11: =MAX(D11,E11) | M11: =IF(K11="MATCHED",0,L11) | N11: =IF(K11="UNMATCHED",ROW()-1,"")
A12: =Raw_Bank!A12 | B12: =Raw_Bank!B12 | C12: =Raw_Bank!C12 | D12: =Raw_Bank!D12 | E12: =Raw_Bank!E12 | F12: =TEXT(MAX(D12,E12),"0.00")&"|"&IF(E12>0,"R","P") | G12: =MATCH(F12,Raw_Book!$G$2:$G$128,0) | H12: =IF(ISNA(G12),"",INDEX(Raw_Book!$A$2:$A$128,G12)) | I12: =IF(ISNA(G12),"",INDEX(Raw_Book!$B$2:$B$128,G12)) | J12: =IF(ISNA(G12),"",ABS(A12-H12)) | K12: =IF(OR(ISNA(G12),J12>3),"UNMATCHED","MATCHED") | L12: =MAX(D12,E12) | M12: =IF(K12="MATCHED",0,L12) | N12: =IF(K12="UNMATCHED",ROW()-1,"")
A13: =Raw_Bank!A13 | B13: =Raw_Bank!B13 | C13: =Raw_Bank!C13 | D13: =Raw_Bank!D13 | E13: =Raw_Bank!E13 | F13: =TEXT(MAX(D13,E13),"0.00")&"|"&IF(E13>0,"R","P") | G13: =MATCH(F13,Raw_Book!$G$2:$G$128,0) | H13: =IF(ISNA(G13),"",INDEX(Raw_Book!$A$2:$A$128,G13)) | I13: =IF(ISNA(G13),"",INDEX(Raw_Book!$B$2:$B$128,G13)) | J13: =IF(ISNA(G13),"",ABS(A13-H13)) | K13: =IF(OR(ISNA(G13),J13>3),"UNMATCHED","MATCHED") | L13: =MAX(D13,E13) | M13: =IF(K13="MATCHED",0,L13) | N13: =IF(K13="UNMATCHED",ROW()-1,"")
... A129: =Raw_Bank!A129 | B129: =Raw_Bank!B129 | C129: =Raw_Bank!C129 | D129: =Raw_Bank!D129 | E129: =Raw_Bank!E129 | F129: =TEXT(MAX(D129,E129),"0.00")&"|"&IF(E129>0,"R","P") | G129: =MATCH(F129,Raw_Book!$G$2:$G$128,0) | H129: =IF(ISNA(G129),"",INDEX(Raw_Book!$A$2:$A$128,G129)) | I129: =IF(ISNA(G129),"",INDEX(Raw_Book!$B$2:$B$128,G129)) | J129: =IF(ISNA(G129),"",ABS(A129-H129)) | K129: =IF(OR(ISNA(G129),J129>3),"UNMATCHED","MATCHED") | L129: =MAX(D129,E129) | M129: =IF(K129="MATCHED",0,L129) | N129: =IF(K129="UNMATCHED",ROW()-1,"")

Sheet Unmatched
A1: Bank-only items — in the statement, not in the books
A2: Item | B2: Date | C2: Amount | D2: Side | E2: Reason | F2: Suggested action | G2: Days outstanding | H2: pos
A3: =IF($H3="","",INDEX(Recon!$B$2:$B$129,$H3)) | B3: =IF($H3="","",INDEX(Recon!$A$2:$A$129,$H3)) | C3: =IF($H3="","",INDEX(Recon!$L$2:$L$129,$H3)) | D3: =IF($H3="","",IF(INDEX(Recon!$E$2:$E$129,$H3)>0,"Receipt","Payment")) | E3: =IF(A3="","",IF(ISNUMBER(SEARCH("charg",A3)),"Bank charges",IF(ISNUMBER(SEARCH("Interest",A3)),"Interest credited","Unidentified deposit")) | F3: =IF(A3="","",IF(E3="Bank charges","Record the charges in the book ledger",IF(E3="Interest credited","Record interest income in the books","Identify the depositor from the UTR; book the receipt or arrange a refund")) | G3: =IF(A3="","",Summary!$B$3-B3) | H3: =IFERROR(SMALL(Recon!$N$2:$N$129,1),"")
A4: =IF($H4="","",INDEX(Recon!$B$2:$B$129,$H4)) | B4: =IF($H4="","",INDEX(Recon!$A$2:$A$129,$H4)) | C4: =IF($H4="","",INDEX(Recon!$L$2:$L$129,$H4)) | D4: =IF($H4="","",IF(INDEX(Recon!$E$2:$E$129,$H4)>0,"Receipt","Payment")) | E4: =IF(A4="","",IF(ISNUMBER(SEARCH("charg",A4)),"Bank charges",IF(ISNUMBER(SEARCH("Interest",A4)),"Interest credited","Unidentified deposit")) | F4: =IF(A4="","",IF(E4="Bank charges","Record the charges in the book ledger",IF(E4="Interest credited","Record interest income in the books","Identify the depositor from the UTR; book the receipt or arrange a refund")) | G4: =IF(A4="","",Summary!$B$3-B4) | H4: =IFERROR(SMALL(Recon!$N$2:$N$129,2),"")
A5: =IF($H5="","",INDEX(Recon!$B$2:$B$129,$H5)) | B5: =IF($H5="","",INDEX(Recon!$A$2:$A$129,$H5)) | C5: =IF($H5="","",INDEX(Recon!$L$2:$L$129,$H5)) | D5: =IF($H5="","",IF(INDEX(Recon!$E$2:$E$129,$H5)>0,"Receipt","Payment")) | E5: =IF(A5="","",IF(ISNUMBER(SEARCH("charg",A5)),"Bank charges",IF(ISNUMBER(SEARCH("Interest",A5)),"Interest credited","Unidentified deposit")) | F5: =IF(A5="","",IF(E5="Bank charges","Record the charges in the book ledger",IF(E5="Interest credited","Record interest income in the books","Identify the depositor from the UTR; book the receipt or arrange a refund")) | G5: =IF(A5="","",Summary!$B$3-B5) | H5: =IFERROR(SMALL(Recon!$N$2:$N$129,3),"")
A6: =IF($H6="","",INDEX(Recon!$B$2:$B$129,$H6)) | B6: =IF($H6="","",INDEX(Recon!$A$2:$A$129,$H6)) | C6: =IF($H6="","",INDEX(Recon!$L$2:$L$129,$H6)) | D6: =IF($H6="","",IF(INDEX(Recon!$E$2:$E$129,$H6)>0,"Receipt","Payment")) | E6: =IF(A6="","",IF(ISNUMBER(SEARCH("charg",A6)),"Bank charges",IF(ISNUMBER(SEARCH("Interest",A6)),"Interest credited","Unidentified deposit")) | F6: =IF(A6="","",IF(E6="Bank charges","Record the charges in the book ledger",IF(E6="Interest credited","Record interest income in the books","Identify the depositor from the UTR; book the receipt or arrange a refund")) | G6: =IF(A6="","",Summary!$B$3-B6) | H6: =IFERROR(SMALL(Recon!$N$2:$N$129,4),"")
A7: =IF($H7="","",INDEX(Recon!$B$2:$B$129,$H7)) | B7: =IF($H7="","",INDEX(Recon!$A$2:$A$129,$H7)) | C7: =IF($H7="","",INDEX(Recon!$L$2:$L$129,$H7)) | D7: =IF($H7="","",IF(INDEX(Recon!$E$2:$E$129,$H7)>0,"Receipt","Payment")) | E7: =IF(A7="","",IF(ISNUMBER(SEARCH("charg",A7)),"Bank charges",IF(ISNUMBER(SEARCH("Interest",A7)),"Interest credited","Unidentified deposit")) | F7: =IF(A7="","",IF(E7="Bank charges","Record the charges in the book ledger",IF(E7="Interest credited","Record interest income in the books","Identify the depositor from the UTR; book the receipt or arrange a refund")) | G7: =IF(A7="","",Summary!$B$3-B7) | H7: =IFERROR(SMALL(Recon!$N$2:$N$129,5),"")
A8: =IF($H8="","",INDEX(Recon!$B$2:$B$129,$H8)) | B8: =IF($H8="","",INDEX(Recon!$A$2:$A$129,$H8)) | C8: =IF($H8="","",INDEX(Recon!$L$2:$L$129,$H8)) | D8: =IF($H8="","",IF(INDEX(Recon!$E$2:$E$129,$H8)>0,"Receipt","Payment")) | E8: =IF(A8="","",IF(ISNUMBER(SEARCH("charg",A8)),"Bank charges",IF(ISNUMBER(SEARCH("Interest",A8)),"Interest credited","Unidentified deposit")) | F8: =IF(A8="","",IF(E8="Bank charges","Record the charges in the book ledger",IF(E8="Interest credited","Record interest income in the books","Identify the depositor from the UTR; book the receipt or arrange a refund")) | G8: =IF(A8="","",Summary!$B$3-B8) | H8: =IFERROR(SMALL(Recon!$N$2:$N$129,6),"")
A10: Book-only items — in the books, not yet at the bank
A11: Item | B11: Date | C11: Amount | D11: Side | E11: Reason | F11: Suggested action | G11: Days outstanding | H11: pos
A12: =IF($H12="","",INDEX(Raw_Book!$B$2:$B$128,$H12)) | B12: =IF($H12="","",INDEX(Raw_Book!$A$2:$A$128,$H12)) | C12: =IF($H12="","",MAX(INDEX(Raw_Book!$D$2:$D$128,$H12),INDEX(Raw_Book!$E$2:$E$128,$H12))) | D12: =IF(A12="","",IF(ISNUMBER(SEARCH("transit",A12)),"Receipt","Payment")) | E12: =IF(A12="","",IF(ISNUMBER(SEARCH("unpresented",A12)),"Unpresented cheque","Deposit in transit")) | F12: =IF(A12="","",IF(E12="Unpresented cheque","Follow up with the payee; reissue if stale (>3 months)","Confirm credit in the next statement; then it auto-matches")) | G12: =IF(A12="","",Summary!$B$3-B12) | H12: =IFERROR(SMALL(Raw_Book!$I$2:$I$128,1),"")
A13: =IF($H13="","",INDEX(Raw_Book!$B$2:$B$128,$H13)) | B13: =IF($H13="","",INDEX(Raw_Book!$A$2:$A$128,$H13)) | C13: =IF($H13="","",MAX(INDEX(Raw_Book!$D$2:$D$128,$H13),INDEX(Raw_Book!$E$2:$E$128,$H13))) | D13: =IF(A13="","",IF(ISNUMBER(SEARCH("transit",A13)),"Receipt","Payment")) | E13: =IF(A13="","",IF(ISNUMBER(SEARCH("unpresented",A13)),"Unpresented cheque","Deposit in transit")) | F13: =IF(A13="","",IF(E13="Unpresented cheque","Follow up with the payee; reissue if stale (>3 months)","Confirm credit in the next statement; then it auto-matches")) | G13: =IF(A13="","",Summary!$B$3-B13) | H13: =IFERROR(SMALL(Raw_Book!$I$2:$I$128,2),"")
A14: =IF($H14="","",INDEX(Raw_Book!$B$2:$B$128,$H14)) | B14: =IF($H14="","",INDEX(Raw_Book!$A$2:$A$128,$H14)) | C14: =IF($H14="","",MAX(INDEX(Raw_Book!$D$2:$D$128,$H14),INDEX(Raw_Book!$E$2:$E$128,$H14))) | D14: =IF(A14="","",IF(ISNUMBER(SEARCH("transit",A14)),"Receipt","Payment")) | E14: =IF(A14="","",IF(ISNUMBER(SEARCH("unpresented",A14)),"Unpresented cheque","Deposit in transit")) | F14: =IF(A14="","",IF(E14="Unpresented cheque","Follow up with the payee; reissue if stale (>3 months)","Confirm credit in the next statement; then it auto-matches")) | G14: =IF(A14="","",Summary!$B$3-B14) | H14: =IFERROR(SMALL(Raw_Book!$I$2:$I$128,3),"")
A15: =IF($H15="","",INDEX(Raw_Book!$B$2:$B$128,$H15)) | B15: =IF($H15="","",INDEX(Raw_Book!$A$2:$A$128,$H15)) | C15: =IF($H15="","",MAX(INDEX(Raw_Book!$D$2:$D$128,$H15),INDEX(Raw_Book!$E$2:$E$128,$H15))) | D15: =IF(A15="","",IF(ISNUMBER(SEARCH("transit",A15)),"Receipt","Payment")) | E15: =IF(A15="","",IF(ISNUMBER(SEARCH("unpresented",A15)),"Unpresented cheque","Deposit in transit")) | F15: =IF(A15="","",IF(E15="Unpresented cheque","Follow up with the payee; reissue if stale (>3 months)","Confirm credit in the next statement; then it auto-matches")) | G15: =IF(A15="","",Summary!$B$3-B15) | H15: =IFERROR(SMALL(Raw_Book!$I$2:$I$128,4),"")
A16: =IF($H16="","",INDEX(Raw_Book!$B$2:$B$128,$H16)) | B16: =IF($H16="","",INDEX(Raw_Book!$A$2:$A$128,$H16)) | C16: =IF($H16="","",MAX(INDEX(Raw_Book!$D$2:$D$128,$H16),INDEX(Raw_Book!$E$2:$E$128,$H16))) | D16: =IF(A16="","",IF(ISNUMBER(SEARCH("transit",A16)),"Receipt","Payment")) | E16: =IF(A16="","",IF(ISNUMBER(SEARCH("unpresented",A16)),"Unpresented cheque","Deposit in transit")) | F16: =IF(A16="","",IF(E16="Unpresented cheque","Follow up with the payee; reissue if stale (>3 months)","Confirm credit in the next statement; then it auto-matches")) | G16: =IF(A16="","",Summary!$B$3-B16) | H16: =IFERROR(SMALL(Raw_Book!$I$2:$I$128,5),"")
A17: =IF($H17="","",INDEX(Raw_Book!$B$2:$B$128,$H17)) | B17: =IF($H17="","",INDEX(Raw_Book!$A$2:$A$128,$H17)) | C17: =IF($H17="","",MAX(INDEX(Raw_Book!$D$2:$D$128,$H17),INDEX(Raw_Book!$E$2:$E$128,$H17))) | D17: =IF(A17="","",IF(ISNUMBER(SEARCH("transit",A17)),"Receipt","Payment")) | E17: =IF(A17="","",IF(ISNUMBER(SEARCH("unpresented",A17)),"Unpresented cheque","Deposit in transit")) | F17: =IF(A17="","",IF(E17="Unpresented cheque","Follow up with the payee; reissue if stale (>3 months)","Confirm credit in the next statement; then it auto-matches")) | G17: =IF(A17="","",Summary!$B$3-B17) | H17: =IFERROR(SMALL(Raw_Book!$I$2:$I$128,6),"")
A18: =IF($H18="","",INDEX(Raw_Book!$B$2:$B$128,$H18)) | B18: =IF($H18="","",INDEX(Raw_Book!$A$2:$A$128,$H18)) | C18: =IF($H18="","",MAX(INDEX(Raw_Book!$D$2:$D$128,$H18),INDEX(Raw_Book!$E$2:$E$128,$H18))) | D18: =IF(A18="","",IF(ISNUMBER(SEARCH("transit",A18)),"Receipt","Payment")) | E18: =IF(A18="","",IF(ISNUMBER(SEARCH("unpresented",A18)),"Unpresented cheque","Deposit in transit")) | F18: =IF(A18="","",IF(E18="Unpresented cheque","Follow up with the payee; reissue if stale (>3 months)","Confirm credit in the next statement; then it auto-matches")) | G18: =IF(A18="","",Summary!$B$3-B18) | H18: =IFERROR(SMALL(Raw_Book!$I$2:$I$128,7),"")
A19: =IF($H19="","",INDEX(Raw_Book!$B$2:$B$128,$H19)) | B19: =IF($H19="","",INDEX(Raw_Book!$A$2:$A$128,$H19)) | C19: =IF($H19="","",MAX(INDEX(Raw_Book!$D$2:$D$128,$H19),INDEX(Raw_Book!$E$2:$E$128,$H19))) | D19: =IF(A19="","",IF(ISNUMBER(SEARCH("transit",A19)),"Receipt","Payment")) | E19: =IF(A19="","",IF(ISNUMBER(SEARCH("unpresented",A19)),"Unpresented cheque","Deposit in transit")) | F19: =IF(A19="","",IF(E19="Unpresented cheque","Follow up with the payee; reissue if stale (>3 months)","Confirm credit in the next statement; then it auto-matches")) | G19: =IF(A19="","",Summary!$B$3-B19) | H19: =IFERROR(SMALL(Raw_Book!$I$2:$I$128,8),"")

Sheet Daily
A1: Date | B1: Bank balance (EOD) | C1: Book balance (EOD)
A2: 46296 | B2: =Summary!$B$2+SUMIFS(Raw_Bank!$E$2:$E$129,Raw_Bank!$A$2:$A$129,"<="&A2)-SUMIFS(Raw_Bank!$D$2:$D$129,Raw_Bank!$A$2:$A$129,"<="&A2) | C2: =Summary!$B$2+SUMIFS(Raw_Book!$D$2:$D$128,Raw_Book!$A$2:$A$128,"<="&A2)-SUMIFS(Raw_Book!$E$2:$E$128,Raw_Book!$A$2:$A$128,"<="&A2)
A3: 46297 | B3: =Summary!$B$2+SUMIFS(Raw_Bank!$E$2:$E$129,Raw_Bank!$A$2:$A$129,"<="&A3)-SUMIFS(Raw_Bank!$D$2:$D$129,Raw_Bank!$A$2:$A$129,"<="&A3) | C3: =Summary!$B$2+SUMIFS(Raw_Book!$D$2:$D$128,Raw_Book!$A$2:$A$128,"<="&A3)-SUMIFS(Raw_Book!$E$2:$E$128,Raw_Book!$A$2:$A$128,"<="&A3)
A4: 46298 | B4: =Summary!$B$2+SUMIFS(Raw_Bank!$E$2:$E$129,Raw_Bank!$A$2:$A$129,"<="&A4)-SUMIFS(Raw_Bank!$D$2:$D$129,Raw_Bank!$A$2:$A$129,"<="&A4) | C4: =Summary!$B$2+SUMIFS(Raw_Book!$D$2:$D$128,Raw_Book!$A$2:$A$128,"<="&A4)-SUMIFS(Raw_Book!$E$2:$E$128,Raw_Book!$A$2:$A$128,"<="&A4)
A5: 46299 | B5: =Summary!$B$2+SUMIFS(Raw_Bank!$E$2:$E$129,Raw_Bank!$A$2:$A$129,"<="&A5)-SUMIFS(Raw_Bank!$D$2:$D$129,Raw_Bank!$A$2:$A$129,"<="&A5) | C5: =Summary!$B$2+SUMIFS(Raw_Book!$D$2:$D$128,Raw_Book!$A$2:$A$128,"<="&A5)-SUMIFS(Raw_Book!$E$2:$E$128,Raw_Book!$A$2:$A$128,"<="&A5)
A6: 46300 | B6: =Summary!$B$2+SUMIFS(Raw_Bank!$E$2:$E$129,Raw_Bank!$A$2:$A$129,"<="&A6)-SUMIFS(Raw_Bank!$D$2:$D$129,Raw_Bank!$A$2:$A$129,"<="&A6) | C6: =Summary!$B$2+SUMIFS(Raw_Book!$D$2:$D$128,Raw_Book!$A$2:$A$128,"<="&A6)-SUMIFS(Raw_Book!$E$2:$E$128,Raw_Book!$A$2:$A$128,"<="&A6)
A7: 46301 | B7: =Summary!$B$2+SUMIFS(Raw_Bank!$E$2:$E$129,Raw_Bank!$A$2:$A$129,"<="&A7)-SUMIFS(Raw_Bank!$D$2:$D$129,Raw_Bank!$A$2:$A$129,"<="&A7) | C7: =Summary!$B$2+SUMIFS(Raw_Book!$D$2:$D$128,Raw_Book!$A$2:$A$128,"<="&A7)-SUMIFS(Raw_Book!$E$2:$E$128,Raw_Book!$A$2:$A$128,"<="&A7)
A8: 46302 | B8: =Summary!$B$2+SUMIFS(Raw_Bank!$E$2:$E$129,Raw_Bank!$A$2:$A$129,"<="&A8)-SUMIFS(Raw_Bank!$D$2:$D$129,Raw_Bank!$A$2:$A$129,"<="&A8) | C8: =Summary!$B$2+SUMIFS(Raw_Book!$D$2:$D$128,Raw_Book!$A$2:$A$128,"<="&A8)-SUMIFS(Raw_Book!$E$2:$E$128,Raw_Book!$A$2:$A$128,"<="&A8)
A9: 46303 | B9: =Summary!$B$2+SUMIFS(Raw_Bank!$E$2:$E$129,Raw_Bank!$A$2:$A$129,"<="&A9)-SUMIFS(Raw_Bank!$D$2:$D$129,Raw_Bank!$A$2:$A$129,"<="&A9) | C9: =Summary!$B$2+SUMIFS(Raw_Book!$D$2:$D$128,Raw_Book!$A$2:$A$128,"<="&A9)-SUMIFS(Raw_Book!$E$2:$E$128,Raw_Book!$A$2:$A$128,"<="&A9)
A10: 46304 | B10: =Summary!$B$2+SUMIFS(Raw_Bank!$E$2:$E$129,Raw_Bank!$A$2:$A$129,"<="&A10)-SUMIFS(Raw_Bank!$D$2:$D$129,Raw_Bank!$A$2:$A$129,"<="&A10) | C10: =Summary!$B$2+SUMIFS(Raw_Book!$D$2:$D$128,Raw_Book!$A$2:$A$128,"<="&A10)-SUMIFS(Raw_Book!$E$2:$E$128,Raw_Book!$A$2:$A$128,"<="&A10)
A11: 46305 | B11: =Summary!$B$2+SUMIFS(Raw_Bank!$E$2:$E$129,Raw_Bank!$A$2:$A$129,"<="&A11)-SUMIFS(Raw_Bank!$D$2:$D$129,Raw_Bank!$A$2:$A$129,"<="&A11) | C11: =Summary!$B$2+SUMIFS(Raw_Book!$D$2:$D$128,Raw_Book!$A$2:$A$128,"<="&A11)-SUMIFS(Raw_Book!$E$2:$E$128,Raw_Book!$A$2:$A$128,"<="&A11)
A12: 46306 | B12: =Summary!$B$2+SUMIFS(Raw_Bank!$E$2:$E$129,Raw_Bank!$A$2:$A$129,"<="&A12)-SUMIFS(Raw_Bank!$D$2:$D$129,Raw_Bank!$A$2:$A$129,"<="&A12) | C12: =Summary!$B$2+SUMIFS(Raw_Book!$D$2:$D$128,Raw_Book!$A$2:$A$128,"<="&A12)-SUMIFS(Raw_Book!$E$2:$E$128,Raw_Book!$A$2:$A$128,"<="&A12)
A13: 46307 | B13: =Summary!$B$2+SUMIFS(Raw_Bank!$E$2:$E$129,Raw_Bank!$A$2:$A$129,"<="&A13)-SUMIFS(Raw_Bank!$D$2:$D$129,Raw_Bank!$A$2:$A$129,"<="&A13) | C13: =Summary!$B$2+SUMIFS(Raw_Book!$D$2:$D$128,Raw_Book!$A$2:$A$128,"<="&A13)-SUMIFS(Raw_Book!$E$2:$E$128,Raw_Book!$A$2:$A$128,"<="&A13)
... A22: 46316 | B22: =Summary!$B$2+SUMIFS(Raw_Bank!$E$2:$E$129,Raw_Bank!$A$2:$A$129,"<="&A22)-SUMIFS(Raw_Bank!$D$2:$D$129,Raw_Bank!$A$2:$A$129,"<="&A22) | C22: =Summary!$B$2+SUMIFS(Raw_Book!$D$2:$D$128,Raw_Book!$A$2:$A$128,"<="&A22)-SUMIFS(Raw_Book!$E$2:$E$128,Raw_Book!$A$2:$A$128,"<="&A22)

Sheet Summary
A1: Bank reconciliation — Mehta Trading Co. (demo)
A2: Opening balance 30-Sep-2026 | B2: 4500000
A3: As-of date | B3: 46316
A4: Balance per bank statement | B4: =Raw_Bank!F129
A5: Balance per books | B5: =Raw_Book!F128
A6: Walk — bank side
A7: Balance per bank statement | B7: =B4
A8: Add: bank charges not yet in books | B8: =SUMIFS(Unmatched!$C$3:$C$8,Unmatched!$E$3:$E$8,"Bank charges")
A9: Less: interest credited, not yet in books | B9: =SUMIFS(Unmatched!$C$3:$C$8,Unmatched!$E$3:$E$8,"Interest credited")
A10: Less: unidentified deposits, not yet in books | B10: =SUMIFS(Unmatched!$C$3:$C$8,Unmatched!$E$3:$E$8,"Unidentified deposit")
A11: Adjusted bank balance | B11: =B7+B8-B9-B10
A12: Walk — book side
A13: Balance per books | B13: =B5
A14: Add: cheques issued, not yet presented | B14: =SUMIFS(Unmatched!$C$12:$C$19,Unmatched!$E$12:$E$19,"Unpresented cheque")
A15: Less: deposits in transit | B15: =SUMIFS(Unmatched!$C$12:$C$19,Unmatched!$E$12:$E$19,"Deposit in transit")
A16: Adjusted book balance | B16: =B13+B14-B15
A17: Reconciliation difference (must be 0) | B17: =B11-B16
A19: Total receipts (bank) | B19: =SUM(Raw_Bank!$E$2:$E$129)
A20: Total payments (bank) | B20: =SUM(Raw_Bank!$D$2:$D$129)
A21: Lines matched | B21: =COUNTIF(Recon!$K$2:$K$129,"MATCHED")
A22: Unmatched — bank side | B22: =COUNTIF(Recon!$K$2:$K$129,"UNMATCHED")
A23: Unmatched — book side | B23: =COUNTIF(Raw_Book!$H$2:$H$128,FALSE)
A24: Match rate | B24: =B21/(B21+B22)
A25: Oldest outstanding item (days) | B25: =MAX(Unmatched!$G$3:$G$8,Unmatched!$G$12:$G$19)

Sheet Dashboard
A1: Reconciliation dashboard — as of 21 Oct 2026
A3: Match rate | B3: =Summary!B24 | D3: Bank balance | E3: =Summary!B4
A4: Lines matched | B4: =Summary!B21 | D4: Book balance | E4: =Summary!B5
A5: Unmatched items | B5: =Summary!B22+Summary!B23 | D5: Adjusted balance | E5: =Summary!B11
A6: Recon difference | B6: =Summary!B17 | D6: Oldest outstanding (days) | E6: =Summary!B25
A9: Status | B9: Lines
A10: Matched | B10: =Summary!B21
A11: Unmatched | B11: =Summary!B22
A13: Reason | B13: Amount
A14: Bank charges | B14: =Summary!B8
A15: Interest credited | B15: =Summary!B9
A16: Unidentified deposit | B16: =Summary!B10
A17: Unpresented cheques | B17: =Summary!B14
A18: Deposits in transit | B18: =Summary!B15

Sheet Checks
A1: # | B1: Check | C1: Result
A2: 1 | B2: Every bank line classified (MATCHED/UNMATCHED) | C2: =COUNTA(Recon!$K$2:$K$129)=128
A3: 2 | B3: Matched pairs agree on amount (total diff = 0) | C3: =SUMIFS(Recon!$M$2:$M$129,Recon!$K$2:$K$129,"MATCHED")=0
A4: 3 | B4: Reconciliation difference is zero | C4: =Summary!$B$17=0
A5: 4 | B5: 124 book lines matched | C5: =COUNTIF(Raw_Book!$H$2:$H$128,TRUE)=124
A6: 5 | B6: 4 unmatched bank-side items | C6: =Summary!$B$22=4
A7: 6 | B7: 3 unmatched book-side items | C7: =Summary!$B$23=3
A8: 7 | B8: Daily bank EOD ties to statement balance | C8: =Daily!$B$22=Summary!$B$4
A9: 8 | B9: Daily book EOD ties to ledger balance | C9: =Daily!$C$22=Summary!$B$5
