Workbook

Sheet Guide
A1: Owner Dashboard — Maple Ridge Builders Ltd. (CAD)
A2: WHAT THIS IS: the monthly owner dashboard a construction CFO would hand
A3: an owner: P&L, cash, receivables and payables in one workbook, built from
A4: QuickBooks Online exports plus spreadsheet inputs. Built as a demo around
A5: a live freelance brief (construction financial dashboard, QuickBooks +
A6: spreadsheets, simple for owners).
A8: DATA: all figures are SYNTHETIC demo data (seed 20261025), invented for
A9: this demo — not a real client's books. Amounts in Canadian dollars.
A11: HOW TO REFRESH: paste the new month's QBO P&L export into Raw_QBO
A12: (columns Month / Category / Amount), new invoices into AR_Aging and
A13: new bills into AP_Aging, then update the As-of date cell (AR J2 / AP I2).
A14: Monthly_PL, Dashboard, Cash and Checks all recalculate from formulas.
... A19: must read TRUE throughout after any refresh.

Sheet Dashboard
A1: Owner Dashboard — Maple Ridge Builders Ltd. (CAD)
A3: YTD Revenue | B3: =Monthly_PL!H11
A4: Gross Margin % | B4: =Monthly_PL!H14
A5: Cash on Hand | B5: =Cash!B6
A6: AR Outstanding | B6: =SUM(AR_Aging!G3:G32)
A7: AP Outstanding | B7: =SUM(AP_Aging!F3:F26)
A8: AR Overdue 61+ days | B8: =AR_Aging!B38

Sheet Raw_QBO
A1: Raw QBO P&L export (paste new exports below row 49)
A2: Month | B2: Category | C2: Amount
A3: 2026-05 | B3: Revenue - Residential | C3: 145594
A4: 2026-05 | B4: Revenue - Commercial | C4: 64846
A5: 2026-05 | B5: Cost - Labour | C5: -49428
A6: 2026-05 | B6: Cost - Materials | C6: -55264
A7: 2026-05 | B7: Cost - Subcontractors | C7: -38583
A8: 2026-05 | B8: Overhead - Office | C8: -7230
A9: 2026-05 | B9: Overhead - Insurance | C9: -4527
A10: 2026-05 | B10: Overhead - Vehicle | C10: -6660
A11: 2026-06 | B11: Revenue - Residential | C11: 148155
A12: 2026-06 | B12: Revenue - Commercial | C12: 44722
A13: 2026-06 | B13: Cost - Labour | C13: -48245
A14: 2026-06 | B14: Cost - Materials | C14: -43195
... A50: 2026-10 | B50: Overhead - Vehicle | C50: -8067

Sheet Monthly_PL
A1: Monthly P&L — every figure a SUMIFS over Raw_QBO
A2: Category | B2: 2026-05 | C2: 2026-06 | D2: 2026-07 | E2: 2026-08 | F2: 2026-09 | G2: 2026-10 | H2: YTD
A3: Revenue - Residential | B3: =SUMIFS(Raw_QBO!$C$2:$C$500,Raw_QBO!$A$2:$A$500,B$2,Raw_QBO!$B$2:$B$500,$A3) | C3: =SUMIFS(Raw_QBO!$C$2:$C$500,Raw_QBO!$A$2:$A$500,C$2,Raw_QBO!$B$2:$B$500,$A3) | D3: =SUMIFS(Raw_QBO!$C$2:$C$500,Raw_QBO!$A$2:$A$500,D$2,Raw_QBO!$B$2:$B$500,$A3) | E3: =SUMIFS(Raw_QBO!$C$2:$C$500,Raw_QBO!$A$2:$A$500,E$2,Raw_QBO!$B$2:$B$500,$A3) | F3: =SUMIFS(Raw_QBO!$C$2:$C$500,Raw_QBO!$A$2:$A$500,F$2,Raw_QBO!$B$2:$B$500,$A3) | G3: =SUMIFS(Raw_QBO!$C$2:$C$500,Raw_QBO!$A$2:$A$500,G$2,Raw_QBO!$B$2:$B$500,$A3) | H3: =SUM(B3:G3)
A4: Revenue - Commercial | B4: =SUMIFS(Raw_QBO!$C$2:$C$500,Raw_QBO!$A$2:$A$500,B$2,Raw_QBO!$B$2:$B$500,$A4) | C4: =SUMIFS(Raw_QBO!$C$2:$C$500,Raw_QBO!$A$2:$A$500,C$2,Raw_QBO!$B$2:$B$500,$A4) | D4: =SUMIFS(Raw_QBO!$C$2:$C$500,Raw_QBO!$A$2:$A$500,D$2,Raw_QBO!$B$2:$B$500,$A4) | E4: =SUMIFS(Raw_QBO!$C$2:$C$500,Raw_QBO!$A$2:$A$500,E$2,Raw_QBO!$B$2:$B$500,$A4) | F4: =SUMIFS(Raw_QBO!$C$2:$C$500,Raw_QBO!$A$2:$A$500,F$2,Raw_QBO!$B$2:$B$500,$A4) | G4: =SUMIFS(Raw_QBO!$C$2:$C$500,Raw_QBO!$A$2:$A$500,G$2,Raw_QBO!$B$2:$B$500,$A4) | H4: =SUM(B4:G4)
A5: Cost - Labour | B5: =SUMIFS(Raw_QBO!$C$2:$C$500,Raw_QBO!$A$2:$A$500,B$2,Raw_QBO!$B$2:$B$500,$A5) | C5: =SUMIFS(Raw_QBO!$C$2:$C$500,Raw_QBO!$A$2:$A$500,C$2,Raw_QBO!$B$2:$B$500,$A5) | D5: =SUMIFS(Raw_QBO!$C$2:$C$500,Raw_QBO!$A$2:$A$500,D$2,Raw_QBO!$B$2:$B$500,$A5) | E5: =SUMIFS(Raw_QBO!$C$2:$C$500,Raw_QBO!$A$2:$A$500,E$2,Raw_QBO!$B$2:$B$500,$A5) | F5: =SUMIFS(Raw_QBO!$C$2:$C$500,Raw_QBO!$A$2:$A$500,F$2,Raw_QBO!$B$2:$B$500,$A5) | G5: =SUMIFS(Raw_QBO!$C$2:$C$500,Raw_QBO!$A$2:$A$500,G$2,Raw_QBO!$B$2:$B$500,$A5) | H5: =SUM(B5:G5)
A6: Cost - Materials | B6: =SUMIFS(Raw_QBO!$C$2:$C$500,Raw_QBO!$A$2:$A$500,B$2,Raw_QBO!$B$2:$B$500,$A6) | C6: =SUMIFS(Raw_QBO!$C$2:$C$500,Raw_QBO!$A$2:$A$500,C$2,Raw_QBO!$B$2:$B$500,$A6) | D6: =SUMIFS(Raw_QBO!$C$2:$C$500,Raw_QBO!$A$2:$A$500,D$2,Raw_QBO!$B$2:$B$500,$A6) | E6: =SUMIFS(Raw_QBO!$C$2:$C$500,Raw_QBO!$A$2:$A$500,E$2,Raw_QBO!$B$2:$B$500,$A6) | F6: =SUMIFS(Raw_QBO!$C$2:$C$500,Raw_QBO!$A$2:$A$500,F$2,Raw_QBO!$B$2:$B$500,$A6) | G6: =SUMIFS(Raw_QBO!$C$2:$C$500,Raw_QBO!$A$2:$A$500,G$2,Raw_QBO!$B$2:$B$500,$A6) | H6: =SUM(B6:G6)
A7: Cost - Subcontractors | B7: =SUMIFS(Raw_QBO!$C$2:$C$500,Raw_QBO!$A$2:$A$500,B$2,Raw_QBO!$B$2:$B$500,$A7) | C7: =SUMIFS(Raw_QBO!$C$2:$C$500,Raw_QBO!$A$2:$A$500,C$2,Raw_QBO!$B$2:$B$500,$A7) | D7: =SUMIFS(Raw_QBO!$C$2:$C$500,Raw_QBO!$A$2:$A$500,D$2,Raw_QBO!$B$2:$B$500,$A7) | E7: =SUMIFS(Raw_QBO!$C$2:$C$500,Raw_QBO!$A$2:$A$500,E$2,Raw_QBO!$B$2:$B$500,$A7) | F7: =SUMIFS(Raw_QBO!$C$2:$C$500,Raw_QBO!$A$2:$A$500,F$2,Raw_QBO!$B$2:$B$500,$A7) | G7: =SUMIFS(Raw_QBO!$C$2:$C$500,Raw_QBO!$A$2:$A$500,G$2,Raw_QBO!$B$2:$B$500,$A7) | H7: =SUM(B7:G7)
A8: Overhead - Office | B8: =SUMIFS(Raw_QBO!$C$2:$C$500,Raw_QBO!$A$2:$A$500,B$2,Raw_QBO!$B$2:$B$500,$A8) | C8: =SUMIFS(Raw_QBO!$C$2:$C$500,Raw_QBO!$A$2:$A$500,C$2,Raw_QBO!$B$2:$B$500,$A8) | D8: =SUMIFS(Raw_QBO!$C$2:$C$500,Raw_QBO!$A$2:$A$500,D$2,Raw_QBO!$B$2:$B$500,$A8) | E8: =SUMIFS(Raw_QBO!$C$2:$C$500,Raw_QBO!$A$2:$A$500,E$2,Raw_QBO!$B$2:$B$500,$A8) | F8: =SUMIFS(Raw_QBO!$C$2:$C$500,Raw_QBO!$A$2:$A$500,F$2,Raw_QBO!$B$2:$B$500,$A8) | G8: =SUMIFS(Raw_QBO!$C$2:$C$500,Raw_QBO!$A$2:$A$500,G$2,Raw_QBO!$B$2:$B$500,$A8) | H8: =SUM(B8:G8)
A9: Overhead - Insurance | B9: =SUMIFS(Raw_QBO!$C$2:$C$500,Raw_QBO!$A$2:$A$500,B$2,Raw_QBO!$B$2:$B$500,$A9) | C9: =SUMIFS(Raw_QBO!$C$2:$C$500,Raw_QBO!$A$2:$A$500,C$2,Raw_QBO!$B$2:$B$500,$A9) | D9: =SUMIFS(Raw_QBO!$C$2:$C$500,Raw_QBO!$A$2:$A$500,D$2,Raw_QBO!$B$2:$B$500,$A9) | E9: =SUMIFS(Raw_QBO!$C$2:$C$500,Raw_QBO!$A$2:$A$500,E$2,Raw_QBO!$B$2:$B$500,$A9) | F9: =SUMIFS(Raw_QBO!$C$2:$C$500,Raw_QBO!$A$2:$A$500,F$2,Raw_QBO!$B$2:$B$500,$A9) | G9: =SUMIFS(Raw_QBO!$C$2:$C$500,Raw_QBO!$A$2:$A$500,G$2,Raw_QBO!$B$2:$B$500,$A9) | H9: =SUM(B9:G9)
A10: Overhead - Vehicle | B10: =SUMIFS(Raw_QBO!$C$2:$C$500,Raw_QBO!$A$2:$A$500,B$2,Raw_QBO!$B$2:$B$500,$A10) | C10: =SUMIFS(Raw_QBO!$C$2:$C$500,Raw_QBO!$A$2:$A$500,C$2,Raw_QBO!$B$2:$B$500,$A10) | D10: =SUMIFS(Raw_QBO!$C$2:$C$500,Raw_QBO!$A$2:$A$500,D$2,Raw_QBO!$B$2:$B$500,$A10) | E10: =SUMIFS(Raw_QBO!$C$2:$C$500,Raw_QBO!$A$2:$A$500,E$2,Raw_QBO!$B$2:$B$500,$A10) | F10: =SUMIFS(Raw_QBO!$C$2:$C$500,Raw_QBO!$A$2:$A$500,F$2,Raw_QBO!$B$2:$B$500,$A10) | G10: =SUMIFS(Raw_QBO!$C$2:$C$500,Raw_QBO!$A$2:$A$500,G$2,Raw_QBO!$B$2:$B$500,$A10) | H10: =SUM(B10:G10)
A11: Total Revenue | B11: =SUM(B3:B4) | C11: =SUM(C3:C4) | D11: =SUM(D3:D4) | E11: =SUM(E3:E4) | F11: =SUM(F3:F4) | G11: =SUM(G3:G4) | H11: =SUM(H3:H4)
A12: Total Costs | B12: =SUM(B5:B10) | C12: =SUM(C5:C10) | D12: =SUM(D5:D10) | E12: =SUM(E5:E10) | F12: =SUM(F5:F10) | G12: =SUM(G5:G10) | H12: =SUM(H5:H10)
A13: Gross Profit | B13: =B11+B12 | C13: =C11+C12 | D13: =D11+D12 | E13: =E11+E12 | F13: =F11+F12 | G13: =G11+G12 | H13: =H11+H12
A14: Gross Margin % | B14: =IF(B11=0,0,B13/B11) | C14: =IF(C11=0,0,C13/C11) | D14: =IF(D11=0,0,D13/D11) | E14: =IF(E11=0,0,E13/E11) | F14: =IF(F11=0,0,F13/F11) | G14: =IF(G11=0,0,G13/G11) | H14: =IF(H11=0,0,H13/H11)

Sheet AR_Aging
A1: Receivables — aging buckets are formulas off the As-of date
A2: InvoiceID | B2: Customer | C2: IssueDate | D2: DueDate | E2: Amount | F2: PaidAmount | G2: Outstanding | H2: Bucket | J2: As-of date | K2: 46320
A3: INV-1001 | B3: Sooke Bay Estates | C3: 46283 | D3: 46313 | E3: 10942 | F3: 4191 | G3: =E3-F3 | H3: =IF(G3=0,"Paid",IF(D3>=$K$2,"Current",IF($K$2-D3<=30,"1-30",IF($K$2-D3<=60,"31-60","61+"))))
A4: INV-1002 | B4: Westshore Properties | C4: 46280 | D4: 46310 | E4: 23450 | F4: 0 | G4: =E4-F4 | H4: =IF(G4=0,"Paid",IF(D4>=$K$2,"Current",IF($K$2-D4<=30,"1-30",IF($K$2-D4<=60,"31-60","61+"))))
A5: INV-1003 | B5: Gordon Head Builders | C5: 46244 | D5: 46275 | E5: 22386 | F5: 10873 | G5: =E5-F5 | H5: =IF(G5=0,"Paid",IF(D5>=$K$2,"Current",IF($K$2-D5<=30,"1-30",IF($K$2-D5<=60,"31-60","61+"))))
A6: INV-1004 | B6: Westshore Properties | C6: 46287 | D6: 46317 | E6: 18818 | F6: 18818 | G6: =E6-F6 | H6: =IF(G6=0,"Paid",IF(D6>=$K$2,"Current",IF($K$2-D6<=30,"1-30",IF($K$2-D6<=60,"31-60","61+"))))
A7: INV-1005 | B7: Gordon Head Builders | C7: 46283 | D7: 46313 | E7: 20156 | F7: 20156 | G7: =E7-F7 | H7: =IF(G7=0,"Paid",IF(D7>=$K$2,"Current",IF($K$2-D7<=30,"1-30",IF($K$2-D7<=60,"31-60","61+"))))
A8: INV-1006 | B8: Harbourview Developments | C8: 46257 | D8: 46288 | E8: 4616 | F8: 4616 | G8: =E8-F8 | H8: =IF(G8=0,"Paid",IF(D8>=$K$2,"Current",IF($K$2-D8<=30,"1-30",IF($K$2-D8<=60,"31-60","61+"))))
A9: INV-1007 | B9: Colwood Construction | C9: 46297 | D9: 46328 | E9: 11755 | F9: 6884 | G9: =E9-F9 | H9: =IF(G9=0,"Paid",IF(D9>=$K$2,"Current",IF($K$2-D9<=30,"1-30",IF($K$2-D9<=60,"31-60","61+"))))
A10: INV-1008 | B10: Peninsula Contracting | C10: 46301 | D10: 46332 | E10: 10922 | F10: 1806 | G10: =E10-F10 | H10: =IF(G10=0,"Paid",IF(D10>=$K$2,"Current",IF($K$2-D10<=30,"1-30",IF($K$2-D10<=60,"31-60","61+"))))
A11: INV-1009 | B11: Westshore Properties | C11: 46259 | D11: 46290 | E11: 26766 | F11: 24226 | G11: =E11-F11 | H11: =IF(G11=0,"Paid",IF(D11>=$K$2,"Current",IF($K$2-D11<=30,"1-30",IF($K$2-D11<=60,"31-60","61+"))))
A12: INV-1010 | B12: Sooke Bay Estates | C12: 46287 | D12: 46317 | E12: 25917 | F12: 25917 | G12: =E12-F12 | H12: =IF(G12=0,"Paid",IF(D12>=$K$2,"Current",IF($K$2-D12<=30,"1-30",IF($K$2-D12<=60,"31-60","61+"))))
A13: INV-1011 | B13: Fairfield Renovations | C13: 46286 | D13: 46316 | E13: 23503 | F13: 23503 | G13: =E13-F13 | H13: =IF(G13=0,"Paid",IF(D13>=$K$2,"Current",IF($K$2-D13<=30,"1-30",IF($K$2-D13<=60,"31-60","61+"))))
A14: INV-1012 | B14: Colwood Construction | C14: 46269 | D14: 46299 | E14: 13978 | F14: 13978 | G14: =E14-F14 | H14: =IF(G14=0,"Paid",IF(D14>=$K$2,"Current",IF($K$2-D14<=30,"1-30",IF($K$2-D14<=60,"31-60","61+"))))
... A32: INV-1030 | B32: Sooke Bay Estates | C32: 46236 | D32: 46267 | E32: 5801 | F32: 1985 | G32: =E32-F32 | H32: =IF(G32=0,"Paid",IF(D32>=$K$2,"Current",IF($K$2-D32<=30,"1-30",IF($K$2-D32<=60,"31-60","61+"))))
A34: Bucket | B34: Outstanding
A35: Current | B35: =SUMIFS($G$3:$G$32,$H$3:$H$32,$A35)
A36: 1-30 | B36: =SUMIFS($G$3:$G$32,$H$3:$H$32,$A36)
A37: 31-60 | B37: =SUMIFS($G$3:$G$32,$H$3:$H$32,$A37)
A38: 61+ | B38: =SUMIFS($G$3:$G$32,$H$3:$H$32,$A38)
A39: Total | B39: =SUM(B35:B38)

Sheet AP_Aging
A1: Payables — aging buckets are formulas off the As-of date
A2: BillID | B2: Vendor | C2: DueDate | D2: Amount | E2: PaidAmount | F2: Outstanding | G2: Bucket | I2: As-of date | J2: 46320
A3: BILL-2001 | B3: Victoria Roofing Supply | C3: 46317 | D3: 8174 | E3: 3415 | F3: =D3-E3 | G3: =IF(F3=0,"Paid",IF(C3>=$J$2,"Current",IF($J$2-C3<=30,"1-30",IF($J$2-C3<=60,"31-60","61+"))))
A4: BILL-2002 | B4: Pacific Concrete Ltd. | C4: 46299 | D4: 18953 | E4: 18953 | F4: =D4-E4 | G4: =IF(F4=0,"Paid",IF(C4>=$J$2,"Current",IF($J$2-C4<=30,"1-30",IF($J$2-C4<=60,"31-60","61+"))))
A5: BILL-2003 | B5: West Coast Electrical | C5: 46268 | D5: 4374 | E5: 966 | F5: =D5-E5 | G5: =IF(F5=0,"Paid",IF(C5>=$J$2,"Current",IF($J$2-C5<=30,"1-30",IF($J$2-C5<=60,"31-60","61+"))))
A6: BILL-2004 | B6: Peninsula Scaffolding | C6: 46344 | D6: 17230 | E6: 17230 | F6: =D6-E6 | G6: =IF(F6=0,"Paid",IF(C6>=$J$2,"Current",IF($J$2-C6<=30,"1-30",IF($J$2-C6<=60,"31-60","61+"))))
A7: BILL-2005 | B7: West Coast Electrical | C7: 46308 | D7: 19290 | E7: 19290 | F7: =D7-E7 | G7: =IF(F7=0,"Paid",IF(C7>=$J$2,"Current",IF($J$2-C7<=30,"1-30",IF($J$2-C7<=60,"31-60","61+"))))
A8: BILL-2006 | B8: Island Lumber Supply | C8: 46289 | D8: 14431 | E8: 0 | F8: =D8-E8 | G8: =IF(F8=0,"Paid",IF(C8>=$J$2,"Current",IF($J$2-C8<=30,"1-30",IF($J$2-C8<=60,"31-60","61+"))))
A9: BILL-2007 | B9: West Coast Electrical | C9: 46283 | D9: 15455 | E9: 15455 | F9: =D9-E9 | G9: =IF(F9=0,"Paid",IF(C9>=$J$2,"Current",IF($J$2-C9<=30,"1-30",IF($J$2-C9<=60,"31-60","61+"))))
A10: BILL-2008 | B10: Capital Drywall | C10: 46319 | D10: 20121 | E10: 20121 | F10: =D10-E10 | G10: =IF(F10=0,"Paid",IF(C10>=$J$2,"Current",IF($J$2-C10<=30,"1-30",IF($J$2-C10<=60,"31-60","61+"))))
A11: BILL-2009 | B11: Harbour Paint & Finishes | C11: 46340 | D11: 15386 | E11: 0 | F11: =D11-E11 | G11: =IF(F11=0,"Paid",IF(C11>=$J$2,"Current",IF($J$2-C11<=30,"1-30",IF($J$2-C11<=60,"31-60","61+"))))
A12: BILL-2010 | B12: Victoria Roofing Supply | C12: 46318 | D12: 9826 | E12: 9826 | F12: =D12-E12 | G12: =IF(F12=0,"Paid",IF(C12>=$J$2,"Current",IF($J$2-C12<=30,"1-30",IF($J$2-C12<=60,"31-60","61+"))))
A13: BILL-2011 | B13: Harbour Paint & Finishes | C13: 46331 | D13: 7712 | E13: 7712 | F13: =D13-E13 | G13: =IF(F13=0,"Paid",IF(C13>=$J$2,"Current",IF($J$2-C13<=30,"1-30",IF($J$2-C13<=60,"31-60","61+"))))
A14: BILL-2012 | B14: Victoria Roofing Supply | C14: 46331 | D14: 3352 | E14: 3352 | F14: =D14-E14 | G14: =IF(F14=0,"Paid",IF(C14>=$J$2,"Current",IF($J$2-C14<=30,"1-30",IF($J$2-C14<=60,"31-60","61+"))))
... A26: BILL-2024 | B26: Capital Drywall | C26: 46303 | D26: 20786 | E26: 10338 | F26: =D26-E26 | G26: =IF(F26=0,"Paid",IF(C26>=$J$2,"Current",IF($J$2-C26<=30,"1-30",IF($J$2-C26<=60,"31-60","61+"))))
A28: Bucket | B28: Outstanding
A29: Current | B29: =SUMIFS($F$3:$F$26,$G$3:$G$26,$A29)
A30: 1-30 | B30: =SUMIFS($F$3:$F$26,$G$3:$G$26,$A30)
A31: 31-60 | B31: =SUMIFS($F$3:$F$26,$G$3:$G$26,$A31)
A32: 61+ | B32: =SUMIFS($F$3:$F$26,$G$3:$G$26,$A32)
A33: Total | B33: =SUM(B29:B32)

Sheet Cash
A1: Cash position — opening + collected - paid
A3: Opening bank balance (2026-05-01) | B3: 84500
A4: AR collected (paid amounts) | B4: =SUM(AR_Aging!$F$3:$F$32)
A5: AP paid | B5: =SUM(AP_Aging!$E$3:$E$26)
A6: Cash on hand | B6: =B3+B4-B5

Sheet Checks
A1: Tie-out checks — every row must read TRUE
A2: Check | B2: Result
A3: PL YTD revenue = raw revenue rows | B3: =ROUND(Monthly_PL!H11-(SUMIFS(Raw_QBO!$C$2:$C$500,Raw_QBO!$B$2:$B$500,"Revenue - Residential")+SUMIFS(Raw_QBO!$C$2:$C$500,Raw_QBO!$B$2:$B$500,"Revenue - Commercial")),2)=0
A4: PL YTD costs = raw total - raw revenue | B4: =ROUND(Monthly_PL!H12-(SUM(Raw_QBO!$C$2:$C$500)-(SUMIFS(Raw_QBO!$C$2:$C$500,Raw_QBO!$B$2:$B$500,"Revenue - Residential")+SUMIFS(Raw_QBO!$C$2:$C$500,Raw_QBO!$B$2:$B$500,"Revenue - Commercial"))),2)=0
A5: AR bucket total = AR outstanding | B5: =ROUND(AR_Aging!B39-SUM(AR_Aging!G3:G32),2)=0
A6: AP bucket total = AP outstanding | B6: =ROUND(AP_Aging!B33-SUM(AP_Aging!F3:F26),2)=0
A7: Dashboard revenue = PL YTD revenue | B7: =Dashboard!B3=Monthly_PL!H11
A8: Dashboard cash = Cash sheet | B8: =Dashboard!B5=Cash!B6
A9: Gross margin within 0-100% | B9: =AND(Monthly_PL!H14>=0,Monthly_PL!H14<=1)
A10: No negative revenue month | B10: =MIN(Monthly_PL!B11:G11)>=0
