Workbook

Sheet Guide
A1: ProfitPulse — Profitability & Financial-Ratio Dashboard
A2: Company (fictional): Shakti Consumer Goods Pvt. Ltd.
A3: Currency: INR lakh | Period: FY21–FY25 (balance sheet from FY20 for averages)
A5: SHEETS
A6: Raw_PNL — profit & loss inputs (FY21–FY25); gross/EBITDA/EBIT/EBT/net are formulas
A7: Raw_BS — balance-sheet inputs (FY20–FY25); totals are formulas; Cash is the balancing plug
A8: Ratios — 22 ratios, ALL formulas: liquidity, profitability, leverage, efficiency, growth
A9: DuPont — ROE decomposition (net margin × asset turnover × equity multiplier) + tie-out
A10: Dashboard — FY25 KPI cards + 3 native charts (all formula-fed)
A11: AI_Report — rule-based narrative + red-flag checklist with live formulas
A12: Checks — 8 integrity checks (all must read TRUE / 0)
A14: HOW TO REFRESH
... A22: Receivable days rising YoY (collections slipping)

Sheet Raw_PNL
A1: Item | B1: FY21 | C1: FY22 | D1: FY23 | E1: FY24 | F1: FY25
A2: Revenue | B2: 8450 | C2: 9240 | D2: 10180 | E2: 11090 | F2: 12150
A3: COGS | B3: 5220 | C3: 5650 | D3: 6180 | E3: 6720 | F3: 7360
A4: Gross profit | B4: =B2-B3 | C4: =C2-C3 | D4: =D2-D3 | E4: =E2-E3 | F4: =F2-F3
A5: SG&A | B5: 2010 | C5: 2140 | D5: 2290 | E5: 2430 | F5: 2610
A6: EBITDA | B6: =B4-B5 | C6: =C4-C5 | D6: =D4-D5 | E6: =E4-E5 | F6: =F4-F5
A7: Depreciation | B7: 320 | C7: 345 | D7: 370 | E7: 395 | F7: 420
A8: EBIT | B8: =B6-B7 | C8: =C6-C7 | D8: =D6-D7 | E8: =E6-E7 | F8: =F6-F7
A9: Interest | B9: 180 | C9: 195 | D9: 170 | E9: 150 | F9: 135
A10: EBT | B10: =B8-B9 | C10: =C8-C9 | D10: =D8-D9 | E10: =E8-E9 | F10: =F8-F9
A11: Tax | B11: 180 | C11: 228 | D11: 292 | E11: 349 | F11: 406
A12: Net income | B12: =B10-B11 | C12: =C10-C11 | D12: =D10-D11 | E12: =E10-E11 | F12: =F10-F11

Sheet Raw_BS
A1: Item | B1: FY20 | C1: FY21 | D1: FY22 | E1: FY23 | F1: FY24 | G1: FY25
A2: Cash & bank (plug) | B2: 2320 | C2: 2520 | D2: 2832 | E2: 3020 | F2: 3466 | G2: 4025
A3: Receivables | B3: 1290 | C3: 1410 | D3: 1560 | E3: 1780 | F3: 1980 | G3: 2240
A4: Inventory | B4: 1040 | C4: 1120 | D4: 1230 | E4: 1380 | F4: 1520 | G4: 1690
A5: Other current assets | B5: 240 | C5: 260 | D5: 280 | E5: 300 | F5: 320 | G5: 340
A6: PPE (net) | B6: 2840 | C6: 2980 | D6: 3120 | E6: 3260 | F6: 3380 | G6: 3500
A7: Other non-current assets | B7: 170 | C7: 180 | D7: 190 | E7: 200 | F7: 210 | G7: 220
A8: Total current assets | B8: =B2+B3+B4+B5 | C8: =C2+C3+C4+C5 | D8: =D2+D3+D4+D5 | E8: =E2+E3+E4+E5 | F8: =F2+F3+F4+F5 | G8: =G2+G3+G4+G5
A9: Total non-current assets | B9: =B6+B7 | C9: =C6+C7 | D9: =D6+D7 | E9: =E6+E7 | F9: =F6+F7 | G9: =G6+G7
A10: Total assets | B10: =B8+B9 | C10: =C8+C9 | D10: =D8+D9 | E10: =E8+E9 | F10: =F8+F9 | G10: =G8+G9
A11: Payables | B11: 900 | C11: 980 | D11: 1080 | E11: 1190 | F11: 1300 | G11: 1420
A12: Short-term debt | B12: 500 | C12: 520 | D12: 560 | E12: 480 | F12: 420 | G12: 380
A13: Other current liabilities | B13: 290 | C13: 310 | D13: 340 | E13: 370 | F13: 400 | G13: 430
A14: Total current liabilities | B14: =B11+B12+B13 | C14: =C11+C12+C13 | D14: =D11+D12+D13 | E14: =E11+E12+E13 | F14: =F11+F12+F13 | G14: =G11+G12+G13
A15: Long-term debt | B15: 1520 | C15: 1420 | D15: 1300 | E15: 1080 | F15: 880 | G15: 680
A16: Other non-current liabilities | B16: 230 | C16: 240 | D16: 250 | E16: 260 | F16: 270 | G16: 280
A17: Total non-current liabilities | B17: =B15+B16 | C17: =C15+C16 | D17: =D15+D16 | E17: =E15+E16 | F17: =F15+F16 | G17: =G15+G16
A18: Total liabilities | B18: =B14+B17 | C18: =C14+C17 | D18: =D14+D17 | E18: =E14+E17 | F18: =F14+F17 | G18: =G14+G17
A19: Share capital | B19: 2000 | C19: 2000 | D19: 2000 | E19: 2000 | F19: 2000 | G19: 2000
A20: Reserves & surplus | B20: 2460 | C20: 3000 | D20: 3682 | E20: 4560 | F20: 5606 | G20: 6825
A21: Total equity | B21: =B19+B20 | C21: =C19+C20 | D21: =D19+D20 | E21: =E19+E20 | F21: =F19+F20 | G21: =G19+G20
A22: Total L&E | B22: =B18+B21 | C22: =C18+C21 | D22: =D18+D21 | E22: =E18+E21 | F22: =F18+F21 | G22: =G18+G21

Sheet Ratios
A1: Ratio | B1: FY21 | C1: FY22 | D1: FY23 | E1: FY24 | F1: FY25
A2: Current ratio | B2: =IF(Raw_BS!C14=0,0,Raw_BS!C8/Raw_BS!C14) | C2: =IF(Raw_BS!D14=0,0,Raw_BS!D8/Raw_BS!D14) | D2: =IF(Raw_BS!E14=0,0,Raw_BS!E8/Raw_BS!E14) | E2: =IF(Raw_BS!F14=0,0,Raw_BS!F8/Raw_BS!F14) | F2: =IF(Raw_BS!G14=0,0,Raw_BS!G8/Raw_BS!G14)
A3: Quick ratio | B3: =IF(Raw_BS!C14=0,0,(Raw_BS!C2+Raw_BS!C3)/Raw_BS!C14) | C3: =IF(Raw_BS!D14=0,0,(Raw_BS!D2+Raw_BS!D3)/Raw_BS!D14) | D3: =IF(Raw_BS!E14=0,0,(Raw_BS!E2+Raw_BS!E3)/Raw_BS!E14) | E3: =IF(Raw_BS!F14=0,0,(Raw_BS!F2+Raw_BS!F3)/Raw_BS!F14) | F3: =IF(Raw_BS!G14=0,0,(Raw_BS!G2+Raw_BS!G3)/Raw_BS!G14)
A4: Cash ratio | B4: =IF(Raw_BS!C14=0,0,Raw_BS!C2/Raw_BS!C14) | C4: =IF(Raw_BS!D14=0,0,Raw_BS!D2/Raw_BS!D14) | D4: =IF(Raw_BS!E14=0,0,Raw_BS!E2/Raw_BS!E14) | E4: =IF(Raw_BS!F14=0,0,Raw_BS!F2/Raw_BS!F14) | F4: =IF(Raw_BS!G14=0,0,Raw_BS!G2/Raw_BS!G14)
A5: Working capital | B5: =Raw_BS!C8-Raw_BS!C14 | C5: =Raw_BS!D8-Raw_BS!D14 | D5: =Raw_BS!E8-Raw_BS!E14 | E5: =Raw_BS!F8-Raw_BS!F14 | F5: =Raw_BS!G8-Raw_BS!G14
A6: Gross margin | B6: =IF(Raw_PNL!B2=0,0,Raw_PNL!B4/Raw_PNL!B2) | C6: =IF(Raw_PNL!C2=0,0,Raw_PNL!C4/Raw_PNL!C2) | D6: =IF(Raw_PNL!D2=0,0,Raw_PNL!D4/Raw_PNL!D2) | E6: =IF(Raw_PNL!E2=0,0,Raw_PNL!E4/Raw_PNL!E2) | F6: =IF(Raw_PNL!F2=0,0,Raw_PNL!F4/Raw_PNL!F2)
A7: EBITDA margin | B7: =IF(Raw_PNL!B2=0,0,Raw_PNL!B6/Raw_PNL!B2) | C7: =IF(Raw_PNL!C2=0,0,Raw_PNL!C6/Raw_PNL!C2) | D7: =IF(Raw_PNL!D2=0,0,Raw_PNL!D6/Raw_PNL!D2) | E7: =IF(Raw_PNL!E2=0,0,Raw_PNL!E6/Raw_PNL!E2) | F7: =IF(Raw_PNL!F2=0,0,Raw_PNL!F6/Raw_PNL!F2)
A8: EBIT margin | B8: =IF(Raw_PNL!B2=0,0,Raw_PNL!B8/Raw_PNL!B2) | C8: =IF(Raw_PNL!C2=0,0,Raw_PNL!C8/Raw_PNL!C2) | D8: =IF(Raw_PNL!D2=0,0,Raw_PNL!D8/Raw_PNL!D2) | E8: =IF(Raw_PNL!E2=0,0,Raw_PNL!E8/Raw_PNL!E2) | F8: =IF(Raw_PNL!F2=0,0,Raw_PNL!F8/Raw_PNL!F2)
A9: Net margin | B9: =IF(Raw_PNL!B2=0,0,Raw_PNL!B12/Raw_PNL!B2) | C9: =IF(Raw_PNL!C2=0,0,Raw_PNL!C12/Raw_PNL!C2) | D9: =IF(Raw_PNL!D2=0,0,Raw_PNL!D12/Raw_PNL!D2) | E9: =IF(Raw_PNL!E2=0,0,Raw_PNL!E12/Raw_PNL!E2) | F9: =IF(Raw_PNL!F2=0,0,Raw_PNL!F12/Raw_PNL!F2)
A10: Return on equity (ROE) | B10: =IF(((Raw_BS!C21+Raw_BS!B21)/2)=0,0,Raw_PNL!B12/((Raw_BS!C21+Raw_BS!B21)/2)) | C10: =IF(((Raw_BS!D21+Raw_BS!C21)/2)=0,0,Raw_PNL!C12/((Raw_BS!D21+Raw_BS!C21)/2)) | D10: =IF(((Raw_BS!E21+Raw_BS!D21)/2)=0,0,Raw_PNL!D12/((Raw_BS!E21+Raw_BS!D21)/2)) | E10: =IF(((Raw_BS!F21+Raw_BS!E21)/2)=0,0,Raw_PNL!E12/((Raw_BS!F21+Raw_BS!E21)/2)) | F10: =IF(((Raw_BS!G21+Raw_BS!F21)/2)=0,0,Raw_PNL!F12/((Raw_BS!G21+Raw_BS!F21)/2))
A11: Return on assets (ROA) | B11: =IF(((Raw_BS!C10+Raw_BS!B10)/2)=0,0,Raw_PNL!B12/((Raw_BS!C10+Raw_BS!B10)/2)) | C11: =IF(((Raw_BS!D10+Raw_BS!C10)/2)=0,0,Raw_PNL!C12/((Raw_BS!D10+Raw_BS!C10)/2)) | D11: =IF(((Raw_BS!E10+Raw_BS!D10)/2)=0,0,Raw_PNL!D12/((Raw_BS!E10+Raw_BS!D10)/2)) | E11: =IF(((Raw_BS!F10+Raw_BS!E10)/2)=0,0,Raw_PNL!E12/((Raw_BS!F10+Raw_BS!E10)/2)) | F11: =IF(((Raw_BS!G10+Raw_BS!F10)/2)=0,0,Raw_PNL!F12/((Raw_BS!G10+Raw_BS!F10)/2))
A12: Return on capital employed (ROCE) | B12: =IF((Raw_BS!C21+Raw_BS!C17)=0,0,Raw_PNL!B8/(Raw_BS!C21+Raw_BS!C17)) | C12: =IF((Raw_BS!D21+Raw_BS!D17)=0,0,Raw_PNL!C8/(Raw_BS!D21+Raw_BS!D17)) | D12: =IF((Raw_BS!E21+Raw_BS!E17)=0,0,Raw_PNL!D8/(Raw_BS!E21+Raw_BS!E17)) | E12: =IF((Raw_BS!F21+Raw_BS!F17)=0,0,Raw_PNL!E8/(Raw_BS!F21+Raw_BS!F17)) | F12: =IF((Raw_BS!G21+Raw_BS!G17)=0,0,Raw_PNL!F8/(Raw_BS!G21+Raw_BS!G17))
A13: Debt / Equity | B13: =IF(Raw_BS!C21=0,0,Raw_BS!C18/Raw_BS!C21) | C13: =IF(Raw_BS!D21=0,0,Raw_BS!D18/Raw_BS!D21) | D13: =IF(Raw_BS!E21=0,0,Raw_BS!E18/Raw_BS!E21) | E13: =IF(Raw_BS!F21=0,0,Raw_BS!F18/Raw_BS!F21) | F13: =IF(Raw_BS!G21=0,0,Raw_BS!G18/Raw_BS!G21)
A14: Debt / Assets | B14: =IF(Raw_BS!C10=0,0,Raw_BS!C18/Raw_BS!C10) | C14: =IF(Raw_BS!D10=0,0,Raw_BS!D18/Raw_BS!D10) | D14: =IF(Raw_BS!E10=0,0,Raw_BS!E18/Raw_BS!E10) | E14: =IF(Raw_BS!F10=0,0,Raw_BS!F18/Raw_BS!F10) | F14: =IF(Raw_BS!G10=0,0,Raw_BS!G18/Raw_BS!G10)
A15: Interest coverage (x) | B15: =IF(Raw_PNL!B9=0,0,Raw_PNL!B8/Raw_PNL!B9) | C15: =IF(Raw_PNL!C9=0,0,Raw_PNL!C8/Raw_PNL!C9) | D15: =IF(Raw_PNL!D9=0,0,Raw_PNL!D8/Raw_PNL!D9) | E15: =IF(Raw_PNL!E9=0,0,Raw_PNL!E8/Raw_PNL!E9) | F15: =IF(Raw_PNL!F9=0,0,Raw_PNL!F8/Raw_PNL!F9)
A16: Equity ratio | B16: =IF(Raw_BS!C10=0,0,Raw_BS!C21/Raw_BS!C10) | C16: =IF(Raw_BS!D10=0,0,Raw_BS!D21/Raw_BS!D10) | D16: =IF(Raw_BS!E10=0,0,Raw_BS!E21/Raw_BS!E10) | E16: =IF(Raw_BS!F10=0,0,Raw_BS!F21/Raw_BS!F10) | F16: =IF(Raw_BS!G10=0,0,Raw_BS!G21/Raw_BS!G10)
A17: Receivable days | B17: =IF(Raw_PNL!B2=0,0,((Raw_BS!C3+Raw_BS!B3)/2)/Raw_PNL!B2)*365 | C17: =IF(Raw_PNL!C2=0,0,((Raw_BS!D3+Raw_BS!C3)/2)/Raw_PNL!C2)*365 | D17: =IF(Raw_PNL!D2=0,0,((Raw_BS!E3+Raw_BS!D3)/2)/Raw_PNL!D2)*365 | E17: =IF(Raw_PNL!E2=0,0,((Raw_BS!F3+Raw_BS!E3)/2)/Raw_PNL!E2)*365 | F17: =IF(Raw_PNL!F2=0,0,((Raw_BS!G3+Raw_BS!F3)/2)/Raw_PNL!F2)*365
A18: Inventory days | B18: =IF(Raw_PNL!B3=0,0,((Raw_BS!C4+Raw_BS!B4)/2)/Raw_PNL!B3)*365 | C18: =IF(Raw_PNL!C3=0,0,((Raw_BS!D4+Raw_BS!C4)/2)/Raw_PNL!C3)*365 | D18: =IF(Raw_PNL!D3=0,0,((Raw_BS!E4+Raw_BS!D4)/2)/Raw_PNL!D3)*365 | E18: =IF(Raw_PNL!E3=0,0,((Raw_BS!F4+Raw_BS!E4)/2)/Raw_PNL!E3)*365 | F18: =IF(Raw_PNL!F3=0,0,((Raw_BS!G4+Raw_BS!F4)/2)/Raw_PNL!F3)*365
A19: Payable days | B19: =IF(Raw_PNL!B3=0,0,((Raw_BS!C11+Raw_BS!B11)/2)/Raw_PNL!B3)*365 | C19: =IF(Raw_PNL!C3=0,0,((Raw_BS!D11+Raw_BS!C11)/2)/Raw_PNL!C3)*365 | D19: =IF(Raw_PNL!D3=0,0,((Raw_BS!E11+Raw_BS!D11)/2)/Raw_PNL!D3)*365 | E19: =IF(Raw_PNL!E3=0,0,((Raw_BS!F11+Raw_BS!E11)/2)/Raw_PNL!E3)*365 | F19: =IF(Raw_PNL!F3=0,0,((Raw_BS!G11+Raw_BS!F11)/2)/Raw_PNL!F3)*365
A20: Cash conversion cycle (days) | B20: =Ratios!B17+Ratios!B18-Ratios!B19 | C20: =Ratios!C17+Ratios!C18-Ratios!C19 | D20: =Ratios!D17+Ratios!D18-Ratios!D19 | E20: =Ratios!E17+Ratios!E18-Ratios!E19 | F20: =Ratios!F17+Ratios!F18-Ratios!F19
A21: Asset turnover (x) | B21: =IF(((Raw_BS!C10+Raw_BS!B10)/2)=0,0,Raw_PNL!B2/((Raw_BS!C10+Raw_BS!B10)/2)) | C21: =IF(((Raw_BS!D10+Raw_BS!C10)/2)=0,0,Raw_PNL!C2/((Raw_BS!D10+Raw_BS!C10)/2)) | D21: =IF(((Raw_BS!E10+Raw_BS!D10)/2)=0,0,Raw_PNL!D2/((Raw_BS!E10+Raw_BS!D10)/2)) | E21: =IF(((Raw_BS!F10+Raw_BS!E10)/2)=0,0,Raw_PNL!E2/((Raw_BS!F10+Raw_BS!E10)/2)) | F21: =IF(((Raw_BS!G10+Raw_BS!F10)/2)=0,0,Raw_PNL!F2/((Raw_BS!G10+Raw_BS!F10)/2))
A22: Revenue growth YoY | B22: n/a | C22: =IF(Raw_PNL!B2=0,0,(Raw_PNL!C2-Raw_PNL!B2)/Raw_PNL!B2) | D22: =IF(Raw_PNL!C2=0,0,(Raw_PNL!D2-Raw_PNL!C2)/Raw_PNL!C2) | E22: =IF(Raw_PNL!D2=0,0,(Raw_PNL!E2-Raw_PNL!D2)/Raw_PNL!D2) | F22: =IF(Raw_PNL!E2=0,0,(Raw_PNL!F2-Raw_PNL!E2)/Raw_PNL!E2)
A23: Net income growth YoY | B23: n/a | C23: =IF(Raw_PNL!B12=0,0,(Raw_PNL!C12-Raw_PNL!B12)/Raw_PNL!B12) | D23: =IF(Raw_PNL!C12=0,0,(Raw_PNL!D12-Raw_PNL!C12)/Raw_PNL!C12) | E23: =IF(Raw_PNL!D12=0,0,(Raw_PNL!E12-Raw_PNL!D12)/Raw_PNL!D12) | F23: =IF(Raw_PNL!E12=0,0,(Raw_PNL!F12-Raw_PNL!E12)/Raw_PNL!E12)

Sheet DuPont
A1: DuPont decomposition of ROE | B1: FY21 | C1: FY22 | D1: FY23 | E1: FY24 | F1: FY25
A2: Net margin (Net income / Revenue) | B2: =Ratios!B9 | C2: =Ratios!C9 | D2: =Ratios!D9 | E2: =Ratios!E9 | F2: =Ratios!F9
A3: Asset turnover (Revenue / Avg assets) | B3: =Ratios!B21 | C3: =Ratios!C21 | D3: =Ratios!D21 | E3: =Ratios!E21 | F3: =Ratios!F21
A4: Equity multiplier (Avg assets / Avg equity) | B4: =IF(((Raw_BS!C21+Raw_BS!B21)/2)=0,0,((Raw_BS!C10+Raw_BS!B10)/2)/((Raw_BS!C21+Raw_BS!B21)/2)) | C4: =IF(((Raw_BS!D21+Raw_BS!C21)/2)=0,0,((Raw_BS!D10+Raw_BS!C10)/2)/((Raw_BS!D21+Raw_BS!C21)/2)) | D4: =IF(((Raw_BS!E21+Raw_BS!D21)/2)=0,0,((Raw_BS!E10+Raw_BS!D10)/2)/((Raw_BS!E21+Raw_BS!D21)/2)) | E4: =IF(((Raw_BS!F21+Raw_BS!E21)/2)=0,0,((Raw_BS!F10+Raw_BS!E10)/2)/((Raw_BS!F21+Raw_BS!E21)/2)) | F4: =IF(((Raw_BS!G21+Raw_BS!F21)/2)=0,0,((Raw_BS!G10+Raw_BS!F10)/2)/((Raw_BS!G21+Raw_BS!F21)/2))
A5: ROE — DuPont product | B5: =DuPont!B2*DuPont!B3*DuPont!B4 | C5: =DuPont!C2*DuPont!C3*DuPont!C4 | D5: =DuPont!D2*DuPont!D3*DuPont!D4 | E5: =DuPont!E2*DuPont!E3*DuPont!E4 | F5: =DuPont!F2*DuPont!F3*DuPont!F4
A6: ROE — direct (check) | B6: =Ratios!B10 | C6: =Ratios!C10 | D6: =Ratios!D10 | E6: =Ratios!E10 | F6: =Ratios!F10
A7: Difference (must be 0) | B7: =DuPont!B5-DuPont!B6 | C7: =DuPont!C5-DuPont!C6 | D7: =DuPont!D5-DuPont!D6 | E7: =DuPont!E5-DuPont!E6 | F7: =DuPont!F5-DuPont!F6

Sheet Dashboard
A1: ProfitPulse — FY25 KPI cards (all formula-fed) | B1: FY25 | C1: vs FY21
A2: Revenue (INR lakh) | B2: =Raw_PNL!F2 | C2: =Raw_PNL!F2-Raw_PNL!B2
A3: Net margin | B3: =Ratios!F9 | C3: =Ratios!F9-Ratios!B9
A4: Return on equity | B4: =Ratios!F10 | C4: =Ratios!F10-Ratios!B10
A5: Current ratio | B5: =Ratios!F2 | C5: =Ratios!F2-Ratios!B2
A6: Debt / Equity | B6: =Ratios!F13 | C6: =Ratios!F13-Ratios!B13
A7: Cash conversion cycle (days) | B7: =Ratios!F20 | C7: =Ratios!F20-Ratios!B20
A8: Interest coverage (x) | B8: =Ratios!F15
A9: Cash & bank (INR lakh) | B9: =Raw_BS!G2

Sheet AI_Report
A1: ProfitPulse — rule-based weekly narrative
A3: Shakti Consumer Goods grew revenue every year FY21–FY25 while cutting debt: long-term debt roughly halved and interest coverage improved — a classic deleveraging story.
A4: Margins expanded across the board (gross, EBITDA and net), driven by COGS and SG&A growing slower than revenue. ROE strengthened as net margin outpaced the equity build.
A5: The watch item is working capital: receivable days drifted up over the period while inventory discipline held — collections, not operations, are the drag on the cash conversion cycle. See the red-flag checklist below (all statuses are live formulas).
A7: Red-flag checklist (FY25, live)
A8: Check | B8: FY25 value | C8: Threshold | D8: Status | E8: Reading
A9: Current ratio < 1.20 | B9: =Ratios!F2 | C9: 1.20 | D9: =IF(Ratios!F2<1.2,"⚠ WATCH","✓ OK") | E9: Short-term liquidity buffer
A10: Quick ratio < 1.00 | B10: =Ratios!F3 | C10: 1.00 | D10: =IF(Ratios!F3<1,"⚠ WATCH","✓ OK") | E10: Liquidity without inventory
A11: Debt/Equity > 1.00 | B11: =Ratios!F13 | C11: 1.00 | D11: =IF(Ratios!F13>1,"⚠ WATCH","✓ OK") | E11: Leverage comfort zone
A12: Interest coverage < 3× | B12: =Ratios!F15 | C12: 3.0× | D12: =IF(Ratios!F15<3,"⚠ WATCH","✓ OK") | E12: Debt-service headroom
A13: Net margin falling YoY | B13: =Ratios!F9 | C13: vs FY24 | D13: =IF(Ratios!F9<Ratios!E9,"⚠ WATCH","✓ OK") | E13: Profitability momentum
A14: Receivable days rising YoY | B14: =Ratios!F17 | C14: vs FY24 | D14: =IF(Ratios!F17>Ratios!E17,"⚠ WATCH","✓ OK") | E14: Collections discipline
A15: CCC > 90 days | B15: =Ratios!F20 | C15: 90 days | D15: =IF(Ratios!F20>90,"⚠ WATCH","✓ OK") | E15: Cash tied in operations
A16: Working capital falling YoY | B16: =Ratios!F5 | C16: vs FY24 | D16: =IF(Ratios!F5<Ratios!E5,"⚠ WATCH","✓ OK") | E16: Net short-term resources

Sheet Checks
A1: Integrity checks — every row must read TRUE / 0
A2: Check | B2: FY21 | C2: FY22 | D2: FY23 | E2: FY24 | F2: FY25
A3: Balance sheet balances (Assets − L&E = 0) | B3: =Raw_BS!C10-Raw_BS!C22 | C3: =Raw_BS!D10-Raw_BS!D22 | D3: =Raw_BS!E10-Raw_BS!E22 | E3: =Raw_BS!F10-Raw_BS!F22 | F3: =Raw_BS!G10-Raw_BS!G22
A4: Reserves rollforward (Res_t − Res_{t−1} − Net_t = 0) | B4: =Raw_BS!C20-Raw_BS!B20-Raw_PNL!B12 | C4: =Raw_BS!D20-Raw_BS!C20-Raw_PNL!C12 | D4: =Raw_BS!E20-Raw_BS!D20-Raw_PNL!D12 | E4: =Raw_BS!F20-Raw_BS!E20-Raw_PNL!E12 | F4: =Raw_BS!G20-Raw_BS!F20-Raw_PNL!F12
A5: P&L foots (Net − (EBT − Tax) = 0) | B5: =Raw_PNL!B12-(Raw_PNL!B10-Raw_PNL!B11) | C5: =Raw_PNL!C12-(Raw_PNL!C10-Raw_PNL!C11) | D5: =Raw_PNL!D12-(Raw_PNL!D10-Raw_PNL!D11) | E5: =Raw_PNL!E12-(Raw_PNL!E10-Raw_PNL!E11) | F5: =Raw_PNL!F12-(Raw_PNL!F10-Raw_PNL!F11)
A6: DuPont tie-out (product − direct = 0) | B6: =DuPont!B7 | C6: =DuPont!C7 | D6: =DuPont!D7 | E6: =DuPont!E7 | F6: =DuPont!F7
A7: Cash positive every year | B7: =Raw_BS!C2>0 | C7: =Raw_BS!D2>0 | D7: =Raw_BS!E2>0 | E7: =Raw_BS!F2>0 | F7: =Raw_BS!G2>0
A8: Margins within [0, 100%] | B8: =AND(Ratios!B6>=0,Ratios!B6<=1,Ratios!B9>=0,Ratios!B9<=1) | C8: =AND(Ratios!C6>=0,Ratios!C6<=1,Ratios!C9>=0,Ratios!C9<=1) | D8: =AND(Ratios!D6>=0,Ratios!D6<=1,Ratios!D9>=0,Ratios!D9<=1) | E8: =AND(Ratios!E6>=0,Ratios!E6<=1,Ratios!E9>=0,Ratios!E9<=1) | F8: =AND(Ratios!F6>=0,Ratios!F6<=1,Ratios!F9>=0,Ratios!F9<=1)
A9: Current ratio positive | B9: =Ratios!B2>0 | C9: =Ratios!C2>0 | D9: =Ratios!D2>0 | E9: =Ratios!E2>0 | F9: =Ratios!F2>0
A10: Working capital = CA − CL | B10: =Ratios!B5-(Raw_BS!C8-Raw_BS!C14) | C10: =Ratios!C5-(Raw_BS!D8-Raw_BS!D14) | D10: =Ratios!D5-(Raw_BS!E8-Raw_BS!E14) | E10: =Ratios!E5-(Raw_BS!F8-Raw_BS!F14) | F10: =Ratios!F5-(Raw_BS!G8-Raw_BS!G14)
