Workbook

Sheet Dashboard
A1: Finance Tracker — Executive Dashboard
A2: KPI | B2: Amount
A3: Total Income | B3: =SUMIF(Transactions!B:B,"Income",Transactions!E:E)
A4: Total Expenses | B4: =SUMIF(Transactions!B:B,"Expense",Transactions!E:E)
A5: Net Profit | B5: =B3-B4
A6: Cash on Hand | B6: =B3-B4
A7: Outstanding Receivables | B7: =SUMIFS(Invoices!E:E,Invoices!F:F,"Unpaid",Invoices!H:H,"Outstanding")
A8: Overdue Amount | B8: =SUMIFS(Invoices!E:E,Invoices!F:F,"Unpaid",Invoices!H:H,"Overdue")
A9: Budget health: see 'Budget vs Actual' (red = over budget)

Sheet Transactions
A1: Date | B1: Type | C1: Category | D1: Description | E1: Amount | F1: Month | G1: TaxCat
A2: 46027 | B2: Income | C2: Client Retainer | D2: Monthly retainer | E2: 42000 | F2: =TEXT(A2,"mmm-yy") | G2: =IF(B2="Income","",VLOOKUP(C2,'Tax Prep'!$A$21:$B$29,2,FALSE))
A3: 46042 | B3: Income | C3: Product Sales | D3: Online product sales | E3: 18000 | F3: =TEXT(A3,"mmm-yy") | G3: =IF(B3="Income","",VLOOKUP(C3,'Tax Prep'!$A$21:$B$29,2,FALSE))
A4: 46023 | B4: Expense | C4: Rent | D4: Office rent | E4: 12000 | F4: =TEXT(A4,"mmm-yy") | G4: =IF(B4="Income","",VLOOKUP(C4,'Tax Prep'!$A$21:$B$29,2,FALSE))
A5: 46025 | B5: Expense | C5: Salaries | D5: Team payroll | E5: 55000 | F5: =TEXT(A5,"mmm-yy") | G5: =IF(B5="Income","",VLOOKUP(C5,'Tax Prep'!$A$21:$B$29,2,FALSE))
A6: 46032 | B6: Expense | C6: Marketing | D6: Ads & campaigns | E6: 8000 | F6: =TEXT(A6,"mmm-yy") | G6: =IF(B6="Income","",VLOOKUP(C6,'Tax Prep'!$A$21:$B$29,2,FALSE))
A7: 46037 | B7: Expense | C7: Travel | D7: Field travel | E7: 4000 | F7: =TEXT(A7,"mmm-yy") | G7: =IF(B7="Income","",VLOOKUP(C7,'Tax Prep'!$A$21:$B$29,2,FALSE))
A8: 46034 | B8: Expense | C8: Utilities | D8: Power & internet | E8: 2500 | F8: =TEXT(A8,"mmm-yy") | G8: =IF(B8="Income","",VLOOKUP(C8,'Tax Prep'!$A$21:$B$29,2,FALSE))
A9: 46030 | B9: Expense | C9: Software | D9: SaaS subscriptions | E9: 3200 | F9: =TEXT(A9,"mmm-yy") | G9: =IF(B9="Income","",VLOOKUP(C9,'Tax Prep'!$A$21:$B$29,2,FALSE))
A10: 46040 | B10: Expense | C10: Office Supplies | D10: Stationery | E10: 1500 | F10: =TEXT(A10,"mmm-yy") | G10: =IF(B10="Income","",VLOOKUP(C10,'Tax Prep'!$A$21:$B$29,2,FALSE))
A11: 46024 | B11: Expense | C11: Insurance | D11: Quarterly premium | E11: 6000 | F11: =TEXT(A11,"mmm-yy") | G11: =IF(B11="Income","",VLOOKUP(C11,'Tax Prep'!$A$21:$B$29,2,FALSE))
A12: 46058 | B12: Income | C12: Client Retainer | D12: Monthly retainer | E12: 42000 | F12: =TEXT(A12,"mmm-yy") | G12: =IF(B12="Income","",VLOOKUP(C12,'Tax Prep'!$A$21:$B$29,2,FALSE))
A13: 46073 | B13: Income | C13: Product Sales | D13: Online product sales | E13: 18500 | F13: =TEXT(A13,"mmm-yy") | G13: =IF(B13="Income","",VLOOKUP(C13,'Tax Prep'!$A$21:$B$29,2,FALSE))
... A88: 46283 | B88: Expense | C88: Office Supplies | D88: Stationery | E88: 1900 | F88: =TEXT(A88,"mmm-yy") | G88: =IF(B88="Income","",VLOOKUP(C88,'Tax Prep'!$A$21:$B$29,2,FALSE))

Sheet Budget vs Actual
A1: Category | B1: Monthly Budget | C1: 9-mo Budget | D1: Actual | E1: Variance | F1: Var%
A2: Rent | B2: 12000 | C2: =B2*9 | D2: =SUMIFS(Transactions!$E:$E,Transactions!$C:$C,$A2,Transactions!$B:$B,"Expense") | E2: =C2-D2 | F2: =IF(C2=0,"",E2/C2)
A3: Salaries | B3: 55000 | C3: =B3*9 | D3: =SUMIFS(Transactions!$E:$E,Transactions!$C:$C,$A3,Transactions!$B:$B,"Expense") | E3: =C3-D3 | F3: =IF(C3=0,"",E3/C3)
A4: Marketing | B4: 9000 | C4: =B4*9 | D4: =SUMIFS(Transactions!$E:$E,Transactions!$C:$C,$A4,Transactions!$B:$B,"Expense") | E4: =C4-D4 | F4: =IF(C4=0,"",E4/C4)
A5: Travel | B5: 4500 | C5: =B5*9 | D5: =SUMIFS(Transactions!$E:$E,Transactions!$C:$C,$A5,Transactions!$B:$B,"Expense") | E5: =C5-D5 | F5: =IF(C5=0,"",E5/C5)
A6: Utilities | B6: 2500 | C6: =B6*9 | D6: =SUMIFS(Transactions!$E:$E,Transactions!$C:$C,$A6,Transactions!$B:$B,"Expense") | E6: =C6-D6 | F6: =IF(C6=0,"",E6/C6)
A7: Software | B7: 3200 | C7: =B7*9 | D7: =SUMIFS(Transactions!$E:$E,Transactions!$C:$C,$A7,Transactions!$B:$B,"Expense") | E7: =C7-D7 | F7: =IF(C7=0,"",E7/C7)
A8: Office Supplies | B8: 1700 | C8: =B8*9 | D8: =SUMIFS(Transactions!$E:$E,Transactions!$C:$C,$A8,Transactions!$B:$B,"Expense") | E8: =C8-D8 | F8: =IF(C8=0,"",E8/C8)
A9: Insurance | B9: 2000 | C9: =B9*9 | D9: =SUMIFS(Transactions!$E:$E,Transactions!$C:$C,$A9,Transactions!$B:$B,"Expense") | E9: =C9-D9 | F9: =IF(C9=0,"",E9/C9)
A10: Professional Fees | B10: 1500 | C10: =B10*9 | D10: =SUMIFS(Transactions!$E:$E,Transactions!$C:$C,$A10,Transactions!$B:$B,"Expense") | E10: =C10-D10 | F10: =IF(C10=0,"",E10/C10)
A11: TOTAL | B11: =SUM(B2:B10) | C11: =SUM(C2:C10) | D11: =SUM(D2:D10) | E11: =SUM(E2:E10) | F11: =E11/C11

Sheet Invoices
A1: As of: | B1: 46304
A3: InvoiceNo | B3: Client | C3: IssueDate | D3: DueDate | E3: Amount | F3: Status | G3: Days Outstanding | H3: Payment Flag
A4: INV-26001 | B4: Acme Corp | C4: 46175 | D4: 46205 | E4: 45000 | F4: Paid | G4: =IF(F4="Paid","",MAX(0,$B$1-D4)) | H4: =IF(F4="Paid","Paid",IF(D4<=$B$1,"Overdue","Outstanding"))
A5: INV-26002 | B5: Beta Ltd | C5: 46182 | D5: 46212 | E5: 28000 | F5: Paid | G5: =IF(F5="Paid","",MAX(0,$B$1-D5)) | H5: =IF(F5="Paid","Paid",IF(D5<=$B$1,"Overdue","Outstanding"))
A6: INV-26003 | B6: Gamma Inc | C6: 46189 | D6: 46219 | E6: 52000 | F6: Paid | G6: =IF(F6="Paid","",MAX(0,$B$1-D6)) | H6: =IF(F6="Paid","Paid",IF(D6<=$B$1,"Overdue","Outstanding"))
A7: INV-26004 | B7: Delta Co | C7: 46196 | D7: 46226 | E7: 31000 | F7: Paid | G7: =IF(F7="Paid","",MAX(0,$B$1-D7)) | H7: =IF(F7="Paid","Paid",IF(D7<=$B$1,"Overdue","Outstanding"))
A8: INV-26005 | B8: Epsilon LLC | C8: 46203 | D8: 46233 | E8: 47000 | F8: Paid | G8: =IF(F8="Paid","",MAX(0,$B$1-D8)) | H8: =IF(F8="Paid","Paid",IF(D8<=$B$1,"Overdue","Outstanding"))
A9: INV-26006 | B9: Acme Corp | C9: 46210 | D9: 46240 | E9: 39000 | F9: Paid | G9: =IF(F9="Paid","",MAX(0,$B$1-D9)) | H9: =IF(F9="Paid","Paid",IF(D9<=$B$1,"Overdue","Outstanding"))
A10: INV-26007 | B10: Beta Ltd | C10: 46217 | D10: 46247 | E10: 55000 | F10: Paid | G10: =IF(F10="Paid","",MAX(0,$B$1-D10)) | H10: =IF(F10="Paid","Paid",IF(D10<=$B$1,"Overdue","Outstanding"))
A11: INV-26008 | B11: Gamma Inc | C11: 46224 | D11: 46254 | E11: 26000 | F11: Paid | G11: =IF(F11="Paid","",MAX(0,$B$1-D11)) | H11: =IF(F11="Paid","Paid",IF(D11<=$B$1,"Overdue","Outstanding"))
A12: INV-26009 | B12: Delta Co | C12: 46231 | D12: 46261 | E12: 61000 | F12: Paid | G12: =IF(F12="Paid","",MAX(0,$B$1-D12)) | H12: =IF(F12="Paid","Paid",IF(D12<=$B$1,"Overdue","Outstanding"))
A13: INV-26010 | B13: Epsilon LLC | C13: 46238 | D13: 46268 | E13: 33000 | F13: Paid | G13: =IF(F13="Paid","",MAX(0,$B$1-D13)) | H13: =IF(F13="Paid","Paid",IF(D13<=$B$1,"Overdue","Outstanding"))
A14: INV-26011 | B14: Acme Corp | C14: 46245 | D14: 46275 | E14: 48000 | F14: Paid | G14: =IF(F14="Paid","",MAX(0,$B$1-D14)) | H14: =IF(F14="Paid","Paid",IF(D14<=$B$1,"Overdue","Outstanding"))
A15: INV-26012 | B15: Beta Ltd | C15: 46252 | D15: 46282 | E15: 29000 | F15: Paid | G15: =IF(F15="Paid","",MAX(0,$B$1-D15)) | H15: =IF(F15="Paid","Paid",IF(D15<=$B$1,"Overdue","Outstanding"))
... A23: INV-26020 | B23: Epsilon LLC | C23: 46266 | D23: 46296 | E23: 46000 | F23: Paid | G23: =IF(F23="Paid","",MAX(0,$B$1-D23)) | H23: =IF(F23="Paid","Paid",IF(D23<=$B$1,"Overdue","Outstanding"))

Sheet Tax Prep
A1: Deductible expenses by tax category (live from Transactions)
A2: Tax Category | B2: Deductible Total | C2: Transactions
A3: Advertising | B3: =SUMIFS(Transactions!$E:$E,Transactions!$G:$G,$A3,Transactions!$B:$B,"Expense") | C3: =COUNTIFS(Transactions!$G:$G,$A3,Transactions!$B:$B,"Expense")
A4: Insurance | B4: =SUMIFS(Transactions!$E:$E,Transactions!$G:$G,$A4,Transactions!$B:$B,"Expense") | C4: =COUNTIFS(Transactions!$G:$G,$A4,Transactions!$B:$B,"Expense")
A5: Office | B5: =SUMIFS(Transactions!$E:$E,Transactions!$G:$G,$A5,Transactions!$B:$B,"Expense") | C5: =COUNTIFS(Transactions!$G:$G,$A5,Transactions!$B:$B,"Expense")
A6: Payroll | B6: =SUMIFS(Transactions!$E:$E,Transactions!$G:$G,$A6,Transactions!$B:$B,"Expense") | C6: =COUNTIFS(Transactions!$G:$G,$A6,Transactions!$B:$B,"Expense")
A7: Professional Services | B7: =SUMIFS(Transactions!$E:$E,Transactions!$G:$G,$A7,Transactions!$B:$B,"Expense") | C7: =COUNTIFS(Transactions!$G:$G,$A7,Transactions!$B:$B,"Expense")
A8: Technology | B8: =SUMIFS(Transactions!$E:$E,Transactions!$G:$G,$A8,Transactions!$B:$B,"Expense") | C8: =COUNTIFS(Transactions!$G:$G,$A8,Transactions!$B:$B,"Expense")
A9: Travel | B9: =SUMIFS(Transactions!$E:$E,Transactions!$G:$G,$A9,Transactions!$B:$B,"Expense") | C9: =COUNTIFS(Transactions!$G:$G,$A9,Transactions!$B:$B,"Expense")
A10: TOTAL | B10: =SUM(B3:B9) | C10: =SUM(C3:C9)
A19: Expense category -> tax category mapping
A20: Expense Category | B20: Tax Category
A21: Insurance | B21: Insurance
A22: Marketing | B22: Advertising
A23: Office Supplies | B23: Office
A24: Professional Fees | B24: Professional Services
A25: Rent | B25: Office
A26: Salaries | B26: Payroll
A27: Software | B27: Technology
A28: Travel | B28: Travel
A29: Utilities | B29: Office

Sheet ChartData
A1: Month | B1: Income | C1: Expenses | D1: Cumulative Net
A2: Jan-26 | B2: =SUMIFS(Transactions!$E:$E,Transactions!$B:$B,"Income",Transactions!$F:$F,$A2) | C2: =SUMIFS(Transactions!$E:$E,Transactions!$B:$B,"Expense",Transactions!$F:$F,$A2) | D2: =B2-C2
A3: Feb-26 | B3: =SUMIFS(Transactions!$E:$E,Transactions!$B:$B,"Income",Transactions!$F:$F,$A3) | C3: =SUMIFS(Transactions!$E:$E,Transactions!$B:$B,"Expense",Transactions!$F:$F,$A3) | D3: =B3-C3+D2
A4: Mar-26 | B4: =SUMIFS(Transactions!$E:$E,Transactions!$B:$B,"Income",Transactions!$F:$F,$A4) | C4: =SUMIFS(Transactions!$E:$E,Transactions!$B:$B,"Expense",Transactions!$F:$F,$A4) | D4: =B4-C4+D3
A5: Apr-26 | B5: =SUMIFS(Transactions!$E:$E,Transactions!$B:$B,"Income",Transactions!$F:$F,$A5) | C5: =SUMIFS(Transactions!$E:$E,Transactions!$B:$B,"Expense",Transactions!$F:$F,$A5) | D5: =B5-C5+D4
A6: May-26 | B6: =SUMIFS(Transactions!$E:$E,Transactions!$B:$B,"Income",Transactions!$F:$F,$A6) | C6: =SUMIFS(Transactions!$E:$E,Transactions!$B:$B,"Expense",Transactions!$F:$F,$A6) | D6: =B6-C6+D5
A7: Jun-26 | B7: =SUMIFS(Transactions!$E:$E,Transactions!$B:$B,"Income",Transactions!$F:$F,$A7) | C7: =SUMIFS(Transactions!$E:$E,Transactions!$B:$B,"Expense",Transactions!$F:$F,$A7) | D7: =B7-C7+D6
A8: Jul-26 | B8: =SUMIFS(Transactions!$E:$E,Transactions!$B:$B,"Income",Transactions!$F:$F,$A8) | C8: =SUMIFS(Transactions!$E:$E,Transactions!$B:$B,"Expense",Transactions!$F:$F,$A8) | D8: =B8-C8+D7
A9: Aug-26 | B9: =SUMIFS(Transactions!$E:$E,Transactions!$B:$B,"Income",Transactions!$F:$F,$A9) | C9: =SUMIFS(Transactions!$E:$E,Transactions!$B:$B,"Expense",Transactions!$F:$F,$A9) | D9: =B9-C9+D8
A10: Sep-26 | B10: =SUMIFS(Transactions!$E:$E,Transactions!$B:$B,"Income",Transactions!$F:$F,$A10) | C10: =SUMIFS(Transactions!$E:$E,Transactions!$B:$B,"Expense",Transactions!$F:$F,$A10) | D10: =B10-C10+D9
