Workbook

Sheet Guide
A1: InvoiceLedger — invoice-to-reports workbook
A2: Report date (all aging measured from here): | B2: 46295
A4: 1. Paste new invoice rows into Raw_Invoices (keep the column order).
A5: 2. Paste new payment rows into Raw_Payments.
A6: 3. Everything else recalculates: P&L, CashFlow, Receivables aging,
A7: Dashboard KPIs/charts, the AI_Report narrative and the Checks.
A8: 4. Change the report date in B2 and the aging buckets move with it.
A9: Data dictionary — Raw_Invoices: inv_id, date, party, type
A10: (SALES/PURCHASE/EXPENSE), category, amount (ex-GST), gst_rate,
A11: gst_amt, total, paid_amount, paid_date, balance (=total-paid),
A12: days_to_pay (=paid_date - date, paid invoices only).
A13: Raw_Payments: pay_id, inv_id, type, category, date, amount.
A14: All records are fictional demo data for 'Gupta Garments & Textiles'.

Sheet Raw_Invoices
A1: inv_id | B1: date | C1: party | D1: type | E1: category | F1: amount | G1: gst_rate | H1: gst_amt | I1: total | J1: paid_amount | K1: paid_date | L1: balance | M1: days_to_pay
A2: S-00001 | B2: 45949 | C2: Gaya Textile Traders | D2: SALES | E2: Fabrics | F2: 33474.18 | G2: 5 | H2: 1673.71 | I2: 35147.89 | J2: 35147.89 | K2: 46000 | L2: =IF(I2="","",I2-J2) | M2: =IF(K2="","",K2-B2)
A3: S-00002 | B3: 45932 | C3: City Centre Apparel | D3: SALES | E3: Fabrics | F3: 75604.95 | G3: 5 | H3: 3780.25 | I3: 79385.2 | J3: 79385.2 | K3: 45967 | L3: =IF(I3="","",I3-J3) | M3: =IF(K3="","",K3-B3)
A4: S-00003 | B4: 45934 | C4: City Centre Apparel | D4: SALES | E4: Fabrics | F4: 88644.42 | G4: 5 | H4: 4432.22 | I4: 93076.64 | J4: 44997.63 | K4: 45977 | L4: =IF(I4="","",I4-J4) | M4: =IF(K4="","",K4-B4)
A5: S-00004 | B5: 45933 | C5: Bhagalpur Silk Centre | D5: SALES | E5: Fabrics | F5: 39211 | G5: 5 | H5: 1960.55 | I5: 41171.55 | J5: 41171.55 | K5: 45963 | L5: =IF(I5="","",I5-J5) | M5: =IF(K5="","",K5-B5)
A6: S-00005 | B6: 45961 | C6: Lakshmi Cloth Store | D6: SALES | E6: Fabrics | F6: 77485.72 | G6: 5 | H6: 3874.29 | I6: 81360.01 | J6: 81360.01 | K6: 45983 | L6: =IF(I6="","",I6-J6) | M6: =IF(K6="","",K6-B6)
A7: S-00006 | B7: 45950 | C7: Patna Fashion House | D7: SALES | E7: Fabrics | F7: 89845.5 | G7: 5 | H7: 4492.27 | I7: 94337.77 | J7: 47036.71 | K7: 46017 | L7: =IF(I7="","",I7-J7) | M7: =IF(K7="","",K7-B7)
A8: S-00007 | B8: 45960 | C8: Sharma Retail Store | D8: SALES | E8: Garments | F8: 39726.42 | G8: 12 | H8: 4767.17 | I8: 44493.59 | J8: 44493.59 | K8: 45986 | L8: =IF(I8="","",I8-J8) | M8: =IF(K8="","",K8-B8)
A9: S-00008 | B9: 45961 | C9: Gaya Textile Traders | D9: SALES | E9: Garments | F9: 82133.18 | G9: 12 | H9: 9855.98 | I9: 91989.16 | J9: 0 | L9: =IF(I9="","",I9-J9) | M9: =IF(K9="","",K9-B9)
A10: S-00009 | B10: 45942 | C10: Arrah Garment Plaza | D10: SALES | E10: Garments | F10: 69916.32 | G10: 12 | H10: 8389.96 | I10: 78306.28 | J10: 45569.08 | K10: 45955 | L10: =IF(I10="","",I10-J10) | M10: =IF(K10="","",K10-B10)
A11: S-00010 | B11: 45958 | C11: Purnia Fashion Hub | D11: SALES | E11: Fabrics | F11: 18254.46 | G11: 5 | H11: 912.72 | I11: 19167.18 | J11: 19167.18 | K11: 46022 | L11: =IF(I11="","",I11-J11) | M11: =IF(K11="","",K11-B11)
A12: S-00011 | B12: 45955 | C12: Bhagalpur Silk Centre | D12: SALES | E12: Garments | F12: 46369.74 | G12: 12 | H12: 5564.37 | I12: 51934.11 | J12: 51934.11 | K12: 45996 | L12: =IF(I12="","",I12-J12) | M12: =IF(K12="","",K12-B12)
A13: S-00012 | B13: 45956 | C13: Kumkum Saree Sadan | D13: SALES | E13: Accessories | F13: 11576.19 | G13: 12 | H13: 1389.14 | I13: 12965.33 | J13: 12965.33 | K13: 45971 | L13: =IF(I13="","",I13-J13) | M13: =IF(K13="","",K13-B13)
A14: S-00013 | B14: 45948 | C14: Sharma Retail Store | D14: SALES | E14: Fabrics | F14: 92978.93 | G14: 5 | H14: 4648.95 | I14: 97627.88 | J14: 97627.88 | K14: 45999 | L14: =IF(I14="","",I14-J14) | M14: =IF(K14="","",K14-B14)
A15: S-00014 | B15: 45938 | C15: Lakshmi Cloth Store | D15: SALES | E15: Garments | F15: 72129.12 | G15: 12 | H15: 8655.49 | I15: 80784.61 | J15: 0 | L15: =IF(I15="","",I15-J15) | M15: =IF(K15="","",K15-B15)
A16: S-00015 | B16: 45952 | C16: Lakshmi Cloth Store | D16: SALES | E16: Garments | F16: 38547.73 | G16: 12 | H16: 4625.73 | I16: 43173.46 | J16: 43173.46 | K16: 45975 | L16: =IF(I16="","",I16-J16) | M16: =IF(K16="","",K16-B16)
A17: S-00016 | B17: 45932 | C17: Muzaffarpur Cloth House | D17: SALES | E17: Accessories | F17: 40611.95 | G17: 12 | H17: 4873.43 | I17: 45485.38 | J17: 0 | L17: =IF(I17="","",I17-J17) | M17: =IF(K17="","",K17-B17)
A18: S-00017 | B18: 45960 | C18: Arrah Garment Plaza | D18: SALES | E18: Garments | F18: 19201.36 | G18: 12 | H18: 2304.16 | I18: 21505.52 | J18: 21505.52 | K18: 46031 | L18: =IF(I18="","",I18-J18) | M18: =IF(K18="","",K18-B18)
A19: S-00018 | B19: 45941 | C19: Trendy Threads | D19: SALES | E19: Fabrics | F19: 78227.06 | G19: 5 | H19: 3911.35 | I19: 82138.41 | J19: 48055.6 | K19: 46002 | L19: =IF(I19="","",I19-J19) | M19: =IF(K19="","",K19-B19)
A20: S-00019 | B20: 45951 | C20: Gaya Textile Traders | D20: SALES | E20: Fabrics | F20: 85368.07 | G20: 5 | H20: 4268.4 | I20: 89636.47 | J20: 89636.47 | K20: 45968 | L20: =IF(I20="","",I20-J20) | M20: =IF(K20="","",K20-B20)
A21: S-00020 | B21: 45939 | C21: City Centre Apparel | D21: SALES | E21: Fabrics | F21: 48161.2 | G21: 5 | H21: 2408.06 | I21: 50569.26 | J21: 50569.26 | K21: 45953 | L21: =IF(I21="","",I21-J21) | M21: =IF(K21="","",K21-B21)
A22: S-00021 | B22: 45944 | C22: Muzaffarpur Cloth House | D22: SALES | E22: Accessories | F22: 26130.13 | G22: 12 | H22: 3135.62 | I22: 29265.75 | J22: 29265.75 | K22: 45980 | L22: =IF(I22="","",I22-J22) | M22: =IF(K22="","",K22-B22)
A23: S-00022 | B23: 45961 | C23: Patna Fashion House | D23: SALES | E23: Garments | F23: 54681.33 | G23: 12 | H23: 6561.76 | I23: 61243.09 | J23: 61243.09 | K23: 46016 | L23: =IF(I23="","",I23-J23) | M23: =IF(K23="","",K23-B23)
A24: S-00023 | B24: 45943 | C24: Bhagalpur Silk Centre | D24: SALES | E24: Garments | F24: 21524.59 | G24: 12 | H24: 2582.95 | I24: 24107.54 | J24: 24107.54 | K24: 45986 | L24: =IF(I24="","",I24-J24) | M24: =IF(K24="","",K24-B24)
A25: S-00024 | B25: 45932 | C25: Sharma Retail Store | D25: SALES | E25: Garments | F25: 84328.27 | G25: 12 | H25: 10119.39 | I25: 94447.66 | J25: 94447.66 | K25: 45963 | L25: =IF(I25="","",I25-J25) | M25: =IF(K25="","",K25-B25)
A26: S-00025 | B26: 45947 | C26: Bazaar Collection | D26: SALES | E26: Garments | F26: 92705.54 | G26: 12 | H26: 11124.66 | I26: 103830.2 | J26: 103830.2 | K26: 45973 | L26: =IF(I26="","",I26-J26) | M26: =IF(K26="","",K26-B26)
A27: S-00026 | B27: 45953 | C27: Trendy Threads | D27: SALES | E27: Accessories | F27: 48811.13 | G27: 12 | H27: 5857.34 | I27: 54668.47 | J27: 26916.26 | K27: 46009 | L27: =IF(I27="","",I27-J27) | M27: =IF(K27="","",K27-B27)
A28: S-00027 | B28: 45951 | C28: City Centre Apparel | D28: SALES | E28: Garments | F28: 35581.48 | G28: 12 | H28: 4269.78 | I28: 39851.26 | J28: 39851.26 | K28: 45985 | L28: =IF(I28="","",I28-J28) | M28: =IF(K28="","",K28-B28)
A29: S-00028 | B29: 45949 | C29: Vishal Mega Mart (franchise) | D29: SALES | E29: Fabrics | F29: 73908.34 | G29: 5 | H29: 3695.42 | I29: 77603.76 | J29: 77603.76 | K29: 45968 | L29: =IF(I29="","",I29-J29) | M29: =IF(K29="","",K29-B29)
... A41: P-00001 | B41: 45943 | C41: Kolkata Hosiery House | D41: PURCHASE | E41: Inventory purchases | F41: 68123.91 | G41: 5 | H41: 3406.2 | I41: 71530.11 | J41: 71530.11 | K41: 45962 | L41: =IF(I41="","",I41-J41) | M41: =IF(K41="","",K41-B41)
A42: P-00002 | B42: 45960 | C42: Kolkata Hosiery House | D42: PURCHASE | E42: Inventory purchases | F42: 22432.41 | G42: 5 | H42: 1121.62 | I42: 23554.03 | J42: 0 | L42: =IF(I42="","",I42-J42) | M42: =IF(K42="","",K42-B42)
A43: P-00003 | B43: 45939 | C43: Kolkata Hosiery House | D43: PURCHASE | E43: Inventory purchases | F43: 13905.84 | G43: 5 | H43: 695.29 | I43: 14601.13 | J43: 14601.13 | K43: 45954 | L43: =IF(I43="","",I43-J43) | M43: =IF(K43="","",K43-B43)
A44: P-00004 | B44: 45957 | C44: Delhi Fabric Suppliers | D44: PURCHASE | E44: Inventory purchases | F44: 115697.95 | G44: 5 | H44: 5784.9 | I44: 121482.85 | J44: 121482.85 | K44: 45976 | L44: =IF(I44="","",I44-J44) | M44: =IF(K44="","",K44-B44)
A45: P-00005 | B45: 45934 | C45: Surat Textile Mills | D45: PURCHASE | E45: Inventory purchases | F45: 68504.43 | G45: 5 | H45: 3425.22 | I45: 71929.65 | J45: 71929.65 | K45: 45959 | L45: =IF(I45="","",I45-J45) | M45: =IF(K45="","",K45-B45)
A46: P-00006 | B46: 45941 | C46: Jaipur Print Works | D46: PURCHASE | E46: Inventory purchases | F46: 49816.64 | G46: 5 | H46: 2490.83 | I46: 52307.47 | J46: 52307.47 | K46: 45971 | L46: =IF(I46="","",I46-J46) | M46: =IF(K46="","",K46-B46)
A47: P-00007 | B47: 45948 | C47: Tiruppur Garment Works | D47: PURCHASE | E47: Inventory purchases | F47: 114530.45 | G47: 5 | H47: 5726.52 | I47: 120256.97 | J47: 120256.97 | K47: 45961 | L47: =IF(I47="","",I47-J47) | M47: =IF(K47="","",K47-B47)
A48: P-00008 | B48: 45950 | C48: Kolkata Hosiery House | D48: PURCHASE | E48: Inventory purchases | F48: 67394.42 | G48: 5 | H48: 3369.72 | I48: 70764.14 | J48: 70764.14 | K48: 45966 | L48: =IF(I48="","",I48-J48) | M48: =IF(K48="","",K48-B48)
A49: P-00009 | B49: 45953 | C49: Jaipur Print Works | D49: PURCHASE | E49: Inventory purchases | F49: 98811.07 | G49: 5 | H49: 4940.55 | I49: 103751.62 | J49: 48854.72 | K49: 45963 | L49: =IF(I49="","",I49-J49) | M49: =IF(K49="","",K49-B49)
A50: P-00010 | B50: 45938 | C50: Jaipur Print Works | D50: PURCHASE | E50: Inventory purchases | F50: 106745.09 | G50: 5 | H50: 5337.25 | I50: 112082.34 | J50: 112082.34 | K50: 45964 | L50: =IF(I50="","",I50-J50) | M50: =IF(K50="","",K50-B50)
A51: P-00011 | B51: 45932 | C51: Ludhiana Knitwear Co | D51: PURCHASE | E51: Inventory purchases | F51: 109229 | G51: 5 | H51: 5461.45 | I51: 114690.45 | J51: 0 | L51: =IF(I51="","",I51-J51) | M51: =IF(K51="","",K51-B51)
A52: P-00012 | B52: 45936 | C52: Kolkata Hosiery House | D52: PURCHASE | E52: Inventory purchases | F52: 72141.64 | G52: 5 | H52: 3607.08 | I52: 75748.72 | J52: 75748.72 | K52: 45950 | L52: =IF(I52="","",I52-J52) | M52: =IF(K52="","",K52-B52)
A53: P-00013 | B53: 45954 | C53: Jaipur Print Works | D53: PURCHASE | E53: Inventory purchases | F53: 46969.86 | G53: 5 | H53: 2348.49 | I53: 49318.35 | J53: 49318.35 | K53: 45971 | L53: =IF(I53="","",I53-J53) | M53: =IF(K53="","",K53-B53)
A54: P-00014 | B54: 45932 | C54: Tiruppur Garment Works | D54: PURCHASE | E54: Inventory purchases | F54: 49901.69 | G54: 5 | H54: 2495.08 | I54: 52396.77 | J54: 52396.77 | K54: 45941 | L54: =IF(I54="","",I54-J54) | M54: =IF(K54="","",K54-B54)
A55: P-00015 | B55: 45937 | C55: Ludhiana Knitwear Co | D55: PURCHASE | E55: Inventory purchases | F55: 35707.39 | G55: 5 | H55: 1785.37 | I55: 37492.76 | J55: 37492.76 | K55: 45962 | L55: =IF(I55="","",I55-J55) | M55: =IF(K55="","",K55-B55)
A56: P-00016 | B56: 45953 | C56: Ludhiana Knitwear Co | D56: PURCHASE | E56: Inventory purchases | F56: 65006.82 | G56: 5 | H56: 3250.34 | I56: 68257.16 | J56: 68257.16 | K56: 45981 | L56: =IF(I56="","",I56-J56) | M56: =IF(K56="","",K56-B56)
A57: E-00001 | B57: 45931 | C57: Various | D57: EXPENSE | E57: Rent | F57: 25323.41 | G57: 18 | H57: 4558.21 | I57: 29881.62 | J57: 29881.62 | K57: 45938 | L57: =IF(I57="","",I57-J57) | M57: =IF(K57="","",K57-B57)
A58: E-00002 | B58: 45960 | C58: Various | D58: EXPENSE | E58: Salaries | F58: 85376.86 | G58: 0 | H58: 0 | I58: 85376.86 | J58: 85376.86 | K58: 45962 | L58: =IF(I58="","",I58-J58) | M58: =IF(K58="","",K58-B58)
A59: E-00003 | B59: 45933 | C59: Various | D59: EXPENSE | E59: Utilities | F59: 6432 | G59: 18 | H59: 1157.76 | I59: 7589.76 | J59: 7589.76 | K59: 45936 | L59: =IF(I59="","",I59-J59) | M59: =IF(K59="","",K59-B59)
A60: E-00004 | B60: 45943 | C60: Various | D60: EXPENSE | E60: Transport | F60: 6477.7 | G60: 5 | H60: 323.88 | I60: 6801.58 | J60: 6801.58 | K60: 45947 | L60: =IF(I60="","",I60-J60) | M60: =IF(K60="","",K60-B60)
A61: E-00005 | B61: 45951 | C61: Various | D61: EXPENSE | E61: Transport | F61: 4900.87 | G61: 5 | H61: 245.04 | I61: 5145.91 | J61: 5145.91 | K61: 45952 | L61: =IF(I61="","",I61-J61) | M61: =IF(K61="","",K61-B61)
A62: E-00006 | B62: 45942 | C62: Various | D62: EXPENSE | E62: Transport | F62: 1552.57 | G62: 5 | H62: 77.63 | I62: 1630.2 | J62: 0 | L62: =IF(I62="","",I62-J62) | M62: =IF(K62="","",K62-B62)
A63: E-00007 | B63: 45951 | C63: Various | D63: EXPENSE | E63: Transport | F63: 4439.62 | G63: 5 | H63: 221.98 | I63: 4661.6 | J63: 4661.6 | K63: 45955 | L63: =IF(I63="","",I63-J63) | M63: =IF(K63="","",K63-B63)
A64: E-00008 | B64: 45954 | C64: Various | D64: EXPENSE | E64: Transport | F64: 3910.68 | G64: 5 | H64: 195.53 | I64: 4106.21 | J64: 4106.21 | K64: 45956 | L64: =IF(I64="","",I64-J64) | M64: =IF(K64="","",K64-B64)
A65: E-00009 | B65: 45954 | C65: Various | D65: EXPENSE | E65: Transport | F65: 5171.31 | G65: 5 | H65: 258.57 | I65: 5429.88 | J65: 5429.88 | K65: 45954 | L65: =IF(I65="","",I65-J65) | M65: =IF(K65="","",K65-B65)
A66: E-00010 | B66: 45935 | C66: Various | D66: EXPENSE | E66: Marketing | F66: 23413.73 | G66: 18 | H66: 4214.47 | I66: 27628.2 | J66: 27628.2 | K66: 45939 | L66: =IF(I66="","",I66-J66) | M66: =IF(K66="","",K66-B66)
A67: E-00011 | B67: 45939 | C67: Various | D67: EXPENSE | E67: Marketing | F67: 18271.6 | G67: 18 | H67: 3288.89 | I67: 21560.49 | J67: 21560.49 | K67: 45942 | L67: =IF(I67="","",I67-J67) | M67: =IF(K67="","",K67-B67)
A68: E-00012 | B68: 45952 | C68: Various | D68: EXPENSE | E68: Professional fees | F68: 6366.81 | G68: 18 | H68: 1146.03 | I68: 7512.84 | J68: 7512.84 | K68: 45955 | L68: =IF(I68="","",I68-J68) | M68: =IF(K68="","",K68-B68)
A69: E-00013 | B69: 45951 | C69: Various | D69: EXPENSE | E69: Misc | F69: 1426.93 | G69: 18 | H69: 256.85 | I69: 1683.78 | J69: 1683.78 | K69: 45954 | L69: =IF(I69="","",I69-J69) | M69: =IF(K69="","",K69-B69)
A70: E-00014 | B70: 45933 | C70: Various | D70: EXPENSE | E70: Misc | F70: 5981.3 | G70: 18 | H70: 1076.63 | I70: 7057.93 | J70: 7057.93 | K70: 45938 | L70: =IF(I70="","",I70-J70) | M70: =IF(K70="","",K70-B70)
A71: E-00015 | B71: 45949 | C71: Various | D71: EXPENSE | E71: Misc | F71: 3052.93 | G71: 18 | H71: 549.53 | I71: 3602.46 | J71: 3602.46 | K71: 45954 | L71: =IF(I71="","",I71-J71) | M71: =IF(K71="","",K71-B71)
A72: S-00040 | B72: 45968 | C72: Gaya Textile Traders | D72: SALES | E72: Fabrics | F72: 44758.17 | G72: 5 | H72: 2237.91 | I72: 46996.08 | J72: 46996.08 | K72: 46014 | L72: =IF(I72="","",I72-J72) | M72: =IF(K72="","",K72-B72)
A73: S-00041 | B73: 45989 | C73: Patna Fashion House | D73: SALES | E73: Fabrics | F73: 10203.72 | G73: 5 | H73: 510.19 | I73: 10713.91 | J73: 8084.75 | K73: 46016 | L73: =IF(I73="","",I73-J73) | M73: =IF(K73="","",K73-B73)
A74: S-00042 | B74: 45979 | C74: Trendy Threads | D74: SALES | E74: Garments | F74: 65145.67 | G74: 12 | H74: 7817.48 | I74: 72963.15 | J74: 72963.15 | K74: 46040 | L74: =IF(I74="","",I74-J74) | M74: =IF(K74="","",K74-B74)
... A76: S-00044 | B76: 45962 | C76: City Centre Apparel | D76: SALES | E76: Fabrics | F76: 75804.45 | G76: 5 | H76: 3790.22 | I76: 79594.67 | J76: 79594.67 | K76: 46005 | L76: =IF(I76="","",I76-J76) | M76: =IF(K76="","",K76-B76)
A77: S-00045 | B77: 45967 | C77: New Look Garments | D77: SALES | E77: Garments | F77: 68576.16 | G77: 12 | H77: 8229.14 | I77: 76805.3 | J77: 0 | L77: =IF(I77="","",I77-J77) | M77: =IF(K77="","",K77-B77)
A78: S-00046 | B78: 45964 | C78: Gaya Textile Traders | D78: SALES | E78: Garments | F78: 8605.32 | G78: 12 | H78: 1032.64 | I78: 9637.96 | J78: 9637.96 | K78: 45994 | L78: =IF(I78="","",I78-J78) | M78: =IF(K78="","",K78-B78)
A79: S-00047 | B79: 45970 | C79: Gaya Textile Traders | D79: SALES | E79: Accessories | F79: 11665.06 | G79: 12 | H79: 1399.81 | I79: 13064.87 | J79: 13064.87 | K79: 45976 | L79: =IF(I79="","",I79-J79) | M79: =IF(K79="","",K79-B79)
A80: S-00048 | B80: 45981 | C80: City Centre Apparel | D80: SALES | E80: Fabrics | F80: 79488.54 | G80: 5 | H80: 3974.43 | I80: 83462.97 | J80: 83462.97 | K80: 46019 | L80: =IF(I80="","",I80-J80) | M80: =IF(K80="","",K80-B80)
A81: S-00049 | B81: 45984 | C81: Arrah Garment Plaza | D81: SALES | E81: Garments | F81: 81454.29 | G81: 12 | H81: 9774.51 | I81: 91228.8 | J81: 91228.8 | K81: 46018 | L81: =IF(I81="","",I81-J81) | M81: =IF(K81="","",K81-B81)
A82: S-00050 | B82: 45989 | C82: Patna Fashion House | D82: SALES | E82: Fabrics | F82: 88838.11 | G82: 5 | H82: 4441.91 | I82: 93280.02 | J82: 93280.02 | K82: 46043 | L82: =IF(I82="","",I82-J82) | M82: =IF(K82="","",K82-B82)
A83: S-00051 | B83: 45963 | C83: Bazaar Collection | D83: SALES | E83: Garments | F83: 61735.78 | G83: 12 | H83: 7408.29 | I83: 69144.07 | J83: 69144.07 | K83: 45991 | L83: =IF(I83="","",I83-J83) | M83: =IF(K83="","",K83-B83)
A84: S-00052 | B84: 45985 | C84: Sharma Retail Store | D84: SALES | E84: Fabrics | F84: 45533.36 | G84: 5 | H84: 2276.67 | I84: 47810.03 | J84: 0 | L84: =IF(I84="","",I84-J84) | M84: =IF(K84="","",K84-B84)
A85: S-00053 | B85: 45984 | C85: Sharma Retail Store | D85: SALES | E85: Accessories | F85: 79570.72 | G85: 12 | H85: 9548.49 | I85: 89119.21 | J85: 0 | L85: =IF(I85="","",I85-J85) | M85: =IF(K85="","",K85-B85)
A86: S-00054 | B86: 45981 | C86: Vishal Mega Mart (franchise) | D86: SALES | E86: Garments | F86: 26654.98 | G86: 12 | H86: 3198.6 | I86: 29853.58 | J86: 29853.58 | K86: 46001 | L86: =IF(I86="","",I86-J86) | M86: =IF(K86="","",K86-B86)
A87: S-00055 | B87: 45966 | C87: Trendy Threads | D87: SALES | E87: Garments | F87: 31174.07 | G87: 12 | H87: 3740.89 | I87: 34914.96 | J87: 0 | L87: =IF(I87="","",I87-J87) | M87: =IF(K87="","",K87-B87)
A88: S-00056 | B88: 45970 | C88: Kumkum Saree Sadan | D88: SALES | E88: Garments | F88: 40743.93 | G88: 12 | H88: 4889.27 | I88: 45633.2 | J88: 45633.2 | K88: 45982 | L88: =IF(I88="","",I88-J88) | M88: =IF(K88="","",K88-B88)
A89: S-00057 | B89: 45991 | C89: Muzaffarpur Cloth House | D89: SALES | E89: Garments | F89: 52026.17 | G89: 12 | H89: 6243.14 | I89: 58269.31 | J89: 58269.31 | K89: 46024 | L89: =IF(I89="","",I89-J89) | M89: =IF(K89="","",K89-B89)
A90: S-00058 | B90: 45964 | C90: Vishal Mega Mart (franchise) | D90: SALES | E90: Accessories | F90: 19267.23 | G90: 12 | H90: 2312.07 | I90: 21579.3 | J90: 21579.3 | K90: 46025 | L90: =IF(I90="","",I90-J90) | M90: =IF(K90="","",K90-B90)
A91: S-00059 | B91: 45970 | C91: Kumkum Saree Sadan | D91: SALES | E91: Garments | F91: 41626.74 | G91: 12 | H91: 4995.21 | I91: 46621.95 | J91: 46621.95 | K91: 46004 | L91: =IF(I91="","",I91-J91) | M91: =IF(K91="","",K91-B91)
A92: S-00060 | B92: 45987 | C92: Purnia Fashion Hub | D92: SALES | E92: Garments | F92: 92276.79 | G92: 12 | H92: 11073.21 | I92: 103350 | J92: 0 | L92: =IF(I92="","",I92-J92) | M92: =IF(K92="","",K92-B92)
A93: S-00061 | B93: 45982 | C93: Patna Fashion House | D93: SALES | E93: Fabrics | F93: 77202.18 | G93: 5 | H93: 3860.11 | I93: 81062.29 | J93: 81062.29 | K93: 46047 | L93: =IF(I93="","",I93-J93) | M93: =IF(K93="","",K93-B93)
A94: S-00062 | B94: 45991 | C94: Patna Fashion House | D94: SALES | E94: Accessories | F94: 14094.78 | G94: 12 | H94: 1691.37 | I94: 15786.15 | J94: 15786.15 | K94: 46021 | L94: =IF(I94="","",I94-J94) | M94: =IF(K94="","",K94-B94)
A95: S-00063 | B95: 45975 | C95: Vishal Mega Mart (franchise) | D95: SALES | E95: Fabrics | F95: 46135.29 | G95: 5 | H95: 2306.76 | I95: 48442.05 | J95: 48442.05 | K95: 46034 | L95: =IF(I95="","",I95-J95) | M95: =IF(K95="","",K95-B95)
A96: S-00064 | B96: 45964 | C96: Arrah Garment Plaza | D96: SALES | E96: Fabrics | F96: 57020.18 | G96: 5 | H96: 2851.01 | I96: 59871.19 | J96: 59871.19 | K96: 46015 | L96: =IF(I96="","",I96-J96) | M96: =IF(K96="","",K96-B96)
A97: S-00065 | B97: 45989 | C97: New Look Garments | D97: SALES | E97: Garments | F97: 67149.28 | G97: 12 | H97: 8057.91 | I97: 75207.19 | J97: 75207.19 | K97: 46032 | L97: =IF(I97="","",I97-J97) | M97: =IF(K97="","",K97-B97)
A98: S-00066 | B98: 45974 | C98: City Centre Apparel | D98: SALES | E98: Fabrics | F98: 18626.77 | G98: 5 | H98: 931.34 | I98: 19558.11 | J98: 19558.11 | K98: 46030 | L98: =IF(I98="","",I98-J98) | M98: =IF(K98="","",K98-B98)
A99: S-00067 | B99: 45986 | C99: Trendy Threads | D99: SALES | E99: Fabrics | F99: 36970.73 | G99: 5 | H99: 1848.54 | I99: 38819.27 | J99: 16404.24 | K99: 46011 | L99: =IF(I99="","",I99-J99) | M99: =IF(K99="","",K99-B99)
A100: S-00068 | B100: 45976 | C100: Vishal Mega Mart (franchise) | D100: SALES | E100: Accessories | F100: 72562.88 | G100: 12 | H100: 8707.55 | I100: 81270.43 | J100: 81270.43 | K100: 46017 | L100: =IF(I100="","",I100-J100) | M100: =IF(K100="","",K100-B100)
A101: S-00069 | B101: 45966 | C101: Muzaffarpur Cloth House | D101: SALES | E101: Accessories | F101: 63956.65 | G101: 12 | H101: 7674.8 | I101: 71631.45 | J101: 71631.45 | K101: 45992 | L101: =IF(I101="","",I101-J101) | M101: =IF(K101="","",K101-B101)
A102: S-00070 | B102: 45963 | C102: Bhagalpur Silk Centre | D102: SALES | E102: Fabrics | F102: 14934.72 | G102: 5 | H102: 746.74 | I102: 15681.46 | J102: 15681.46 | K102: 46014 | L102: =IF(I102="","",I102-J102) | M102: =IF(K102="","",K102-B102)
A103: S-00071 | B103: 45975 | C103: Muzaffarpur Cloth House | D103: SALES | E103: Accessories | F103: 46504.74 | G103: 12 | H103: 5580.57 | I103: 52085.31 | J103: 52085.31 | K103: 46010 | L103: =IF(I103="","",I103-J103) | M103: =IF(K103="","",K103-B103)
A104: S-00072 | B104: 45989 | C104: City Centre Apparel | D104: SALES | E104: Fabrics | F104: 80775.57 | G104: 5 | H104: 4038.78 | I104: 84814.35 | J104: 84814.35 | K104: 46040 | L104: =IF(I104="","",I104-J104) | M104: =IF(K104="","",K104-B104)
... A119: P-00025 | B119: 45977 | C119: Kolkata Hosiery House | D119: PURCHASE | E119: Inventory purchases | F119: 42109.81 | G119: 5 | H119: 2105.49 | I119: 44215.3 | J119: 44215.3 | K119: 46008 | L119: =IF(I119="","",I119-J119) | M119: =IF(K119="","",K119-B119)
A120: P-00026 | B120: 45964 | C120: Tiruppur Garment Works | D120: PURCHASE | E120: Inventory purchases | F120: 14816.37 | G120: 5 | H120: 740.82 | I120: 15557.19 | J120: 0 | L120: =IF(I120="","",I120-J120) | M120: =IF(K120="","",K120-B120)
A121: P-00027 | B121: 45981 | C121: Surat Textile Mills | D121: PURCHASE | E121: Inventory purchases | F121: 92626.11 | G121: 5 | H121: 4631.31 | I121: 97257.42 | J121: 97257.42 | K121: 46003 | L121: =IF(I121="","",I121-J121) | M121: =IF(K121="","",K121-B121)
A122: P-00028 | B122: 45983 | C122: Tiruppur Garment Works | D122: PURCHASE | E122: Inventory purchases | F122: 35030.68 | G122: 5 | H122: 1751.53 | I122: 36782.21 | J122: 36782.21 | K122: 46000 | L122: =IF(I122="","",I122-J122) | M122: =IF(K122="","",K122-B122)
A123: P-00029 | B123: 45972 | C123: Jaipur Print Works | D123: PURCHASE | E123: Inventory purchases | F123: 76577.54 | G123: 5 | H123: 3828.88 | I123: 80406.42 | J123: 80406.42 | K123: 45987 | L123: =IF(I123="","",I123-J123) | M123: =IF(K123="","",K123-B123)
A124: P-00030 | B124: 45979 | C124: Jaipur Print Works | D124: PURCHASE | E124: Inventory purchases | F124: 17634.23 | G124: 5 | H124: 881.71 | I124: 18515.94 | J124: 18515.94 | K124: 46001 | L124: =IF(I124="","",I124-J124) | M124: =IF(K124="","",K124-B124)
A125: P-00031 | B125: 45990 | C125: Kolkata Hosiery House | D125: PURCHASE | E125: Inventory purchases | F125: 90098.99 | G125: 5 | H125: 4504.95 | I125: 94603.94 | J125: 94603.94 | K125: 46001 | L125: =IF(I125="","",I125-J125) | M125: =IF(K125="","",K125-B125)
A126: P-00032 | B126: 45968 | C126: Kolkata Hosiery House | D126: PURCHASE | E126: Inventory purchases | F126: 113783.91 | G126: 5 | H126: 5689.2 | I126: 119473.11 | J126: 119473.11 | K126: 45981 | L126: =IF(I126="","",I126-J126) | M126: =IF(K126="","",K126-B126)
...

Sheet Raw_Payments
A1: pay_id | B1: inv_id | C1: type | D1: category | E1: date | F1: amount
A2: PAY-00001 | B2: S-00001 | C2: SALES | D2: Fabrics | E2: 46000 | F2: 35147.89
A3: PAY-00002 | B3: S-00002 | C3: SALES | D3: Fabrics | E3: 45967 | F3: 79385.2
A4: PAY-00003 | B4: S-00003 | C4: SALES | D4: Fabrics | E4: 45977 | F4: 44997.63
A5: PAY-00004 | B5: S-00004 | C5: SALES | D5: Fabrics | E5: 45963 | F5: 41171.55
A6: PAY-00005 | B6: S-00005 | C6: SALES | D6: Fabrics | E6: 45983 | F6: 81360.01
A7: PAY-00006 | B7: S-00006 | C7: SALES | D7: Fabrics | E7: 46017 | F7: 47036.71
A8: PAY-00007 | B8: S-00007 | C8: SALES | D8: Garments | E8: 45986 | F8: 44493.59
A9: PAY-00008 | B9: S-00009 | C9: SALES | D9: Garments | E9: 45955 | F9: 45569.08
A10: PAY-00009 | B10: S-00010 | C10: SALES | D10: Fabrics | E10: 46022 | F10: 19167.18
A11: PAY-00010 | B11: S-00011 | C11: SALES | D11: Garments | E11: 45996 | F11: 51934.11
A12: PAY-00011 | B12: S-00012 | C12: SALES | D12: Accessories | E12: 45971 | F12: 12965.33
A13: PAY-00012 | B13: S-00013 | C13: SALES | D13: Fabrics | E13: 45999 | F13: 97627.88
... A658: PAY-00657 | B658: E-00180 | C658: EXPENSE | D658: Misc | E658: 46290 | F658: 3750.56

Sheet P&L
A1: P&L — monthly (formula-driven)
A2: Line | B2: 45931 | C2: 45962 | D2: 45992 | E2: 46023 | F2: 46054 | G2: 46082 | H2: 46113 | I2: 46143 | J2: 46174 | K2: 46204 | L2: 46235 | M2: 46266 | N2: FY total
A3: Revenue — Fabrics | B3: =SUMIFS(Raw_Invoices!$F:$F,Raw_Invoices!$B:$B,">="&B$2,Raw_Invoices!$B:$B,"<="&EOMONTH(B$2,0),Raw_Invoices!$D:$D,"SALES",Raw_Invoices!$E:$E,"Fabrics") | C3: =SUMIFS(Raw_Invoices!$F:$F,Raw_Invoices!$B:$B,">="&C$2,Raw_Invoices!$B:$B,"<="&EOMONTH(C$2,0),Raw_Invoices!$D:$D,"SALES",Raw_Invoices!$E:$E,"Fabrics") | D3: =SUMIFS(Raw_Invoices!$F:$F,Raw_Invoices!$B:$B,">="&D$2,Raw_Invoices!$B:$B,"<="&EOMONTH(D$2,0),Raw_Invoices!$D:$D,"SALES",Raw_Invoices!$E:$E,"Fabrics") | E3: =SUMIFS(Raw_Invoices!$F:$F,Raw_Invoices!$B:$B,">="&E$2,Raw_Invoices!$B:$B,"<="&EOMONTH(E$2,0),Raw_Invoices!$D:$D,"SALES",Raw_Invoices!$E:$E,"Fabrics") | F3: =SUMIFS(Raw_Invoices!$F:$F,Raw_Invoices!$B:$B,">="&F$2,Raw_Invoices!$B:$B,"<="&EOMONTH(F$2,0),Raw_Invoices!$D:$D,"SALES",Raw_Invoices!$E:$E,"Fabrics") | G3: =SUMIFS(Raw_Invoices!$F:$F,Raw_Invoices!$B:$B,">="&G$2,Raw_Invoices!$B:$B,"<="&EOMONTH(G$2,0),Raw_Invoices!$D:$D,"SALES",Raw_Invoices!$E:$E,"Fabrics") | H3: =SUMIFS(Raw_Invoices!$F:$F,Raw_Invoices!$B:$B,">="&H$2,Raw_Invoices!$B:$B,"<="&EOMONTH(H$2,0),Raw_Invoices!$D:$D,"SALES",Raw_Invoices!$E:$E,"Fabrics") | I3: =SUMIFS(Raw_Invoices!$F:$F,Raw_Invoices!$B:$B,">="&I$2,Raw_Invoices!$B:$B,"<="&EOMONTH(I$2,0),Raw_Invoices!$D:$D,"SALES",Raw_Invoices!$E:$E,"Fabrics") | ... M3: =SUMIFS(Raw_Invoices!$F:$F,Raw_Invoices!$B:$B,">="&M$2,Raw_Invoices!$B:$B,"<="&EOMONTH(M$2,0),Raw_Invoices!$D:$D,"SALES",Raw_Invoices!$E:$E,"Fabrics") | N3: =SUM(B3:M3)
A4: Revenue — Garments | B4: =SUMIFS(Raw_Invoices!$F:$F,Raw_Invoices!$B:$B,">="&B$2,Raw_Invoices!$B:$B,"<="&EOMONTH(B$2,0),Raw_Invoices!$D:$D,"SALES",Raw_Invoices!$E:$E,"Garments") | C4: =SUMIFS(Raw_Invoices!$F:$F,Raw_Invoices!$B:$B,">="&C$2,Raw_Invoices!$B:$B,"<="&EOMONTH(C$2,0),Raw_Invoices!$D:$D,"SALES",Raw_Invoices!$E:$E,"Garments") | D4: =SUMIFS(Raw_Invoices!$F:$F,Raw_Invoices!$B:$B,">="&D$2,Raw_Invoices!$B:$B,"<="&EOMONTH(D$2,0),Raw_Invoices!$D:$D,"SALES",Raw_Invoices!$E:$E,"Garments") | E4: =SUMIFS(Raw_Invoices!$F:$F,Raw_Invoices!$B:$B,">="&E$2,Raw_Invoices!$B:$B,"<="&EOMONTH(E$2,0),Raw_Invoices!$D:$D,"SALES",Raw_Invoices!$E:$E,"Garments") | F4: =SUMIFS(Raw_Invoices!$F:$F,Raw_Invoices!$B:$B,">="&F$2,Raw_Invoices!$B:$B,"<="&EOMONTH(F$2,0),Raw_Invoices!$D:$D,"SALES",Raw_Invoices!$E:$E,"Garments") | G4: =SUMIFS(Raw_Invoices!$F:$F,Raw_Invoices!$B:$B,">="&G$2,Raw_Invoices!$B:$B,"<="&EOMONTH(G$2,0),Raw_Invoices!$D:$D,"SALES",Raw_Invoices!$E:$E,"Garments") | H4: =SUMIFS(Raw_Invoices!$F:$F,Raw_Invoices!$B:$B,">="&H$2,Raw_Invoices!$B:$B,"<="&EOMONTH(H$2,0),Raw_Invoices!$D:$D,"SALES",Raw_Invoices!$E:$E,"Garments") | I4: =SUMIFS(Raw_Invoices!$F:$F,Raw_Invoices!$B:$B,">="&I$2,Raw_Invoices!$B:$B,"<="&EOMONTH(I$2,0),Raw_Invoices!$D:$D,"SALES",Raw_Invoices!$E:$E,"Garments") | ... M4: =SUMIFS(Raw_Invoices!$F:$F,Raw_Invoices!$B:$B,">="&M$2,Raw_Invoices!$B:$B,"<="&EOMONTH(M$2,0),Raw_Invoices!$D:$D,"SALES",Raw_Invoices!$E:$E,"Garments") | N4: =SUM(B4:M4)
A5: Revenue — Accessories | B5: =SUMIFS(Raw_Invoices!$F:$F,Raw_Invoices!$B:$B,">="&B$2,Raw_Invoices!$B:$B,"<="&EOMONTH(B$2,0),Raw_Invoices!$D:$D,"SALES",Raw_Invoices!$E:$E,"Accessories") | C5: =SUMIFS(Raw_Invoices!$F:$F,Raw_Invoices!$B:$B,">="&C$2,Raw_Invoices!$B:$B,"<="&EOMONTH(C$2,0),Raw_Invoices!$D:$D,"SALES",Raw_Invoices!$E:$E,"Accessories") | D5: =SUMIFS(Raw_Invoices!$F:$F,Raw_Invoices!$B:$B,">="&D$2,Raw_Invoices!$B:$B,"<="&EOMONTH(D$2,0),Raw_Invoices!$D:$D,"SALES",Raw_Invoices!$E:$E,"Accessories") | E5: =SUMIFS(Raw_Invoices!$F:$F,Raw_Invoices!$B:$B,">="&E$2,Raw_Invoices!$B:$B,"<="&EOMONTH(E$2,0),Raw_Invoices!$D:$D,"SALES",Raw_Invoices!$E:$E,"Accessories") | F5: =SUMIFS(Raw_Invoices!$F:$F,Raw_Invoices!$B:$B,">="&F$2,Raw_Invoices!$B:$B,"<="&EOMONTH(F$2,0),Raw_Invoices!$D:$D,"SALES",Raw_Invoices!$E:$E,"Accessories") | G5: =SUMIFS(Raw_Invoices!$F:$F,Raw_Invoices!$B:$B,">="&G$2,Raw_Invoices!$B:$B,"<="&EOMONTH(G$2,0),Raw_Invoices!$D:$D,"SALES",Raw_Invoices!$E:$E,"Accessories") | H5: =SUMIFS(Raw_Invoices!$F:$F,Raw_Invoices!$B:$B,">="&H$2,Raw_Invoices!$B:$B,"<="&EOMONTH(H$2,0),Raw_Invoices!$D:$D,"SALES",Raw_Invoices!$E:$E,"Accessories") | I5: =SUMIFS(Raw_Invoices!$F:$F,Raw_Invoices!$B:$B,">="&I$2,Raw_Invoices!$B:$B,"<="&EOMONTH(I$2,0),Raw_Invoices!$D:$D,"SALES",Raw_Invoices!$E:$E,"Accessories") | ... M5: =SUMIFS(Raw_Invoices!$F:$F,Raw_Invoices!$B:$B,">="&M$2,Raw_Invoices!$B:$B,"<="&EOMONTH(M$2,0),Raw_Invoices!$D:$D,"SALES",Raw_Invoices!$E:$E,"Accessories") | N5: =SUM(B5:M5)
A6: Total revenue | B6: =SUM(B3:B5) | C6: =SUM(C3:C5) | D6: =SUM(D3:D5) | E6: =SUM(E3:E5) | F6: =SUM(F3:F5) | G6: =SUM(G3:G5) | H6: =SUM(H3:H5) | I6: =SUM(I3:I5) | ... M6: =SUM(M3:M5) | N6: =SUM(B6:M6)
A7: COGS — Inventory purchases | B7: =SUMIFS(Raw_Invoices!$F:$F,Raw_Invoices!$B:$B,">="&B$2,Raw_Invoices!$B:$B,"<="&EOMONTH(B$2,0),Raw_Invoices!$D:$D,"PURCHASE",Raw_Invoices!$E:$E,"Inventory purchases") | C7: =SUMIFS(Raw_Invoices!$F:$F,Raw_Invoices!$B:$B,">="&C$2,Raw_Invoices!$B:$B,"<="&EOMONTH(C$2,0),Raw_Invoices!$D:$D,"PURCHASE",Raw_Invoices!$E:$E,"Inventory purchases") | D7: =SUMIFS(Raw_Invoices!$F:$F,Raw_Invoices!$B:$B,">="&D$2,Raw_Invoices!$B:$B,"<="&EOMONTH(D$2,0),Raw_Invoices!$D:$D,"PURCHASE",Raw_Invoices!$E:$E,"Inventory purchases") | E7: =SUMIFS(Raw_Invoices!$F:$F,Raw_Invoices!$B:$B,">="&E$2,Raw_Invoices!$B:$B,"<="&EOMONTH(E$2,0),Raw_Invoices!$D:$D,"PURCHASE",Raw_Invoices!$E:$E,"Inventory purchases") | F7: =SUMIFS(Raw_Invoices!$F:$F,Raw_Invoices!$B:$B,">="&F$2,Raw_Invoices!$B:$B,"<="&EOMONTH(F$2,0),Raw_Invoices!$D:$D,"PURCHASE",Raw_Invoices!$E:$E,"Inventory purchases") | G7: =SUMIFS(Raw_Invoices!$F:$F,Raw_Invoices!$B:$B,">="&G$2,Raw_Invoices!$B:$B,"<="&EOMONTH(G$2,0),Raw_Invoices!$D:$D,"PURCHASE",Raw_Invoices!$E:$E,"Inventory purchases") | H7: =SUMIFS(Raw_Invoices!$F:$F,Raw_Invoices!$B:$B,">="&H$2,Raw_Invoices!$B:$B,"<="&EOMONTH(H$2,0),Raw_Invoices!$D:$D,"PURCHASE",Raw_Invoices!$E:$E,"Inventory purchases") | I7: =SUMIFS(Raw_Invoices!$F:$F,Raw_Invoices!$B:$B,">="&I$2,Raw_Invoices!$B:$B,"<="&EOMONTH(I$2,0),Raw_Invoices!$D:$D,"PURCHASE",Raw_Invoices!$E:$E,"Inventory purchases") | ... M7: =SUMIFS(Raw_Invoices!$F:$F,Raw_Invoices!$B:$B,">="&M$2,Raw_Invoices!$B:$B,"<="&EOMONTH(M$2,0),Raw_Invoices!$D:$D,"PURCHASE",Raw_Invoices!$E:$E,"Inventory purchases") | N7: =SUM(B7:M7)
A8: Gross profit | B8: =B6-B7 | C8: =C6-C7 | D8: =D6-D7 | E8: =E6-E7 | F8: =F6-F7 | G8: =G6-G7 | H8: =H6-H7 | I8: =I6-I7 | ... M8: =M6-M7 | N8: =SUM(B8:M8)
A9: Expenses — Rent | B9: =SUMIFS(Raw_Invoices!$F:$F,Raw_Invoices!$B:$B,">="&B$2,Raw_Invoices!$B:$B,"<="&EOMONTH(B$2,0),Raw_Invoices!$D:$D,"EXPENSE",Raw_Invoices!$E:$E,"Rent") | C9: =SUMIFS(Raw_Invoices!$F:$F,Raw_Invoices!$B:$B,">="&C$2,Raw_Invoices!$B:$B,"<="&EOMONTH(C$2,0),Raw_Invoices!$D:$D,"EXPENSE",Raw_Invoices!$E:$E,"Rent") | D9: =SUMIFS(Raw_Invoices!$F:$F,Raw_Invoices!$B:$B,">="&D$2,Raw_Invoices!$B:$B,"<="&EOMONTH(D$2,0),Raw_Invoices!$D:$D,"EXPENSE",Raw_Invoices!$E:$E,"Rent") | E9: =SUMIFS(Raw_Invoices!$F:$F,Raw_Invoices!$B:$B,">="&E$2,Raw_Invoices!$B:$B,"<="&EOMONTH(E$2,0),Raw_Invoices!$D:$D,"EXPENSE",Raw_Invoices!$E:$E,"Rent") | F9: =SUMIFS(Raw_Invoices!$F:$F,Raw_Invoices!$B:$B,">="&F$2,Raw_Invoices!$B:$B,"<="&EOMONTH(F$2,0),Raw_Invoices!$D:$D,"EXPENSE",Raw_Invoices!$E:$E,"Rent") | G9: =SUMIFS(Raw_Invoices!$F:$F,Raw_Invoices!$B:$B,">="&G$2,Raw_Invoices!$B:$B,"<="&EOMONTH(G$2,0),Raw_Invoices!$D:$D,"EXPENSE",Raw_Invoices!$E:$E,"Rent") | H9: =SUMIFS(Raw_Invoices!$F:$F,Raw_Invoices!$B:$B,">="&H$2,Raw_Invoices!$B:$B,"<="&EOMONTH(H$2,0),Raw_Invoices!$D:$D,"EXPENSE",Raw_Invoices!$E:$E,"Rent") | I9: =SUMIFS(Raw_Invoices!$F:$F,Raw_Invoices!$B:$B,">="&I$2,Raw_Invoices!$B:$B,"<="&EOMONTH(I$2,0),Raw_Invoices!$D:$D,"EXPENSE",Raw_Invoices!$E:$E,"Rent") | ... M9: =SUMIFS(Raw_Invoices!$F:$F,Raw_Invoices!$B:$B,">="&M$2,Raw_Invoices!$B:$B,"<="&EOMONTH(M$2,0),Raw_Invoices!$D:$D,"EXPENSE",Raw_Invoices!$E:$E,"Rent") | N9: =SUM(B9:M9)
A10: Expenses — Salaries | B10: =SUMIFS(Raw_Invoices!$F:$F,Raw_Invoices!$B:$B,">="&B$2,Raw_Invoices!$B:$B,"<="&EOMONTH(B$2,0),Raw_Invoices!$D:$D,"EXPENSE",Raw_Invoices!$E:$E,"Salaries") | C10: =SUMIFS(Raw_Invoices!$F:$F,Raw_Invoices!$B:$B,">="&C$2,Raw_Invoices!$B:$B,"<="&EOMONTH(C$2,0),Raw_Invoices!$D:$D,"EXPENSE",Raw_Invoices!$E:$E,"Salaries") | D10: =SUMIFS(Raw_Invoices!$F:$F,Raw_Invoices!$B:$B,">="&D$2,Raw_Invoices!$B:$B,"<="&EOMONTH(D$2,0),Raw_Invoices!$D:$D,"EXPENSE",Raw_Invoices!$E:$E,"Salaries") | E10: =SUMIFS(Raw_Invoices!$F:$F,Raw_Invoices!$B:$B,">="&E$2,Raw_Invoices!$B:$B,"<="&EOMONTH(E$2,0),Raw_Invoices!$D:$D,"EXPENSE",Raw_Invoices!$E:$E,"Salaries") | F10: =SUMIFS(Raw_Invoices!$F:$F,Raw_Invoices!$B:$B,">="&F$2,Raw_Invoices!$B:$B,"<="&EOMONTH(F$2,0),Raw_Invoices!$D:$D,"EXPENSE",Raw_Invoices!$E:$E,"Salaries") | G10: =SUMIFS(Raw_Invoices!$F:$F,Raw_Invoices!$B:$B,">="&G$2,Raw_Invoices!$B:$B,"<="&EOMONTH(G$2,0),Raw_Invoices!$D:$D,"EXPENSE",Raw_Invoices!$E:$E,"Salaries") | H10: =SUMIFS(Raw_Invoices!$F:$F,Raw_Invoices!$B:$B,">="&H$2,Raw_Invoices!$B:$B,"<="&EOMONTH(H$2,0),Raw_Invoices!$D:$D,"EXPENSE",Raw_Invoices!$E:$E,"Salaries") | I10: =SUMIFS(Raw_Invoices!$F:$F,Raw_Invoices!$B:$B,">="&I$2,Raw_Invoices!$B:$B,"<="&EOMONTH(I$2,0),Raw_Invoices!$D:$D,"EXPENSE",Raw_Invoices!$E:$E,"Salaries") | ... M10: =SUMIFS(Raw_Invoices!$F:$F,Raw_Invoices!$B:$B,">="&M$2,Raw_Invoices!$B:$B,"<="&EOMONTH(M$2,0),Raw_Invoices!$D:$D,"EXPENSE",Raw_Invoices!$E:$E,"Salaries") | N10: =SUM(B10:M10)
A11: Expenses — Utilities | B11: =SUMIFS(Raw_Invoices!$F:$F,Raw_Invoices!$B:$B,">="&B$2,Raw_Invoices!$B:$B,"<="&EOMONTH(B$2,0),Raw_Invoices!$D:$D,"EXPENSE",Raw_Invoices!$E:$E,"Utilities") | C11: =SUMIFS(Raw_Invoices!$F:$F,Raw_Invoices!$B:$B,">="&C$2,Raw_Invoices!$B:$B,"<="&EOMONTH(C$2,0),Raw_Invoices!$D:$D,"EXPENSE",Raw_Invoices!$E:$E,"Utilities") | D11: =SUMIFS(Raw_Invoices!$F:$F,Raw_Invoices!$B:$B,">="&D$2,Raw_Invoices!$B:$B,"<="&EOMONTH(D$2,0),Raw_Invoices!$D:$D,"EXPENSE",Raw_Invoices!$E:$E,"Utilities") | E11: =SUMIFS(Raw_Invoices!$F:$F,Raw_Invoices!$B:$B,">="&E$2,Raw_Invoices!$B:$B,"<="&EOMONTH(E$2,0),Raw_Invoices!$D:$D,"EXPENSE",Raw_Invoices!$E:$E,"Utilities") | F11: =SUMIFS(Raw_Invoices!$F:$F,Raw_Invoices!$B:$B,">="&F$2,Raw_Invoices!$B:$B,"<="&EOMONTH(F$2,0),Raw_Invoices!$D:$D,"EXPENSE",Raw_Invoices!$E:$E,"Utilities") | G11: =SUMIFS(Raw_Invoices!$F:$F,Raw_Invoices!$B:$B,">="&G$2,Raw_Invoices!$B:$B,"<="&EOMONTH(G$2,0),Raw_Invoices!$D:$D,"EXPENSE",Raw_Invoices!$E:$E,"Utilities") | H11: =SUMIFS(Raw_Invoices!$F:$F,Raw_Invoices!$B:$B,">="&H$2,Raw_Invoices!$B:$B,"<="&EOMONTH(H$2,0),Raw_Invoices!$D:$D,"EXPENSE",Raw_Invoices!$E:$E,"Utilities") | I11: =SUMIFS(Raw_Invoices!$F:$F,Raw_Invoices!$B:$B,">="&I$2,Raw_Invoices!$B:$B,"<="&EOMONTH(I$2,0),Raw_Invoices!$D:$D,"EXPENSE",Raw_Invoices!$E:$E,"Utilities") | ... M11: =SUMIFS(Raw_Invoices!$F:$F,Raw_Invoices!$B:$B,">="&M$2,Raw_Invoices!$B:$B,"<="&EOMONTH(M$2,0),Raw_Invoices!$D:$D,"EXPENSE",Raw_Invoices!$E:$E,"Utilities") | N11: =SUM(B11:M11)
A12: Expenses — Transport | B12: =SUMIFS(Raw_Invoices!$F:$F,Raw_Invoices!$B:$B,">="&B$2,Raw_Invoices!$B:$B,"<="&EOMONTH(B$2,0),Raw_Invoices!$D:$D,"EXPENSE",Raw_Invoices!$E:$E,"Transport") | C12: =SUMIFS(Raw_Invoices!$F:$F,Raw_Invoices!$B:$B,">="&C$2,Raw_Invoices!$B:$B,"<="&EOMONTH(C$2,0),Raw_Invoices!$D:$D,"EXPENSE",Raw_Invoices!$E:$E,"Transport") | D12: =SUMIFS(Raw_Invoices!$F:$F,Raw_Invoices!$B:$B,">="&D$2,Raw_Invoices!$B:$B,"<="&EOMONTH(D$2,0),Raw_Invoices!$D:$D,"EXPENSE",Raw_Invoices!$E:$E,"Transport") | E12: =SUMIFS(Raw_Invoices!$F:$F,Raw_Invoices!$B:$B,">="&E$2,Raw_Invoices!$B:$B,"<="&EOMONTH(E$2,0),Raw_Invoices!$D:$D,"EXPENSE",Raw_Invoices!$E:$E,"Transport") | F12: =SUMIFS(Raw_Invoices!$F:$F,Raw_Invoices!$B:$B,">="&F$2,Raw_Invoices!$B:$B,"<="&EOMONTH(F$2,0),Raw_Invoices!$D:$D,"EXPENSE",Raw_Invoices!$E:$E,"Transport") | G12: =SUMIFS(Raw_Invoices!$F:$F,Raw_Invoices!$B:$B,">="&G$2,Raw_Invoices!$B:$B,"<="&EOMONTH(G$2,0),Raw_Invoices!$D:$D,"EXPENSE",Raw_Invoices!$E:$E,"Transport") | H12: =SUMIFS(Raw_Invoices!$F:$F,Raw_Invoices!$B:$B,">="&H$2,Raw_Invoices!$B:$B,"<="&EOMONTH(H$2,0),Raw_Invoices!$D:$D,"EXPENSE",Raw_Invoices!$E:$E,"Transport") | I12: =SUMIFS(Raw_Invoices!$F:$F,Raw_Invoices!$B:$B,">="&I$2,Raw_Invoices!$B:$B,"<="&EOMONTH(I$2,0),Raw_Invoices!$D:$D,"EXPENSE",Raw_Invoices!$E:$E,"Transport") | ... M12: =SUMIFS(Raw_Invoices!$F:$F,Raw_Invoices!$B:$B,">="&M$2,Raw_Invoices!$B:$B,"<="&EOMONTH(M$2,0),Raw_Invoices!$D:$D,"EXPENSE",Raw_Invoices!$E:$E,"Transport") | N12: =SUM(B12:M12)
A13: Expenses — Marketing | B13: =SUMIFS(Raw_Invoices!$F:$F,Raw_Invoices!$B:$B,">="&B$2,Raw_Invoices!$B:$B,"<="&EOMONTH(B$2,0),Raw_Invoices!$D:$D,"EXPENSE",Raw_Invoices!$E:$E,"Marketing") | C13: =SUMIFS(Raw_Invoices!$F:$F,Raw_Invoices!$B:$B,">="&C$2,Raw_Invoices!$B:$B,"<="&EOMONTH(C$2,0),Raw_Invoices!$D:$D,"EXPENSE",Raw_Invoices!$E:$E,"Marketing") | D13: =SUMIFS(Raw_Invoices!$F:$F,Raw_Invoices!$B:$B,">="&D$2,Raw_Invoices!$B:$B,"<="&EOMONTH(D$2,0),Raw_Invoices!$D:$D,"EXPENSE",Raw_Invoices!$E:$E,"Marketing") | E13: =SUMIFS(Raw_Invoices!$F:$F,Raw_Invoices!$B:$B,">="&E$2,Raw_Invoices!$B:$B,"<="&EOMONTH(E$2,0),Raw_Invoices!$D:$D,"EXPENSE",Raw_Invoices!$E:$E,"Marketing") | F13: =SUMIFS(Raw_Invoices!$F:$F,Raw_Invoices!$B:$B,">="&F$2,Raw_Invoices!$B:$B,"<="&EOMONTH(F$2,0),Raw_Invoices!$D:$D,"EXPENSE",Raw_Invoices!$E:$E,"Marketing") | G13: =SUMIFS(Raw_Invoices!$F:$F,Raw_Invoices!$B:$B,">="&G$2,Raw_Invoices!$B:$B,"<="&EOMONTH(G$2,0),Raw_Invoices!$D:$D,"EXPENSE",Raw_Invoices!$E:$E,"Marketing") | H13: =SUMIFS(Raw_Invoices!$F:$F,Raw_Invoices!$B:$B,">="&H$2,Raw_Invoices!$B:$B,"<="&EOMONTH(H$2,0),Raw_Invoices!$D:$D,"EXPENSE",Raw_Invoices!$E:$E,"Marketing") | I13: =SUMIFS(Raw_Invoices!$F:$F,Raw_Invoices!$B:$B,">="&I$2,Raw_Invoices!$B:$B,"<="&EOMONTH(I$2,0),Raw_Invoices!$D:$D,"EXPENSE",Raw_Invoices!$E:$E,"Marketing") | ... M13: =SUMIFS(Raw_Invoices!$F:$F,Raw_Invoices!$B:$B,">="&M$2,Raw_Invoices!$B:$B,"<="&EOMONTH(M$2,0),Raw_Invoices!$D:$D,"EXPENSE",Raw_Invoices!$E:$E,"Marketing") | N13: =SUM(B13:M13)
A14: Expenses — Professional fees | B14: =SUMIFS(Raw_Invoices!$F:$F,Raw_Invoices!$B:$B,">="&B$2,Raw_Invoices!$B:$B,"<="&EOMONTH(B$2,0),Raw_Invoices!$D:$D,"EXPENSE",Raw_Invoices!$E:$E,"Professional fees") | C14: =SUMIFS(Raw_Invoices!$F:$F,Raw_Invoices!$B:$B,">="&C$2,Raw_Invoices!$B:$B,"<="&EOMONTH(C$2,0),Raw_Invoices!$D:$D,"EXPENSE",Raw_Invoices!$E:$E,"Professional fees") | D14: =SUMIFS(Raw_Invoices!$F:$F,Raw_Invoices!$B:$B,">="&D$2,Raw_Invoices!$B:$B,"<="&EOMONTH(D$2,0),Raw_Invoices!$D:$D,"EXPENSE",Raw_Invoices!$E:$E,"Professional fees") | E14: =SUMIFS(Raw_Invoices!$F:$F,Raw_Invoices!$B:$B,">="&E$2,Raw_Invoices!$B:$B,"<="&EOMONTH(E$2,0),Raw_Invoices!$D:$D,"EXPENSE",Raw_Invoices!$E:$E,"Professional fees") | F14: =SUMIFS(Raw_Invoices!$F:$F,Raw_Invoices!$B:$B,">="&F$2,Raw_Invoices!$B:$B,"<="&EOMONTH(F$2,0),Raw_Invoices!$D:$D,"EXPENSE",Raw_Invoices!$E:$E,"Professional fees") | G14: =SUMIFS(Raw_Invoices!$F:$F,Raw_Invoices!$B:$B,">="&G$2,Raw_Invoices!$B:$B,"<="&EOMONTH(G$2,0),Raw_Invoices!$D:$D,"EXPENSE",Raw_Invoices!$E:$E,"Professional fees") | H14: =SUMIFS(Raw_Invoices!$F:$F,Raw_Invoices!$B:$B,">="&H$2,Raw_Invoices!$B:$B,"<="&EOMONTH(H$2,0),Raw_Invoices!$D:$D,"EXPENSE",Raw_Invoices!$E:$E,"Professional fees") | I14: =SUMIFS(Raw_Invoices!$F:$F,Raw_Invoices!$B:$B,">="&I$2,Raw_Invoices!$B:$B,"<="&EOMONTH(I$2,0),Raw_Invoices!$D:$D,"EXPENSE",Raw_Invoices!$E:$E,"Professional fees") | ... M14: =SUMIFS(Raw_Invoices!$F:$F,Raw_Invoices!$B:$B,">="&M$2,Raw_Invoices!$B:$B,"<="&EOMONTH(M$2,0),Raw_Invoices!$D:$D,"EXPENSE",Raw_Invoices!$E:$E,"Professional fees") | N14: =SUM(B14:M14)
A15: Expenses — Misc | B15: =SUMIFS(Raw_Invoices!$F:$F,Raw_Invoices!$B:$B,">="&B$2,Raw_Invoices!$B:$B,"<="&EOMONTH(B$2,0),Raw_Invoices!$D:$D,"EXPENSE",Raw_Invoices!$E:$E,"Misc") | C15: =SUMIFS(Raw_Invoices!$F:$F,Raw_Invoices!$B:$B,">="&C$2,Raw_Invoices!$B:$B,"<="&EOMONTH(C$2,0),Raw_Invoices!$D:$D,"EXPENSE",Raw_Invoices!$E:$E,"Misc") | D15: =SUMIFS(Raw_Invoices!$F:$F,Raw_Invoices!$B:$B,">="&D$2,Raw_Invoices!$B:$B,"<="&EOMONTH(D$2,0),Raw_Invoices!$D:$D,"EXPENSE",Raw_Invoices!$E:$E,"Misc") | E15: =SUMIFS(Raw_Invoices!$F:$F,Raw_Invoices!$B:$B,">="&E$2,Raw_Invoices!$B:$B,"<="&EOMONTH(E$2,0),Raw_Invoices!$D:$D,"EXPENSE",Raw_Invoices!$E:$E,"Misc") | F15: =SUMIFS(Raw_Invoices!$F:$F,Raw_Invoices!$B:$B,">="&F$2,Raw_Invoices!$B:$B,"<="&EOMONTH(F$2,0),Raw_Invoices!$D:$D,"EXPENSE",Raw_Invoices!$E:$E,"Misc") | G15: =SUMIFS(Raw_Invoices!$F:$F,Raw_Invoices!$B:$B,">="&G$2,Raw_Invoices!$B:$B,"<="&EOMONTH(G$2,0),Raw_Invoices!$D:$D,"EXPENSE",Raw_Invoices!$E:$E,"Misc") | H15: =SUMIFS(Raw_Invoices!$F:$F,Raw_Invoices!$B:$B,">="&H$2,Raw_Invoices!$B:$B,"<="&EOMONTH(H$2,0),Raw_Invoices!$D:$D,"EXPENSE",Raw_Invoices!$E:$E,"Misc") | I15: =SUMIFS(Raw_Invoices!$F:$F,Raw_Invoices!$B:$B,">="&I$2,Raw_Invoices!$B:$B,"<="&EOMONTH(I$2,0),Raw_Invoices!$D:$D,"EXPENSE",Raw_Invoices!$E:$E,"Misc") | ... M15: =SUMIFS(Raw_Invoices!$F:$F,Raw_Invoices!$B:$B,">="&M$2,Raw_Invoices!$B:$B,"<="&EOMONTH(M$2,0),Raw_Invoices!$D:$D,"EXPENSE",Raw_Invoices!$E:$E,"Misc") | N15: =SUM(B15:M15)
A16: Total expenses | B16: =SUM(B9:B15) | C16: =SUM(C9:C15) | D16: =SUM(D9:D15) | E16: =SUM(E9:E15) | F16: =SUM(F9:F15) | G16: =SUM(G9:G15) | H16: =SUM(H9:H15) | I16: =SUM(I9:I15) | ... M16: =SUM(M9:M15) | N16: =SUM(B16:M16)
A17: Net profit | B17: =B8-B16 | C17: =C8-C16 | D17: =D8-D16 | E17: =E8-E16 | F17: =F8-F16 | G17: =G8-G16 | H17: =H8-H16 | I17: =I8-I16 | ... M17: =M8-M16 | N17: =SUM(B17:M17)
A18: Gross margin % | B18: =IF(B6=0,0,B8/B6) | C18: =IF(C6=0,0,C8/C6) | D18: =IF(D6=0,0,D8/D6) | E18: =IF(E6=0,0,E8/E6) | F18: =IF(F6=0,0,F8/F6) | G18: =IF(G6=0,0,G8/G6) | H18: =IF(H6=0,0,H8/H6) | I18: =IF(I6=0,0,I8/I6) | ... M18: =IF(M6=0,0,M8/M6) | N18: =SUM(B18:M18)
A19: Net margin % | B19: =IF(B6=0,0,B17/B6) | C19: =IF(C6=0,0,C17/C6) | D19: =IF(D6=0,0,D17/D6) | E19: =IF(E6=0,0,E17/E6) | F19: =IF(F6=0,0,F17/F6) | G19: =IF(G6=0,0,G17/G6) | H19: =IF(H6=0,0,H17/H6) | I19: =IF(I6=0,0,I17/I6) | ... M19: =IF(M6=0,0,M17/M6) | N19: =SUM(B19:M19)
A20: GST — Output | B20: =SUMIFS(Raw_Invoices!$H:$H,Raw_Invoices!$B:$B,">="&B$2,Raw_Invoices!$B:$B,"<="&EOMONTH(B$2,0),Raw_Invoices!$D:$D,"SALES") | C20: =SUMIFS(Raw_Invoices!$H:$H,Raw_Invoices!$B:$B,">="&C$2,Raw_Invoices!$B:$B,"<="&EOMONTH(C$2,0),Raw_Invoices!$D:$D,"SALES") | D20: =SUMIFS(Raw_Invoices!$H:$H,Raw_Invoices!$B:$B,">="&D$2,Raw_Invoices!$B:$B,"<="&EOMONTH(D$2,0),Raw_Invoices!$D:$D,"SALES") | E20: =SUMIFS(Raw_Invoices!$H:$H,Raw_Invoices!$B:$B,">="&E$2,Raw_Invoices!$B:$B,"<="&EOMONTH(E$2,0),Raw_Invoices!$D:$D,"SALES") | F20: =SUMIFS(Raw_Invoices!$H:$H,Raw_Invoices!$B:$B,">="&F$2,Raw_Invoices!$B:$B,"<="&EOMONTH(F$2,0),Raw_Invoices!$D:$D,"SALES") | G20: =SUMIFS(Raw_Invoices!$H:$H,Raw_Invoices!$B:$B,">="&G$2,Raw_Invoices!$B:$B,"<="&EOMONTH(G$2,0),Raw_Invoices!$D:$D,"SALES") | H20: =SUMIFS(Raw_Invoices!$H:$H,Raw_Invoices!$B:$B,">="&H$2,Raw_Invoices!$B:$B,"<="&EOMONTH(H$2,0),Raw_Invoices!$D:$D,"SALES") | I20: =SUMIFS(Raw_Invoices!$H:$H,Raw_Invoices!$B:$B,">="&I$2,Raw_Invoices!$B:$B,"<="&EOMONTH(I$2,0),Raw_Invoices!$D:$D,"SALES") | ... M20: =SUMIFS(Raw_Invoices!$H:$H,Raw_Invoices!$B:$B,">="&M$2,Raw_Invoices!$B:$B,"<="&EOMONTH(M$2,0),Raw_Invoices!$D:$D,"SALES") | N20: =SUM(B20:M20)
A21: GST — Input | B21: =SUMIFS(Raw_Invoices!$H:$H,Raw_Invoices!$B:$B,">="&B$2,Raw_Invoices!$B:$B,"<="&EOMONTH(B$2,0),Raw_Invoices!$D:$D,"PURCHASE")+SUMIFS(Raw_Invoices!$H:$H,Raw_Invoices!$B:$B,">="&B$2,Raw_Invoices!$B:$B,"<="&EOMONTH(B$2,0),Raw_Invoices!$D:$D,"EXPENSE") | C21: =SUMIFS(Raw_Invoices!$H:$H,Raw_Invoices!$B:$B,">="&C$2,Raw_Invoices!$B:$B,"<="&EOMONTH(C$2,0),Raw_Invoices!$D:$D,"PURCHASE")+SUMIFS(Raw_Invoices!$H:$H,Raw_Invoices!$B:$B,">="&C$2,Raw_Invoices!$B:$B,"<="&EOMONTH(C$2,0),Raw_Invoices!$D:$D,"EXPENSE") | D21: =SUMIFS(Raw_Invoices!$H:$H,Raw_Invoices!$B:$B,">="&D$2,Raw_Invoices!$B:$B,"<="&EOMONTH(D$2,0),Raw_Invoices!$D:$D,"PURCHASE")+SUMIFS(Raw_Invoices!$H:$H,Raw_Invoices!$B:$B,">="&D$2,Raw_Invoices!$B:$B,"<="&EOMONTH(D$2,0),Raw_Invoices!$D:$D,"EXPENSE") | E21: =SUMIFS(Raw_Invoices!$H:$H,Raw_Invoices!$B:$B,">="&E$2,Raw_Invoices!$B:$B,"<="&EOMONTH(E$2,0),Raw_Invoices!$D:$D,"PURCHASE")+SUMIFS(Raw_Invoices!$H:$H,Raw_Invoices!$B:$B,">="&E$2,Raw_Invoices!$B:$B,"<="&EOMONTH(E$2,0),Raw_Invoices!$D:$D,"EXPENSE") | F21: =SUMIFS(Raw_Invoices!$H:$H,Raw_Invoices!$B:$B,">="&F$2,Raw_Invoices!$B:$B,"<="&EOMONTH(F$2,0),Raw_Invoices!$D:$D,"PURCHASE")+SUMIFS(Raw_Invoices!$H:$H,Raw_Invoices!$B:$B,">="&F$2,Raw_Invoices!$B:$B,"<="&EOMONTH(F$2,0),Raw_Invoices!$D:$D,"EXPENSE") | G21: =SUMIFS(Raw_Invoices!$H:$H,Raw_Invoices!$B:$B,">="&G$2,Raw_Invoices!$B:$B,"<="&EOMONTH(G$2,0),Raw_Invoices!$D:$D,"PURCHASE")+SUMIFS(Raw_Invoices!$H:$H,Raw_Invoices!$B:$B,">="&G$2,Raw_Invoices!$B:$B,"<="&EOMONTH(G$2,0),Raw_Invoices!$D:$D,"EXPENSE") | H21: =SUMIFS(Raw_Invoices!$H:$H,Raw_Invoices!$B:$B,">="&H$2,Raw_Invoices!$B:$B,"<="&EOMONTH(H$2,0),Raw_Invoices!$D:$D,"PURCHASE")+SUMIFS(Raw_Invoices!$H:$H,Raw_Invoices!$B:$B,">="&H$2,Raw_Invoices!$B:$B,"<="&EOMONTH(H$2,0),Raw_Invoices!$D:$D,"EXPENSE") | I21: =SUMIFS(Raw_Invoices!$H:$H,Raw_Invoices!$B:$B,">="&I$2,Raw_Invoices!$B:$B,"<="&EOMONTH(I$2,0),Raw_Invoices!$D:$D,"PURCHASE")+SUMIFS(Raw_Invoices!$H:$H,Raw_Invoices!$B:$B,">="&I$2,Raw_Invoices!$B:$B,"<="&EOMONTH(I$2,0),Raw_Invoices!$D:$D,"EXPENSE") | ... M21: =SUMIFS(Raw_Invoices!$H:$H,Raw_Invoices!$B:$B,">="&M$2,Raw_Invoices!$B:$B,"<="&EOMONTH(M$2,0),Raw_Invoices!$D:$D,"PURCHASE")+SUMIFS(Raw_Invoices!$H:$H,Raw_Invoices!$B:$B,">="&M$2,Raw_Invoices!$B:$B,"<="&EOMONTH(M$2,0),Raw_Invoices!$D:$D,"EXPENSE") | N21: =SUM(B21:M21)
A22: GST — Net payable | B22: =B20-B21 | C22: =C20-C21 | D22: =D20-D21 | E22: =E20-E21 | F22: =F20-F21 | G22: =G20-G21 | H22: =H20-H21 | I22: =I20-I21 | ... M22: =M20-M21 | N22: =SUM(B22:M22)

Sheet CashFlow
A1: CashFlow — monthly (formula-driven)
A2: Line | B2: 45931 | C2: 45962 | D2: 45992 | E2: 46023 | F2: 46054 | G2: 46082 | H2: 46113 | I2: 46143 | J2: 46174 | K2: 46204 | L2: 46235 | M2: 46266 | N2: FY total
A3: Cash receipts — customers | B3: =SUMIFS(Raw_Payments!$F:$F,Raw_Payments!$E:$E,">="&B$2,Raw_Payments!$E:$E,"<="&EOMONTH(B$2,0),Raw_Payments!$C:$C,"SALES") | C3: =SUMIFS(Raw_Payments!$F:$F,Raw_Payments!$E:$E,">="&C$2,Raw_Payments!$E:$E,"<="&EOMONTH(C$2,0),Raw_Payments!$C:$C,"SALES") | D3: =SUMIFS(Raw_Payments!$F:$F,Raw_Payments!$E:$E,">="&D$2,Raw_Payments!$E:$E,"<="&EOMONTH(D$2,0),Raw_Payments!$C:$C,"SALES") | E3: =SUMIFS(Raw_Payments!$F:$F,Raw_Payments!$E:$E,">="&E$2,Raw_Payments!$E:$E,"<="&EOMONTH(E$2,0),Raw_Payments!$C:$C,"SALES") | F3: =SUMIFS(Raw_Payments!$F:$F,Raw_Payments!$E:$E,">="&F$2,Raw_Payments!$E:$E,"<="&EOMONTH(F$2,0),Raw_Payments!$C:$C,"SALES") | G3: =SUMIFS(Raw_Payments!$F:$F,Raw_Payments!$E:$E,">="&G$2,Raw_Payments!$E:$E,"<="&EOMONTH(G$2,0),Raw_Payments!$C:$C,"SALES") | H3: =SUMIFS(Raw_Payments!$F:$F,Raw_Payments!$E:$E,">="&H$2,Raw_Payments!$E:$E,"<="&EOMONTH(H$2,0),Raw_Payments!$C:$C,"SALES") | I3: =SUMIFS(Raw_Payments!$F:$F,Raw_Payments!$E:$E,">="&I$2,Raw_Payments!$E:$E,"<="&EOMONTH(I$2,0),Raw_Payments!$C:$C,"SALES") | ... M3: =SUMIFS(Raw_Payments!$F:$F,Raw_Payments!$E:$E,">="&M$2,Raw_Payments!$E:$E,"<="&EOMONTH(M$2,0),Raw_Payments!$C:$C,"SALES") | N3: =SUM(B3:M3)
A4: Cash paid — inventory | B4: =SUMIFS(Raw_Payments!$F:$F,Raw_Payments!$E:$E,">="&B$2,Raw_Payments!$E:$E,"<="&EOMONTH(B$2,0),Raw_Payments!$C:$C,"PURCHASE") | C4: =SUMIFS(Raw_Payments!$F:$F,Raw_Payments!$E:$E,">="&C$2,Raw_Payments!$E:$E,"<="&EOMONTH(C$2,0),Raw_Payments!$C:$C,"PURCHASE") | D4: =SUMIFS(Raw_Payments!$F:$F,Raw_Payments!$E:$E,">="&D$2,Raw_Payments!$E:$E,"<="&EOMONTH(D$2,0),Raw_Payments!$C:$C,"PURCHASE") | E4: =SUMIFS(Raw_Payments!$F:$F,Raw_Payments!$E:$E,">="&E$2,Raw_Payments!$E:$E,"<="&EOMONTH(E$2,0),Raw_Payments!$C:$C,"PURCHASE") | F4: =SUMIFS(Raw_Payments!$F:$F,Raw_Payments!$E:$E,">="&F$2,Raw_Payments!$E:$E,"<="&EOMONTH(F$2,0),Raw_Payments!$C:$C,"PURCHASE") | G4: =SUMIFS(Raw_Payments!$F:$F,Raw_Payments!$E:$E,">="&G$2,Raw_Payments!$E:$E,"<="&EOMONTH(G$2,0),Raw_Payments!$C:$C,"PURCHASE") | H4: =SUMIFS(Raw_Payments!$F:$F,Raw_Payments!$E:$E,">="&H$2,Raw_Payments!$E:$E,"<="&EOMONTH(H$2,0),Raw_Payments!$C:$C,"PURCHASE") | I4: =SUMIFS(Raw_Payments!$F:$F,Raw_Payments!$E:$E,">="&I$2,Raw_Payments!$E:$E,"<="&EOMONTH(I$2,0),Raw_Payments!$C:$C,"PURCHASE") | ... M4: =SUMIFS(Raw_Payments!$F:$F,Raw_Payments!$E:$E,">="&M$2,Raw_Payments!$E:$E,"<="&EOMONTH(M$2,0),Raw_Payments!$C:$C,"PURCHASE") | N4: =SUM(B4:M4)
A5: Cash paid — expenses | B5: =SUMIFS(Raw_Payments!$F:$F,Raw_Payments!$E:$E,">="&B$2,Raw_Payments!$E:$E,"<="&EOMONTH(B$2,0),Raw_Payments!$C:$C,"EXPENSE") | C5: =SUMIFS(Raw_Payments!$F:$F,Raw_Payments!$E:$E,">="&C$2,Raw_Payments!$E:$E,"<="&EOMONTH(C$2,0),Raw_Payments!$C:$C,"EXPENSE") | D5: =SUMIFS(Raw_Payments!$F:$F,Raw_Payments!$E:$E,">="&D$2,Raw_Payments!$E:$E,"<="&EOMONTH(D$2,0),Raw_Payments!$C:$C,"EXPENSE") | E5: =SUMIFS(Raw_Payments!$F:$F,Raw_Payments!$E:$E,">="&E$2,Raw_Payments!$E:$E,"<="&EOMONTH(E$2,0),Raw_Payments!$C:$C,"EXPENSE") | F5: =SUMIFS(Raw_Payments!$F:$F,Raw_Payments!$E:$E,">="&F$2,Raw_Payments!$E:$E,"<="&EOMONTH(F$2,0),Raw_Payments!$C:$C,"EXPENSE") | G5: =SUMIFS(Raw_Payments!$F:$F,Raw_Payments!$E:$E,">="&G$2,Raw_Payments!$E:$E,"<="&EOMONTH(G$2,0),Raw_Payments!$C:$C,"EXPENSE") | H5: =SUMIFS(Raw_Payments!$F:$F,Raw_Payments!$E:$E,">="&H$2,Raw_Payments!$E:$E,"<="&EOMONTH(H$2,0),Raw_Payments!$C:$C,"EXPENSE") | I5: =SUMIFS(Raw_Payments!$F:$F,Raw_Payments!$E:$E,">="&I$2,Raw_Payments!$E:$E,"<="&EOMONTH(I$2,0),Raw_Payments!$C:$C,"EXPENSE") | ... M5: =SUMIFS(Raw_Payments!$F:$F,Raw_Payments!$E:$E,">="&M$2,Raw_Payments!$E:$E,"<="&EOMONTH(M$2,0),Raw_Payments!$C:$C,"EXPENSE") | N5: =SUM(B5:M5)
A6: Net cash flow | B6: =B3-B4-B5 | C6: =C3-C4-C5 | D6: =D3-D4-D5 | E6: =E3-E4-E5 | F6: =F3-F4-F5 | G6: =G3-G4-G5 | H6: =H3-H4-H5 | I6: =I3-I4-I5 | ... M6: =M3-M4-M5 | N6: =SUM(B6:M6)
A7: Cumulative cash flow | B7: =B6 | C7: =B7+C6 | D7: =C7+D6 | E7: =D7+E6 | F7: =E7+F6 | G7: =F7+G6 | H7: =G7+H6 | I7: =H7+I6 | J7: =I7+J6 | ... M7: =L7+M6 | N7: =M7

Sheet Receivables
A1: Receivables — outstanding invoices & aging (formula-driven) | J1: Aging summary
J2: Bucket | K2: Outstanding
A3: inv_id | B3: party | C3: invoice date | D3: total | E3: paid | F3: balance | G3: days outstanding | H3: bucket | J3: 0-30 | K3: =SUMIFS($F$4:$F$173,$H$4:$H$173,"0-30")
A4: S-00003 | B4: City Centre Apparel | C4: 45934 | D4: 93076.64 | E4: 44997.63 | F4: =D4-E4 | G4: =Guide!$B$2-C4 | H4: =IF(G4="","",IF(G4<=30,"0-30",IF(G4<=60,"31-60",IF(G4<=90,"61-90","90+")))) | J4: 31-60 | K4: =SUMIFS($F$4:$F$173,$H$4:$H$173,"31-60")
A5: S-00006 | B5: Patna Fashion House | C5: 45950 | D5: 94337.77 | E5: 47036.71 | F5: =D5-E5 | G5: =Guide!$B$2-C5 | H5: =IF(G5="","",IF(G5<=30,"0-30",IF(G5<=60,"31-60",IF(G5<=90,"61-90","90+")))) | J5: 61-90 | K5: =SUMIFS($F$4:$F$173,$H$4:$H$173,"61-90")
A6: S-00008 | B6: Gaya Textile Traders | C6: 45961 | D6: 91989.16 | E6: 0 | F6: =D6-E6 | G6: =Guide!$B$2-C6 | H6: =IF(G6="","",IF(G6<=30,"0-30",IF(G6<=60,"31-60",IF(G6<=90,"61-90","90+")))) | J6: 90+ | K6: =SUMIFS($F$4:$F$173,$H$4:$H$173,"90+")
A7: S-00009 | B7: Arrah Garment Plaza | C7: 45942 | D7: 78306.28 | E7: 45569.08 | F7: =D7-E7 | G7: =Guide!$B$2-C7 | H7: =IF(G7="","",IF(G7<=30,"0-30",IF(G7<=60,"31-60",IF(G7<=90,"61-90","90+")))) | J7: Total outstanding | K7: =SUM(F4:F173)
A8: S-00014 | B8: Lakshmi Cloth Store | C8: 45938 | D8: 80784.61 | E8: 0 | F8: =D8-E8 | G8: =Guide!$B$2-C8 | H8: =IF(G8="","",IF(G8<=30,"0-30",IF(G8<=60,"31-60",IF(G8<=90,"61-90","90+")))) | J8: Invoices outstanding | K8: =COUNTA(A4:A173)
A9: S-00016 | B9: Muzaffarpur Cloth House | C9: 45932 | D9: 45485.38 | E9: 0 | F9: =D9-E9 | G9: =Guide!$B$2-C9 | H9: =IF(G9="","",IF(G9<=30,"0-30",IF(G9<=60,"31-60",IF(G9<=90,"61-90","90+")))) | J9: Avg collection days (paid sales) | K9: =AVERAGEIFS(Raw_Invoices!$M:$M,Raw_Invoices!$D:$D,"SALES",Raw_Invoices!$M:$M,"<>")
A10: S-00018 | B10: Trendy Threads | C10: 45941 | D10: 82138.41 | E10: 48055.6 | F10: =D10-E10 | G10: =Guide!$B$2-C10 | H10: =IF(G10="","",IF(G10<=30,"0-30",IF(G10<=60,"31-60",IF(G10<=90,"61-90","90+")))) | J10: Overdue 61+ days | K10: =K5+K6
A11: S-00026 | B11: Trendy Threads | C11: 45953 | D11: 54668.47 | E11: 26916.26 | F11: =D11-E11 | G11: =Guide!$B$2-C11 | H11: =IF(G11="","",IF(G11<=30,"0-30",IF(G11<=60,"31-60",IF(G11<=90,"61-90","90+"))))
A12: S-00030 | B12: Bazaar Collection | C12: 45954 | D12: 85087.37 | E12: 40598.37 | F12: =D12-E12 | G12: =Guide!$B$2-C12 | H12: =IF(G12="","",IF(G12<=30,"0-30",IF(G12<=60,"31-60",IF(G12<=90,"61-90","90+"))))
A13: P-00002 | B13: Kolkata Hosiery House | C13: 45960 | D13: 23554.03 | E13: 0 | F13: =D13-E13 | G13: =Guide!$B$2-C13 | H13: =IF(G13="","",IF(G13<=30,"0-30",IF(G13<=60,"31-60",IF(G13<=90,"61-90","90+"))))
A14: P-00009 | B14: Jaipur Print Works | C14: 45953 | D14: 103751.62 | E14: 48854.72 | F14: =D14-E14 | G14: =Guide!$B$2-C14 | H14: =IF(G14="","",IF(G14<=30,"0-30",IF(G14<=60,"31-60",IF(G14<=90,"61-90","90+"))))
A15: P-00011 | B15: Ludhiana Knitwear Co | C15: 45932 | D15: 114690.45 | E15: 0 | F15: =D15-E15 | G15: =Guide!$B$2-C15 | H15: =IF(G15="","",IF(G15<=30,"0-30",IF(G15<=60,"31-60",IF(G15<=90,"61-90","90+"))))
A16: E-00006 | B16: Various | C16: 45942 | D16: 1630.2 | E16: 0 | F16: =D16-E16 | G16: =Guide!$B$2-C16 | H16: =IF(G16="","",IF(G16<=30,"0-30",IF(G16<=60,"31-60",IF(G16<=90,"61-90","90+"))))
A17: S-00041 | B17: Patna Fashion House | C17: 45989 | D17: 10713.91 | E17: 8084.75 | F17: =D17-E17 | G17: =Guide!$B$2-C17 | H17: =IF(G17="","",IF(G17<=30,"0-30",IF(G17<=60,"31-60",IF(G17<=90,"61-90","90+"))))
A18: S-00045 | B18: New Look Garments | C18: 45967 | D18: 76805.3 | E18: 0 | F18: =D18-E18 | G18: =Guide!$B$2-C18 | H18: =IF(G18="","",IF(G18<=30,"0-30",IF(G18<=60,"31-60",IF(G18<=90,"61-90","90+"))))
A19: S-00052 | B19: Sharma Retail Store | C19: 45985 | D19: 47810.03 | E19: 0 | F19: =D19-E19 | G19: =Guide!$B$2-C19 | H19: =IF(G19="","",IF(G19<=30,"0-30",IF(G19<=60,"31-60",IF(G19<=90,"61-90","90+"))))
A20: S-00053 | B20: Sharma Retail Store | C20: 45984 | D20: 89119.21 | E20: 0 | F20: =D20-E20 | G20: =Guide!$B$2-C20 | H20: =IF(G20="","",IF(G20<=30,"0-30",IF(G20<=60,"31-60",IF(G20<=90,"61-90","90+"))))
A21: S-00055 | B21: Trendy Threads | C21: 45966 | D21: 34914.96 | E21: 0 | F21: =D21-E21 | G21: =Guide!$B$2-C21 | H21: =IF(G21="","",IF(G21<=30,"0-30",IF(G21<=60,"31-60",IF(G21<=90,"61-90","90+"))))
A22: S-00060 | B22: Purnia Fashion Hub | C22: 45987 | D22: 103350 | E22: 0 | F22: =D22-E22 | G22: =Guide!$B$2-C22 | H22: =IF(G22="","",IF(G22<=30,"0-30",IF(G22<=60,"31-60",IF(G22<=90,"61-90","90+"))))
... A173: E-00172 | B173: Various | C173: 46292 | D173: 3567.05 | E173: 0 | F173: =D173-E173 | G173: =Guide!$B$2-C173 | H173: =IF(G173="","",IF(G173<=30,"0-30",IF(G173<=60,"31-60",IF(G173<=90,"61-90","90+"))))

Sheet Dashboard
A1: Dashboard — KPIs (all formula-linked)
A3: FY revenue | B3: ='P&L'!N6
A4: FY net profit | B4: ='P&L'!N17
A5: Net margin | B5: ='P&L'!N19
A6: Receivables outstanding | B6: =Receivables!K7
A7: Avg collection days | B7: =Receivables!K9
A8: Closing cash balance | B8: ='CashFlow'!N7

Sheet AI_Report
A1: AI_Report — rule-based narrative (recalculates with the data)
A3: Key findings
B4: =B5+B6
A5: ="FY revenue was "&TEXT(B4,"#,##0")&", H2 vs H1: "&TEXT(B7,"0.0%")&". Best month: "&TEXT(B8,"mmm-yy")&". Net margin "&TEXT(B12,"0.0%")&"." | B5: =SUM('P&L'!B6:G6)
A6: Flags | B6: =SUM('P&L'!H6:M6)
A7: =IF(B9>0.15,"⚠ Receivables are "&TEXT(B9,"0%")&" of revenue — tighten collections","✓ Receivables at "&TEXT(B9,"0%")&" of revenue") | B7: =IF(B5=0,0,(B6-B5)/B5)
A8: =IF(B12<0.08,"⚠ Net margin "&TEXT(B12,"0.0%")&" is thin — review pricing or costs","✓ Net margin healthy at "&TEXT(B12,"0.0%")) | B8: =INDEX('P&L'!B2:M2,MATCH(MAX('P&L'!B6:M6),'P&L'!B6:M6,0))
A9: =IF(B10>0.25,"⚠ "&TEXT(B10,"0%")&" of receivables are 61+ days overdue — prioritise recovery","✓ Overdue 61+ days under control") | B9: =Receivables!K7/'P&L'!N6
A10: =IF(B11<0,"⚠ Cash went negative intra-year (lowest "&TEXT(B11,"#,##0")&") — arrange a buffer","✓ Cash stayed positive all year") | B10: =Receivables!K10/Receivables!K7
A11: =IF(B13>45,"⚠ Avg collection "&TEXT(B13,"0")&" days — slower than 45-day terms","✓ Avg collection "&TEXT(B13,"0")&" days") | B11: =MIN('CashFlow'!B7:M7)
A12: =IF(B14>0.5,"⚠ One category is "&TEXT(B14,"0%")&" of revenue — concentration risk","✓ Revenue spread across categories") | B12: ='P&L'!N19
A13: =IF('P&L'!N22>0,"ℹ Net GST payable for the year: "&TEXT('P&L'!N22,"#,##0"),"ℹ Net GST credit for the year") | B13: =Receivables!K9
A14: =IF(B7>0,"✓ H2 revenue momentum positive","⚠ H2 revenue declined vs H1 — investigate demand") | B14: =MAX('P&L'!N3:N5)/'P&L'!N6

Sheet Checks
A1: Checks — all must be TRUE after recalculation
A2: Check | B2: Result
A3: P&L FY revenue = SUM of raw SALES amounts | B3: =ABS('P&L'!N6-SUMIFS(Raw_Invoices!$F:$F,Raw_Invoices!$D:$D,"SALES"))<0.01
A4: Gross profit = revenue − COGS | B4: =ABS('P&L'!N8-('P&L'!N6-'P&L'!N7))<0.01
A5: Net profit = gross profit − total expenses | B5: =ABS('P&L'!N17-('P&L'!N8-'P&L'!N16))<0.01
A6: CashFlow receipts FY = SUM of raw SALES payments | B6: =ABS('CashFlow'!N3-SUMIFS(Raw_Payments!$F:$F,Raw_Payments!$C:$C,"SALES"))<0.01
A7: Closing cash = last month cumulative | B7: =ABS('CashFlow'!N7-'CashFlow'!M7)<0.01
A8: Aging buckets sum = total outstanding | B8: =ABS(Receivables!K7-SUM(Receivables!K3:K6))<0.01
A9: No negative balances in Raw_Invoices | B9: =COUNTIFS(Raw_Invoices!$L:$L,"<0")=0
A10: No paid_amount exceeding invoice total | B10: =SUMPRODUCT((Raw_Invoices!$J$2:$J$788>Raw_Invoices!$I$2:$I$788)+0)=0
