Workbook

Sheet Sales
A1: Date | B1: Invoice | C1: Customer | D1: Product | E1: Category | F1: Qty | G1: Rate | H1: Amount | I1: COGS
A2: 46113 | B2: INV-2604-0001 | C2: Dubey Kirana | D2: Mango Juice 1L | E2: Beverages | F2: 39 | G2: 125.72 | H2: =F2*G2 | I2: =F2*VLOOKUP(D2,Products!$B$2:$E$13,3,FALSE)
A3: 46113 | B3: INV-2604-0002 | C3: Sharma Provision | D3: Curd Cup 400g | E3: Dairy | F3: 34 | G3: 44.45 | H3: =F3*G3 | I3: =F3*VLOOKUP(D3,Products!$B$2:$E$13,3,FALSE)
A4: 46113 | B4: INV-2604-0003 | C4: Verma Retail | D4: Packaged Water 1L | E4: Beverages | F4: 18 | G4: 20.81 | H4: =F4*G4 | I4: =F4*VLOOKUP(D4,Products!$B$2:$E$13,3,FALSE)
A5: 46113 | B5: INV-2604-0004 | C5: Tiwari General | D5: Cola 750ml | E5: Beverages | F5: 43 | G5: 46.01 | H5: =F5*G5 | I5: =F5*VLOOKUP(D5,Products!$B$2:$E$13,3,FALSE)
A6: 46113 | B6: INV-2604-0005 | C6: Raza Brothers | D6: Cola 750ml | E6: Beverages | F6: 52 | G6: 43.95 | H6: =F6*G6 | I6: =F6*VLOOKUP(D6,Products!$B$2:$E$13,3,FALSE)
A7: 46113 | B7: INV-2604-0006 | C7: Jha Provisions | D7: Biscuits 400g | E7: Snacks | F7: 43 | G7: 40.89 | H7: =F7*G7 | I7: =F7*VLOOKUP(D7,Products!$B$2:$E$13,3,FALSE)
A8: 46113 | B8: INV-2604-0007 | C8: Choudhary Mart | D8: Cola 750ml | E8: Beverages | F8: 24 | G8: 43.99 | H8: =F8*G8 | I8: =F8*VLOOKUP(D8,Products!$B$2:$E$13,3,FALSE)
A9: 46113 | B9: INV-2604-0008 | C9: Kumari Kirana | D9: Paneer 200g | E9: Dairy | F9: 47 | G9: 94.71 | H9: =F9*G9 | I9: =F9*VLOOKUP(D9,Products!$B$2:$E$13,3,FALSE)
A10: 46114 | B10: INV-2604-0009 | C10: Sinha Super Mart | D10: Paneer 200g | E10: Dairy | F10: 60 | G10: 94.38 | H10: =F10*G10 | I10: =F10*VLOOKUP(D10,Products!$B$2:$E$13,3,FALSE)
A11: 46114 | B11: INV-2604-0010 | C11: Sahu Traders | D11: Mango Juice 1L | E11: Beverages | F11: 56 | G11: 125.41 | H11: =F11*G11 | I11: =F11*VLOOKUP(D11,Products!$B$2:$E$13,3,FALSE)
A12: 46114 | B12: INV-2604-0011 | C12: Sharma Provision | D12: Cola 750ml | E12: Beverages | F12: 16 | G12: 46.62 | H12: =F12*G12 | I12: =F12*VLOOKUP(D12,Products!$B$2:$E$13,3,FALSE)
A13: 46114 | B13: INV-2604-0012 | C13: Prasad Traders | D13: Cola 750ml | E13: Beverages | F13: 25 | G13: 43.8 | H13: =F13*G13 | I13: =F13*VLOOKUP(D13,Products!$B$2:$E$13,3,FALSE)
... A1480: 46160 | B1480: INV-2605-1489 | C1480: Singh Super Bazaar | D1480: Mango Juice 1L | E1480: Beverages | F1480: 4000 | G1480: 118 | H1480: =F1480*G1480 | I1480: =F1480*VLOOKUP(D1480,Products!$B$2:$E$13,3,FALSE)
H1481: =F1481*G1481 | I1481: =IF(D1481="","",F1481*VLOOKUP(D1481,Products!$B$2:$E$13,3,FALSE))
H1482: =F1482*G1482 | I1482: =IF(D1482="","",F1482*VLOOKUP(D1482,Products!$B$2:$E$13,3,FALSE))
H1483: =F1483*G1483 | I1483: =IF(D1483="","",F1483*VLOOKUP(D1483,Products!$B$2:$E$13,3,FALSE))
H1484: =F1484*G1484 | I1484: =IF(D1484="","",F1484*VLOOKUP(D1484,Products!$B$2:$E$13,3,FALSE))
H1485: =F1485*G1485 | I1485: =IF(D1485="","",F1485*VLOOKUP(D1485,Products!$B$2:$E$13,3,FALSE))
H1486: =F1486*G1486 | I1486: =IF(D1486="","",F1486*VLOOKUP(D1486,Products!$B$2:$E$13,3,FALSE))
H1487: =F1487*G1487 | I1487: =IF(D1487="","",F1487*VLOOKUP(D1487,Products!$B$2:$E$13,3,FALSE))
H1488: =F1488*G1488 | I1488: =IF(D1488="","",F1488*VLOOKUP(D1488,Products!$B$2:$E$13,3,FALSE))
H1489: =F1489*G1489 | I1489: =IF(D1489="","",F1489*VLOOKUP(D1489,Products!$B$2:$E$13,3,FALSE))
H1490: =F1490*G1490 | I1490: =IF(D1490="","",F1490*VLOOKUP(D1490,Products!$B$2:$E$13,3,FALSE))
H1491: =F1491*G1491 | I1491: =IF(D1491="","",F1491*VLOOKUP(D1491,Products!$B$2:$E$13,3,FALSE))
H1492: =F1492*G1492 | I1492: =IF(D1492="","",F1492*VLOOKUP(D1492,Products!$B$2:$E$13,3,FALSE))
... H2500: =F2500*G2500 | I2500: =IF(D2500="","",F2500*VLOOKUP(D2500,Products!$B$2:$E$13,3,FALSE))

Sheet Purchases
A1: Date | B1: Bill | C1: Supplier | D1: Product | E1: Category | F1: Qty | G1: CostRate | H1: Amount
A2: 46113 | B2: BIL-2604-0001 | C2: Patliputra Agencies | D2: Biscuits 400g | E2: Snacks | F2: 114 | G2: 30.01 | H2: =F2*G2
A3: 46115 | B3: BIL-2604-0002 | C3: Ganga FMCG Supply | D3: Packaged Water 1L | E3: Beverages | F3: 337 | G3: 14.96 | H3: =F3*G3
A4: 46115 | B4: BIL-2604-0003 | C4: Nalanda Distribution | D4: Potato Chips 150g | E4: Snacks | F4: 58 | G4: 38.34 | H4: =F4*G4
A5: 46115 | B5: BIL-2604-0004 | C5: Patliputra Agencies | D5: Dish Soap 500ml | E5: Household | F5: 328 | G5: 80.47 | H5: =F5*G5
A6: 46115 | B6: BIL-2604-0005 | C6: Vaishali Supply House | D6: Instant Noodles 280g | E6: Snacks | F6: 342 | G6: 42.73 | H6: =F6*G6
A7: 46116 | B7: BIL-2604-0006 | C7: Bihar Foods Distributors | D7: Floor Cleaner 1L | E7: Household | F7: 312 | G7: 88.19 | H7: =F7*G7
A8: 46116 | B8: BIL-2604-0007 | C8: Koshi Enterprises | D8: Instant Noodles 280g | E8: Snacks | F8: 325 | G8: 41.5 | H8: =F8*G8
A9: 46116 | B9: BIL-2604-0008 | C9: Ganga FMCG Supply | D9: Detergent 1kg | E9: Household | F9: 114 | G9: 106.29 | H9: =F9*G9
A10: 46117 | B10: BIL-2604-0009 | C10: Ganga FMCG Supply | D10: Floor Cleaner 1L | E10: Household | F10: 308 | G10: 87.41 | H10: =F10*G10
A11: 46117 | B11: BIL-2604-0010 | C11: Vaishali Supply House | D11: Detergent 1kg | E11: Household | F11: 293 | G11: 103.62 | H11: =F11*G11
A12: 46117 | B12: BIL-2604-0011 | C12: Patliputra Agencies | D12: Toned Milk 1L | E12: Dairy | F12: 300 | G12: 55.05 | H12: =F12*G12
A13: 46118 | B13: BIL-2604-0012 | C13: Magadh Wholesale Co. | D13: Detergent 1kg | E13: Household | F13: 292 | G13: 105.4 | H13: =F13*G13
... A357: 46295 | B357: BIL-2609-0356 | C357: Vaishali Supply House | D357: Cola 750ml | E357: Beverages | F357: 294 | G357: 35.39 | H357: =F357*G357
H358: =F358*G358
H359: =F359*G359
H360: =F360*G360
H361: =F361*G361
H362: =F362*G362
H363: =F363*G363
H364: =F364*G364
H365: =F365*G365
H366: =F366*G366
H367: =F367*G367
H368: =F368*G368
H369: =F369*G369
... H1500: =F1500*G1500

Sheet Products
A1: Code | B1: Product | C1: Category | D1: StdCost | E1: TotalSales | F1: TotalQty
A2: P001 | B2: Mango Juice 1L | C2: Beverages | D2: =AVERAGEIF(Purchases!$D$2:$D$2000,B2,Purchases!$G$2:$G$2000) | E2: =SUMIF(Sales!$D$2:$D$5000,B2,Sales!$H$2:$H$5000) | F2: =SUMIF(Sales!$D$2:$D$5000,B2,Sales!$F$2:$F$5000)
A3: P002 | B3: Cola 750ml | C3: Beverages | D3: =AVERAGEIF(Purchases!$D$2:$D$2000,B3,Purchases!$G$2:$G$2000) | E3: =SUMIF(Sales!$D$2:$D$5000,B3,Sales!$H$2:$H$5000) | F3: =SUMIF(Sales!$D$2:$D$5000,B3,Sales!$F$2:$F$5000)
A4: P003 | B4: Packaged Water 1L | C4: Beverages | D4: =AVERAGEIF(Purchases!$D$2:$D$2000,B4,Purchases!$G$2:$G$2000) | E4: =SUMIF(Sales!$D$2:$D$5000,B4,Sales!$H$2:$H$5000) | F4: =SUMIF(Sales!$D$2:$D$5000,B4,Sales!$F$2:$F$5000)
A5: P004 | B5: Potato Chips 150g | C5: Snacks | D5: =AVERAGEIF(Purchases!$D$2:$D$2000,B5,Purchases!$G$2:$G$2000) | E5: =SUMIF(Sales!$D$2:$D$5000,B5,Sales!$H$2:$H$5000) | F5: =SUMIF(Sales!$D$2:$D$5000,B5,Sales!$F$2:$F$5000)
A6: P005 | B6: Biscuits 400g | C6: Snacks | D6: =AVERAGEIF(Purchases!$D$2:$D$2000,B6,Purchases!$G$2:$G$2000) | E6: =SUMIF(Sales!$D$2:$D$5000,B6,Sales!$H$2:$H$5000) | F6: =SUMIF(Sales!$D$2:$D$5000,B6,Sales!$F$2:$F$5000)
A7: P006 | B7: Instant Noodles 280g | C7: Snacks | D7: =AVERAGEIF(Purchases!$D$2:$D$2000,B7,Purchases!$G$2:$G$2000) | E7: =SUMIF(Sales!$D$2:$D$5000,B7,Sales!$H$2:$H$5000) | F7: =SUMIF(Sales!$D$2:$D$5000,B7,Sales!$F$2:$F$5000)
A8: P007 | B8: Toned Milk 1L | C8: Dairy | D8: =AVERAGEIF(Purchases!$D$2:$D$2000,B8,Purchases!$G$2:$G$2000) | E8: =SUMIF(Sales!$D$2:$D$5000,B8,Sales!$H$2:$H$5000) | F8: =SUMIF(Sales!$D$2:$D$5000,B8,Sales!$F$2:$F$5000)
A9: P008 | B9: Paneer 200g | C9: Dairy | D9: =AVERAGEIF(Purchases!$D$2:$D$2000,B9,Purchases!$G$2:$G$2000) | E9: =SUMIF(Sales!$D$2:$D$5000,B9,Sales!$H$2:$H$5000) | F9: =SUMIF(Sales!$D$2:$D$5000,B9,Sales!$F$2:$F$5000)
A10: P009 | B10: Curd Cup 400g | C10: Dairy | D10: =AVERAGEIF(Purchases!$D$2:$D$2000,B10,Purchases!$G$2:$G$2000) | E10: =SUMIF(Sales!$D$2:$D$5000,B10,Sales!$H$2:$H$5000) | F10: =SUMIF(Sales!$D$2:$D$5000,B10,Sales!$F$2:$F$5000)
A11: P010 | B11: Detergent 1kg | C11: Household | D11: =AVERAGEIF(Purchases!$D$2:$D$2000,B11,Purchases!$G$2:$G$2000) | E11: =SUMIF(Sales!$D$2:$D$5000,B11,Sales!$H$2:$H$5000) | F11: =SUMIF(Sales!$D$2:$D$5000,B11,Sales!$F$2:$F$5000)
A12: P011 | B12: Dish Soap 500ml | C12: Household | D12: =AVERAGEIF(Purchases!$D$2:$D$2000,B12,Purchases!$G$2:$G$2000) | E12: =SUMIF(Sales!$D$2:$D$5000,B12,Sales!$H$2:$H$5000) | F12: =SUMIF(Sales!$D$2:$D$5000,B12,Sales!$F$2:$F$5000)
A13: P012 | B13: Floor Cleaner 1L | C13: Household | D13: =AVERAGEIF(Purchases!$D$2:$D$2000,B13,Purchases!$G$2:$G$2000) | E13: =SUMIF(Sales!$D$2:$D$5000,B13,Sales!$H$2:$H$5000) | F13: =SUMIF(Sales!$D$2:$D$5000,B13,Sales!$F$2:$F$5000)

Sheet Monthly
A1: Month | B1: Sales | C1: Purchases | D1: COGS | E1: GrossProfit | F1: Margin% | G1: SeasonalityIdx
A2: 46113 | B2: =SUMIFS(Sales!$H$2:$H$5000,Sales!$A$2:$A$5000,">="&A2,Sales!$A$2:$A$5000,"<"&EDATE(A2,1)) | C2: =SUMIFS(Purchases!$H$2:$H$2000,Purchases!$A$2:$A$2000,">="&A2,Purchases!$A$2:$A$2000,"<"&EDATE(A2,1)) | D2: =SUMIFS(Sales!$I$2:$I$5000,Sales!$A$2:$A$5000,">="&A2,Sales!$A$2:$A$5000,"<"&EDATE(A2,1)) | E2: =B2-D2 | F2: =IF(B2=0,0,E2/B2) | G2: =B2/AVERAGE($B$2:$B$7)
A3: 46143 | B3: =SUMIFS(Sales!$H$2:$H$5000,Sales!$A$2:$A$5000,">="&A3,Sales!$A$2:$A$5000,"<"&EDATE(A3,1)) | C3: =SUMIFS(Purchases!$H$2:$H$2000,Purchases!$A$2:$A$2000,">="&A3,Purchases!$A$2:$A$2000,"<"&EDATE(A3,1)) | D3: =SUMIFS(Sales!$I$2:$I$5000,Sales!$A$2:$A$5000,">="&A3,Sales!$A$2:$A$5000,"<"&EDATE(A3,1)) | E3: =B3-D3 | F3: =IF(B3=0,0,E3/B3) | G3: =B3/AVERAGE($B$2:$B$7)
A4: 46174 | B4: =SUMIFS(Sales!$H$2:$H$5000,Sales!$A$2:$A$5000,">="&A4,Sales!$A$2:$A$5000,"<"&EDATE(A4,1)) | C4: =SUMIFS(Purchases!$H$2:$H$2000,Purchases!$A$2:$A$2000,">="&A4,Purchases!$A$2:$A$2000,"<"&EDATE(A4,1)) | D4: =SUMIFS(Sales!$I$2:$I$5000,Sales!$A$2:$A$5000,">="&A4,Sales!$A$2:$A$5000,"<"&EDATE(A4,1)) | E4: =B4-D4 | F4: =IF(B4=0,0,E4/B4) | G4: =B4/AVERAGE($B$2:$B$7)
A5: 46204 | B5: =SUMIFS(Sales!$H$2:$H$5000,Sales!$A$2:$A$5000,">="&A5,Sales!$A$2:$A$5000,"<"&EDATE(A5,1)) | C5: =SUMIFS(Purchases!$H$2:$H$2000,Purchases!$A$2:$A$2000,">="&A5,Purchases!$A$2:$A$2000,"<"&EDATE(A5,1)) | D5: =SUMIFS(Sales!$I$2:$I$5000,Sales!$A$2:$A$5000,">="&A5,Sales!$A$2:$A$5000,"<"&EDATE(A5,1)) | E5: =B5-D5 | F5: =IF(B5=0,0,E5/B5) | G5: =B5/AVERAGE($B$2:$B$7)
A6: 46235 | B6: =SUMIFS(Sales!$H$2:$H$5000,Sales!$A$2:$A$5000,">="&A6,Sales!$A$2:$A$5000,"<"&EDATE(A6,1)) | C6: =SUMIFS(Purchases!$H$2:$H$2000,Purchases!$A$2:$A$2000,">="&A6,Purchases!$A$2:$A$2000,"<"&EDATE(A6,1)) | D6: =SUMIFS(Sales!$I$2:$I$5000,Sales!$A$2:$A$5000,">="&A6,Sales!$A$2:$A$5000,"<"&EDATE(A6,1)) | E6: =B6-D6 | F6: =IF(B6=0,0,E6/B6) | G6: =B6/AVERAGE($B$2:$B$7)
A7: 46266 | B7: =SUMIFS(Sales!$H$2:$H$5000,Sales!$A$2:$A$5000,">="&A7,Sales!$A$2:$A$5000,"<"&EDATE(A7,1)) | C7: =SUMIFS(Purchases!$H$2:$H$2000,Purchases!$A$2:$A$2000,">="&A7,Purchases!$A$2:$A$2000,"<"&EDATE(A7,1)) | D7: =SUMIFS(Sales!$I$2:$I$5000,Sales!$A$2:$A$5000,">="&A7,Sales!$A$2:$A$5000,"<"&EDATE(A7,1)) | E7: =B7-D7 | F7: =IF(B7=0,0,E7/B7) | G7: =B7/AVERAGE($B$2:$B$7)

Sheet Daily
A1: Date | B1: Sales | C1: Avg | D1: Stdev | E1: Upper(2s) | F1: Lower(2s) | G1: Flag
A2: 46113 | B2: =SUMIF(Sales!$A$2:$A$5000,A2,Sales!$H$2:$H$5000) | C2: =AVERAGE($B$2:$B$184) | D2: =STDEVP($B$2:$B$184) | E2: =C2+2*D2 | F2: =MAX(0,C2-2*D2) | G2: =IF(OR(B2>E2,B2<F2,AND(B2=0,C2>0)),"ANOMALY","")
A3: 46114 | B3: =SUMIF(Sales!$A$2:$A$5000,A3,Sales!$H$2:$H$5000) | C3: =AVERAGE($B$2:$B$184) | D3: =STDEVP($B$2:$B$184) | E3: =C2+2*D2 | F3: =MAX(0,C2-2*D2) | G3: =IF(OR(B3>E3,B3<F3,AND(B3=0,C3>0)),"ANOMALY","")
A4: 46115 | B4: =SUMIF(Sales!$A$2:$A$5000,A4,Sales!$H$2:$H$5000) | C4: =AVERAGE($B$2:$B$184) | D4: =STDEVP($B$2:$B$184) | E4: =C2+2*D2 | F4: =MAX(0,C2-2*D2) | G4: =IF(OR(B4>E4,B4<F4,AND(B4=0,C4>0)),"ANOMALY","")
A5: 46116 | B5: =SUMIF(Sales!$A$2:$A$5000,A5,Sales!$H$2:$H$5000) | C5: =AVERAGE($B$2:$B$184) | D5: =STDEVP($B$2:$B$184) | E5: =C2+2*D2 | F5: =MAX(0,C2-2*D2) | G5: =IF(OR(B5>E5,B5<F5,AND(B5=0,C5>0)),"ANOMALY","")
A6: 46117 | B6: =SUMIF(Sales!$A$2:$A$5000,A6,Sales!$H$2:$H$5000) | C6: =AVERAGE($B$2:$B$184) | D6: =STDEVP($B$2:$B$184) | E6: =C2+2*D2 | F6: =MAX(0,C2-2*D2) | G6: =IF(OR(B6>E6,B6<F6,AND(B6=0,C6>0)),"ANOMALY","")
A7: 46118 | B7: =SUMIF(Sales!$A$2:$A$5000,A7,Sales!$H$2:$H$5000) | C7: =AVERAGE($B$2:$B$184) | D7: =STDEVP($B$2:$B$184) | E7: =C2+2*D2 | F7: =MAX(0,C2-2*D2) | G7: =IF(OR(B7>E7,B7<F7,AND(B7=0,C7>0)),"ANOMALY","")
A8: 46119 | B8: =SUMIF(Sales!$A$2:$A$5000,A8,Sales!$H$2:$H$5000) | C8: =AVERAGE($B$2:$B$184) | D8: =STDEVP($B$2:$B$184) | E8: =C2+2*D2 | F8: =MAX(0,C2-2*D2) | G8: =IF(OR(B8>E8,B8<F8,AND(B8=0,C8>0)),"ANOMALY","")
A9: 46120 | B9: =SUMIF(Sales!$A$2:$A$5000,A9,Sales!$H$2:$H$5000) | C9: =AVERAGE($B$2:$B$184) | D9: =STDEVP($B$2:$B$184) | E9: =C2+2*D2 | F9: =MAX(0,C2-2*D2) | G9: =IF(OR(B9>E9,B9<F9,AND(B9=0,C9>0)),"ANOMALY","")
A10: 46121 | B10: =SUMIF(Sales!$A$2:$A$5000,A10,Sales!$H$2:$H$5000) | C10: =AVERAGE($B$2:$B$184) | D10: =STDEVP($B$2:$B$184) | E10: =C2+2*D2 | F10: =MAX(0,C2-2*D2) | G10: =IF(OR(B10>E10,B10<F10,AND(B10=0,C10>0)),"ANOMALY","")
A11: 46122 | B11: =SUMIF(Sales!$A$2:$A$5000,A11,Sales!$H$2:$H$5000) | C11: =AVERAGE($B$2:$B$184) | D11: =STDEVP($B$2:$B$184) | E11: =C2+2*D2 | F11: =MAX(0,C2-2*D2) | G11: =IF(OR(B11>E11,B11<F11,AND(B11=0,C11>0)),"ANOMALY","")
A12: 46123 | B12: =SUMIF(Sales!$A$2:$A$5000,A12,Sales!$H$2:$H$5000) | C12: =AVERAGE($B$2:$B$184) | D12: =STDEVP($B$2:$B$184) | E12: =C2+2*D2 | F12: =MAX(0,C2-2*D2) | G12: =IF(OR(B12>E12,B12<F12,AND(B12=0,C12>0)),"ANOMALY","")
A13: 46124 | B13: =SUMIF(Sales!$A$2:$A$5000,A13,Sales!$H$2:$H$5000) | C13: =AVERAGE($B$2:$B$184) | D13: =STDEVP($B$2:$B$184) | E13: =C2+2*D2 | F13: =MAX(0,C2-2*D2) | G13: =IF(OR(B13>E13,B13<F13,AND(B13=0,C13>0)),"ANOMALY","")
A14: 46125 | B14: =SUMIF(Sales!$A$2:$A$5000,A14,Sales!$H$2:$H$5000) | C14: =AVERAGE($B$2:$B$184) | D14: =STDEVP($B$2:$B$184) | E14: =C2+2*D2 | F14: =MAX(0,C2-2*D2) | G14: =IF(OR(B14>E14,B14<F14,AND(B14=0,C14>0)),"ANOMALY","")
A15: 46126 | B15: =SUMIF(Sales!$A$2:$A$5000,A15,Sales!$H$2:$H$5000) | C15: =AVERAGE($B$2:$B$184) | D15: =STDEVP($B$2:$B$184) | E15: =C2+2*D2 | F15: =MAX(0,C2-2*D2) | G15: =IF(OR(B15>E15,B15<F15,AND(B15=0,C15>0)),"ANOMALY","")
A16: 46127 | B16: =SUMIF(Sales!$A$2:$A$5000,A16,Sales!$H$2:$H$5000) | C16: =AVERAGE($B$2:$B$184) | D16: =STDEVP($B$2:$B$184) | E16: =C2+2*D2 | F16: =MAX(0,C2-2*D2) | G16: =IF(OR(B16>E16,B16<F16,AND(B16=0,C16>0)),"ANOMALY","")
A17: 46128 | B17: =SUMIF(Sales!$A$2:$A$5000,A17,Sales!$H$2:$H$5000) | C17: =AVERAGE($B$2:$B$184) | D17: =STDEVP($B$2:$B$184) | E17: =C2+2*D2 | F17: =MAX(0,C2-2*D2) | G17: =IF(OR(B17>E17,B17<F17,AND(B17=0,C17>0)),"ANOMALY","")
A18: 46129 | B18: =SUMIF(Sales!$A$2:$A$5000,A18,Sales!$H$2:$H$5000) | C18: =AVERAGE($B$2:$B$184) | D18: =STDEVP($B$2:$B$184) | E18: =C2+2*D2 | F18: =MAX(0,C2-2*D2) | G18: =IF(OR(B18>E18,B18<F18,AND(B18=0,C18>0)),"ANOMALY","")
A19: 46130 | B19: =SUMIF(Sales!$A$2:$A$5000,A19,Sales!$H$2:$H$5000) | C19: =AVERAGE($B$2:$B$184) | D19: =STDEVP($B$2:$B$184) | E19: =C2+2*D2 | F19: =MAX(0,C2-2*D2) | G19: =IF(OR(B19>E19,B19<F19,AND(B19=0,C19>0)),"ANOMALY","")
A20: 46131 | B20: =SUMIF(Sales!$A$2:$A$5000,A20,Sales!$H$2:$H$5000) | C20: =AVERAGE($B$2:$B$184) | D20: =STDEVP($B$2:$B$184) | E20: =C2+2*D2 | F20: =MAX(0,C2-2*D2) | G20: =IF(OR(B20>E20,B20<F20,AND(B20=0,C20>0)),"ANOMALY","")
A21: 46132 | B21: =SUMIF(Sales!$A$2:$A$5000,A21,Sales!$H$2:$H$5000) | C21: =AVERAGE($B$2:$B$184) | D21: =STDEVP($B$2:$B$184) | E21: =C2+2*D2 | F21: =MAX(0,C2-2*D2) | G21: =IF(OR(B21>E21,B21<F21,AND(B21=0,C21>0)),"ANOMALY","")
A22: 46133 | B22: =SUMIF(Sales!$A$2:$A$5000,A22,Sales!$H$2:$H$5000) | C22: =AVERAGE($B$2:$B$184) | D22: =STDEVP($B$2:$B$184) | E22: =C2+2*D2 | F22: =MAX(0,C2-2*D2) | G22: =IF(OR(B22>E22,B22<F22,AND(B22=0,C22>0)),"ANOMALY","")
A23: 46134 | B23: =SUMIF(Sales!$A$2:$A$5000,A23,Sales!$H$2:$H$5000) | C23: =AVERAGE($B$2:$B$184) | D23: =STDEVP($B$2:$B$184) | E23: =C2+2*D2 | F23: =MAX(0,C2-2*D2) | G23: =IF(OR(B23>E23,B23<F23,AND(B23=0,C23>0)),"ANOMALY","")
A24: 46135 | B24: =SUMIF(Sales!$A$2:$A$5000,A24,Sales!$H$2:$H$5000) | C24: =AVERAGE($B$2:$B$184) | D24: =STDEVP($B$2:$B$184) | E24: =C2+2*D2 | F24: =MAX(0,C2-2*D2) | G24: =IF(OR(B24>E24,B24<F24,AND(B24=0,C24>0)),"ANOMALY","")
A25: 46136 | B25: =SUMIF(Sales!$A$2:$A$5000,A25,Sales!$H$2:$H$5000) | C25: =AVERAGE($B$2:$B$184) | D25: =STDEVP($B$2:$B$184) | E25: =C2+2*D2 | F25: =MAX(0,C2-2*D2) | G25: =IF(OR(B25>E25,B25<F25,AND(B25=0,C25>0)),"ANOMALY","")
A26: 46137 | B26: =SUMIF(Sales!$A$2:$A$5000,A26,Sales!$H$2:$H$5000) | C26: =AVERAGE($B$2:$B$184) | D26: =STDEVP($B$2:$B$184) | E26: =C2+2*D2 | F26: =MAX(0,C2-2*D2) | G26: =IF(OR(B26>E26,B26<F26,AND(B26=0,C26>0)),"ANOMALY","")
A27: 46138 | B27: =SUMIF(Sales!$A$2:$A$5000,A27,Sales!$H$2:$H$5000) | C27: =AVERAGE($B$2:$B$184) | D27: =STDEVP($B$2:$B$184) | E27: =C2+2*D2 | F27: =MAX(0,C2-2*D2) | G27: =IF(OR(B27>E27,B27<F27,AND(B27=0,C27>0)),"ANOMALY","")
A28: 46139 | B28: =SUMIF(Sales!$A$2:$A$5000,A28,Sales!$H$2:$H$5000) | C28: =AVERAGE($B$2:$B$184) | D28: =STDEVP($B$2:$B$184) | E28: =C2+2*D2 | F28: =MAX(0,C2-2*D2) | G28: =IF(OR(B28>E28,B28<F28,AND(B28=0,C28>0)),"ANOMALY","")
A29: 46140 | B29: =SUMIF(Sales!$A$2:$A$5000,A29,Sales!$H$2:$H$5000) | C29: =AVERAGE($B$2:$B$184) | D29: =STDEVP($B$2:$B$184) | E29: =C2+2*D2 | F29: =MAX(0,C2-2*D2) | G29: =IF(OR(B29>E29,B29<F29,AND(B29=0,C29>0)),"ANOMALY","")
A30: 46141 | B30: =SUMIF(Sales!$A$2:$A$5000,A30,Sales!$H$2:$H$5000) | C30: =AVERAGE($B$2:$B$184) | D30: =STDEVP($B$2:$B$184) | E30: =C2+2*D2 | F30: =MAX(0,C2-2*D2) | G30: =IF(OR(B30>E30,B30<F30,AND(B30=0,C30>0)),"ANOMALY","")
A31: 46142 | B31: =SUMIF(Sales!$A$2:$A$5000,A31,Sales!$H$2:$H$5000) | C31: =AVERAGE($B$2:$B$184) | D31: =STDEVP($B$2:$B$184) | E31: =C2+2*D2 | F31: =MAX(0,C2-2*D2) | G31: =IF(OR(B31>E31,B31<F31,AND(B31=0,C31>0)),"ANOMALY","")
A32: 46143 | B32: =SUMIF(Sales!$A$2:$A$5000,A32,Sales!$H$2:$H$5000) | C32: =AVERAGE($B$2:$B$184) | D32: =STDEVP($B$2:$B$184) | E32: =C2+2*D2 | F32: =MAX(0,C2-2*D2) | G32: =IF(OR(B32>E32,B32<F32,AND(B32=0,C32>0)),"ANOMALY","")
A33: 46144 | B33: =SUMIF(Sales!$A$2:$A$5000,A33,Sales!$H$2:$H$5000) | C33: =AVERAGE($B$2:$B$184) | D33: =STDEVP($B$2:$B$184) | E33: =C2+2*D2 | F33: =MAX(0,C2-2*D2) | G33: =IF(OR(B33>E33,B33<F33,AND(B33=0,C33>0)),"ANOMALY","")
A34: 46145 | B34: =SUMIF(Sales!$A$2:$A$5000,A34,Sales!$H$2:$H$5000) | C34: =AVERAGE($B$2:$B$184) | D34: =STDEVP($B$2:$B$184) | E34: =C2+2*D2 | F34: =MAX(0,C2-2*D2) | G34: =IF(OR(B34>E34,B34<F34,AND(B34=0,C34>0)),"ANOMALY","")
A35: 46146 | B35: =SUMIF(Sales!$A$2:$A$5000,A35,Sales!$H$2:$H$5000) | C35: =AVERAGE($B$2:$B$184) | D35: =STDEVP($B$2:$B$184) | E35: =C2+2*D2 | F35: =MAX(0,C2-2*D2) | G35: =IF(OR(B35>E35,B35<F35,AND(B35=0,C35>0)),"ANOMALY","")
A36: 46147 | B36: =SUMIF(Sales!$A$2:$A$5000,A36,Sales!$H$2:$H$5000) | C36: =AVERAGE($B$2:$B$184) | D36: =STDEVP($B$2:$B$184) | E36: =C2+2*D2 | F36: =MAX(0,C2-2*D2) | G36: =IF(OR(B36>E36,B36<F36,AND(B36=0,C36>0)),"ANOMALY","")
A37: 46148 | B37: =SUMIF(Sales!$A$2:$A$5000,A37,Sales!$H$2:$H$5000) | C37: =AVERAGE($B$2:$B$184) | D37: =STDEVP($B$2:$B$184) | E37: =C2+2*D2 | F37: =MAX(0,C2-2*D2) | G37: =IF(OR(B37>E37,B37<F37,AND(B37=0,C37>0)),"ANOMALY","")
A38: 46149 | B38: =SUMIF(Sales!$A$2:$A$5000,A38,Sales!$H$2:$H$5000) | C38: =AVERAGE($B$2:$B$184) | D38: =STDEVP($B$2:$B$184) | E38: =C2+2*D2 | F38: =MAX(0,C2-2*D2) | G38: =IF(OR(B38>E38,B38<F38,AND(B38=0,C38>0)),"ANOMALY","")
A39: 46150 | B39: =SUMIF(Sales!$A$2:$A$5000,A39,Sales!$H$2:$H$5000) | C39: =AVERAGE($B$2:$B$184) | D39: =STDEVP($B$2:$B$184) | E39: =C2+2*D2 | F39: =MAX(0,C2-2*D2) | G39: =IF(OR(B39>E39,B39<F39,AND(B39=0,C39>0)),"ANOMALY","")
A40: 46151 | B40: =SUMIF(Sales!$A$2:$A$5000,A40,Sales!$H$2:$H$5000) | C40: =AVERAGE($B$2:$B$184) | D40: =STDEVP($B$2:$B$184) | E40: =C2+2*D2 | F40: =MAX(0,C2-2*D2) | G40: =IF(OR(B40>E40,B40<F40,AND(B40=0,C40>0)),"ANOMALY","")
A41: 46152 | B41: =SUMIF(Sales!$A$2:$A$5000,A41,Sales!$H$2:$H$5000) | C41: =AVERAGE($B$2:$B$184) | D41: =STDEVP($B$2:$B$184) | E41: =C2+2*D2 | F41: =MAX(0,C2-2*D2) | G41: =IF(OR(B41>E41,B41<F41,AND(B41=0,C41>0)),"ANOMALY","")
A42: 46153 | B42: =SUMIF(Sales!$A$2:$A$5000,A42,Sales!$H$2:$H$5000) | C42: =AVERAGE($B$2:$B$184) | D42: =STDEVP($B$2:$B$184) | E42: =C2+2*D2 | F42: =MAX(0,C2-2*D2) | G42: =IF(OR(B42>E42,B42<F42,AND(B42=0,C42>0)),"ANOMALY","")
A43: 46154 | B43: =SUMIF(Sales!$A$2:$A$5000,A43,Sales!$H$2:$H$5000) | C43: =AVERAGE($B$2:$B$184) | D43: =STDEVP($B$2:$B$184) | E43: =C2+2*D2 | F43: =MAX(0,C2-2*D2) | G43: =IF(OR(B43>E43,B43<F43,AND(B43=0,C43>0)),"ANOMALY","")
A44: 46155 | B44: =SUMIF(Sales!$A$2:$A$5000,A44,Sales!$H$2:$H$5000) | C44: =AVERAGE($B$2:$B$184) | D44: =STDEVP($B$2:$B$184) | E44: =C2+2*D2 | F44: =MAX(0,C2-2*D2) | G44: =IF(OR(B44>E44,B44<F44,AND(B44=0,C44>0)),"ANOMALY","")
A45: 46156 | B45: =SUMIF(Sales!$A$2:$A$5000,A45,Sales!$H$2:$H$5000) | C45: =AVERAGE($B$2:$B$184) | D45: =STDEVP($B$2:$B$184) | E45: =C2+2*D2 | F45: =MAX(0,C2-2*D2) | G45: =IF(OR(B45>E45,B45<F45,AND(B45=0,C45>0)),"ANOMALY","")
A46: 46157 | B46: =SUMIF(Sales!$A$2:$A$5000,A46,Sales!$H$2:$H$5000) | C46: =AVERAGE($B$2:$B$184) | D46: =STDEVP($B$2:$B$184) | E46: =C2+2*D2 | F46: =MAX(0,C2-2*D2) | G46: =IF(OR(B46>E46,B46<F46,AND(B46=0,C46>0)),"ANOMALY","")
A47: 46158 | B47: =SUMIF(Sales!$A$2:$A$5000,A47,Sales!$H$2:$H$5000) | C47: =AVERAGE($B$2:$B$184) | D47: =STDEVP($B$2:$B$184) | E47: =C2+2*D2 | F47: =MAX(0,C2-2*D2) | G47: =IF(OR(B47>E47,B47<F47,AND(B47=0,C47>0)),"ANOMALY","")
A48: 46159 | B48: =SUMIF(Sales!$A$2:$A$5000,A48,Sales!$H$2:$H$5000) | C48: =AVERAGE($B$2:$B$184) | D48: =STDEVP($B$2:$B$184) | E48: =C2+2*D2 | F48: =MAX(0,C2-2*D2) | G48: =IF(OR(B48>E48,B48<F48,AND(B48=0,C48>0)),"ANOMALY","")
A49: 46160 | B49: =SUMIF(Sales!$A$2:$A$5000,A49,Sales!$H$2:$H$5000) | C49: =AVERAGE($B$2:$B$184) | D49: =STDEVP($B$2:$B$184) | E49: =C2+2*D2 | F49: =MAX(0,C2-2*D2) | G49: =IF(OR(B49>E49,B49<F49,AND(B49=0,C49>0)),"ANOMALY","")
A50: 46161 | B50: =SUMIF(Sales!$A$2:$A$5000,A50,Sales!$H$2:$H$5000) | C50: =AVERAGE($B$2:$B$184) | D50: =STDEVP($B$2:$B$184) | E50: =C2+2*D2 | F50: =MAX(0,C2-2*D2) | G50: =IF(OR(B50>E50,B50<F50,AND(B50=0,C50>0)),"ANOMALY","")
A51: 46162 | B51: =SUMIF(Sales!$A$2:$A$5000,A51,Sales!$H$2:$H$5000) | C51: =AVERAGE($B$2:$B$184) | D51: =STDEVP($B$2:$B$184) | E51: =C2+2*D2 | F51: =MAX(0,C2-2*D2) | G51: =IF(OR(B51>E51,B51<F51,AND(B51=0,C51>0)),"ANOMALY","")
A52: 46163 | B52: =SUMIF(Sales!$A$2:$A$5000,A52,Sales!$H$2:$H$5000) | C52: =AVERAGE($B$2:$B$184) | D52: =STDEVP($B$2:$B$184) | E52: =C2+2*D2 | F52: =MAX(0,C2-2*D2) | G52: =IF(OR(B52>E52,B52<F52,AND(B52=0,C52>0)),"ANOMALY","")
A53: 46164 | B53: =SUMIF(Sales!$A$2:$A$5000,A53,Sales!$H$2:$H$5000) | C53: =AVERAGE($B$2:$B$184) | D53: =STDEVP($B$2:$B$184) | E53: =C2+2*D2 | F53: =MAX(0,C2-2*D2) | G53: =IF(OR(B53>E53,B53<F53,AND(B53=0,C53>0)),"ANOMALY","")
A54: 46165 | B54: =SUMIF(Sales!$A$2:$A$5000,A54,Sales!$H$2:$H$5000) | C54: =AVERAGE($B$2:$B$184) | D54: =STDEVP($B$2:$B$184) | E54: =C2+2*D2 | F54: =MAX(0,C2-2*D2) | G54: =IF(OR(B54>E54,B54<F54,AND(B54=0,C54>0)),"ANOMALY","")
A55: 46166 | B55: =SUMIF(Sales!$A$2:$A$5000,A55,Sales!$H$2:$H$5000) | C55: =AVERAGE($B$2:$B$184) | D55: =STDEVP($B$2:$B$184) | E55: =C2+2*D2 | F55: =MAX(0,C2-2*D2) | G55: =IF(OR(B55>E55,B55<F55,AND(B55=0,C55>0)),"ANOMALY","")
A56: 46167 | B56: =SUMIF(Sales!$A$2:$A$5000,A56,Sales!$H$2:$H$5000) | C56: =AVERAGE($B$2:$B$184) | D56: =STDEVP($B$2:$B$184) | E56: =C2+2*D2 | F56: =MAX(0,C2-2*D2) | G56: =IF(OR(B56>E56,B56<F56,AND(B56=0,C56>0)),"ANOMALY","")
A57: 46168 | B57: =SUMIF(Sales!$A$2:$A$5000,A57,Sales!$H$2:$H$5000) | C57: =AVERAGE($B$2:$B$184) | D57: =STDEVP($B$2:$B$184) | E57: =C2+2*D2 | F57: =MAX(0,C2-2*D2) | G57: =IF(OR(B57>E57,B57<F57,AND(B57=0,C57>0)),"ANOMALY","")
A58: 46169 | B58: =SUMIF(Sales!$A$2:$A$5000,A58,Sales!$H$2:$H$5000) | C58: =AVERAGE($B$2:$B$184) | D58: =STDEVP($B$2:$B$184) | E58: =C2+2*D2 | F58: =MAX(0,C2-2*D2) | G58: =IF(OR(B58>E58,B58<F58,AND(B58=0,C58>0)),"ANOMALY","")
A59: 46170 | B59: =SUMIF(Sales!$A$2:$A$5000,A59,Sales!$H$2:$H$5000) | C59: =AVERAGE($B$2:$B$184) | D59: =STDEVP($B$2:$B$184) | E59: =C2+2*D2 | F59: =MAX(0,C2-2*D2) | G59: =IF(OR(B59>E59,B59<F59,AND(B59=0,C59>0)),"ANOMALY","")
A60: 46171 | B60: =SUMIF(Sales!$A$2:$A$5000,A60,Sales!$H$2:$H$5000) | C60: =AVERAGE($B$2:$B$184) | D60: =STDEVP($B$2:$B$184) | E60: =C2+2*D2 | F60: =MAX(0,C2-2*D2) | G60: =IF(OR(B60>E60,B60<F60,AND(B60=0,C60>0)),"ANOMALY","")
A61: 46172 | B61: =SUMIF(Sales!$A$2:$A$5000,A61,Sales!$H$2:$H$5000) | C61: =AVERAGE($B$2:$B$184) | D61: =STDEVP($B$2:$B$184) | E61: =C2+2*D2 | F61: =MAX(0,C2-2*D2) | G61: =IF(OR(B61>E61,B61<F61,AND(B61=0,C61>0)),"ANOMALY","")
A62: 46173 | B62: =SUMIF(Sales!$A$2:$A$5000,A62,Sales!$H$2:$H$5000) | C62: =AVERAGE($B$2:$B$184) | D62: =STDEVP($B$2:$B$184) | E62: =C2+2*D2 | F62: =MAX(0,C2-2*D2) | G62: =IF(OR(B62>E62,B62<F62,AND(B62=0,C62>0)),"ANOMALY","")
A63: 46174 | B63: =SUMIF(Sales!$A$2:$A$5000,A63,Sales!$H$2:$H$5000) | C63: =AVERAGE($B$2:$B$184) | D63: =STDEVP($B$2:$B$184) | E63: =C2+2*D2 | F63: =MAX(0,C2-2*D2) | G63: =IF(OR(B63>E63,B63<F63,AND(B63=0,C63>0)),"ANOMALY","")
A64: 46175 | B64: =SUMIF(Sales!$A$2:$A$5000,A64,Sales!$H$2:$H$5000) | C64: =AVERAGE($B$2:$B$184) | D64: =STDEVP($B$2:$B$184) | E64: =C2+2*D2 | F64: =MAX(0,C2-2*D2) | G64: =IF(OR(B64>E64,B64<F64,AND(B64=0,C64>0)),"ANOMALY","")
A65: 46176 | B65: =SUMIF(Sales!$A$2:$A$5000,A65,Sales!$H$2:$H$5000) | C65: =AVERAGE($B$2:$B$184) | D65: =STDEVP($B$2:$B$184) | E65: =C2+2*D2 | F65: =MAX(0,C2-2*D2) | G65: =IF(OR(B65>E65,B65<F65,AND(B65=0,C65>0)),"ANOMALY","")
A66: 46177 | B66: =SUMIF(Sales!$A$2:$A$5000,A66,Sales!$H$2:$H$5000) | C66: =AVERAGE($B$2:$B$184) | D66: =STDEVP($B$2:$B$184) | E66: =C2+2*D2 | F66: =MAX(0,C2-2*D2) | G66: =IF(OR(B66>E66,B66<F66,AND(B66=0,C66>0)),"ANOMALY","")
A67: 46178 | B67: =SUMIF(Sales!$A$2:$A$5000,A67,Sales!$H$2:$H$5000) | C67: =AVERAGE($B$2:$B$184) | D67: =STDEVP($B$2:$B$184) | E67: =C2+2*D2 | F67: =MAX(0,C2-2*D2) | G67: =IF(OR(B67>E67,B67<F67,AND(B67=0,C67>0)),"ANOMALY","")
A68: 46179 | B68: =SUMIF(Sales!$A$2:$A$5000,A68,Sales!$H$2:$H$5000) | C68: =AVERAGE($B$2:$B$184) | D68: =STDEVP($B$2:$B$184) | E68: =C2+2*D2 | F68: =MAX(0,C2-2*D2) | G68: =IF(OR(B68>E68,B68<F68,AND(B68=0,C68>0)),"ANOMALY","")
A69: 46180 | B69: =SUMIF(Sales!$A$2:$A$5000,A69,Sales!$H$2:$H$5000) | C69: =AVERAGE($B$2:$B$184) | D69: =STDEVP($B$2:$B$184) | E69: =C2+2*D2 | F69: =MAX(0,C2-2*D2) | G69: =IF(OR(B69>E69,B69<F69,AND(B69=0,C69>0)),"ANOMALY","")
A70: 46181 | B70: =SUMIF(Sales!$A$2:$A$5000,A70,Sales!$H$2:$H$5000) | C70: =AVERAGE($B$2:$B$184) | D70: =STDEVP($B$2:$B$184) | E70: =C2+2*D2 | F70: =MAX(0,C2-2*D2) | G70: =IF(OR(B70>E70,B70<F70,AND(B70=0,C70>0)),"ANOMALY","")
A71: 46182 | B71: =SUMIF(Sales!$A$2:$A$5000,A71,Sales!$H$2:$H$5000) | C71: =AVERAGE($B$2:$B$184) | D71: =STDEVP($B$2:$B$184) | E71: =C2+2*D2 | F71: =MAX(0,C2-2*D2) | G71: =IF(OR(B71>E71,B71<F71,AND(B71=0,C71>0)),"ANOMALY","")
A72: 46183 | B72: =SUMIF(Sales!$A$2:$A$5000,A72,Sales!$H$2:$H$5000) | C72: =AVERAGE($B$2:$B$184) | D72: =STDEVP($B$2:$B$184) | E72: =C2+2*D2 | F72: =MAX(0,C2-2*D2) | G72: =IF(OR(B72>E72,B72<F72,AND(B72=0,C72>0)),"ANOMALY","")
A73: 46184 | B73: =SUMIF(Sales!$A$2:$A$5000,A73,Sales!$H$2:$H$5000) | C73: =AVERAGE($B$2:$B$184) | D73: =STDEVP($B$2:$B$184) | E73: =C2+2*D2 | F73: =MAX(0,C2-2*D2) | G73: =IF(OR(B73>E73,B73<F73,AND(B73=0,C73>0)),"ANOMALY","")
A74: 46185 | B74: =SUMIF(Sales!$A$2:$A$5000,A74,Sales!$H$2:$H$5000) | C74: =AVERAGE($B$2:$B$184) | D74: =STDEVP($B$2:$B$184) | E74: =C2+2*D2 | F74: =MAX(0,C2-2*D2) | G74: =IF(OR(B74>E74,B74<F74,AND(B74=0,C74>0)),"ANOMALY","")
A75: 46186 | B75: =SUMIF(Sales!$A$2:$A$5000,A75,Sales!$H$2:$H$5000) | C75: =AVERAGE($B$2:$B$184) | D75: =STDEVP($B$2:$B$184) | E75: =C2+2*D2 | F75: =MAX(0,C2-2*D2) | G75: =IF(OR(B75>E75,B75<F75,AND(B75=0,C75>0)),"ANOMALY","")
A76: 46187 | B76: =SUMIF(Sales!$A$2:$A$5000,A76,Sales!$H$2:$H$5000) | C76: =AVERAGE($B$2:$B$184) | D76: =STDEVP($B$2:$B$184) | E76: =C2+2*D2 | F76: =MAX(0,C2-2*D2) | G76: =IF(OR(B76>E76,B76<F76,AND(B76=0,C76>0)),"ANOMALY","")
A77: 46188 | B77: =SUMIF(Sales!$A$2:$A$5000,A77,Sales!$H$2:$H$5000) | C77: =AVERAGE($B$2:$B$184) | D77: =STDEVP($B$2:$B$184) | E77: =C2+2*D2 | F77: =MAX(0,C2-2*D2) | G77: =IF(OR(B77>E77,B77<F77,AND(B77=0,C77>0)),"ANOMALY","")
A78: 46189 | B78: =SUMIF(Sales!$A$2:$A$5000,A78,Sales!$H$2:$H$5000) | C78: =AVERAGE($B$2:$B$184) | D78: =STDEVP($B$2:$B$184) | E78: =C2+2*D2 | F78: =MAX(0,C2-2*D2) | G78: =IF(OR(B78>E78,B78<F78,AND(B78=0,C78>0)),"ANOMALY","")
A79: 46190 | B79: =SUMIF(Sales!$A$2:$A$5000,A79,Sales!$H$2:$H$5000) | C79: =AVERAGE($B$2:$B$184) | D79: =STDEVP($B$2:$B$184) | E79: =C2+2*D2 | F79: =MAX(0,C2-2*D2) | G79: =IF(OR(B79>E79,B79<F79,AND(B79=0,C79>0)),"ANOMALY","")
A80: 46191 | B80: =SUMIF(Sales!$A$2:$A$5000,A80,Sales!$H$2:$H$5000) | C80: =AVERAGE($B$2:$B$184) | D80: =STDEVP($B$2:$B$184) | E80: =C2+2*D2 | F80: =MAX(0,C2-2*D2) | G80: =IF(OR(B80>E80,B80<F80,AND(B80=0,C80>0)),"ANOMALY","")
A81: 46192 | B81: =SUMIF(Sales!$A$2:$A$5000,A81,Sales!$H$2:$H$5000) | C81: =AVERAGE($B$2:$B$184) | D81: =STDEVP($B$2:$B$184) | E81: =C2+2*D2 | F81: =MAX(0,C2-2*D2) | G81: =IF(OR(B81>E81,B81<F81,AND(B81=0,C81>0)),"ANOMALY","")
A82: 46193 | B82: =SUMIF(Sales!$A$2:$A$5000,A82,Sales!$H$2:$H$5000) | C82: =AVERAGE($B$2:$B$184) | D82: =STDEVP($B$2:$B$184) | E82: =C2+2*D2 | F82: =MAX(0,C2-2*D2) | G82: =IF(OR(B82>E82,B82<F82,AND(B82=0,C82>0)),"ANOMALY","")
A83: 46194 | B83: =SUMIF(Sales!$A$2:$A$5000,A83,Sales!$H$2:$H$5000) | C83: =AVERAGE($B$2:$B$184) | D83: =STDEVP($B$2:$B$184) | E83: =C2+2*D2 | F83: =MAX(0,C2-2*D2) | G83: =IF(OR(B83>E83,B83<F83,AND(B83=0,C83>0)),"ANOMALY","")
A84: 46195 | B84: =SUMIF(Sales!$A$2:$A$5000,A84,Sales!$H$2:$H$5000) | C84: =AVERAGE($B$2:$B$184) | D84: =STDEVP($B$2:$B$184) | E84: =C2+2*D2 | F84: =MAX(0,C2-2*D2) | G84: =IF(OR(B84>E84,B84<F84,AND(B84=0,C84>0)),"ANOMALY","")
A85: 46196 | B85: =SUMIF(Sales!$A$2:$A$5000,A85,Sales!$H$2:$H$5000) | C85: =AVERAGE($B$2:$B$184) | D85: =STDEVP($B$2:$B$184) | E85: =C2+2*D2 | F85: =MAX(0,C2-2*D2) | G85: =IF(OR(B85>E85,B85<F85,AND(B85=0,C85>0)),"ANOMALY","")
A86: 46197 | B86: =SUMIF(Sales!$A$2:$A$5000,A86,Sales!$H$2:$H$5000) | C86: =AVERAGE($B$2:$B$184) | D86: =STDEVP($B$2:$B$184) | E86: =C2+2*D2 | F86: =MAX(0,C2-2*D2) | G86: =IF(OR(B86>E86,B86<F86,AND(B86=0,C86>0)),"ANOMALY","")
A87: 46198 | B87: =SUMIF(Sales!$A$2:$A$5000,A87,Sales!$H$2:$H$5000) | C87: =AVERAGE($B$2:$B$184) | D87: =STDEVP($B$2:$B$184) | E87: =C2+2*D2 | F87: =MAX(0,C2-2*D2) | G87: =IF(OR(B87>E87,B87<F87,AND(B87=0,C87>0)),"ANOMALY","")
A88: 46199 | B88: =SUMIF(Sales!$A$2:$A$5000,A88,Sales!$H$2:$H$5000) | C88: =AVERAGE($B$2:$B$184) | D88: =STDEVP($B$2:$B$184) | E88: =C2+2*D2 | F88: =MAX(0,C2-2*D2) | G88: =IF(OR(B88>E88,B88<F88,AND(B88=0,C88>0)),"ANOMALY","")
A89: 46200 | B89: =SUMIF(Sales!$A$2:$A$5000,A89,Sales!$H$2:$H$5000) | C89: =AVERAGE($B$2:$B$184) | D89: =STDEVP($B$2:$B$184) | E89: =C2+2*D2 | F89: =MAX(0,C2-2*D2) | G89: =IF(OR(B89>E89,B89<F89,AND(B89=0,C89>0)),"ANOMALY","")
A90: 46201 | B90: =SUMIF(Sales!$A$2:$A$5000,A90,Sales!$H$2:$H$5000) | C90: =AVERAGE($B$2:$B$184) | D90: =STDEVP($B$2:$B$184) | E90: =C2+2*D2 | F90: =MAX(0,C2-2*D2) | G90: =IF(OR(B90>E90,B90<F90,AND(B90=0,C90>0)),"ANOMALY","")
A91: 46202 | B91: =SUMIF(Sales!$A$2:$A$5000,A91,Sales!$H$2:$H$5000) | C91: =AVERAGE($B$2:$B$184) | D91: =STDEVP($B$2:$B$184) | E91: =C2+2*D2 | F91: =MAX(0,C2-2*D2) | G91: =IF(OR(B91>E91,B91<F91,AND(B91=0,C91>0)),"ANOMALY","")
A92: 46203 | B92: =SUMIF(Sales!$A$2:$A$5000,A92,Sales!$H$2:$H$5000) | C92: =AVERAGE($B$2:$B$184) | D92: =STDEVP($B$2:$B$184) | E92: =C2+2*D2 | F92: =MAX(0,C2-2*D2) | G92: =IF(OR(B92>E92,B92<F92,AND(B92=0,C92>0)),"ANOMALY","")
A93: 46204 | B93: =SUMIF(Sales!$A$2:$A$5000,A93,Sales!$H$2:$H$5000) | C93: =AVERAGE($B$2:$B$184) | D93: =STDEVP($B$2:$B$184) | E93: =C2+2*D2 | F93: =MAX(0,C2-2*D2) | G93: =IF(OR(B93>E93,B93<F93,AND(B93=0,C93>0)),"ANOMALY","")
A94: 46205 | B94: =SUMIF(Sales!$A$2:$A$5000,A94,Sales!$H$2:$H$5000) | C94: =AVERAGE($B$2:$B$184) | D94: =STDEVP($B$2:$B$184) | E94: =C2+2*D2 | F94: =MAX(0,C2-2*D2) | G94: =IF(OR(B94>E94,B94<F94,AND(B94=0,C94>0)),"ANOMALY","")
A95: 46206 | B95: =SUMIF(Sales!$A$2:$A$5000,A95,Sales!$H$2:$H$5000) | C95: =AVERAGE($B$2:$B$184) | D95: =STDEVP($B$2:$B$184) | E95: =C2+2*D2 | F95: =MAX(0,C2-2*D2) | G95: =IF(OR(B95>E95,B95<F95,AND(B95=0,C95>0)),"ANOMALY","")
A96: 46207 | B96: =SUMIF(Sales!$A$2:$A$5000,A96,Sales!$H$2:$H$5000) | C96: =AVERAGE($B$2:$B$184) | D96: =STDEVP($B$2:$B$184) | E96: =C2+2*D2 | F96: =MAX(0,C2-2*D2) | G96: =IF(OR(B96>E96,B96<F96,AND(B96=0,C96>0)),"ANOMALY","")
A97: 46208 | B97: =SUMIF(Sales!$A$2:$A$5000,A97,Sales!$H$2:$H$5000) | C97: =AVERAGE($B$2:$B$184) | D97: =STDEVP($B$2:$B$184) | E97: =C2+2*D2 | F97: =MAX(0,C2-2*D2) | G97: =IF(OR(B97>E97,B97<F97,AND(B97=0,C97>0)),"ANOMALY","")
A98: 46209 | B98: =SUMIF(Sales!$A$2:$A$5000,A98,Sales!$H$2:$H$5000) | C98: =AVERAGE($B$2:$B$184) | D98: =STDEVP($B$2:$B$184) | E98: =C2+2*D2 | F98: =MAX(0,C2-2*D2) | G98: =IF(OR(B98>E98,B98<F98,AND(B98=0,C98>0)),"ANOMALY","")
A99: 46210 | B99: =SUMIF(Sales!$A$2:$A$5000,A99,Sales!$H$2:$H$5000) | C99: =AVERAGE($B$2:$B$184) | D99: =STDEVP($B$2:$B$184) | E99: =C2+2*D2 | F99: =MAX(0,C2-2*D2) | G99: =IF(OR(B99>E99,B99<F99,AND(B99=0,C99>0)),"ANOMALY","")
A100: 46211 | B100: =SUMIF(Sales!$A$2:$A$5000,A100,Sales!$H$2:$H$5000) | C100: =AVERAGE($B$2:$B$184) | D100: =STDEVP($B$2:$B$184) | E100: =C2+2*D2 | F100: =MAX(0,C2-2*D2) | G100: =IF(OR(B100>E100,B100<F100,AND(B100=0,C100>0)),"ANOMALY","")
...

Sheet Dashboard
A1: Verma Trading Co., Patna (fictional demo data)
A2: Consolidated MIS dashboard — every figure below is a live formula over the Sales / Purchases ranges. Paste new rows into those tables and this page refreshes.
A4: KEY PERFORMANCE INDICATORS
A5: Total Sales (Rs.) | C5: Total Purchases (Rs.) | E5: Gross Profit (Rs.) | G5: Margin %
A6: =SUM(Sales!$H$2:$H$5000) | C6: =SUM(Purchases!$H$2:$H$2000) | E6: =SUM(Sales!$H$2:$H$5000)-SUM(Sales!$I$2:$I$5000) | G6: =IF(SUM(Sales!$H$2:$H$5000)=0,0,(SUM(Sales!$H$2:$H$5000)-SUM(Sales!$I$2:$I$5000))/SUM(Sales!$H$2:$H$5000))
A8: Transactions | C8: Avg Ticket (Rs.) | E8: Anomaly Days | G8: Products Sold
A9: =COUNTA(Sales!$B$2:$B$5000) | C9: =AVERAGE(Sales!$H$2:$H$5000) | E9: =COUNTIF(Daily!$G$2:$G$184,"ANOMALY") | G9: =SUMPRODUCT(--(Products!$E$2:$E$13>0))
A12: Sales by Category | E12: Top 5 Products by Sales
A13: Category | B13: Sales | E13: Product | F13: Sales
A14: Beverages | B14: =SUMIF(Sales!$E$2:$E$5000,A14,Sales!$H$2:$H$5000) | E14: =INDEX(Products!$B$2:$B$13,MATCH(LARGE(Products!$E$2:$E$13,1),Products!$E$2:$E$13,0)) | F14: =LARGE(Products!$E$2:$E$13,1)
A15: Dairy | B15: =SUMIF(Sales!$E$2:$E$5000,A15,Sales!$H$2:$H$5000) | E15: =INDEX(Products!$B$2:$B$13,MATCH(LARGE(Products!$E$2:$E$13,2),Products!$E$2:$E$13,0)) | F15: =LARGE(Products!$E$2:$E$13,2)
A16: Household | B16: =SUMIF(Sales!$E$2:$E$5000,A16,Sales!$H$2:$H$5000) | E16: =INDEX(Products!$B$2:$B$13,MATCH(LARGE(Products!$E$2:$E$13,3),Products!$E$2:$E$13,0)) | F16: =LARGE(Products!$E$2:$E$13,3)
A17: Snacks | B17: =SUMIF(Sales!$E$2:$E$5000,A17,Sales!$H$2:$H$5000) | E17: =INDEX(Products!$B$2:$B$13,MATCH(LARGE(Products!$E$2:$E$13,4),Products!$E$2:$E$13,0)) | F17: =LARGE(Products!$E$2:$E$13,4)
E18: =INDEX(Products!$B$2:$B$13,MATCH(LARGE(Products!$E$2:$E$13,5),Products!$E$2:$E$13,0)) | F18: =LARGE(Products!$E$2:$E$13,5)

Sheet Checks
A1: INTEGRITY CHECKS — all must read OK
A2: Check | B2: Difference | C2: Status
A3: Sales amounts = Qty x Rate on every row | B3: =SUM(Sales!$H$2:$H$5000)-SUMPRODUCT(Sales!$F$2:$F$5000,Sales!$G$2:$G$5000) | C3: =IF(ABS(B3)<0.01,"OK","FAIL")
A4: Purchase amounts = Qty x CostRate on every row | B4: =SUM(Purchases!$H$2:$H$2000)-SUMPRODUCT(Purchases!$F$2:$F$2000,Purchases!$G$2:$G$2000) | C4: =IF(ABS(B4)<0.01,"OK","FAIL")
A5: No negative quantities | B5: =SUMPRODUCT(--(Sales!$F$2:$F$5000<0))+SUMPRODUCT(--(Purchases!$F$2:$F$2000<0)) | C5: =IF(B5=0,"OK","FAIL")
A6: All sale products exist in master | B6: =SUMPRODUCT(--(Sales!$D$2:$D$5000<>""),--ISNA(MATCH(Sales!$D$2:$D$5000,Products!$B$2:$B$13,0))) | C6: =IF(B6=0,"OK","FAIL")
A7: Dates inside Apr-Sep 2026 | B7: =SUMPRODUCT(--(Sales!$A$2:$A$5000<>""),--((Sales!$A$2:$A$5000<DATE(2026,4,1))+(Sales!$A$2:$A$5000>DATE(2026,9,30)))) | C7: =IF(B7=0,"OK","FAIL")
A8: Every product has a StdCost | B8: =SUMPRODUCT(--(Products!$D$2:$D$13=0)) | C8: =IF(B8=0,"OK","FAIL")

Sheet Guide
A1: HANDOVER GUIDE — keeping this MIS fresh
A3: 1. Paste new daily rows at the bottom of the Sales / Purchases data ranges (rows 2-5000 / 2-2000 carry formula headroom; Amount and COGS columns are pre-filled with formulas down to the headroom limit — copy the last formula row down if you outgrow it).
A4: 2. Never type over the blue formula columns (Amount, COGS, StdCost, TotalSales, TotalQty) — they recalculate on paste.
A5: 3. Formula ranges carry headroom (Sales rows 2-5000, Purchases 2-2000): if you outgrow them, extend the range ends in the formulas.
A6: 4. Monthly, Daily, Dashboard and Checks sheets need no manual refresh: open the file and Excel recalculates.
A7: 5. Charts read the Monthly / Dashboard tables, so new months appear once you extend the Monthly sheet's month column.
A8: 6. Checks sheet: every row must read OK before the weekly review — a FAIL pinpoints the exact broken rule.
A9: 7. Anomaly flags (Daily sheet) use avg ± 2 standard deviations on daily sales: investigate any ANOMALY row before the management meeting.
A10: Source files simulated here as data/*.csv (two sales parts + one purchases file, mirroring the client's several workbooks); in production, import each client workbook into the Sales / Purchases tables (Data > From Text/CSV) or paste directly.
