Workbook

Sheet Guide
A1: FlowForge — 13-week cash-flow forecast + budget-variance dashboard
A2: Fictional demo data: 'Patna Traders Pvt. Ltd.', FMCG wholesale distributor. All values in INR. Every money figure on History/Forecast is a live formula — nothing is hard-coded, so one assumption change re-flows the whole model.
A3: HOW TO USE
A4: 1. Edit the yellow cells on Assumptions (growth rates, cash floor, openings).
A5: 2. Paste new weekly actuals into History columns B–D and F–K (values only); totals, net, balances, variances and alerts are all formulas and extend automatically.
A6: 3. Forecast re-projects from the trailing-4-week average of History plus your growth assumptions. Weeks under the cash floor are flagged in red.
A7: 4. Dashboard KPIs and all three charts read live from History/Forecast.
A8: 5. Checks must all read PASS after any edit — a FAIL means a formula was overwritten.
A9: WEEKLY ROUTINE (15 min): paste actuals → check Report for the narrative → act on any BELOW FLOOR or ⚠ Review flags → re-export.

Sheet Assumptions
A1: Setting | B1: Value | C1: Notes
A2: history_opening_balance | B2: 4250000 | C2: Opening bank balance at start of W-25
A3: forecast_opening_balance | B3: 5094820 | C3: Opening balance for F1 (= W0 closing)
A4: inflow_growth | B4: 0.02 | C4: Weekly inflow growth vs trailing-4-week average
A5: outflow_growth | B5: 0.015 | C5: Weekly outflow growth vs trailing-4-week average
A6: cash_floor | B6: 500000 | C6: Minimum safe cash — forecast weeks below this are flagged
A7: trailing_weeks | B7: 4 | C7: Weeks of history averaged for the run-rate forecast
A8: variance_alert_pct | B8: 10 | C8: Budget-vs-actual variance % that triggers a review flag

Sheet History
A1: Week | B1: Sales Receipts | C1: Gst Refund | D1: Other Income | E1: Total Inflow | F1: Supplier Payments | G1: Payroll | H1: Rent | I1: Logistics | J1: Gst Tax | K1: Loan Emi | L1: Total Outflow | M1: Net | N1: Opening | O1: Closing | P1: Budget Inflow | Q1: Budget Outflow | R1: Inflow Var % | S1: Outflow Var % | T1: Alert
A2: W-25 | B2: 844022 | C2: 45000 | D2: 2136 | E2: =SUM(B2:D2) | F2: 657357 | G2: 116239 | H2: 25000 | I2: 40717 | J2: 0 | K2: 0 | L2: =SUM(F2:K2) | M2: =E2-L2 | N2: =Assumptions!$B$2 | O2: =N2+M2 | P2: 950037 | Q2: 788950 | R2: =IF(P2=0,0,(E2-P2)/P2) | S2: =IF(Q2=0,0,(L2-Q2)/Q2) | T2: =IF(OR(ABS(R2)>Assumptions!$B$8/100,ABS(S2)>Assumptions!$B$8/100),"⚠ Review","")
A3: W-24 | B3: 1004307 | C3: 72000 | D3: 10483 | E3: =SUM(B3:D3) | F3: 801072 | G3: 121049 | H3: 25000 | I3: 47143 | J3: 158437 | K3: 0 | L3: =SUM(F3:K3) | M3: =E3-L3 | N3: =O2 | O3: =N3+M3 | P3: 941168 | Q3: 798409 | R3: =IF(P3=0,0,(E3-P3)/P3) | S3: =IF(Q3=0,0,(L3-Q3)/Q3) | T3: =IF(OR(ABS(R3)>Assumptions!$B$8/100,ABS(S3)>Assumptions!$B$8/100),"⚠ Review","")
A4: W-23 | B4: 992295 | C4: 45000 | D4: 10926 | E4: =SUM(B4:D4) | F4: 782675 | G4: 123910 | H4: 25000 | I4: 45724 | J4: 0 | K4: 78000 | L4: =SUM(F4:K4) | M4: =E4-L4 | N4: =O3 | O4: =N4+M4 | P4: 918505 | Q4: 790198 | R4: =IF(P4=0,0,(E4-P4)/P4) | S4: =IF(Q4=0,0,(L4-Q4)/Q4) | T4: =IF(OR(ABS(R4)>Assumptions!$B$8/100,ABS(S4)>Assumptions!$B$8/100),"⚠ Review","")
A5: W-22 | B5: 963741 | C5: 0 | D5: 6566 | E5: =SUM(B5:D5) | F5: 762913 | G5: 118160 | H5: 25000 | I5: 43471 | J5: 0 | K5: 0 | L5: =SUM(F5:K5) | M5: =E5-L5 | N5: =O4 | O5: =N5+M5 | P5: 933968 | Q5: 815179 | R5: =IF(P5=0,0,(E5-P5)/P5) | S5: =IF(Q5=0,0,(L5-Q5)/Q5) | T5: =IF(OR(ABS(R5)>Assumptions!$B$8/100,ABS(S5)>Assumptions!$B$8/100),"⚠ Review","")
A6: W-21 | B6: 835321 | C6: 0 | D6: 8989 | E6: =SUM(B6:D6) | F6: 610640 | G6: 123089 | H6: 25000 | I6: 47043 | J6: 0 | K6: 0 | L6: =SUM(F6:K6) | M6: =E6-L6 | N6: =O5 | O6: =N6+M6 | P6: 938899 | Q6: 813075 | R6: =IF(P6=0,0,(E6-P6)/P6) | S6: =IF(Q6=0,0,(L6-Q6)/Q6) | T6: =IF(OR(ABS(R6)>Assumptions!$B$8/100,ABS(S6)>Assumptions!$B$8/100),"⚠ Review","")
A7: W-20 | B7: 943906 | C7: 0 | D7: 11378 | E7: =SUM(B7:D7) | F7: 739123 | G7: 120268 | H7: 25000 | I7: 51403 | J7: 131656 | K7: 0 | L7: =SUM(F7:K7) | M7: =E7-L7 | N7: =O6 | O7: =N7+M7 | P7: 947080 | Q7: 801264 | R7: =IF(P7=0,0,(E7-P7)/P7) | S7: =IF(Q7=0,0,(L7-Q7)/Q7) | T7: =IF(OR(ABS(R7)>Assumptions!$B$8/100,ABS(S7)>Assumptions!$B$8/100),"⚠ Review","")
A8: W-19 | B8: 946879 | C8: 45000 | D8: 14282 | E8: =SUM(B8:D8) | F8: 707668 | G8: 120657 | H8: 25000 | I8: 47964 | J8: 0 | K8: 78000 | L8: =SUM(F8:K8) | M8: =E8-L8 | N8: =O7 | O8: =N8+M8 | P8: 926862 | Q8: 813686 | R8: =IF(P8=0,0,(E8-P8)/P8) | S8: =IF(Q8=0,0,(L8-Q8)/Q8) | T8: =IF(OR(ABS(R8)>Assumptions!$B$8/100,ABS(S8)>Assumptions!$B$8/100),"⚠ Review","")
A9: W-18 | B9: 1077818 | C9: 45000 | D9: 3736 | E9: =SUM(B9:D9) | F9: 854547 | G9: 122601 | H9: 25000 | I9: 39368 | J9: 0 | K9: 0 | L9: =SUM(F9:K9) | M9: =E9-L9 | N9: =O8 | O9: =N9+M9 | P9: 911093 | Q9: 827209 | R9: =IF(P9=0,0,(E9-P9)/P9) | S9: =IF(Q9=0,0,(L9-Q9)/Q9) | T9: =IF(OR(ABS(R9)>Assumptions!$B$8/100,ABS(S9)>Assumptions!$B$8/100),"⚠ Review","")
A10: W-17 | B10: 937373 | C10: 0 | D10: 13074 | E10: =SUM(B10:D10) | F10: 683884 | G10: 121601 | H10: 25000 | I10: 44522 | J10: 0 | K10: 0 | L10: =SUM(F10:K10) | M10: =E10-L10 | N10: =O9 | O10: =N10+M10 | P10: 934727 | Q10: 830593 | R10: =IF(P10=0,0,(E10-P10)/P10) | S10: =IF(Q10=0,0,(L10-Q10)/Q10) | T10: =IF(OR(ABS(R10)>Assumptions!$B$8/100,ABS(S10)>Assumptions!$B$8/100),"⚠ Review","")
A11: W-16 | B11: 896021 | C11: 30000 | D11: 9568 | E11: =SUM(B11:D11) | F11: 623780 | G11: 119790 | H11: 25000 | I11: 47748 | J11: 109730 | K11: 0 | L11: =SUM(F11:K11) | M11: =E11-L11 | N11: =O10 | O11: =N11+M11 | P11: 912402 | Q11: 797232 | R11: =IF(P11=0,0,(E11-P11)/P11) | S11: =IF(Q11=0,0,(L11-Q11)/Q11) | T11: =IF(OR(ABS(R11)>Assumptions!$B$8/100,ABS(S11)>Assumptions!$B$8/100),"⚠ Review","")
A12: W-15 | B12: 1042308 | C12: 0 | D12: 11719 | E12: =SUM(B12:D12) | F12: 817634 | G12: 120605 | H12: 25000 | I12: 50580 | J12: 0 | K12: 78000 | L12: =SUM(F12:K12) | M12: =E12-L12 | N12: =O11 | O12: =N12+M12 | P12: 909202 | Q12: 789772 | R12: =IF(P12=0,0,(E12-P12)/P12) | S12: =IF(Q12=0,0,(L12-Q12)/Q12) | T12: =IF(OR(ABS(R12)>Assumptions!$B$8/100,ABS(S12)>Assumptions!$B$8/100),"⚠ Review","")
A13: W-14 | B13: 1091104 | C13: 0 | D13: 11220 | E13: =SUM(B13:D13) | F13: 797191 | G13: 123629 | H13: 25000 | I13: 51009 | J13: 0 | K13: 0 | L13: =SUM(F13:K13) | M13: =E13-L13 | N13: =O12 | O13: =N13+M13 | P13: 921524 | Q13: 826763 | R13: =IF(P13=0,0,(E13-P13)/P13) | S13: =IF(Q13=0,0,(L13-Q13)/Q13) | T13: =IF(OR(ABS(R13)>Assumptions!$B$8/100,ABS(S13)>Assumptions!$B$8/100),"⚠ Review","")
A14: W-13 | B14: 1000159 | C14: 0 | D14: 3465 | E14: =SUM(B14:D14) | F14: 786720 | G14: 122499 | H14: 25000 | I14: 47129 | J14: 0 | K14: 0 | L14: =SUM(F14:K14) | M14: =E14-L14 | N14: =O13 | O14: =N14+M14 | P14: 907523 | Q14: 797251 | R14: =IF(P14=0,0,(E14-P14)/P14) | S14: =IF(Q14=0,0,(L14-Q14)/Q14) | T14: =IF(OR(ABS(R14)>Assumptions!$B$8/100,ABS(S14)>Assumptions!$B$8/100),"⚠ Review","")
... A27: W0 | B27: 1026085 | C27: 72000 | D27: 4016 | E27: =SUM(B27:D27) | F27: 705788 | G27: 119903 | H27: 25000 | I27: 40728 | J27: 122941 | K27: 0 | L27: =SUM(F27:K27) | M27: =E27-L27 | N27: =O26 | O27: =N27+M27 | P27: 913829 | Q27: 791165 | R27: =IF(P27=0,0,(E27-P27)/P27) | S27: =IF(Q27=0,0,(L27-Q27)/Q27) | T27: =IF(OR(ABS(R27)>Assumptions!$B$8/100,ABS(S27)>Assumptions!$B$8/100),"⚠ Review","")

Sheet Forecast
A1: Week | B1: Forecast Inflow | C1: Forecast Outflow | D1: Net | E1: Opening | F1: Closing | G1: Floor Check
A2: F1 | B2: =ROUND(AVERAGE(History!$E$24:$E$27)*(1+Assumptions!$B$4)^(2-1),0) | C2: =ROUND(AVERAGE(History!$L$24:$L$27)*(1+Assumptions!$B$5)^(2-1),0) | D2: =B2-C2 | E2: =Assumptions!$B$3 | F2: =E2+D2 | G2: =IF(F2<Assumptions!$B$6,"▼ BELOW FLOOR","✓")
A3: F2 | B3: =ROUND(AVERAGE(History!$E$24:$E$27)*(1+Assumptions!$B$4)^(3-1),0) | C3: =ROUND(AVERAGE(History!$L$24:$L$27)*(1+Assumptions!$B$5)^(3-1),0) | D3: =B3-C3 | E3: =F2 | F3: =E3+D3 | G3: =IF(F3<Assumptions!$B$6,"▼ BELOW FLOOR","✓")
A4: F3 | B4: =ROUND(AVERAGE(History!$E$24:$E$27)*(1+Assumptions!$B$4)^(4-1),0) | C4: =ROUND(AVERAGE(History!$L$24:$L$27)*(1+Assumptions!$B$5)^(4-1),0) | D4: =B4-C4 | E4: =F3 | F4: =E4+D4 | G4: =IF(F4<Assumptions!$B$6,"▼ BELOW FLOOR","✓")
A5: F4 | B5: =ROUND(AVERAGE(History!$E$24:$E$27)*(1+Assumptions!$B$4)^(5-1),0) | C5: =ROUND(AVERAGE(History!$L$24:$L$27)*(1+Assumptions!$B$5)^(5-1),0) | D5: =B5-C5 | E5: =F4 | F5: =E5+D5 | G5: =IF(F5<Assumptions!$B$6,"▼ BELOW FLOOR","✓")
A6: F5 | B6: =ROUND(AVERAGE(History!$E$24:$E$27)*(1+Assumptions!$B$4)^(6-1),0) | C6: =ROUND(AVERAGE(History!$L$24:$L$27)*(1+Assumptions!$B$5)^(6-1),0) | D6: =B6-C6 | E6: =F5 | F6: =E6+D6 | G6: =IF(F6<Assumptions!$B$6,"▼ BELOW FLOOR","✓")
A7: F6 | B7: =ROUND(AVERAGE(History!$E$24:$E$27)*(1+Assumptions!$B$4)^(7-1),0) | C7: =ROUND(AVERAGE(History!$L$24:$L$27)*(1+Assumptions!$B$5)^(7-1),0) | D7: =B7-C7 | E7: =F6 | F7: =E7+D7 | G7: =IF(F7<Assumptions!$B$6,"▼ BELOW FLOOR","✓")
A8: F7 | B8: =ROUND(AVERAGE(History!$E$24:$E$27)*(1+Assumptions!$B$4)^(8-1),0) | C8: =ROUND(AVERAGE(History!$L$24:$L$27)*(1+Assumptions!$B$5)^(8-1),0) | D8: =B8-C8 | E8: =F7 | F8: =E8+D8 | G8: =IF(F8<Assumptions!$B$6,"▼ BELOW FLOOR","✓")
A9: F8 | B9: =ROUND(AVERAGE(History!$E$24:$E$27)*(1+Assumptions!$B$4)^(9-1),0) | C9: =ROUND(AVERAGE(History!$L$24:$L$27)*(1+Assumptions!$B$5)^(9-1),0) | D9: =B9-C9 | E9: =F8 | F9: =E9+D9 | G9: =IF(F9<Assumptions!$B$6,"▼ BELOW FLOOR","✓")
A10: F9 | B10: =ROUND(AVERAGE(History!$E$24:$E$27)*(1+Assumptions!$B$4)^(10-1),0) | C10: =ROUND(AVERAGE(History!$L$24:$L$27)*(1+Assumptions!$B$5)^(10-1),0) | D10: =B10-C10 | E10: =F9 | F10: =E10+D10 | G10: =IF(F10<Assumptions!$B$6,"▼ BELOW FLOOR","✓")
A11: F10 | B11: =ROUND(AVERAGE(History!$E$24:$E$27)*(1+Assumptions!$B$4)^(11-1),0) | C11: =ROUND(AVERAGE(History!$L$24:$L$27)*(1+Assumptions!$B$5)^(11-1),0) | D11: =B11-C11 | E11: =F10 | F11: =E11+D11 | G11: =IF(F11<Assumptions!$B$6,"▼ BELOW FLOOR","✓")
A12: F11 | B12: =ROUND(AVERAGE(History!$E$24:$E$27)*(1+Assumptions!$B$4)^(12-1),0) | C12: =ROUND(AVERAGE(History!$L$24:$L$27)*(1+Assumptions!$B$5)^(12-1),0) | D12: =B12-C12 | E12: =F11 | F12: =E12+D12 | G12: =IF(F12<Assumptions!$B$6,"▼ BELOW FLOOR","✓")
A13: F12 | B13: =ROUND(AVERAGE(History!$E$24:$E$27)*(1+Assumptions!$B$4)^(13-1),0) | C13: =ROUND(AVERAGE(History!$L$24:$L$27)*(1+Assumptions!$B$5)^(13-1),0) | D13: =B13-C13 | E13: =F12 | F13: =E13+D13 | G13: =IF(F13<Assumptions!$B$6,"▼ BELOW FLOOR","✓")
A14: F13 | B14: =ROUND(AVERAGE(History!$E$24:$E$27)*(1+Assumptions!$B$4)^(14-1),0) | C14: =ROUND(AVERAGE(History!$L$24:$L$27)*(1+Assumptions!$B$5)^(14-1),0) | D14: =B14-C14 | E14: =F13 | F14: =E14+D14 | G14: =IF(F14<Assumptions!$B$6,"▼ BELOW FLOOR","✓")

Sheet Dashboard
A1: FlowForge — Cash Flow Dashboard
A2: Live from History/Forecast. Fictional demo data — 'Patna Traders Pvt. Ltd.', INR.
K3: Outflow mix (history)
A4: Forecast opening balance | B4: =Assumptions!$B$3 | K4: Supplier Payments | L4: =SUM(History!F2:F27)
A5: Projected closing (F13) | B5: =Forecast!F14 | K5: Payroll | L5: =SUM(History!G2:G27)
A6: Minimum cash over forecast | B6: =MIN(Forecast!F2:F14) | K6: Rent | L6: =SUM(History!H2:H27)
A7: Weeks below cash floor | B7: =COUNTIF(Forecast!G2:G14,"*BELOW*") | K7: Logistics | L7: =SUM(History!I2:I27)
A8: Avg weekly net (forecast) | B8: =AVERAGE(Forecast!D2:D14) | K8: Gst Tax | L8: =SUM(History!J2:J27)
A9: History total inflow (26 wks) | B9: =SUM(History!E2:E27) | K9: Loan Emi | L9: =SUM(History!K2:K27)
A10: History total outflow (26 wks) | B10: =SUM(History!L2:L27)
A11: Weeks with budget-review alert | B11: =COUNTIF(History!T2:T27,"*Review*")

Sheet Checks
A1: Integrity checks — all must read PASS
A2: Check | B2: Result
A3: History reconciles: opening + net = closing every week | B3: =IF(SUMPRODUCT((History!N2:N27+History!M2:M27-History!O2:O27)^2)=0,"PASS","FAIL")
A4: History continuity: each week's opening = prior closing | B4: =IF(SUMPRODUCT((History!N3:N27-History!O2:O26)^2)=0,"PASS","FAIL")
A5: Forecast continuity: each week's opening = prior closing | B5: =IF(SUMPRODUCT((Forecast!E3:E14-Forecast!F2:F13)^2)=0,"PASS","FAIL")
A6: Forecast closing = opening + net every week | B6: =IF(SUMPRODUCT((Forecast!F2:F14-Forecast!E2:E14-Forecast!D2:D14)^2)=0,"PASS","FAIL")
A7: Forecast opening equals Assumptions value | B7: =IF(Forecast!E2=Assumptions!$B$3,"PASS","FAIL")
A8: No formula errors anywhere in History/Forecast | B8: =IF(SUMPRODUCT(--ISERROR(History!A2:T27))+SUMPRODUCT(--ISERROR(Forecast!A2:G14))=0,"PASS","FAIL")
A9: Review alerts fire exactly when |variance| exceeds threshold | B9: =IF(SUMPRODUCT((ABS(History!R2:R27)>Assumptions!$B$8/100)*(History!T2:T27=""))+SUMPRODUCT((ABS(History!S2:S27)>Assumptions!$B$8/100)*(History!T2:T27=""))=0,"PASS","FAIL")
A10: Floor flags fire for every forecast week under the cash floor | B10: =IF(SUMPRODUCT((Forecast!F2:F14<Assumptions!$B$6)*(Forecast!G2:G14="✓"))=0,"PASS","FAIL")

Sheet Report
A1: Weekly cash narrative — generated from this workbook's data
A3: Strongest inflow week: W-18 (₹1,126,554); weakest: W-21 (₹844,310).
A4: Heaviest outflow week: W-24 (₹1,152,701) — GST/EMI weeks drive the spikes; the forecast carries them inside the trailing average.
A5: 13-week outlook from F1 opening ₹5,094,820: projected closing ₹6,543,431; minimum cash ₹5,163,798 in F1.
A6: No forecast week breaches the ₹500,000 cash floor — buffer intact.
A7: 23 of 26 history weeks breached the 10% budget-variance threshold — see the Alert column on History.
A8: Weekly routine: paste actuals → re-read this sheet → act on flags.
