Workbook
Name GL_Date: GL_Transactions!$B$2:$B$170
Name GL_Acct: GL_Transactions!$C$2:$C$170
Name GL_Net: GL_Transactions!$H$2:$H$170
Name GL_Debit: GL_Transactions!$F$2:$F$170
Name GL_Credit: GL_Transactions!$G$2:$G$170

Sheet GL_Transactions
A1: Entry | B1: Date | C1: Account Code | D1: Account Name | E1: Description | F1: Debit | G1: Credit | H1: Net (Dr-Cr)
A2: E0001 | B2: 46112 | C2: 1000 | D2: Cash in Bank | E2: Opening balance | F2: 320000 | G2: 0 | H2: =F2-G2
A3: E0001 | B3: 46112 | C3: 1100 | D3: Trade Receivables | E3: Opening balance | F3: 140000 | G3: 0 | H3: =F3-G3
A4: E0001 | B4: 46112 | C4: 1200 | D4: Inventory | E4: Opening balance | F4: 90000 | G4: 0 | H4: =F4-G4
A5: E0001 | B5: 46112 | C5: 1500 | D5: Equipment (net of purchases) | E5: Opening balance | F5: 240000 | G5: 0 | H5: =F5-G5
A6: E0001 | B6: 46112 | C6: 1510 | D6: Accumulated Depreciation | E6: Opening balance | F6: 0 | G6: 48000 | H6: =F6-G6
A7: E0001 | B7: 46112 | C7: 2100 | D7: Trade Payables | E7: Opening balance | F7: 0 | G7: 110000 | H7: =F7-G7
A8: E0001 | B8: 46112 | C8: 3000 | D8: Owner's Capital | E8: Opening balance | F8: 0 | G8: 632000 | H8: =F8-G8
A9: E0002 | B9: 46115 | C9: 1100 | D9: Trade Receivables | E9: Credit sales invoices | F9: 231154.14 | G9: 0 | H9: =F9-G9
A10: E0002 | B10: 46115 | C10: 4000 | D10: Sales Revenue | E10: Credit sales invoices | F10: 0 | G10: 231154.14 | H10: =F10-G10
A11: E0003 | B11: 46120 | C11: 1000 | D11: Cash in Bank | E11: Service revenue received | F11: 30750.32 | G11: 0 | H11: =F11-G11
A12: E0003 | B12: 46120 | C12: 4100 | D12: Service Revenue | E12: Service revenue received | F12: 0 | G12: 30750.32 | H12: =F12-G12
A13: E0004 | B13: 46124 | C13: 1000 | D13: Cash in Bank | E13: Customer collections | F13: 172002.35 | G13: 0 | H13: =F13-G13
... A170: E0082 | B170: 46292 | C170: 1000 | D170: Cash in Bank | E170: Loan repayment | F170: 0 | G170: 15000 | H170: =F170-G170

Sheet Chart_of_Accounts
A1: Account Code | B1: Account Name | C1: Group | D1: Normal Balance | E1: Cash-flow Section
A2: 1000 | B2: Cash in Bank | C2: Asset | D2: DR
A3: 1100 | B3: Trade Receivables | C3: Asset | D3: DR | E3: Operating
A4: 1200 | B4: Inventory | C4: Asset | D4: DR | E4: Operating
A5: 1500 | B5: Equipment (net of purchases) | C5: Asset | D5: DR | E5: Investing
A6: 1510 | B6: Accumulated Depreciation | C6: Asset | D6: CR
A7: 2100 | B7: Trade Payables | C7: Liability | D7: CR | E7: Operating
A8: 2500 | B8: Bank Loan | C8: Liability | D8: CR | E8: Financing
A9: 3000 | B9: Owner's Capital | C9: Equity | D9: CR | E9: Financing
A10: 4000 | B10: Sales Revenue | C10: Revenue | D10: CR | E10: Operating
A11: 4100 | B11: Service Revenue | C11: Revenue | D11: CR | E11: Operating
A12: 5000 | B12: Cost of Goods Sold | C12: COGS | D12: DR | E12: Operating
A13: 6000 | B13: Salaries & Wages | C13: Opex | D13: DR | E13: Operating
A14: 6100 | B14: Office Rent | C14: Opex | D14: DR | E14: Operating
A15: 6200 | B15: Utilities | C15: Opex | D15: DR | E15: Operating
A16: 6300 | B16: Marketing | C16: Opex | D16: DR | E16: Operating
A17: 6400 | B17: Depreciation | C17: Opex | D17: DR | E17: Operating
A18: 6999 | B18: Other Operating Expenses | C18: Opex | D18: DR | E18: Operating
... A20: 7100 | B20: Other Expenses | C20: Other Expense | D20: DR | E20: Operating

Sheet Trial_Balance
A1: Account Code | B1: Account Name | C1: Group | D1: Debit | E1: Credit | F1: Balance (Dr-Cr)
A2: 1000 | B2: Cash in Bank | C2: Asset | D2: =SUMIFS(GL_Debit,GL_Acct,"1000") | E2: =SUMIFS(GL_Credit,GL_Acct,"1000") | F2: =D2-E2
A3: 1100 | B3: Trade Receivables | C3: Asset | D3: =SUMIFS(GL_Debit,GL_Acct,"1100") | E3: =SUMIFS(GL_Credit,GL_Acct,"1100") | F3: =D3-E3
A4: 1200 | B4: Inventory | C4: Asset | D4: =SUMIFS(GL_Debit,GL_Acct,"1200") | E4: =SUMIFS(GL_Credit,GL_Acct,"1200") | F4: =D4-E4
A5: 1500 | B5: Equipment (net of purchases) | C5: Asset | D5: =SUMIFS(GL_Debit,GL_Acct,"1500") | E5: =SUMIFS(GL_Credit,GL_Acct,"1500") | F5: =D5-E5
A6: 1510 | B6: Accumulated Depreciation | C6: Asset | D6: =SUMIFS(GL_Debit,GL_Acct,"1510") | E6: =SUMIFS(GL_Credit,GL_Acct,"1510") | F6: =D6-E6
A7: 2100 | B7: Trade Payables | C7: Liability | D7: =SUMIFS(GL_Debit,GL_Acct,"2100") | E7: =SUMIFS(GL_Credit,GL_Acct,"2100") | F7: =D7-E7
A8: 2500 | B8: Bank Loan | C8: Liability | D8: =SUMIFS(GL_Debit,GL_Acct,"2500") | E8: =SUMIFS(GL_Credit,GL_Acct,"2500") | F8: =D8-E8
A9: 3000 | B9: Owner's Capital | C9: Equity | D9: =SUMIFS(GL_Debit,GL_Acct,"3000") | E9: =SUMIFS(GL_Credit,GL_Acct,"3000") | F9: =D9-E9
A10: 4000 | B10: Sales Revenue | C10: Revenue | D10: =SUMIFS(GL_Debit,GL_Acct,"4000") | E10: =SUMIFS(GL_Credit,GL_Acct,"4000") | F10: =D10-E10
A11: 4100 | B11: Service Revenue | C11: Revenue | D11: =SUMIFS(GL_Debit,GL_Acct,"4100") | E11: =SUMIFS(GL_Credit,GL_Acct,"4100") | F11: =D11-E11
A12: 5000 | B12: Cost of Goods Sold | C12: COGS | D12: =SUMIFS(GL_Debit,GL_Acct,"5000") | E12: =SUMIFS(GL_Credit,GL_Acct,"5000") | F12: =D12-E12
A13: 6000 | B13: Salaries & Wages | C13: Opex | D13: =SUMIFS(GL_Debit,GL_Acct,"6000") | E13: =SUMIFS(GL_Credit,GL_Acct,"6000") | F13: =D13-E13
A14: 6100 | B14: Office Rent | C14: Opex | D14: =SUMIFS(GL_Debit,GL_Acct,"6100") | E14: =SUMIFS(GL_Credit,GL_Acct,"6100") | F14: =D14-E14
A15: 6200 | B15: Utilities | C15: Opex | D15: =SUMIFS(GL_Debit,GL_Acct,"6200") | E15: =SUMIFS(GL_Credit,GL_Acct,"6200") | F15: =D15-E15
A16: 6300 | B16: Marketing | C16: Opex | D16: =SUMIFS(GL_Debit,GL_Acct,"6300") | E16: =SUMIFS(GL_Credit,GL_Acct,"6300") | F16: =D16-E16
A17: 6400 | B17: Depreciation | C17: Opex | D17: =SUMIFS(GL_Debit,GL_Acct,"6400") | E17: =SUMIFS(GL_Credit,GL_Acct,"6400") | F17: =D17-E17
A18: 6999 | B18: Other Operating Expenses | C18: Opex | D18: =SUMIFS(GL_Debit,GL_Acct,"6999") | E18: =SUMIFS(GL_Credit,GL_Acct,"6999") | F18: =D18-E18
A19: 7000 | B19: Other Income | C19: Other Income | D19: =SUMIFS(GL_Debit,GL_Acct,"7000") | E19: =SUMIFS(GL_Credit,GL_Acct,"7000") | F19: =D19-E19
A20: 7100 | B20: Other Expenses | C20: Other Expense | D20: =SUMIFS(GL_Debit,GL_Acct,"7100") | E20: =SUMIFS(GL_Credit,GL_Acct,"7100") | F20: =D20-E20
A21: TOTAL | D21: =SUM(D2:D20) | E21: =SUM(E2:E20)
A22: Balanced? | B22: =IF(ABS(D21-E21)<0.01,"OK - balanced","OUT OF BALANCE")

Sheet P&L
A1: Profit & Loss (SAR)
B2: 46113 | C2: 46143 | D2: 46174 | E2: 46204 | F2: 46235 | G2: 46266
A3: Line | B3: Apr-26 | C3: May-26 | D3: Jun-26 | E3: Jul-26 | F3: Aug-26 | G3: Sep-26 | H3: Total
A4: Sales Revenue | B4: =-SUMIFS(GL_Net,GL_Acct,"4000",GL_Date,">="&B$2,GL_Date,"<"&EDATE(B$2,1)) | C4: =-SUMIFS(GL_Net,GL_Acct,"4000",GL_Date,">="&C$2,GL_Date,"<"&EDATE(C$2,1)) | D4: =-SUMIFS(GL_Net,GL_Acct,"4000",GL_Date,">="&D$2,GL_Date,"<"&EDATE(D$2,1)) | E4: =-SUMIFS(GL_Net,GL_Acct,"4000",GL_Date,">="&E$2,GL_Date,"<"&EDATE(E$2,1)) | F4: =-SUMIFS(GL_Net,GL_Acct,"4000",GL_Date,">="&F$2,GL_Date,"<"&EDATE(F$2,1)) | G4: =-SUMIFS(GL_Net,GL_Acct,"4000",GL_Date,">="&G$2,GL_Date,"<"&EDATE(G$2,1)) | H4: =SUM(B4:G4)
A5: Service Revenue | B5: =-SUMIFS(GL_Net,GL_Acct,"4100",GL_Date,">="&B$2,GL_Date,"<"&EDATE(B$2,1)) | C5: =-SUMIFS(GL_Net,GL_Acct,"4100",GL_Date,">="&C$2,GL_Date,"<"&EDATE(C$2,1)) | D5: =-SUMIFS(GL_Net,GL_Acct,"4100",GL_Date,">="&D$2,GL_Date,"<"&EDATE(D$2,1)) | E5: =-SUMIFS(GL_Net,GL_Acct,"4100",GL_Date,">="&E$2,GL_Date,"<"&EDATE(E$2,1)) | F5: =-SUMIFS(GL_Net,GL_Acct,"4100",GL_Date,">="&F$2,GL_Date,"<"&EDATE(F$2,1)) | G5: =-SUMIFS(GL_Net,GL_Acct,"4100",GL_Date,">="&G$2,GL_Date,"<"&EDATE(G$2,1)) | H5: =SUM(B5:G5)
A6: Total Revenue | B6: =B4+B5 | C6: =C4+C5 | D6: =D4+D5 | E6: =E4+E5 | F6: =F4+F5 | G6: =G4+G5 | H6: =H4+H5
A7: Cost of Goods Sold | B7: =SUMIFS(GL_Net,GL_Acct,"5000",GL_Date,">="&B$2,GL_Date,"<"&EDATE(B$2,1)) | C7: =SUMIFS(GL_Net,GL_Acct,"5000",GL_Date,">="&C$2,GL_Date,"<"&EDATE(C$2,1)) | D7: =SUMIFS(GL_Net,GL_Acct,"5000",GL_Date,">="&D$2,GL_Date,"<"&EDATE(D$2,1)) | E7: =SUMIFS(GL_Net,GL_Acct,"5000",GL_Date,">="&E$2,GL_Date,"<"&EDATE(E$2,1)) | F7: =SUMIFS(GL_Net,GL_Acct,"5000",GL_Date,">="&F$2,GL_Date,"<"&EDATE(F$2,1)) | G7: =SUMIFS(GL_Net,GL_Acct,"5000",GL_Date,">="&G$2,GL_Date,"<"&EDATE(G$2,1)) | H7: =SUM(B7:G7)
A8: Gross Profit | B8: =B6-B7 | C8: =C6-C7 | D8: =D6-D7 | E8: =E6-E7 | F8: =F6-F7 | G8: =G6-G7 | H8: =H6-H7
A9: Salaries & Wages | B9: =SUMIFS(GL_Net,GL_Acct,"6000",GL_Date,">="&B$2,GL_Date,"<"&EDATE(B$2,1)) | C9: =SUMIFS(GL_Net,GL_Acct,"6000",GL_Date,">="&C$2,GL_Date,"<"&EDATE(C$2,1)) | D9: =SUMIFS(GL_Net,GL_Acct,"6000",GL_Date,">="&D$2,GL_Date,"<"&EDATE(D$2,1)) | E9: =SUMIFS(GL_Net,GL_Acct,"6000",GL_Date,">="&E$2,GL_Date,"<"&EDATE(E$2,1)) | F9: =SUMIFS(GL_Net,GL_Acct,"6000",GL_Date,">="&F$2,GL_Date,"<"&EDATE(F$2,1)) | G9: =SUMIFS(GL_Net,GL_Acct,"6000",GL_Date,">="&G$2,GL_Date,"<"&EDATE(G$2,1)) | H9: =SUM(B9:G9)
A10: Office Rent | B10: =SUMIFS(GL_Net,GL_Acct,"6100",GL_Date,">="&B$2,GL_Date,"<"&EDATE(B$2,1)) | C10: =SUMIFS(GL_Net,GL_Acct,"6100",GL_Date,">="&C$2,GL_Date,"<"&EDATE(C$2,1)) | D10: =SUMIFS(GL_Net,GL_Acct,"6100",GL_Date,">="&D$2,GL_Date,"<"&EDATE(D$2,1)) | E10: =SUMIFS(GL_Net,GL_Acct,"6100",GL_Date,">="&E$2,GL_Date,"<"&EDATE(E$2,1)) | F10: =SUMIFS(GL_Net,GL_Acct,"6100",GL_Date,">="&F$2,GL_Date,"<"&EDATE(F$2,1)) | G10: =SUMIFS(GL_Net,GL_Acct,"6100",GL_Date,">="&G$2,GL_Date,"<"&EDATE(G$2,1)) | H10: =SUM(B10:G10)
A11: Utilities | B11: =SUMIFS(GL_Net,GL_Acct,"6200",GL_Date,">="&B$2,GL_Date,"<"&EDATE(B$2,1)) | C11: =SUMIFS(GL_Net,GL_Acct,"6200",GL_Date,">="&C$2,GL_Date,"<"&EDATE(C$2,1)) | D11: =SUMIFS(GL_Net,GL_Acct,"6200",GL_Date,">="&D$2,GL_Date,"<"&EDATE(D$2,1)) | E11: =SUMIFS(GL_Net,GL_Acct,"6200",GL_Date,">="&E$2,GL_Date,"<"&EDATE(E$2,1)) | F11: =SUMIFS(GL_Net,GL_Acct,"6200",GL_Date,">="&F$2,GL_Date,"<"&EDATE(F$2,1)) | G11: =SUMIFS(GL_Net,GL_Acct,"6200",GL_Date,">="&G$2,GL_Date,"<"&EDATE(G$2,1)) | H11: =SUM(B11:G11)
A12: Marketing | B12: =SUMIFS(GL_Net,GL_Acct,"6300",GL_Date,">="&B$2,GL_Date,"<"&EDATE(B$2,1)) | C12: =SUMIFS(GL_Net,GL_Acct,"6300",GL_Date,">="&C$2,GL_Date,"<"&EDATE(C$2,1)) | D12: =SUMIFS(GL_Net,GL_Acct,"6300",GL_Date,">="&D$2,GL_Date,"<"&EDATE(D$2,1)) | E12: =SUMIFS(GL_Net,GL_Acct,"6300",GL_Date,">="&E$2,GL_Date,"<"&EDATE(E$2,1)) | F12: =SUMIFS(GL_Net,GL_Acct,"6300",GL_Date,">="&F$2,GL_Date,"<"&EDATE(F$2,1)) | G12: =SUMIFS(GL_Net,GL_Acct,"6300",GL_Date,">="&G$2,GL_Date,"<"&EDATE(G$2,1)) | H12: =SUM(B12:G12)
A13: Depreciation | B13: =SUMIFS(GL_Net,GL_Acct,"6400",GL_Date,">="&B$2,GL_Date,"<"&EDATE(B$2,1)) | C13: =SUMIFS(GL_Net,GL_Acct,"6400",GL_Date,">="&C$2,GL_Date,"<"&EDATE(C$2,1)) | D13: =SUMIFS(GL_Net,GL_Acct,"6400",GL_Date,">="&D$2,GL_Date,"<"&EDATE(D$2,1)) | E13: =SUMIFS(GL_Net,GL_Acct,"6400",GL_Date,">="&E$2,GL_Date,"<"&EDATE(E$2,1)) | F13: =SUMIFS(GL_Net,GL_Acct,"6400",GL_Date,">="&F$2,GL_Date,"<"&EDATE(F$2,1)) | G13: =SUMIFS(GL_Net,GL_Acct,"6400",GL_Date,">="&G$2,GL_Date,"<"&EDATE(G$2,1)) | H13: =SUM(B13:G13)
A14: Other Operating Expenses | B14: =SUMIFS(GL_Net,GL_Acct,"6999",GL_Date,">="&B$2,GL_Date,"<"&EDATE(B$2,1)) | C14: =SUMIFS(GL_Net,GL_Acct,"6999",GL_Date,">="&C$2,GL_Date,"<"&EDATE(C$2,1)) | D14: =SUMIFS(GL_Net,GL_Acct,"6999",GL_Date,">="&D$2,GL_Date,"<"&EDATE(D$2,1)) | E14: =SUMIFS(GL_Net,GL_Acct,"6999",GL_Date,">="&E$2,GL_Date,"<"&EDATE(E$2,1)) | F14: =SUMIFS(GL_Net,GL_Acct,"6999",GL_Date,">="&F$2,GL_Date,"<"&EDATE(F$2,1)) | G14: =SUMIFS(GL_Net,GL_Acct,"6999",GL_Date,">="&G$2,GL_Date,"<"&EDATE(G$2,1)) | H14: =SUM(B14:G14)
A15: Total Operating Expenses | B15: =B9+B10+B11+B12+B13+B14 | C15: =C9+C10+C11+C12+C13+C14 | D15: =D9+D10+D11+D12+D13+D14 | E15: =E9+E10+E11+E12+E13+E14 | F15: =F9+F10+F11+F12+F13+F14 | G15: =G9+G10+G11+G12+G13+G14 | H15: =H9+H10+H11+H12+H13+H14
A16: Operating Income | B16: =B8-B15 | C16: =C8-C15 | D16: =D8-D15 | E16: =E8-E15 | F16: =F8-F15 | G16: =G8-G15 | H16: =H8-H15
A17: Other Income | B17: =-SUMIFS(GL_Net,GL_Acct,"7000",GL_Date,">="&B$2,GL_Date,"<"&EDATE(B$2,1)) | C17: =-SUMIFS(GL_Net,GL_Acct,"7000",GL_Date,">="&C$2,GL_Date,"<"&EDATE(C$2,1)) | D17: =-SUMIFS(GL_Net,GL_Acct,"7000",GL_Date,">="&D$2,GL_Date,"<"&EDATE(D$2,1)) | E17: =-SUMIFS(GL_Net,GL_Acct,"7000",GL_Date,">="&E$2,GL_Date,"<"&EDATE(E$2,1)) | F17: =-SUMIFS(GL_Net,GL_Acct,"7000",GL_Date,">="&F$2,GL_Date,"<"&EDATE(F$2,1)) | G17: =-SUMIFS(GL_Net,GL_Acct,"7000",GL_Date,">="&G$2,GL_Date,"<"&EDATE(G$2,1)) | H17: =SUM(B17:G17)
A18: Other Expenses | B18: =SUMIFS(GL_Net,GL_Acct,"7100",GL_Date,">="&B$2,GL_Date,"<"&EDATE(B$2,1)) | C18: =SUMIFS(GL_Net,GL_Acct,"7100",GL_Date,">="&C$2,GL_Date,"<"&EDATE(C$2,1)) | D18: =SUMIFS(GL_Net,GL_Acct,"7100",GL_Date,">="&D$2,GL_Date,"<"&EDATE(D$2,1)) | E18: =SUMIFS(GL_Net,GL_Acct,"7100",GL_Date,">="&E$2,GL_Date,"<"&EDATE(E$2,1)) | F18: =SUMIFS(GL_Net,GL_Acct,"7100",GL_Date,">="&F$2,GL_Date,"<"&EDATE(F$2,1)) | G18: =SUMIFS(GL_Net,GL_Acct,"7100",GL_Date,">="&G$2,GL_Date,"<"&EDATE(G$2,1)) | H18: =SUM(B18:G18)
A19: NET INCOME | B19: =B16+B17-B18 | C19: =C16+C17-C18 | D19: =D16+D17-D18 | E19: =E16+E17-E18 | F19: =F16+F17-F18 | G19: =G16+G17-G18 | H19: =H16+H17-H18
A20: Total Expenses (for charts) | B20: =B7+B15+B18 | C20: =C7+C15+C18 | D20: =D7+D15+D18 | E20: =E7+E15+E18 | F20: =F7+F15+F18 | G20: =G7+G15+G18 | H20: =H7+H15+H18

Sheet Cash_Flow
A1: Cash Flow Statement - indirect method (SAR), Apr-Sep 2026 | K1: 46113
A2: Line | B2: SAR | K2: =EDATE(K1,6)
A3: Operating activities
A4: Net income | B4: ='P&L'!H19
A5: Add back: depreciation (non-cash) | B5: ='P&L'!H13
A6: Less: increase in trade receivables | B6: =-((SUMIFS(GL_Net,GL_Acct,"1100"))-(SUMIFS(GL_Net,GL_Acct,"1100",GL_Date,"<"&$K$1)))
A7: Less: increase in inventory | B7: =-((SUMIFS(GL_Net,GL_Acct,"1200"))-(SUMIFS(GL_Net,GL_Acct,"1200",GL_Date,"<"&$K$1)))
A8: Add: increase in trade payables | B8: =-((SUMIFS(GL_Net,GL_Acct,"2100"))-(SUMIFS(GL_Net,GL_Acct,"2100",GL_Date,"<"&$K$1)))
A9: Net cash from operating activities | B9: =B4+B5+B6+B7+B8
A10: Investing activities
A11: Equipment purchases | B11: =-(SUMIFS(GL_Net,GL_Acct,"1500",GL_Date,">="&$K$1,GL_Date,"<"&$K$2))
A12: Net cash from investing activities | B12: =B11
A13: Financing activities
A14: Bank loan (drawdown less repayments) | B14: =-(SUMIFS(GL_Net,GL_Acct,"2500",GL_Date,">="&$K$1,GL_Date,"<"&$K$2))
A15: Net cash from financing activities | B15: =B14
A16: NET CHANGE IN CASH | B16: =B9+B12+B15
A17: Cash at beginning of period | B17: =SUMIFS(GL_Net,GL_Acct,"1000",GL_Date,"<"&$K$1)
A18: CASH AT END OF PERIOD | B18: =B16+B17
A19: Check: ties to trial balance cash? | B19: =IF(ABS(B18-'Trial_Balance'!F2)<0.01,"OK - ties to trial balance","DIFF")

Sheet Dashboard
A1: Finance Dashboard - Desert Rose Trading LLC (SAR)
A2: Apr-Sep 2026 | Source: AX-style GL export | All figures are live formulas
A4: Key figures
A5: Total Revenue (6 mo) | B5: ='P&L'!H6
A6: Total Expenses (6 mo) | B6: ='P&L'!H20
A7: Net Income (6 mo) | B7: ='P&L'!H19
A8: Gross Margin % | B8: =IF('P&L'!H6=0,0,'P&L'!H8/'P&L'!H6)
A9: Net Cash Change | B9: ='Cash_Flow'!B16
A10: Closing Cash | B10: ='Cash_Flow'!B18
