Workbook

Sheet Guide
A1: FarmPulse — Farm Ops & Finance Dashboard (SYNTHETIC DEMO)
A3: Fictional farm data (seed 20261026). No client data is used anywhere.
A4: Built around a real brief shape: one interactive dashboard from
A5: Excel/CSV farm data — income by activity, expenses by category,
A6: profit by enterprise over time, with drill-through to transactions.
A8: HOW TO REFRESH: paste new income rows into Raw_Income and new
A9: expense rows into Raw_Expense (same columns, rows 2-1000). Every
A10: summary, KPI and chart updates by formula — nothing is pasted
A11: as values. Keep the Quarter label format YYYY-Qn.
A13: HOW TO FILTER / DRILL: use the AutoFilter on any Raw sheet column
A14: (Season/Quarter, Enterprise, Paddock/Herd, Cost Centre) to drill
A15: from a summary figure down to its transactions. The Dashboard
... A26: measures reproduce this workbook exactly.

Sheet Dashboard
A1: FarmPulse Dashboard — income, expenses & profit by enterprise
A3: KPI | B3: Value
A4: Total Income | B4: =SUM(Raw_Income!$G$2:$G$1000)
A5: Total Expenses | B5: =SUM(Raw_Expense!$G$2:$G$1000)
A6: Net Profit | B6: =B4-B5
A7: Margin | B7: =IF(B4=0,0,B6/B4)
A8: Best Enterprise (profit) | B8: =INDEX(Enterprise_Profit!$A$2:$A$6,MATCH(MAX(Enterprise_Profit!$F$2:$F$6),Enterprise_Profit!$F$2:$F$6,0))
A9: Expense Ratio | B9: =IF(B4=0,0,B5/B4)
A11: Quarter | B11: Income | C11: Expense | D11: Profit
A12: 2025-Q3 | B12: =SUMIFS(Raw_Income!$G$2:$G$1000,Raw_Income!$B$2:$B$1000,$A12) | C12: =SUMIFS(Raw_Expense!$G$2:$G$1000,Raw_Expense!$B$2:$B$1000,$A12) | D12: =B12-C12
A13: 2025-Q4 | B13: =SUMIFS(Raw_Income!$G$2:$G$1000,Raw_Income!$B$2:$B$1000,$A13) | C13: =SUMIFS(Raw_Expense!$G$2:$G$1000,Raw_Expense!$B$2:$B$1000,$A13) | D13: =B13-C13
A14: 2026-Q1 | B14: =SUMIFS(Raw_Income!$G$2:$G$1000,Raw_Income!$B$2:$B$1000,$A14) | C14: =SUMIFS(Raw_Expense!$G$2:$G$1000,Raw_Expense!$B$2:$B$1000,$A14) | D14: =B14-C14
A15: 2026-Q2 | B15: =SUMIFS(Raw_Income!$G$2:$G$1000,Raw_Income!$B$2:$B$1000,$A15) | C15: =SUMIFS(Raw_Expense!$G$2:$G$1000,Raw_Expense!$B$2:$B$1000,$A15) | D15: =B15-C15
A16: TOTAL | B16: =SUM(B12:B15) | C16: =SUM(C12:C15) | D16: =SUM(D12:D15)

Sheet Raw_Income
A1: Date | B1: Quarter | C1: Enterprise | D1: Activity | E1: Paddock/Herd | F1: Cost Centre | G1: Amount
A2: 2025-07-15 | B2: 2025-Q3 | C2: Dairy | D2: Milk Sales | E2: Paddock B | F2: CC-200 Feed & Vet | G2: 7854.72
A3: 2025-11-21 | B3: 2025-Q4 | C3: Dairy | D3: Calf Sales | E3: Herd 2 | F3: CC-100 Operations | G3: 330.28
A4: 2026-02-21 | B4: 2026-Q1 | C4: Dairy | D4: Milk Sales | E4: Herd 2 | F4: CC-300 Machinery | G4: 3304.92
A5: 2026-04-25 | B5: 2026-Q2 | C5: Dairy | D5: Calf Sales | E5: Flock A | F5: CC-300 Machinery | G5: 9473.66
A6: 2025-08-13 | B6: 2025-Q3 | C6: Wheat | D6: Grain Sales | E6: Flock A | F6: CC-300 Machinery | G6: 739.34
A7: 2025-10-28 | B7: 2025-Q4 | C7: Wheat | D7: Straw Sales | E7: Paddock C | F7: CC-400 Admin | G7: 9352.56
A8: 2026-01-27 | B8: 2026-Q1 | C8: Wheat | D8: Grain Sales | E8: Herd 1 | F8: CC-200 Feed & Vet | G8: 7378.3
A9: 2026-05-23 | B9: 2026-Q2 | C9: Wheat | D9: Straw Sales | E9: Paddock C | F9: CC-200 Feed & Vet | G9: 7230.95
A10: 2025-08-20 | B10: 2025-Q3 | C10: Vegetables | D10: Vegetable Sales | E10: Herd 1 | F10: CC-300 Machinery | G10: 2884.73
A11: 2025-11-13 | B11: 2025-Q4 | C11: Vegetables | D11: Market Stall Sales | E11: Paddock C | F11: CC-200 Feed & Vet | G11: 4161.67
A12: 2026-02-09 | B12: 2026-Q1 | C12: Vegetables | D12: Vegetable Sales | E12: Herd 2 | F12: CC-400 Admin | G12: 8952.12
A13: 2026-05-30 | B13: 2026-Q2 | C13: Vegetables | D13: Market Stall Sales | E13: Paddock C | F13: CC-200 Feed & Vet | G13: 8891.37
... A173: 2026-04-24 | B173: 2026-Q2 | C173: Vegetables | D173: Market Stall Sales | E173: Herd 2 | F173: CC-100 Operations | G173: 7208.91

Sheet Raw_Expense
A1: Date | B1: Quarter | C1: Enterprise | D1: Category | E1: Paddock/Herd | F1: Cost Centre | G1: Amount
A2: 2025-08-08 | B2: 2025-Q3 | C2: Dairy | D2: Feed | E2: Flock A | F2: CC-300 Machinery | G2: 1103.64
A3: 2025-11-29 | B3: 2025-Q4 | C3: Dairy | D3: Labour | E3: Paddock C | F3: CC-300 Machinery | G3: 2658.34
A4: 2026-01-10 | B4: 2026-Q1 | C4: Dairy | D4: Veterinary | E4: Paddock C | F4: CC-300 Machinery | G4: 1429.54
A5: 2026-05-13 | B5: 2026-Q2 | C5: Dairy | D5: Fuel & Machinery | E5: Herd 2 | F5: CC-400 Admin | G5: 5054.29
A6: 2025-07-07 | B6: 2025-Q3 | C6: Wheat | D6: Fertiliser & Seed | E6: Herd 2 | F6: CC-400 Admin | G6: 2824.09
A7: 2025-11-10 | B7: 2025-Q4 | C7: Wheat | D7: Transport | E7: Herd 2 | F7: CC-100 Operations | G7: 3557.67
A8: 2026-02-23 | B8: 2026-Q1 | C8: Wheat | D8: Utilities | E8: Paddock B | F8: CC-400 Admin | G8: 4691.44
A9: 2026-04-26 | B9: 2026-Q2 | C9: Wheat | D9: Other | E9: Paddock B | F9: CC-200 Feed & Vet | G9: 4629.88
A10: 2025-08-30 | B10: 2025-Q3 | C10: Vegetables | D10: Feed | E10: Paddock C | F10: CC-100 Operations | G10: 5457.54
A11: 2025-10-31 | B11: 2025-Q4 | C11: Vegetables | D11: Labour | E11: Paddock A | F11: CC-400 Admin | G11: 1007.33
A12: 2026-01-18 | B12: 2026-Q1 | C12: Vegetables | D12: Veterinary | E12: Paddock B | F12: CC-300 Machinery | G12: 4045.36
A13: 2026-06-03 | B13: 2026-Q2 | C13: Vegetables | D13: Fuel & Machinery | E13: Paddock C | F13: CC-200 Feed & Vet | G13: 4067.78
... A165: 2026-05-07 | B165: 2026-Q2 | C165: Dairy | D165: Fuel & Machinery | E165: Paddock B | F165: CC-100 Operations | G165: 2867.33

Sheet Enterprise_Profit
A1: Enterprise | B1: 2025-Q3 | C1: 2025-Q4 | D1: 2026-Q1 | E1: 2026-Q2 | F1: Total Profit | G1: Total Income | H1: Margin
A2: Dairy | B2: =SUMIFS(Raw_Income!$G$2:$G$1000,Raw_Income!$C$2:$C$1000,$A2,Raw_Income!$B$2:$B$1000,B$1)-SUMIFS(Raw_Expense!$G$2:$G$1000,Raw_Expense!$C$2:$C$1000,$A2,Raw_Expense!$B$2:$B$1000,B$1) | C2: =SUMIFS(Raw_Income!$G$2:$G$1000,Raw_Income!$C$2:$C$1000,$A2,Raw_Income!$B$2:$B$1000,C$1)-SUMIFS(Raw_Expense!$G$2:$G$1000,Raw_Expense!$C$2:$C$1000,$A2,Raw_Expense!$B$2:$B$1000,C$1) | D2: =SUMIFS(Raw_Income!$G$2:$G$1000,Raw_Income!$C$2:$C$1000,$A2,Raw_Income!$B$2:$B$1000,D$1)-SUMIFS(Raw_Expense!$G$2:$G$1000,Raw_Expense!$C$2:$C$1000,$A2,Raw_Expense!$B$2:$B$1000,D$1) | E2: =SUMIFS(Raw_Income!$G$2:$G$1000,Raw_Income!$C$2:$C$1000,$A2,Raw_Income!$B$2:$B$1000,E$1)-SUMIFS(Raw_Expense!$G$2:$G$1000,Raw_Expense!$C$2:$C$1000,$A2,Raw_Expense!$B$2:$B$1000,E$1) | F2: =SUM(B2:E2) | G2: =SUMIFS(Raw_Income!$G$2:$G$1000,Raw_Income!$C$2:$C$1000,$A2) | H2: =IF(G2=0,0,F2/G2)
A3: Wheat | B3: =SUMIFS(Raw_Income!$G$2:$G$1000,Raw_Income!$C$2:$C$1000,$A3,Raw_Income!$B$2:$B$1000,B$1)-SUMIFS(Raw_Expense!$G$2:$G$1000,Raw_Expense!$C$2:$C$1000,$A3,Raw_Expense!$B$2:$B$1000,B$1) | C3: =SUMIFS(Raw_Income!$G$2:$G$1000,Raw_Income!$C$2:$C$1000,$A3,Raw_Income!$B$2:$B$1000,C$1)-SUMIFS(Raw_Expense!$G$2:$G$1000,Raw_Expense!$C$2:$C$1000,$A3,Raw_Expense!$B$2:$B$1000,C$1) | D3: =SUMIFS(Raw_Income!$G$2:$G$1000,Raw_Income!$C$2:$C$1000,$A3,Raw_Income!$B$2:$B$1000,D$1)-SUMIFS(Raw_Expense!$G$2:$G$1000,Raw_Expense!$C$2:$C$1000,$A3,Raw_Expense!$B$2:$B$1000,D$1) | E3: =SUMIFS(Raw_Income!$G$2:$G$1000,Raw_Income!$C$2:$C$1000,$A3,Raw_Income!$B$2:$B$1000,E$1)-SUMIFS(Raw_Expense!$G$2:$G$1000,Raw_Expense!$C$2:$C$1000,$A3,Raw_Expense!$B$2:$B$1000,E$1) | F3: =SUM(B3:E3) | G3: =SUMIFS(Raw_Income!$G$2:$G$1000,Raw_Income!$C$2:$C$1000,$A3) | H3: =IF(G3=0,0,F3/G3)
A4: Vegetables | B4: =SUMIFS(Raw_Income!$G$2:$G$1000,Raw_Income!$C$2:$C$1000,$A4,Raw_Income!$B$2:$B$1000,B$1)-SUMIFS(Raw_Expense!$G$2:$G$1000,Raw_Expense!$C$2:$C$1000,$A4,Raw_Expense!$B$2:$B$1000,B$1) | C4: =SUMIFS(Raw_Income!$G$2:$G$1000,Raw_Income!$C$2:$C$1000,$A4,Raw_Income!$B$2:$B$1000,C$1)-SUMIFS(Raw_Expense!$G$2:$G$1000,Raw_Expense!$C$2:$C$1000,$A4,Raw_Expense!$B$2:$B$1000,C$1) | D4: =SUMIFS(Raw_Income!$G$2:$G$1000,Raw_Income!$C$2:$C$1000,$A4,Raw_Income!$B$2:$B$1000,D$1)-SUMIFS(Raw_Expense!$G$2:$G$1000,Raw_Expense!$C$2:$C$1000,$A4,Raw_Expense!$B$2:$B$1000,D$1) | E4: =SUMIFS(Raw_Income!$G$2:$G$1000,Raw_Income!$C$2:$C$1000,$A4,Raw_Income!$B$2:$B$1000,E$1)-SUMIFS(Raw_Expense!$G$2:$G$1000,Raw_Expense!$C$2:$C$1000,$A4,Raw_Expense!$B$2:$B$1000,E$1) | F4: =SUM(B4:E4) | G4: =SUMIFS(Raw_Income!$G$2:$G$1000,Raw_Income!$C$2:$C$1000,$A4) | H4: =IF(G4=0,0,F4/G4)
A5: Poultry | B5: =SUMIFS(Raw_Income!$G$2:$G$1000,Raw_Income!$C$2:$C$1000,$A5,Raw_Income!$B$2:$B$1000,B$1)-SUMIFS(Raw_Expense!$G$2:$G$1000,Raw_Expense!$C$2:$C$1000,$A5,Raw_Expense!$B$2:$B$1000,B$1) | C5: =SUMIFS(Raw_Income!$G$2:$G$1000,Raw_Income!$C$2:$C$1000,$A5,Raw_Income!$B$2:$B$1000,C$1)-SUMIFS(Raw_Expense!$G$2:$G$1000,Raw_Expense!$C$2:$C$1000,$A5,Raw_Expense!$B$2:$B$1000,C$1) | D5: =SUMIFS(Raw_Income!$G$2:$G$1000,Raw_Income!$C$2:$C$1000,$A5,Raw_Income!$B$2:$B$1000,D$1)-SUMIFS(Raw_Expense!$G$2:$G$1000,Raw_Expense!$C$2:$C$1000,$A5,Raw_Expense!$B$2:$B$1000,D$1) | E5: =SUMIFS(Raw_Income!$G$2:$G$1000,Raw_Income!$C$2:$C$1000,$A5,Raw_Income!$B$2:$B$1000,E$1)-SUMIFS(Raw_Expense!$G$2:$G$1000,Raw_Expense!$C$2:$C$1000,$A5,Raw_Expense!$B$2:$B$1000,E$1) | F5: =SUM(B5:E5) | G5: =SUMIFS(Raw_Income!$G$2:$G$1000,Raw_Income!$C$2:$C$1000,$A5) | H5: =IF(G5=0,0,F5/G5)
A6: Sheep | B6: =SUMIFS(Raw_Income!$G$2:$G$1000,Raw_Income!$C$2:$C$1000,$A6,Raw_Income!$B$2:$B$1000,B$1)-SUMIFS(Raw_Expense!$G$2:$G$1000,Raw_Expense!$C$2:$C$1000,$A6,Raw_Expense!$B$2:$B$1000,B$1) | C6: =SUMIFS(Raw_Income!$G$2:$G$1000,Raw_Income!$C$2:$C$1000,$A6,Raw_Income!$B$2:$B$1000,C$1)-SUMIFS(Raw_Expense!$G$2:$G$1000,Raw_Expense!$C$2:$C$1000,$A6,Raw_Expense!$B$2:$B$1000,C$1) | D6: =SUMIFS(Raw_Income!$G$2:$G$1000,Raw_Income!$C$2:$C$1000,$A6,Raw_Income!$B$2:$B$1000,D$1)-SUMIFS(Raw_Expense!$G$2:$G$1000,Raw_Expense!$C$2:$C$1000,$A6,Raw_Expense!$B$2:$B$1000,D$1) | E6: =SUMIFS(Raw_Income!$G$2:$G$1000,Raw_Income!$C$2:$C$1000,$A6,Raw_Income!$B$2:$B$1000,E$1)-SUMIFS(Raw_Expense!$G$2:$G$1000,Raw_Expense!$C$2:$C$1000,$A6,Raw_Expense!$B$2:$B$1000,E$1) | F6: =SUM(B6:E6) | G6: =SUMIFS(Raw_Income!$G$2:$G$1000,Raw_Income!$C$2:$C$1000,$A6) | H6: =IF(G6=0,0,F6/G6)
A7: TOTAL | B7: =SUM(B2:B6) | C7: =SUM(C2:C6) | D7: =SUM(D2:D6) | E7: =SUM(E2:E6) | F7: =SUM(F2:F6) | G7: =SUM(G2:G6) | H7: =IF(G7=0,0,F7/G7)

Sheet Income_Activity
A1: Activity | B1: 2025-Q3 | C1: 2025-Q4 | D1: 2026-Q1 | E1: 2026-Q2 | F1: Total
A2: Milk Sales | B2: =SUMIFS(Raw_Income!$G$2:$G$1000,Raw_Income!$D$2:$D$1000,$A2,Raw_Income!$B$2:$B$1000,B$1) | C2: =SUMIFS(Raw_Income!$G$2:$G$1000,Raw_Income!$D$2:$D$1000,$A2,Raw_Income!$B$2:$B$1000,C$1) | D2: =SUMIFS(Raw_Income!$G$2:$G$1000,Raw_Income!$D$2:$D$1000,$A2,Raw_Income!$B$2:$B$1000,D$1) | E2: =SUMIFS(Raw_Income!$G$2:$G$1000,Raw_Income!$D$2:$D$1000,$A2,Raw_Income!$B$2:$B$1000,E$1) | F2: =SUM(B2:E2)
A3: Calf Sales | B3: =SUMIFS(Raw_Income!$G$2:$G$1000,Raw_Income!$D$2:$D$1000,$A3,Raw_Income!$B$2:$B$1000,B$1) | C3: =SUMIFS(Raw_Income!$G$2:$G$1000,Raw_Income!$D$2:$D$1000,$A3,Raw_Income!$B$2:$B$1000,C$1) | D3: =SUMIFS(Raw_Income!$G$2:$G$1000,Raw_Income!$D$2:$D$1000,$A3,Raw_Income!$B$2:$B$1000,D$1) | E3: =SUMIFS(Raw_Income!$G$2:$G$1000,Raw_Income!$D$2:$D$1000,$A3,Raw_Income!$B$2:$B$1000,E$1) | F3: =SUM(B3:E3)
A4: Grain Sales | B4: =SUMIFS(Raw_Income!$G$2:$G$1000,Raw_Income!$D$2:$D$1000,$A4,Raw_Income!$B$2:$B$1000,B$1) | C4: =SUMIFS(Raw_Income!$G$2:$G$1000,Raw_Income!$D$2:$D$1000,$A4,Raw_Income!$B$2:$B$1000,C$1) | D4: =SUMIFS(Raw_Income!$G$2:$G$1000,Raw_Income!$D$2:$D$1000,$A4,Raw_Income!$B$2:$B$1000,D$1) | E4: =SUMIFS(Raw_Income!$G$2:$G$1000,Raw_Income!$D$2:$D$1000,$A4,Raw_Income!$B$2:$B$1000,E$1) | F4: =SUM(B4:E4)
A5: Straw Sales | B5: =SUMIFS(Raw_Income!$G$2:$G$1000,Raw_Income!$D$2:$D$1000,$A5,Raw_Income!$B$2:$B$1000,B$1) | C5: =SUMIFS(Raw_Income!$G$2:$G$1000,Raw_Income!$D$2:$D$1000,$A5,Raw_Income!$B$2:$B$1000,C$1) | D5: =SUMIFS(Raw_Income!$G$2:$G$1000,Raw_Income!$D$2:$D$1000,$A5,Raw_Income!$B$2:$B$1000,D$1) | E5: =SUMIFS(Raw_Income!$G$2:$G$1000,Raw_Income!$D$2:$D$1000,$A5,Raw_Income!$B$2:$B$1000,E$1) | F5: =SUM(B5:E5)
A6: Vegetable Sales | B6: =SUMIFS(Raw_Income!$G$2:$G$1000,Raw_Income!$D$2:$D$1000,$A6,Raw_Income!$B$2:$B$1000,B$1) | C6: =SUMIFS(Raw_Income!$G$2:$G$1000,Raw_Income!$D$2:$D$1000,$A6,Raw_Income!$B$2:$B$1000,C$1) | D6: =SUMIFS(Raw_Income!$G$2:$G$1000,Raw_Income!$D$2:$D$1000,$A6,Raw_Income!$B$2:$B$1000,D$1) | E6: =SUMIFS(Raw_Income!$G$2:$G$1000,Raw_Income!$D$2:$D$1000,$A6,Raw_Income!$B$2:$B$1000,E$1) | F6: =SUM(B6:E6)
A7: Market Stall Sales | B7: =SUMIFS(Raw_Income!$G$2:$G$1000,Raw_Income!$D$2:$D$1000,$A7,Raw_Income!$B$2:$B$1000,B$1) | C7: =SUMIFS(Raw_Income!$G$2:$G$1000,Raw_Income!$D$2:$D$1000,$A7,Raw_Income!$B$2:$B$1000,C$1) | D7: =SUMIFS(Raw_Income!$G$2:$G$1000,Raw_Income!$D$2:$D$1000,$A7,Raw_Income!$B$2:$B$1000,D$1) | E7: =SUMIFS(Raw_Income!$G$2:$G$1000,Raw_Income!$D$2:$D$1000,$A7,Raw_Income!$B$2:$B$1000,E$1) | F7: =SUM(B7:E7)
A8: Egg Sales | B8: =SUMIFS(Raw_Income!$G$2:$G$1000,Raw_Income!$D$2:$D$1000,$A8,Raw_Income!$B$2:$B$1000,B$1) | C8: =SUMIFS(Raw_Income!$G$2:$G$1000,Raw_Income!$D$2:$D$1000,$A8,Raw_Income!$B$2:$B$1000,C$1) | D8: =SUMIFS(Raw_Income!$G$2:$G$1000,Raw_Income!$D$2:$D$1000,$A8,Raw_Income!$B$2:$B$1000,D$1) | E8: =SUMIFS(Raw_Income!$G$2:$G$1000,Raw_Income!$D$2:$D$1000,$A8,Raw_Income!$B$2:$B$1000,E$1) | F8: =SUM(B8:E8)
A9: Broiler Sales | B9: =SUMIFS(Raw_Income!$G$2:$G$1000,Raw_Income!$D$2:$D$1000,$A9,Raw_Income!$B$2:$B$1000,B$1) | C9: =SUMIFS(Raw_Income!$G$2:$G$1000,Raw_Income!$D$2:$D$1000,$A9,Raw_Income!$B$2:$B$1000,C$1) | D9: =SUMIFS(Raw_Income!$G$2:$G$1000,Raw_Income!$D$2:$D$1000,$A9,Raw_Income!$B$2:$B$1000,D$1) | E9: =SUMIFS(Raw_Income!$G$2:$G$1000,Raw_Income!$D$2:$D$1000,$A9,Raw_Income!$B$2:$B$1000,E$1) | F9: =SUM(B9:E9)
A10: Wool Sales | B10: =SUMIFS(Raw_Income!$G$2:$G$1000,Raw_Income!$D$2:$D$1000,$A10,Raw_Income!$B$2:$B$1000,B$1) | C10: =SUMIFS(Raw_Income!$G$2:$G$1000,Raw_Income!$D$2:$D$1000,$A10,Raw_Income!$B$2:$B$1000,C$1) | D10: =SUMIFS(Raw_Income!$G$2:$G$1000,Raw_Income!$D$2:$D$1000,$A10,Raw_Income!$B$2:$B$1000,D$1) | E10: =SUMIFS(Raw_Income!$G$2:$G$1000,Raw_Income!$D$2:$D$1000,$A10,Raw_Income!$B$2:$B$1000,E$1) | F10: =SUM(B10:E10)
A11: Lamb Sales | B11: =SUMIFS(Raw_Income!$G$2:$G$1000,Raw_Income!$D$2:$D$1000,$A11,Raw_Income!$B$2:$B$1000,B$1) | C11: =SUMIFS(Raw_Income!$G$2:$G$1000,Raw_Income!$D$2:$D$1000,$A11,Raw_Income!$B$2:$B$1000,C$1) | D11: =SUMIFS(Raw_Income!$G$2:$G$1000,Raw_Income!$D$2:$D$1000,$A11,Raw_Income!$B$2:$B$1000,D$1) | E11: =SUMIFS(Raw_Income!$G$2:$G$1000,Raw_Income!$D$2:$D$1000,$A11,Raw_Income!$B$2:$B$1000,E$1) | F11: =SUM(B11:E11)
A12: TOTAL | B12: =SUM(B2:B11) | C12: =SUM(C2:C11) | D12: =SUM(D2:D11) | E12: =SUM(E2:E11) | F12: =SUM(F2:F11)

Sheet Expense_Category
A1: Category | B1: 2025-Q3 | C1: 2025-Q4 | D1: 2026-Q1 | E1: 2026-Q2 | F1: Total
A2: Feed | B2: =SUMIFS(Raw_Expense!$G$2:$G$1000,Raw_Expense!$D$2:$D$1000,$A2,Raw_Expense!$B$2:$B$1000,B$1) | C2: =SUMIFS(Raw_Expense!$G$2:$G$1000,Raw_Expense!$D$2:$D$1000,$A2,Raw_Expense!$B$2:$B$1000,C$1) | D2: =SUMIFS(Raw_Expense!$G$2:$G$1000,Raw_Expense!$D$2:$D$1000,$A2,Raw_Expense!$B$2:$B$1000,D$1) | E2: =SUMIFS(Raw_Expense!$G$2:$G$1000,Raw_Expense!$D$2:$D$1000,$A2,Raw_Expense!$B$2:$B$1000,E$1) | F2: =SUM(B2:E2)
A3: Labour | B3: =SUMIFS(Raw_Expense!$G$2:$G$1000,Raw_Expense!$D$2:$D$1000,$A3,Raw_Expense!$B$2:$B$1000,B$1) | C3: =SUMIFS(Raw_Expense!$G$2:$G$1000,Raw_Expense!$D$2:$D$1000,$A3,Raw_Expense!$B$2:$B$1000,C$1) | D3: =SUMIFS(Raw_Expense!$G$2:$G$1000,Raw_Expense!$D$2:$D$1000,$A3,Raw_Expense!$B$2:$B$1000,D$1) | E3: =SUMIFS(Raw_Expense!$G$2:$G$1000,Raw_Expense!$D$2:$D$1000,$A3,Raw_Expense!$B$2:$B$1000,E$1) | F3: =SUM(B3:E3)
A4: Veterinary | B4: =SUMIFS(Raw_Expense!$G$2:$G$1000,Raw_Expense!$D$2:$D$1000,$A4,Raw_Expense!$B$2:$B$1000,B$1) | C4: =SUMIFS(Raw_Expense!$G$2:$G$1000,Raw_Expense!$D$2:$D$1000,$A4,Raw_Expense!$B$2:$B$1000,C$1) | D4: =SUMIFS(Raw_Expense!$G$2:$G$1000,Raw_Expense!$D$2:$D$1000,$A4,Raw_Expense!$B$2:$B$1000,D$1) | E4: =SUMIFS(Raw_Expense!$G$2:$G$1000,Raw_Expense!$D$2:$D$1000,$A4,Raw_Expense!$B$2:$B$1000,E$1) | F4: =SUM(B4:E4)
A5: Fuel & Machinery | B5: =SUMIFS(Raw_Expense!$G$2:$G$1000,Raw_Expense!$D$2:$D$1000,$A5,Raw_Expense!$B$2:$B$1000,B$1) | C5: =SUMIFS(Raw_Expense!$G$2:$G$1000,Raw_Expense!$D$2:$D$1000,$A5,Raw_Expense!$B$2:$B$1000,C$1) | D5: =SUMIFS(Raw_Expense!$G$2:$G$1000,Raw_Expense!$D$2:$D$1000,$A5,Raw_Expense!$B$2:$B$1000,D$1) | E5: =SUMIFS(Raw_Expense!$G$2:$G$1000,Raw_Expense!$D$2:$D$1000,$A5,Raw_Expense!$B$2:$B$1000,E$1) | F5: =SUM(B5:E5)
A6: Fertiliser & Seed | B6: =SUMIFS(Raw_Expense!$G$2:$G$1000,Raw_Expense!$D$2:$D$1000,$A6,Raw_Expense!$B$2:$B$1000,B$1) | C6: =SUMIFS(Raw_Expense!$G$2:$G$1000,Raw_Expense!$D$2:$D$1000,$A6,Raw_Expense!$B$2:$B$1000,C$1) | D6: =SUMIFS(Raw_Expense!$G$2:$G$1000,Raw_Expense!$D$2:$D$1000,$A6,Raw_Expense!$B$2:$B$1000,D$1) | E6: =SUMIFS(Raw_Expense!$G$2:$G$1000,Raw_Expense!$D$2:$D$1000,$A6,Raw_Expense!$B$2:$B$1000,E$1) | F6: =SUM(B6:E6)
A7: Transport | B7: =SUMIFS(Raw_Expense!$G$2:$G$1000,Raw_Expense!$D$2:$D$1000,$A7,Raw_Expense!$B$2:$B$1000,B$1) | C7: =SUMIFS(Raw_Expense!$G$2:$G$1000,Raw_Expense!$D$2:$D$1000,$A7,Raw_Expense!$B$2:$B$1000,C$1) | D7: =SUMIFS(Raw_Expense!$G$2:$G$1000,Raw_Expense!$D$2:$D$1000,$A7,Raw_Expense!$B$2:$B$1000,D$1) | E7: =SUMIFS(Raw_Expense!$G$2:$G$1000,Raw_Expense!$D$2:$D$1000,$A7,Raw_Expense!$B$2:$B$1000,E$1) | F7: =SUM(B7:E7)
A8: Utilities | B8: =SUMIFS(Raw_Expense!$G$2:$G$1000,Raw_Expense!$D$2:$D$1000,$A8,Raw_Expense!$B$2:$B$1000,B$1) | C8: =SUMIFS(Raw_Expense!$G$2:$G$1000,Raw_Expense!$D$2:$D$1000,$A8,Raw_Expense!$B$2:$B$1000,C$1) | D8: =SUMIFS(Raw_Expense!$G$2:$G$1000,Raw_Expense!$D$2:$D$1000,$A8,Raw_Expense!$B$2:$B$1000,D$1) | E8: =SUMIFS(Raw_Expense!$G$2:$G$1000,Raw_Expense!$D$2:$D$1000,$A8,Raw_Expense!$B$2:$B$1000,E$1) | F8: =SUM(B8:E8)
A9: Other | B9: =SUMIFS(Raw_Expense!$G$2:$G$1000,Raw_Expense!$D$2:$D$1000,$A9,Raw_Expense!$B$2:$B$1000,B$1) | C9: =SUMIFS(Raw_Expense!$G$2:$G$1000,Raw_Expense!$D$2:$D$1000,$A9,Raw_Expense!$B$2:$B$1000,C$1) | D9: =SUMIFS(Raw_Expense!$G$2:$G$1000,Raw_Expense!$D$2:$D$1000,$A9,Raw_Expense!$B$2:$B$1000,D$1) | E9: =SUMIFS(Raw_Expense!$G$2:$G$1000,Raw_Expense!$D$2:$D$1000,$A9,Raw_Expense!$B$2:$B$1000,E$1) | F9: =SUM(B9:E9)
A10: TOTAL | B10: =SUM(B2:B9) | C10: =SUM(C2:C9) | D10: =SUM(D2:D9) | E10: =SUM(E2:E9) | F10: =SUM(F2:F9)

Sheet Checks
A1: Check | B1: Difference / Value | C1: Pass?
A2: Dashboard income = Income_Activity total | B2: =Dashboard!B4-Income_Activity!F12 | C2: =ABS(B2)<0.01
A3: Dashboard expenses = Expense_Category total | B3: =Dashboard!B5-Expense_Category!F10 | C3: =ABS(B3)<0.01
A4: Dashboard net = Enterprise_Profit total profit | B4: =Dashboard!B6-Enterprise_Profit!F7 | C4: =ABS(B4)<0.01
A5: Dashboard income = quarterly table total | B5: =Dashboard!B4-Dashboard!B16 | C5: =ABS(B5)<0.01
A6: Dashboard expenses = quarterly table total | B6: =Dashboard!B5-Dashboard!C16 | C6: =ABS(B6)<0.01
A7: Income rows = 172 | B7: =COUNTA(Raw_Income!$A$2:$A$1000)-172 | C7: =B7=0
A8: Expense rows = 164 | B8: =COUNTA(Raw_Expense!$A$2:$A$1000)-164 | C8: =B8=0
A9: No negative amounts (min income >= 0) | B9: =MIN(Raw_Income!$G$2:$G$1000) | C9: =B9>=0
