Workbook

Sheet Data
A1: FiscalYear | B1: Period | C1: MainAccount | D1: AccountName | E1: AccountCategory | F1: Debit | G1: Credit | H1: Signed
A2: 2026 | B2: 1 | C2: 401000 | D2: Product Sales | E2: Revenue | F2: 0 | G2: 142367.1 | H2: 142367.1
A3: 2026 | B3: 1 | C3: 402000 | D3: Service Revenue | E3: Revenue | F3: 0 | G3: 34180.66 | H3: 34180.66
A4: 2026 | B4: 1 | C4: 403000 | D4: Other Income | E4: Revenue | F4: 0 | G4: 5813.09 | H4: 5813.09
A5: 2026 | B5: 1 | C5: 501000 | D5: Cost of Goods Sold | E5: Expense | F5: 76931.2 | G5: 0 | H5: 76931.2
A6: 2026 | B6: 1 | C6: 502000 | D6: Salaries & Benefits | E6: Expense | F6: 48848.16 | G6: 0 | H6: 48848.16
A7: 2026 | B7: 1 | C7: 503000 | D7: Rent & Facilities | E7: Expense | F7: 12000 | G7: 0 | H7: 12000
A8: 2026 | B8: 1 | C8: 504000 | D8: Marketing & Advertising | E8: Expense | F8: 10411.85 | G8: 0 | H8: 10411.85
A9: 2026 | B9: 1 | C9: 505000 | D9: Travel & Entertainment | E9: Expense | F9: 4760.82 | G9: 0 | H9: 4760.82
A10: 2026 | B10: 1 | C10: 506000 | D10: IT & Software | E10: Expense | F10: 3937.54 | G10: 0 | H10: 3937.54
A11: 2026 | B11: 1 | C11: 507000 | D11: Utilities | E11: Expense | F11: 2264.9 | G11: 0 | H11: 2264.9
A12: 2026 | B12: 1 | C12: 508000 | D12: Depreciation | E12: Expense | F12: 7000 | G12: 0 | H12: 7000
A13: 2026 | B13: 1 | C13: 509000 | D13: Interest Expense | E13: Expense | F13: 3000 | G13: 0 | H13: 3000
... A313: 2026 | B313: 12 | C313: 302000 | D313: Retained Earnings | E313: Equity | F313: 0 | G313: 50000 | H313: 50000

Sheet Income Statement
A1: Account | B1: Line Item | C1: 1 | D1: 2 | E1: 3 | F1: 4 | G1: 5 | H1: 6 | I1: 7 | J1: 8 | K1: 9 | L1: 10 | M1: 11 | N1: 12 | O1: Total
B2: Revenue
A3: 401000 | B3: Product Sales | C3: =SUMIFS(Data!$H:$H,Data!$B:$B,C$1,Data!$C:$C,$A3) | D3: =SUMIFS(Data!$H:$H,Data!$B:$B,D$1,Data!$C:$C,$A3) | E3: =SUMIFS(Data!$H:$H,Data!$B:$B,E$1,Data!$C:$C,$A3) | F3: =SUMIFS(Data!$H:$H,Data!$B:$B,F$1,Data!$C:$C,$A3) | G3: =SUMIFS(Data!$H:$H,Data!$B:$B,G$1,Data!$C:$C,$A3) | H3: =SUMIFS(Data!$H:$H,Data!$B:$B,H$1,Data!$C:$C,$A3) | I3: =SUMIFS(Data!$H:$H,Data!$B:$B,I$1,Data!$C:$C,$A3) | J3: =SUMIFS(Data!$H:$H,Data!$B:$B,J$1,Data!$C:$C,$A3) | ... N3: =SUMIFS(Data!$H:$H,Data!$B:$B,N$1,Data!$C:$C,$A3) | O3: =SUM(C3:N3)
A4: 402000 | B4: Service Revenue | C4: =SUMIFS(Data!$H:$H,Data!$B:$B,C$1,Data!$C:$C,$A4) | D4: =SUMIFS(Data!$H:$H,Data!$B:$B,D$1,Data!$C:$C,$A4) | E4: =SUMIFS(Data!$H:$H,Data!$B:$B,E$1,Data!$C:$C,$A4) | F4: =SUMIFS(Data!$H:$H,Data!$B:$B,F$1,Data!$C:$C,$A4) | G4: =SUMIFS(Data!$H:$H,Data!$B:$B,G$1,Data!$C:$C,$A4) | H4: =SUMIFS(Data!$H:$H,Data!$B:$B,H$1,Data!$C:$C,$A4) | I4: =SUMIFS(Data!$H:$H,Data!$B:$B,I$1,Data!$C:$C,$A4) | J4: =SUMIFS(Data!$H:$H,Data!$B:$B,J$1,Data!$C:$C,$A4) | ... N4: =SUMIFS(Data!$H:$H,Data!$B:$B,N$1,Data!$C:$C,$A4) | O4: =SUM(C4:N4)
A5: 403000 | B5: Other Income | C5: =SUMIFS(Data!$H:$H,Data!$B:$B,C$1,Data!$C:$C,$A5) | D5: =SUMIFS(Data!$H:$H,Data!$B:$B,D$1,Data!$C:$C,$A5) | E5: =SUMIFS(Data!$H:$H,Data!$B:$B,E$1,Data!$C:$C,$A5) | F5: =SUMIFS(Data!$H:$H,Data!$B:$B,F$1,Data!$C:$C,$A5) | G5: =SUMIFS(Data!$H:$H,Data!$B:$B,G$1,Data!$C:$C,$A5) | H5: =SUMIFS(Data!$H:$H,Data!$B:$B,H$1,Data!$C:$C,$A5) | I5: =SUMIFS(Data!$H:$H,Data!$B:$B,I$1,Data!$C:$C,$A5) | J5: =SUMIFS(Data!$H:$H,Data!$B:$B,J$1,Data!$C:$C,$A5) | ... N5: =SUMIFS(Data!$H:$H,Data!$B:$B,N$1,Data!$C:$C,$A5) | O5: =SUM(C5:N5)
B6: Total Revenue | C6: =SUM(C3:C5) | D6: =SUM(D3:D5) | E6: =SUM(E3:E5) | F6: =SUM(F3:F5) | G6: =SUM(G3:G5) | H6: =SUM(H3:H5) | I6: =SUM(I3:I5) | J6: =SUM(J3:J5) | ... N6: =SUM(N3:N5) | O6: =SUM(C6:N6)
B8: Operating Expenses
A9: 501000 | B9: Cost of Goods Sold | C9: =SUMIFS(Data!$H:$H,Data!$B:$B,C$1,Data!$C:$C,$A9) | D9: =SUMIFS(Data!$H:$H,Data!$B:$B,D$1,Data!$C:$C,$A9) | E9: =SUMIFS(Data!$H:$H,Data!$B:$B,E$1,Data!$C:$C,$A9) | F9: =SUMIFS(Data!$H:$H,Data!$B:$B,F$1,Data!$C:$C,$A9) | G9: =SUMIFS(Data!$H:$H,Data!$B:$B,G$1,Data!$C:$C,$A9) | H9: =SUMIFS(Data!$H:$H,Data!$B:$B,H$1,Data!$C:$C,$A9) | I9: =SUMIFS(Data!$H:$H,Data!$B:$B,I$1,Data!$C:$C,$A9) | J9: =SUMIFS(Data!$H:$H,Data!$B:$B,J$1,Data!$C:$C,$A9) | ... N9: =SUMIFS(Data!$H:$H,Data!$B:$B,N$1,Data!$C:$C,$A9) | O9: =SUM(C9:N9)
A10: 502000 | B10: Salaries & Benefits | C10: =SUMIFS(Data!$H:$H,Data!$B:$B,C$1,Data!$C:$C,$A10) | D10: =SUMIFS(Data!$H:$H,Data!$B:$B,D$1,Data!$C:$C,$A10) | E10: =SUMIFS(Data!$H:$H,Data!$B:$B,E$1,Data!$C:$C,$A10) | F10: =SUMIFS(Data!$H:$H,Data!$B:$B,F$1,Data!$C:$C,$A10) | G10: =SUMIFS(Data!$H:$H,Data!$B:$B,G$1,Data!$C:$C,$A10) | H10: =SUMIFS(Data!$H:$H,Data!$B:$B,H$1,Data!$C:$C,$A10) | I10: =SUMIFS(Data!$H:$H,Data!$B:$B,I$1,Data!$C:$C,$A10) | J10: =SUMIFS(Data!$H:$H,Data!$B:$B,J$1,Data!$C:$C,$A10) | ... N10: =SUMIFS(Data!$H:$H,Data!$B:$B,N$1,Data!$C:$C,$A10) | O10: =SUM(C10:N10)
A11: 503000 | B11: Rent & Facilities | C11: =SUMIFS(Data!$H:$H,Data!$B:$B,C$1,Data!$C:$C,$A11) | D11: =SUMIFS(Data!$H:$H,Data!$B:$B,D$1,Data!$C:$C,$A11) | E11: =SUMIFS(Data!$H:$H,Data!$B:$B,E$1,Data!$C:$C,$A11) | F11: =SUMIFS(Data!$H:$H,Data!$B:$B,F$1,Data!$C:$C,$A11) | G11: =SUMIFS(Data!$H:$H,Data!$B:$B,G$1,Data!$C:$C,$A11) | H11: =SUMIFS(Data!$H:$H,Data!$B:$B,H$1,Data!$C:$C,$A11) | I11: =SUMIFS(Data!$H:$H,Data!$B:$B,I$1,Data!$C:$C,$A11) | J11: =SUMIFS(Data!$H:$H,Data!$B:$B,J$1,Data!$C:$C,$A11) | ... N11: =SUMIFS(Data!$H:$H,Data!$B:$B,N$1,Data!$C:$C,$A11) | O11: =SUM(C11:N11)
A12: 504000 | B12: Marketing & Advertising | C12: =SUMIFS(Data!$H:$H,Data!$B:$B,C$1,Data!$C:$C,$A12) | D12: =SUMIFS(Data!$H:$H,Data!$B:$B,D$1,Data!$C:$C,$A12) | E12: =SUMIFS(Data!$H:$H,Data!$B:$B,E$1,Data!$C:$C,$A12) | F12: =SUMIFS(Data!$H:$H,Data!$B:$B,F$1,Data!$C:$C,$A12) | G12: =SUMIFS(Data!$H:$H,Data!$B:$B,G$1,Data!$C:$C,$A12) | H12: =SUMIFS(Data!$H:$H,Data!$B:$B,H$1,Data!$C:$C,$A12) | I12: =SUMIFS(Data!$H:$H,Data!$B:$B,I$1,Data!$C:$C,$A12) | J12: =SUMIFS(Data!$H:$H,Data!$B:$B,J$1,Data!$C:$C,$A12) | ... N12: =SUMIFS(Data!$H:$H,Data!$B:$B,N$1,Data!$C:$C,$A12) | O12: =SUM(C12:N12)
A13: 505000 | B13: Travel & Entertainment | C13: =SUMIFS(Data!$H:$H,Data!$B:$B,C$1,Data!$C:$C,$A13) | D13: =SUMIFS(Data!$H:$H,Data!$B:$B,D$1,Data!$C:$C,$A13) | E13: =SUMIFS(Data!$H:$H,Data!$B:$B,E$1,Data!$C:$C,$A13) | F13: =SUMIFS(Data!$H:$H,Data!$B:$B,F$1,Data!$C:$C,$A13) | G13: =SUMIFS(Data!$H:$H,Data!$B:$B,G$1,Data!$C:$C,$A13) | H13: =SUMIFS(Data!$H:$H,Data!$B:$B,H$1,Data!$C:$C,$A13) | I13: =SUMIFS(Data!$H:$H,Data!$B:$B,I$1,Data!$C:$C,$A13) | J13: =SUMIFS(Data!$H:$H,Data!$B:$B,J$1,Data!$C:$C,$A13) | ... N13: =SUMIFS(Data!$H:$H,Data!$B:$B,N$1,Data!$C:$C,$A13) | O13: =SUM(C13:N13)
A14: 506000 | B14: IT & Software | C14: =SUMIFS(Data!$H:$H,Data!$B:$B,C$1,Data!$C:$C,$A14) | D14: =SUMIFS(Data!$H:$H,Data!$B:$B,D$1,Data!$C:$C,$A14) | E14: =SUMIFS(Data!$H:$H,Data!$B:$B,E$1,Data!$C:$C,$A14) | F14: =SUMIFS(Data!$H:$H,Data!$B:$B,F$1,Data!$C:$C,$A14) | G14: =SUMIFS(Data!$H:$H,Data!$B:$B,G$1,Data!$C:$C,$A14) | H14: =SUMIFS(Data!$H:$H,Data!$B:$B,H$1,Data!$C:$C,$A14) | I14: =SUMIFS(Data!$H:$H,Data!$B:$B,I$1,Data!$C:$C,$A14) | J14: =SUMIFS(Data!$H:$H,Data!$B:$B,J$1,Data!$C:$C,$A14) | ... N14: =SUMIFS(Data!$H:$H,Data!$B:$B,N$1,Data!$C:$C,$A14) | O14: =SUM(C14:N14)
A15: 507000 | B15: Utilities | C15: =SUMIFS(Data!$H:$H,Data!$B:$B,C$1,Data!$C:$C,$A15) | D15: =SUMIFS(Data!$H:$H,Data!$B:$B,D$1,Data!$C:$C,$A15) | E15: =SUMIFS(Data!$H:$H,Data!$B:$B,E$1,Data!$C:$C,$A15) | F15: =SUMIFS(Data!$H:$H,Data!$B:$B,F$1,Data!$C:$C,$A15) | G15: =SUMIFS(Data!$H:$H,Data!$B:$B,G$1,Data!$C:$C,$A15) | H15: =SUMIFS(Data!$H:$H,Data!$B:$B,H$1,Data!$C:$C,$A15) | I15: =SUMIFS(Data!$H:$H,Data!$B:$B,I$1,Data!$C:$C,$A15) | J15: =SUMIFS(Data!$H:$H,Data!$B:$B,J$1,Data!$C:$C,$A15) | ... N15: =SUMIFS(Data!$H:$H,Data!$B:$B,N$1,Data!$C:$C,$A15) | O15: =SUM(C15:N15)
A16: 508000 | B16: Depreciation | C16: =SUMIFS(Data!$H:$H,Data!$B:$B,C$1,Data!$C:$C,$A16) | D16: =SUMIFS(Data!$H:$H,Data!$B:$B,D$1,Data!$C:$C,$A16) | E16: =SUMIFS(Data!$H:$H,Data!$B:$B,E$1,Data!$C:$C,$A16) | F16: =SUMIFS(Data!$H:$H,Data!$B:$B,F$1,Data!$C:$C,$A16) | G16: =SUMIFS(Data!$H:$H,Data!$B:$B,G$1,Data!$C:$C,$A16) | H16: =SUMIFS(Data!$H:$H,Data!$B:$B,H$1,Data!$C:$C,$A16) | I16: =SUMIFS(Data!$H:$H,Data!$B:$B,I$1,Data!$C:$C,$A16) | J16: =SUMIFS(Data!$H:$H,Data!$B:$B,J$1,Data!$C:$C,$A16) | ... N16: =SUMIFS(Data!$H:$H,Data!$B:$B,N$1,Data!$C:$C,$A16) | O16: =SUM(C16:N16)
A17: 509000 | B17: Interest Expense | C17: =SUMIFS(Data!$H:$H,Data!$B:$B,C$1,Data!$C:$C,$A17) | D17: =SUMIFS(Data!$H:$H,Data!$B:$B,D$1,Data!$C:$C,$A17) | E17: =SUMIFS(Data!$H:$H,Data!$B:$B,E$1,Data!$C:$C,$A17) | F17: =SUMIFS(Data!$H:$H,Data!$B:$B,F$1,Data!$C:$C,$A17) | G17: =SUMIFS(Data!$H:$H,Data!$B:$B,G$1,Data!$C:$C,$A17) | H17: =SUMIFS(Data!$H:$H,Data!$B:$B,H$1,Data!$C:$C,$A17) | I17: =SUMIFS(Data!$H:$H,Data!$B:$B,I$1,Data!$C:$C,$A17) | J17: =SUMIFS(Data!$H:$H,Data!$B:$B,J$1,Data!$C:$C,$A17) | ... N17: =SUMIFS(Data!$H:$H,Data!$B:$B,N$1,Data!$C:$C,$A17) | O17: =SUM(C17:N17)
A18: 510000 | B18: Tax Provision | C18: =SUMIFS(Data!$H:$H,Data!$B:$B,C$1,Data!$C:$C,$A18) | D18: =SUMIFS(Data!$H:$H,Data!$B:$B,D$1,Data!$C:$C,$A18) | E18: =SUMIFS(Data!$H:$H,Data!$B:$B,E$1,Data!$C:$C,$A18) | F18: =SUMIFS(Data!$H:$H,Data!$B:$B,F$1,Data!$C:$C,$A18) | G18: =SUMIFS(Data!$H:$H,Data!$B:$B,G$1,Data!$C:$C,$A18) | H18: =SUMIFS(Data!$H:$H,Data!$B:$B,H$1,Data!$C:$C,$A18) | I18: =SUMIFS(Data!$H:$H,Data!$B:$B,I$1,Data!$C:$C,$A18) | J18: =SUMIFS(Data!$H:$H,Data!$B:$B,J$1,Data!$C:$C,$A18) | ... N18: =SUMIFS(Data!$H:$H,Data!$B:$B,N$1,Data!$C:$C,$A18) | O18: =SUM(C18:N18)
B19: Total Expenses | C19: =SUM(C9:C18) | D19: =SUM(D9:D18) | E19: =SUM(E9:E18) | F19: =SUM(F9:F18) | G19: =SUM(G9:G18) | H19: =SUM(H9:H18) | I19: =SUM(I9:I18) | J19: =SUM(J9:J18) | ... N19: =SUM(N9:N18) | O19: =SUM(C19:N19)
B20: Net Income | C20: =C6-C19 | D20: =D6-D19 | E20: =E6-E19 | F20: =F6-F19 | G20: =G6-G19 | H20: =H6-H19 | I20: =I6-I19 | J20: =J6-J19 | ... O20: =O6-O19

Sheet Balance Sheet
A1: Account | B1: Line Item | C1: 1 | D1: 2 | E1: 3 | F1: 4 | G1: 5 | H1: 6 | I1: 7 | J1: 8 | K1: 9 | L1: 10 | M1: 11 | N1: 12 | O1: Total
B2: Assets
A3: 101000 | B3: Cash & Bank | C3: =SUMIFS(Data!$H:$H,Data!$B:$B,C$1,Data!$C:$C,$A3) | D3: =SUMIFS(Data!$H:$H,Data!$B:$B,D$1,Data!$C:$C,$A3) | E3: =SUMIFS(Data!$H:$H,Data!$B:$B,E$1,Data!$C:$C,$A3) | F3: =SUMIFS(Data!$H:$H,Data!$B:$B,F$1,Data!$C:$C,$A3) | G3: =SUMIFS(Data!$H:$H,Data!$B:$B,G$1,Data!$C:$C,$A3) | H3: =SUMIFS(Data!$H:$H,Data!$B:$B,H$1,Data!$C:$C,$A3) | I3: =SUMIFS(Data!$H:$H,Data!$B:$B,I$1,Data!$C:$C,$A3) | J3: =SUMIFS(Data!$H:$H,Data!$B:$B,J$1,Data!$C:$C,$A3) | ... N3: =SUMIFS(Data!$H:$H,Data!$B:$B,N$1,Data!$C:$C,$A3) | O3: =SUM(C3:N3)
A4: 102000 | B4: Accounts Receivable | C4: =SUMIFS(Data!$H:$H,Data!$B:$B,C$1,Data!$C:$C,$A4) | D4: =SUMIFS(Data!$H:$H,Data!$B:$B,D$1,Data!$C:$C,$A4) | E4: =SUMIFS(Data!$H:$H,Data!$B:$B,E$1,Data!$C:$C,$A4) | F4: =SUMIFS(Data!$H:$H,Data!$B:$B,F$1,Data!$C:$C,$A4) | G4: =SUMIFS(Data!$H:$H,Data!$B:$B,G$1,Data!$C:$C,$A4) | H4: =SUMIFS(Data!$H:$H,Data!$B:$B,H$1,Data!$C:$C,$A4) | I4: =SUMIFS(Data!$H:$H,Data!$B:$B,I$1,Data!$C:$C,$A4) | J4: =SUMIFS(Data!$H:$H,Data!$B:$B,J$1,Data!$C:$C,$A4) | ... N4: =SUMIFS(Data!$H:$H,Data!$B:$B,N$1,Data!$C:$C,$A4) | O4: =SUM(C4:N4)
A5: 103000 | B5: Inventory | C5: =SUMIFS(Data!$H:$H,Data!$B:$B,C$1,Data!$C:$C,$A5) | D5: =SUMIFS(Data!$H:$H,Data!$B:$B,D$1,Data!$C:$C,$A5) | E5: =SUMIFS(Data!$H:$H,Data!$B:$B,E$1,Data!$C:$C,$A5) | F5: =SUMIFS(Data!$H:$H,Data!$B:$B,F$1,Data!$C:$C,$A5) | G5: =SUMIFS(Data!$H:$H,Data!$B:$B,G$1,Data!$C:$C,$A5) | H5: =SUMIFS(Data!$H:$H,Data!$B:$B,H$1,Data!$C:$C,$A5) | I5: =SUMIFS(Data!$H:$H,Data!$B:$B,I$1,Data!$C:$C,$A5) | J5: =SUMIFS(Data!$H:$H,Data!$B:$B,J$1,Data!$C:$C,$A5) | ... N5: =SUMIFS(Data!$H:$H,Data!$B:$B,N$1,Data!$C:$C,$A5) | O5: =SUM(C5:N5)
A6: 104000 | B6: Prepaid Expenses | C6: =SUMIFS(Data!$H:$H,Data!$B:$B,C$1,Data!$C:$C,$A6) | D6: =SUMIFS(Data!$H:$H,Data!$B:$B,D$1,Data!$C:$C,$A6) | E6: =SUMIFS(Data!$H:$H,Data!$B:$B,E$1,Data!$C:$C,$A6) | F6: =SUMIFS(Data!$H:$H,Data!$B:$B,F$1,Data!$C:$C,$A6) | G6: =SUMIFS(Data!$H:$H,Data!$B:$B,G$1,Data!$C:$C,$A6) | H6: =SUMIFS(Data!$H:$H,Data!$B:$B,H$1,Data!$C:$C,$A6) | I6: =SUMIFS(Data!$H:$H,Data!$B:$B,I$1,Data!$C:$C,$A6) | J6: =SUMIFS(Data!$H:$H,Data!$B:$B,J$1,Data!$C:$C,$A6) | ... N6: =SUMIFS(Data!$H:$H,Data!$B:$B,N$1,Data!$C:$C,$A6) | O6: =SUM(C6:N6)
A7: 105000 | B7: Fixed Assets (Gross) | C7: =SUMIFS(Data!$H:$H,Data!$B:$B,C$1,Data!$C:$C,$A7) | D7: =SUMIFS(Data!$H:$H,Data!$B:$B,D$1,Data!$C:$C,$A7) | E7: =SUMIFS(Data!$H:$H,Data!$B:$B,E$1,Data!$C:$C,$A7) | F7: =SUMIFS(Data!$H:$H,Data!$B:$B,F$1,Data!$C:$C,$A7) | G7: =SUMIFS(Data!$H:$H,Data!$B:$B,G$1,Data!$C:$C,$A7) | H7: =SUMIFS(Data!$H:$H,Data!$B:$B,H$1,Data!$C:$C,$A7) | I7: =SUMIFS(Data!$H:$H,Data!$B:$B,I$1,Data!$C:$C,$A7) | J7: =SUMIFS(Data!$H:$H,Data!$B:$B,J$1,Data!$C:$C,$A7) | ... N7: =SUMIFS(Data!$H:$H,Data!$B:$B,N$1,Data!$C:$C,$A7) | O7: =SUM(C7:N7)
A8: 106000 | B8: Accumulated Depreciation | C8: =SUMIFS(Data!$H:$H,Data!$B:$B,C$1,Data!$C:$C,$A8) | D8: =SUMIFS(Data!$H:$H,Data!$B:$B,D$1,Data!$C:$C,$A8) | E8: =SUMIFS(Data!$H:$H,Data!$B:$B,E$1,Data!$C:$C,$A8) | F8: =SUMIFS(Data!$H:$H,Data!$B:$B,F$1,Data!$C:$C,$A8) | G8: =SUMIFS(Data!$H:$H,Data!$B:$B,G$1,Data!$C:$C,$A8) | H8: =SUMIFS(Data!$H:$H,Data!$B:$B,H$1,Data!$C:$C,$A8) | I8: =SUMIFS(Data!$H:$H,Data!$B:$B,I$1,Data!$C:$C,$A8) | J8: =SUMIFS(Data!$H:$H,Data!$B:$B,J$1,Data!$C:$C,$A8) | ... N8: =SUMIFS(Data!$H:$H,Data!$B:$B,N$1,Data!$C:$C,$A8) | O8: =SUM(C8:N8)
B9: Total Assets | C9: =SUM(C3:C8) | D9: =SUM(D3:D8) | E9: =SUM(E3:E8) | F9: =SUM(F3:F8) | G9: =SUM(G3:G8) | H9: =SUM(H3:H8) | I9: =SUM(I3:I8) | J9: =SUM(J3:J8) | ... N9: =SUM(N3:N8) | O9: =SUM(C9:N9)
B11: Liabilities
A12: 201000 | B12: Accounts Payable | C12: =SUMIFS(Data!$H:$H,Data!$B:$B,C$1,Data!$C:$C,$A12) | D12: =SUMIFS(Data!$H:$H,Data!$B:$B,D$1,Data!$C:$C,$A12) | E12: =SUMIFS(Data!$H:$H,Data!$B:$B,E$1,Data!$C:$C,$A12) | F12: =SUMIFS(Data!$H:$H,Data!$B:$B,F$1,Data!$C:$C,$A12) | G12: =SUMIFS(Data!$H:$H,Data!$B:$B,G$1,Data!$C:$C,$A12) | H12: =SUMIFS(Data!$H:$H,Data!$B:$B,H$1,Data!$C:$C,$A12) | I12: =SUMIFS(Data!$H:$H,Data!$B:$B,I$1,Data!$C:$C,$A12) | J12: =SUMIFS(Data!$H:$H,Data!$B:$B,J$1,Data!$C:$C,$A12) | ... N12: =SUMIFS(Data!$H:$H,Data!$B:$B,N$1,Data!$C:$C,$A12) | O12: =SUM(C12:N12)
A13: 202000 | B13: Accrued Expenses | C13: =SUMIFS(Data!$H:$H,Data!$B:$B,C$1,Data!$C:$C,$A13) | D13: =SUMIFS(Data!$H:$H,Data!$B:$B,D$1,Data!$C:$C,$A13) | E13: =SUMIFS(Data!$H:$H,Data!$B:$B,E$1,Data!$C:$C,$A13) | F13: =SUMIFS(Data!$H:$H,Data!$B:$B,F$1,Data!$C:$C,$A13) | G13: =SUMIFS(Data!$H:$H,Data!$B:$B,G$1,Data!$C:$C,$A13) | H13: =SUMIFS(Data!$H:$H,Data!$B:$B,H$1,Data!$C:$C,$A13) | I13: =SUMIFS(Data!$H:$H,Data!$B:$B,I$1,Data!$C:$C,$A13) | J13: =SUMIFS(Data!$H:$H,Data!$B:$B,J$1,Data!$C:$C,$A13) | ... N13: =SUMIFS(Data!$H:$H,Data!$B:$B,N$1,Data!$C:$C,$A13) | O13: =SUM(C13:N13)
A14: 203000 | B14: Short-Term Debt | C14: =SUMIFS(Data!$H:$H,Data!$B:$B,C$1,Data!$C:$C,$A14) | D14: =SUMIFS(Data!$H:$H,Data!$B:$B,D$1,Data!$C:$C,$A14) | E14: =SUMIFS(Data!$H:$H,Data!$B:$B,E$1,Data!$C:$C,$A14) | F14: =SUMIFS(Data!$H:$H,Data!$B:$B,F$1,Data!$C:$C,$A14) | G14: =SUMIFS(Data!$H:$H,Data!$B:$B,G$1,Data!$C:$C,$A14) | H14: =SUMIFS(Data!$H:$H,Data!$B:$B,H$1,Data!$C:$C,$A14) | I14: =SUMIFS(Data!$H:$H,Data!$B:$B,I$1,Data!$C:$C,$A14) | J14: =SUMIFS(Data!$H:$H,Data!$B:$B,J$1,Data!$C:$C,$A14) | ... N14: =SUMIFS(Data!$H:$H,Data!$B:$B,N$1,Data!$C:$C,$A14) | O14: =SUM(C14:N14)
A15: 204000 | B15: Long-Term Debt | C15: =SUMIFS(Data!$H:$H,Data!$B:$B,C$1,Data!$C:$C,$A15) | D15: =SUMIFS(Data!$H:$H,Data!$B:$B,D$1,Data!$C:$C,$A15) | E15: =SUMIFS(Data!$H:$H,Data!$B:$B,E$1,Data!$C:$C,$A15) | F15: =SUMIFS(Data!$H:$H,Data!$B:$B,F$1,Data!$C:$C,$A15) | G15: =SUMIFS(Data!$H:$H,Data!$B:$B,G$1,Data!$C:$C,$A15) | H15: =SUMIFS(Data!$H:$H,Data!$B:$B,H$1,Data!$C:$C,$A15) | I15: =SUMIFS(Data!$H:$H,Data!$B:$B,I$1,Data!$C:$C,$A15) | J15: =SUMIFS(Data!$H:$H,Data!$B:$B,J$1,Data!$C:$C,$A15) | ... N15: =SUMIFS(Data!$H:$H,Data!$B:$B,N$1,Data!$C:$C,$A15) | O15: =SUM(C15:N15)
A16: 205000 | B16: Taxes Payable | C16: =SUMIFS(Data!$H:$H,Data!$B:$B,C$1,Data!$C:$C,$A16) | D16: =SUMIFS(Data!$H:$H,Data!$B:$B,D$1,Data!$C:$C,$A16) | E16: =SUMIFS(Data!$H:$H,Data!$B:$B,E$1,Data!$C:$C,$A16) | F16: =SUMIFS(Data!$H:$H,Data!$B:$B,F$1,Data!$C:$C,$A16) | G16: =SUMIFS(Data!$H:$H,Data!$B:$B,G$1,Data!$C:$C,$A16) | H16: =SUMIFS(Data!$H:$H,Data!$B:$B,H$1,Data!$C:$C,$A16) | I16: =SUMIFS(Data!$H:$H,Data!$B:$B,I$1,Data!$C:$C,$A16) | J16: =SUMIFS(Data!$H:$H,Data!$B:$B,J$1,Data!$C:$C,$A16) | ... N16: =SUMIFS(Data!$H:$H,Data!$B:$B,N$1,Data!$C:$C,$A16) | O16: =SUM(C16:N16)
B17: Total Liabilities | C17: =SUM(C12:C16) | D17: =SUM(D12:D16) | E17: =SUM(E12:E16) | F17: =SUM(F12:F16) | G17: =SUM(G12:G16) | H17: =SUM(H12:H16) | I17: =SUM(I12:I16) | J17: =SUM(J12:J16) | ... N17: =SUM(N12:N16) | O17: =SUM(C17:N17)
B19: Equity
A20: 301000 | B20: Share Capital | C20: =SUMIFS(Data!$H:$H,Data!$B:$B,C$1,Data!$C:$C,$A20) | D20: =SUMIFS(Data!$H:$H,Data!$B:$B,D$1,Data!$C:$C,$A20) | E20: =SUMIFS(Data!$H:$H,Data!$B:$B,E$1,Data!$C:$C,$A20) | F20: =SUMIFS(Data!$H:$H,Data!$B:$B,F$1,Data!$C:$C,$A20) | G20: =SUMIFS(Data!$H:$H,Data!$B:$B,G$1,Data!$C:$C,$A20) | H20: =SUMIFS(Data!$H:$H,Data!$B:$B,H$1,Data!$C:$C,$A20) | I20: =SUMIFS(Data!$H:$H,Data!$B:$B,I$1,Data!$C:$C,$A20) | J20: =SUMIFS(Data!$H:$H,Data!$B:$B,J$1,Data!$C:$C,$A20) | ... N20: =SUMIFS(Data!$H:$H,Data!$B:$B,N$1,Data!$C:$C,$A20) | O20: =SUM(C20:N20)
A21: 302000 | B21: Retained Earnings (incl. current profit) | C21: ==SUMIFS(Data!$H:$H,Data!$B:$B,C$1,Data!$C:$C,$A21)+'Income Statement'!C20 | D21: ==SUMIFS(Data!$H:$H,Data!$B:$B,D$1,Data!$C:$C,$A21)+'Income Statement'!D20 | E21: ==SUMIFS(Data!$H:$H,Data!$B:$B,E$1,Data!$C:$C,$A21)+'Income Statement'!E20 | F21: ==SUMIFS(Data!$H:$H,Data!$B:$B,F$1,Data!$C:$C,$A21)+'Income Statement'!F20 | G21: ==SUMIFS(Data!$H:$H,Data!$B:$B,G$1,Data!$C:$C,$A21)+'Income Statement'!G20 | H21: ==SUMIFS(Data!$H:$H,Data!$B:$B,H$1,Data!$C:$C,$A21)+'Income Statement'!H20 | I21: ==SUMIFS(Data!$H:$H,Data!$B:$B,I$1,Data!$C:$C,$A21)+'Income Statement'!I20 | J21: ==SUMIFS(Data!$H:$H,Data!$B:$B,J$1,Data!$C:$C,$A21)+'Income Statement'!J20 | ... N21: ==SUMIFS(Data!$H:$H,Data!$B:$B,N$1,Data!$C:$C,$A21)+'Income Statement'!N20 | O21: =SUM(C21:N21)
B22: Total Equity | C22: =SUM(C20:C21) | D22: =SUM(D20:D21) | E22: =SUM(E20:E21) | F22: =SUM(F20:F21) | G22: =SUM(G20:G21) | H22: =SUM(H20:H21) | I22: =SUM(I20:I21) | J22: =SUM(J20:J21) | ... N22: =SUM(N20:N21) | O22: =SUM(C22:N22)
B23: Total Liabilities & Equity | C23: =C17+C22 | D23: =D17+D22 | E23: =E17+E22 | F23: =F17+F22 | G23: =G17+G22 | H23: =H17+H22 | I23: =I17+I22 | J23: =J17+J22 | ... O23: =O17+O22
B24: Check (Assets - L&E) = 0 | C24: =C9-C23 | D24: =D9-D23 | E24: =E9-E23 | F24: =F9-F23 | G24: =G9-G23 | H24: =H9-H23 | I24: =I9-I23 | J24: =J9-J23 | ... O24: =O9-O23

Sheet KPI Dashboard
A1: KPI Dashboard — FY 2026 (annual)
A3: Total Revenue | B3: ='Income Statement'!O6
A4: Total Expenses | B4: ='Income Statement'!O19
A5: Net Income | B5: ='Income Statement'!O20
A6: Net Margin | B6: =B5/B3
A7: Current Assets | B7: ='Balance Sheet'!O3+'Balance Sheet'!O4+'Balance Sheet'!O5+'Balance Sheet'!O6
A8: Current Liabilities | B8: ='Balance Sheet'!O12+'Balance Sheet'!O13+'Balance Sheet'!O14+'Balance Sheet'!O16
A9: Current Ratio | B9: =B7/B8
A10: Total Debt | B10: ='Balance Sheet'!O14+'Balance Sheet'!O15
A11: Total Equity | B11: ='Balance Sheet'!O22
A12: Debt-to-Equity | B12: =B10/B11

Sheet ChartData
A1: Period | B1: Revenue | C1: Expenses | D1: Net Income
A2: 1 | B2: ='Income Statement'!C6 | C2: ='Income Statement'!C19 | D2: ='Income Statement'!C20
A3: 2 | B3: ='Income Statement'!D6 | C3: ='Income Statement'!D19 | D3: ='Income Statement'!D20
A4: 3 | B4: ='Income Statement'!E6 | C4: ='Income Statement'!E19 | D4: ='Income Statement'!E20
A5: 4 | B5: ='Income Statement'!F6 | C5: ='Income Statement'!F19 | D5: ='Income Statement'!F20
A6: 5 | B6: ='Income Statement'!G6 | C6: ='Income Statement'!G19 | D6: ='Income Statement'!G20
A7: 6 | B7: ='Income Statement'!H6 | C7: ='Income Statement'!H19 | D7: ='Income Statement'!H20
A8: 7 | B8: ='Income Statement'!I6 | C8: ='Income Statement'!I19 | D8: ='Income Statement'!I20
A9: 8 | B9: ='Income Statement'!J6 | C9: ='Income Statement'!J19 | D9: ='Income Statement'!J20
A10: 9 | B10: ='Income Statement'!K6 | C10: ='Income Statement'!K19 | D10: ='Income Statement'!K20
A11: 10 | B11: ='Income Statement'!L6 | C11: ='Income Statement'!L19 | D11: ='Income Statement'!L20
A12: 11 | B12: ='Income Statement'!M6 | C12: ='Income Statement'!M19 | D12: ='Income Statement'!M20
A13: 12 | B13: ='Income Statement'!N6 | C13: ='Income Statement'!N19 | D13: ='Income Statement'!N20

Sheet Charts
